Workbook
Name CompanyAddress: [1]Settings!$C$10
Name CompanyName: '[1]Tour Info'!$F$6
Name Rates: [1]Settings!$C$2:$C$7
Name YesNo: [1]Settings!$C$15:$C$16

Sheet Tour Dates
A1: Tour Dates
A3: Date | B3: City | C3: STATE | D3: VENUE | E3: Country
A4: 46043 | B4: ORLANDO | C4: FL | D4: KIA CENTER | E4: USA
A5: 46044 | B5: JACKSONVILLE | C5: FL | D5: VYSTAR MEMORIAL ARENA | E5: USA
A6: 46046 | B6: KNOXVILLE | C6: TN | D6: THOMPSON-BOLING ARENA | E6: USA
A7: 46047 | B7: CHARLOTTE | C7: NC | D7: SPECTRUM CENTER | E7: USA
A8: 46048 | B8: GREENVILLE | C8: SC | D8: BON SECOURS ARENA | E8: USA
A9: 46050 | B9: UNCASVILLE | C9: CT | D9: MOHEGAN SUN ARENA | E9: USA
A10: 46052 | B10: MONTREAL | C10: QC | D10: BELL CENTRE | E10: CANADA
A11: 46053 | B11: TORONTO | C11: ON | D11: SCOTIABANK ARENA | E11: CANADA
A12: 46055 | B12: COLUMBUS | C12: OH | D12: NATIONWIDE ARENA | E12: USA
A13: 46057 | B13: CINCINNATI | C13: OH | D13: HERITAGE BANK CENTER | E13: USA
A14: 46058 | B14: PEORIA | C14: IL | D14: CIVIC CENTER ARENA | E14: USA
A15: 46060 | B15: TULSA | C15: OK | D15: BOK CENTER | E15: USA
... A23: 46076 | B23: INGLEWOOD | C23: CA | D23: INTUIT DOME | E23: USA

Sheet Inventory
B1: Tour Inventory
B3: Tour | C3: GHOST | D3: GARMENTS x 50 | E3: TRINKETS X 50
B4: Tour Date | C4: JAN-FEB 2026
B5: Formula | E5: Formula | F5: Formula | G5: Formula | J5: QUICK STOCK VIEW | R5: PRODUCT SUMMARY
B6: BC Item Code | C6: Product Description | D6: Supplier | E6: Blank Unit Cost | F6: Print Unit Cost | G6: Full Package | H6: Total Unit Cost | J6: Sales | K6: Used | L6: Road | M6: Ware house | N6: Sales % | P6: End Tour Stock Count | R6: B/F | S6: Purchased | T6: Sold | U6: W/S | V6: Band Comps | W6: GMS Comps | X6: O/U | Y6: Retail | Z6: Web | AA6: Global UK | AB6: Other | AC6: Misprint | AD6: Closing Stock | AE6: Closing Stock
A7: 1 | B7: GHOSNS903311BK | C7: BATWING HOODY | D7: FARSTAR | E7: =VLOOKUP($A:$A,'COG NA'!$A:$G,5,FALSE) -> 0 | F7: =VLOOKUP($A:$A,'COG NA'!$A:$G,6,FALSE) -> 0 | G7: =VLOOKUP($A:$A,'COG NA'!$A:$G,7,FALSE) -> 28.5 | H7: =SUM(E7:G7) -> 28.5 | J7: ='BATWNG HOODY'!$C$64 -> 0 | K7: ='BATWNG HOODY'!$G$64 -> 0 | L7: ='BATWNG HOODY'!$L$64 -> 3667 | M7: ='BATWNG HOODY'!$S$64 -> 3746 | N7: ='BATWNG HOODY'!$M$64 -> 0 | R7: ='BATWNG HOODY'!$V$39 -> 0 | S7: ='BATWNG HOODY'!$V$40 -> 6240 | T7: ='BATWNG HOODY'!$V$41 -> 0 | U7: ='BATWNG HOODY'!$V$44 -> 0 | V7: ='BATWNG HOODY'!$V$42 -> 0 | W7: ='BATWNG HOODY'!$V$43 -> 0 | X7: ='BATWNG HOODY'!$V$46 -> 0 | Y7: ='BATWNG HOODY'!$V$47 -> 0 | Z7: ='BATWNG HOODY'!$V$48 -> 0 | AA7: ='BATWNG HOODY'!$V$49 -> 0 | AB7: ='BATWNG HOODY'!$V$50 -> 2494 | AC7: ='BATWNG HOODY'!$V$51 -> 0 | AD7: ='BATWNG HOODY'!V$52+'BATWNG HOODY'!V$53 -> 3746 | AE7: =(R7+S7)-SUM(T7:AC7) -> 3746
A8: 2 | B8: GHOSRX203275BK | C8: SHORTS BLACK/ WHT PAPA V COSTUME CLAWS | D8: FARSTAR | E8: =VLOOKUP($A:$A,'COG NA'!$A:$G,5,FALSE) -> 0 | F8: =VLOOKUP($A:$A,'COG NA'!$A:$G,6,FALSE) -> 0 | G8: =VLOOKUP($A:$A,'COG NA'!$A:$G,7,FALSE) -> 5.8 | H8: =SUM(E8:G8) -> 5.8 | J8: =SHORTS!$C$64 -> 0 | K8: =SHORTS!$G$64 -> 0 | L8: =SHORTS!$L$64 -> 5358 | M8: =SHORTS!$S$64 -> 4652 | N8: =SHORTS!$M$64 -> 0 | R8: =SHORTS!$V$39 -> 706 | S8: =SHORTS!$V$40 -> 4652 | T8: =SHORTS!$V$41 -> 0 | U8: =SHORTS!$V$44 -> 0 | V8: =SHORTS!$V$42 -> 0 | W8: =SHORTS!$V$43 -> 0 | X8: =SHORTS!$V$46 -> 0 | Y8: =SHORTS!$V$47 -> 0 | Z8: =SHORTS!$V$48 -> 0 | AA8: =SHORTS!$V$49 -> 0 | AB8: =SHORTS!$V$50 -> 0 | AC8: =SHORTS!$V$51 -> 0 | AD8: =SHORTS!V$52+SHORTS!V$53 -> 5358 | AE8: =(R8+S8)-SUM(T8:AC8) -> 5358
A9: 3 | B9: =VLOOKUP(A:A,'COG NA'!A:B,2,FALSE) -> GHOSRX204001BK | C9: =VLOOKUP(B:B,'COG NA'!B:C,2,FALSE) -> BLACK T SKELETOUR 26 ITIN | D9: CULTURE | E9: =VLOOKUP($A:$A,'COG NA'!$A:$G,5,FALSE) -> 0 | F9: =VLOOKUP($A:$A,'COG NA'!$A:$G,6,FALSE) -> 0 | G9: =VLOOKUP($A:$A,'COG NA'!$A:$G,7,FALSE) -> 5.83 | H9: =SUM(E9:G9) -> 5.83 | J9: ='BLK T SKELETOR ITIN'!$C$64 -> 0 | K9: ='BLK T SKELETOR ITIN'!$G$64 -> 0 | L9: ='BLK T SKELETOR ITIN'!$L$64 -> 0 | M9: ='BLK T SKELETOR ITIN'!$S$64 -> 0 | N9: ='BLK T SKELETOR ITIN'!$M$64 -> 0 | R9: ='BLK T SKELETOR ITIN'!$V$39 -> 0 | S9: ='BLK T SKELETOR ITIN'!$V$40 -> 0 | T9: ='BLK T SKELETOR ITIN'!$V$41 -> 0 | U9: ='BLK T SKELETOR ITIN'!$V$44 -> 0 | V9: ='BLK T SKELETOR ITIN'!$V$42 -> 0 | W9: ='BLK T SKELETOR ITIN'!$V$43 -> 0 | X9: ='BLK T SKELETOR ITIN'!$V$46 -> 0 | Y9: ='BLK T SKELETOR ITIN'!$V$47 -> 0 | Z9: ='BLK T SKELETOR ITIN'!$V$48 -> 0 | AA9: ='BLK T SKELETOR ITIN'!$V$49 -> 0 | AB9: ='BLK T SKELETOR ITIN'!$V$50 -> 0 | AC9: ='BLK T SKELETOR ITIN'!$V$51 -> 0 | AD9: ='BLK T SKELETOR ITIN'!V$52+'BLK T SKELETOR ITIN'!V$53 -> 0 | AE9: =(R9+S9)-SUM(T9:AC9) -> 0
A10: 4 | B10: =VLOOKUP(A:A,'COG NA'!A:B,2,FALSE) -> GHOSRX204000BK | C10: =VLOOKUP(B:B,'COG NA'!B:C,2,FALSE) -> BLACK T BAT BRAIN 26 ITIN | D10: CULTURE | E10: =VLOOKUP($A:$A,'COG NA'!$A:$G,5,FALSE) -> 0 | F10: =VLOOKUP($A:$A,'COG NA'!$A:$G,6,FALSE) -> 0 | G10: =VLOOKUP($A:$A,'COG NA'!$A:$G,7,FALSE) -> 5.83 | H10: =SUM(E10:G10) -> 5.83 | J10: ='BLK T BAT BRAIN ITIN'!$C$64 -> 0 | K10: ='BLK T BAT BRAIN ITIN'!$G$64 -> 0 | L10: ='BLK T BAT BRAIN ITIN'!$L$64 -> 0 | M10: ='BLK T BAT BRAIN ITIN'!$S$64 -> 0 | N10: ='BLK T BAT BRAIN ITIN'!$M$64 -> 0 | R10: ='BLK T BAT BRAIN ITIN'!$V$39 -> 0 | S10: ='BLK T BAT BRAIN ITIN'!$V$40 -> 0 | T10: ='BLK T BAT BRAIN ITIN'!$V$41 -> 0 | U10: ='BLK T BAT BRAIN ITIN'!$V$44 -> 0 | V10: ='BLK T BAT BRAIN ITIN'!$V$42 -> 0 | W10: ='BLK T BAT BRAIN ITIN'!$V$43 -> 0 | X10: ='BLK T BAT BRAIN ITIN'!$V$46 -> 0 | Y10: ='BLK T BAT BRAIN ITIN'!$V$47 -> 0 | Z10: ='BLK T BAT BRAIN ITIN'!$V$48 -> 0 | AA10: ='BLK T BAT BRAIN ITIN'!$V$49 -> 0 | AB10: ='BLK T BAT BRAIN ITIN'!$V$50 -> 0 | AC10: ='BLK T BAT BRAIN ITIN'!$V$51 -> 0 | AD10: ='BLK T BAT BRAIN ITIN'!V$52+'BLK T BAT BRAIN ITIN'!V$53 -> 0 | AE10: =(R10+S10)-SUM(T10:AC10) -> 0
A11: 5 | B11: =VLOOKUP(A:A,'COG NA'!A:B,2,FALSE) -> GHOSRX204002BK | C11: =VLOOKUP(B:B,'COG NA'!B:C,2,FALSE) -> BLACK T WESTERN EMERITUS 26 ITIN | D11: CULTURE | E11: =VLOOKUP($A:$A,'COG NA'!$A:$G,5,FALSE) -> 0 | F11: =VLOOKUP($A:$A,'COG NA'!$A:$G,6,FALSE) -> 0 | G11: =VLOOKUP($A:$A,'COG NA'!$A:$G,7,FALSE) -> 5.83 | H11: =SUM(E11:G11) -> 5.83 | J11: ='BLK T WESTERN ITIN'!$C$64 -> 0 | K11: ='BLK T WESTERN ITIN'!$G$64 -> 0 | L11: ='BLK T WESTERN ITIN'!$L$64 -> 0 | M11: ='BLK T WESTERN ITIN'!$S$64 -> 0 | N11: ='BLK T WESTERN ITIN'!$M$64 -> 0 | R11: ='BLK T WESTERN ITIN'!$V$39 -> 0 | S11: ='BLK T WESTERN ITIN'!$V$40 -> 0 | T11: ='BLK T WESTERN ITIN'!$V$41 -> 0 | U11: ='BLK T WESTERN ITIN'!$V$44 -> 0 | V11: ='BLK T WESTERN ITIN'!$V$42 -> 0 | W11: ='BLK T WESTERN ITIN'!$V$43 -> 0 | X11: ='BLK T WESTERN ITIN'!$V$46 -> 0 | Y11: ='BLK T WESTERN ITIN'!$V$47 -> 0 | Z11: ='BLK T WESTERN ITIN'!$V$48 -> 0 | AA11: ='BLK T WESTERN ITIN'!$V$49 -> 0 | AB11: ='BLK T WESTERN ITIN'!$V$50 -> 0 | AC11: ='BLK T WESTERN ITIN'!$V$51 -> 0 | AD11: ='BLK T WESTERN ITIN'!V$52+'BLK T WESTERN ITIN'!V$53 -> 0 | AE11: =(R11+S11)-SUM(T11:AC11) -> 0
A12: 6 | B12: =VLOOKUP(A:A,'COG NA'!A:B,2,FALSE) -> GHOSRX103437OT | C12: =VLOOKUP(B:B,'COG NA'!B:C,2,FALSE) -> CRYSTAL WASHED T AT THE GATES | D12: CULTURE | E12: =VLOOKUP($A:$A,'COG NA'!$A:$G,5,FALSE) -> 0 | F12: =VLOOKUP($A:$A,'COG NA'!$A:$G,6,FALSE) -> 0 | G12: =VLOOKUP($A:$A,'COG NA'!$A:$G,7,FALSE) -> 8.71 | H12: =SUM(E12:G12) -> 8.71 | J12: ='CRYSTAL WASHED'!$C$64 -> 0 | K12: ='CRYSTAL WASHED'!$G$64 -> 0 | L12: ='CRYSTAL WASHED'!$L$64 -> 0 | M12: ='CRYSTAL WASHED'!$S$64 -> 0 | N12: ='CRYSTAL WASHED'!$M$64 -> 0 | R12: ='CRYSTAL WASHED'!$V$39 -> 0 | S12: ='CRYSTAL WASHED'!$V$40 -> 0 | T12: ='CRYSTAL WASHED'!$V$41 -> 0 | U12: ='CRYSTAL WASHED'!$V$44 -> 0 | V12: ='CRYSTAL WASHED'!$V$42 -> 0 | W12: ='CRYSTAL WASHED'!$V$43 -> 0 | X12: ='CRYSTAL WASHED'!$V$46 -> 0 | Y12: ='CRYSTAL WASHED'!$V$47 -> 0 | Z12: ='CRYSTAL WASHED'!$V$48 -> 0 | AA12: ='CRYSTAL WASHED'!$V$49 -> 0 | AB12: ='CRYSTAL WASHED'!$V$50 -> 0 | AC12: ='CRYSTAL WASHED'!$V$51 -> 0 | AD12: ='CRYSTAL WASHED'!V$52+'CRYSTAL WASHED'!V$53 -> 0 | AE12: =(R12+S12)-SUM(T12:AC12) -> 0
A13: 7 | B13: =VLOOKUP(A:A,'COG NA'!A:B,2,FALSE) -> GHOSRX103998BK | C13: =VLOOKUP(B:B,'COG NA'!B:C,2,FALSE) -> BLACK T PAPA COOPER | D13: GAVINA | E13: =VLOOKUP($A:$A,'COG NA'!$A:$G,5,FALSE) -> 0 | F13: =VLOOKUP($A:$A,'COG NA'!$A:$G,6,FALSE) -> 0 | G13: =VLOOKUP($A:$A,'COG NA'!$A:$G,7,FALSE) -> 0 | H13: =SUM(E13:G13) -> 0 | J13: ='BLK T PAPA COOPER'!$C$64 -> 0 | K13: ='BLK T PAPA COOPER'!$G$64 -> 0 | L13: ='BLK T PAPA COOPER'!$L$64 -> 0 | M13: ='BLK T PAPA COOPER'!$S$64 -> 0 | N13: ='BLK T PAPA COOPER'!$M$64 -> 0 | R13: ='BLK T PAPA COOPER'!$V$39 -> 0 | S13: ='BLK T PAPA COOPER'!$V$40 -> 0 | T13: ='BLK T PAPA COOPER'!$V$41 -> 0 | U13: ='BLK T PAPA COOPER'!$V$44 -> 0 | V13: ='BLK T PAPA COOPER'!$V$42 -> 0 | W13: ='BLK T PAPA COOPER'!$V$43 -> 0 | X13: ='BLK T PAPA COOPER'!$V$46 -> 0 | Y13: ='BLK T PAPA COOPER'!$V$47 -> 0 | Z13: ='BLK T PAPA COOPER'!$V$48 -> 0 | AA13: ='BLK T PAPA COOPER'!$V$49 -> 0 | AB13: ='BLK T PAPA COOPER'!$V$50 -> 0 | AC13: ='BLK T PAPA COOPER'!$V$51 -> 0 | AD13: ='BLK T PAPA COOPER'!V$52+'BLK T PAPA COOPER'!V$53 -> 0 | AE13: =(R13+S13)-SUM(T13:AC13) -> 0
A14: 8 | B14: =VLOOKUP(A:A,'COG NA'!A:B,2,FALSE) -> GHOSRX103999OT | C14: =VLOOKUP(B:B,'COG NA'!B:C,2,FALSE) -> WOMENS CROP RAGLAN CHAMBER OF CHILLS | D14: GAVINA | E14: =VLOOKUP($A:$A,'COG NA'!$A:$G,5,FALSE) -> 9.05 | F14: =VLOOKUP($A:$A,'COG NA'!$A:$G,6,FALSE) -> 1.45 | G14: =VLOOKUP($A:$A,'COG NA'!$A:$G,7,FALSE) -> 0 | H14: =SUM(E14:G14) -> 10.5 | J14: ='WOMENS RAGLAN'!$C$64 -> 0 | K14: ='WOMENS RAGLAN'!$G$64 -> 0 | L14: ='WOMENS RAGLAN'!$L$64 -> 0 | M14: ='WOMENS RAGLAN'!$S$64 -> 0 | N14: ='WOMENS RAGLAN'!$M$64 -> 0 | R14: ='WOMENS RAGLAN'!$V$39 -> 0 | S14: ='WOMENS RAGLAN'!$V$40 -> 0 | T14: ='WOMENS RAGLAN'!$V$41 -> 0 | U14: ='WOMENS RAGLAN'!$V$44 -> 0 | V14: ='WOMENS RAGLAN'!$V$42 -> 0 | W14: ='WOMENS RAGLAN'!$V$43 -> 0 | X14: ='WOMENS RAGLAN'!$V$46 -> 0 | Y14: ='WOMENS RAGLAN'!$V$47 -> 0 | Z14: ='WOMENS RAGLAN'!$V$48 -> 0 | AA14: ='WOMENS RAGLAN'!$V$49 -> 0 | AB14: ='WOMENS RAGLAN'!$V$50 -> 0 | AC14: ='WOMENS RAGLAN'!$V$51 -> 0 | AD14: ='WOMENS RAGLAN'!V$52+'WOMENS RAGLAN'!V$53 -> 0 | AE14: =(R14+S14)-SUM(T14:AC14) -> 0
A15: 9 | B15: =VLOOKUP(A:A,'COG NA'!A:B,2,FALSE) -> GHOSRX203401BK | C15: =VLOOKUP(B:B,'COG NA'!B:C,2,FALSE) -> BLACK PO HOODIE SKELETON | D15: GAVINA | E15: =VLOOKUP($A:$A,'COG NA'!$A:$G,5,FALSE) -> 8.25 | F15: =VLOOKUP($A:$A,'COG NA'!$A:$G,6,FALSE) -> 2.95 | G15: =VLOOKUP($A:$A,'COG NA'!$A:$G,7,FALSE) -> 0 | H15: =SUM(E15:G15) -> 11.2 | J15: ='BLK PO HOODIE'!$C$64 -> 0 | K15: ='BLK PO HOODIE'!$G$64 -> 0 | L15: ='BLK PO HOODIE'!$L$64 -> 0 | M15: ='BLK PO HOODIE'!$S$64 -> 0 | N15: ='BLK PO HOODIE'!$M$64 -> 0 | R15: ='BLK PO HOODIE'!$V$39 -> 0 | S15: ='BLK PO HOODIE'!$V$40 -> 0 | T15: ='BLK PO HOODIE'!$V$41 -> 0 | U15: ='BLK PO HOODIE'!$V$44 -> 0 | V15: ='BLK PO HOODIE'!$V$42 -> 0 | W15: ='BLK PO HOODIE'!$V$43 -> 0 | X15: ='BLK PO HOODIE'!$V$46 -> 0 | Y15: ='BLK PO HOODIE'!$V$47 -> 0 | Z15: ='BLK PO HOODIE'!$V$48 -> 0 | AA15: ='BLK PO HOODIE'!$V$49 -> 0 | AB15: ='BLK PO HOODIE'!$V$50 -> 0 | AC15: ='BLK PO HOODIE'!$V$51 -> 0 | AD15: ='BLK PO HOODIE'!V$52+'BLK PO HOODIE'!V$53 -> 0 | AE15: =(R15+S15)-SUM(T15:AC15) -> 0
A16: 10 | B16: =VLOOKUP(A:A,'COG NA'!A:B,2,FALSE) -> 0 | E16: =VLOOKUP($A:$A,'COG NA'!$A:$G,5,FALSE) -> 0 | F16: =VLOOKUP($A:$A,'COG NA'!$A:$G,6,FALSE) -> 0 | G16: =VLOOKUP($A:$A,'COG NA'!$A:$G,7,FALSE) -> 0 | H16: =SUM(E16:G16) -> 0 | J16: ='10'!$C$64 -> 0 | K16: ='10'!$G$64 -> 0 | L16: ='10'!$L$64 -> 0 | M16: ='10'!$S$64 -> 0 | N16: ='10'!$M$64 -> 0 | R16: ='10'!$V$39 -> 0 | S16: ='10'!$V$40 -> 0 | T16: ='10'!$V$41 -> 0 | U16: ='10'!$V$44 -> 0 | V16: ='10'!$V$42 -> 0 | W16: ='10'!$V$43 -> 0 | X16: ='10'!$V$46 -> 0 | Y16: ='10'!$V$47 -> 0 | Z16: ='10'!$V$48 -> 0 | AA16: ='10'!$V$49 -> 0 | AB16: ='10'!$V$50 -> 0 | AC16: ='10'!$V$51 -> 0 | AD16: ='10'!V$52+'10'!V$53 -> 0 | AE16: =(R16+S16)-SUM(T16:AC16) -> 0
A17: 11 | B17: =VLOOKUP(A:A,'COG NA'!A:B,2,FALSE) -> 0 | E17: =VLOOKUP($A:$A,'COG NA'!$A:$G,5,FALSE) -> 0 | F17: =VLOOKUP($A:$A,'COG NA'!$A:$G,6,FALSE) -> 0 | G17: =VLOOKUP($A:$A,'COG NA'!$A:$G,7,FALSE) -> 0 | H17: =SUM(E17:G17) -> 0 | J17: ='11'!$C$64 -> 0 | K17: ='11'!$G$64 -> 0 | L17: ='11'!$L$64 -> 0 | M17: ='11'!$S$64 -> 0 | N17: ='11'!$M$64 -> 0 | R17: ='11'!$V$39 -> 0 | S17: ='11'!$V$40 -> 0 | T17: ='11'!$V$41 -> 0 | U17: ='11'!$V$44 -> 0 | V17: ='11'!$V$42 -> 0 | W17: ='11'!$V$43 -> 0 | X17: ='11'!$V$46 -> 0 | Y17: ='11'!$V$47 -> 0 | Z17: ='11'!$V$48 -> 0 | AA17: ='11'!$V$49 -> 0 | AB17: ='11'!$V$50 -> 0 | AC17: ='11'!$V$51 -> 0 | AD17: ='11'!V$52+'11'!V$53 -> 0 | AE17: =(R17+S17)-SUM(T17:AC17) -> 0
A18: 12 | B18: =VLOOKUP(A:A,'COG NA'!A:B,2,FALSE) -> 0 | E18: =VLOOKUP($A:$A,'COG NA'!$A:$G,5,FALSE) -> 0 | F18: =VLOOKUP($A:$A,'COG NA'!$A:$G,6,FALSE) -> 0 | G18: =VLOOKUP($A:$A,'COG NA'!$A:$G,7,FALSE) -> 0 | H18: =SUM(E18:G18) -> 0 | J18: ='12'!$C$64 -> 0 | K18: ='12'!$G$64 -> 0 | L18: ='12'!$L$64 -> 0 | M18: ='12'!$S$64 -> 0 | N18: ='12'!$M$64 -> 0 | R18: ='12'!$V$39 -> 0 | S18: ='12'!$V$40 -> 0 | T18: ='12'!$V$41 -> 0 | U18: ='12'!$V$44 -> 0 | V18: ='12'!$V$42 -> 0 | W18: ='12'!$V$43 -> 0 | X18: ='12'!$V$46 -> 0 | Y18: ='12'!$V$47 -> 0 | Z18: ='12'!$V$48 -> 0 | AA18: ='12'!$V$49 -> 0 | AB18: ='12'!$V$50 -> 0 | AC18: ='12'!$V$51 -> 0 | AD18: ='12'!V$52+'12'!V$53 -> 0 | AE18: =(R18+S18)-SUM(T18:AC18) -> 0
A19: 13 | B19: =VLOOKUP(A:A,'COG NA'!A:B,2,FALSE) -> 0 | E19: =VLOOKUP($A:$A,'COG NA'!$A:$G,5,FALSE) -> 0 | F19: =VLOOKUP($A:$A,'COG NA'!$A:$G,6,FALSE) -> 0 | G19: =VLOOKUP($A:$A,'COG NA'!$A:$G,7,FALSE) -> 0 | H19: =SUM(E19:G19) -> 0 | J19: ='13'!$C$64 -> 0 | K19: ='13'!$G$64 -> 0 | L19: ='13'!$L$64 -> 0 | M19: ='13'!$S$64 -> 0 | N19: ='13'!$M$64 -> 0 | R19: ='13'!$V$39 -> 0 | S19: ='13'!$V$40 -> 0 | T19: ='13'!$V$41 -> 0 | U19: ='13'!$V$44 -> 0 | V19: ='13'!$V$42 -> 0 | W19: ='13'!$V$43 -> 0 | X19: ='13'!$V$46 -> 0 | Y19: ='13'!$V$47 -> 0 | Z19: ='13'!$V$48 -> 0 | AA19: ='13'!$V$49 -> 0 | AB19: ='13'!$V$50 -> 0 | AC19: ='13'!$V$51 -> 0 | AD19: ='13'!V$52+'13'!V$53 -> 0 | AE19: =(R19+S19)-SUM(T19:AC19) -> 0
A20: 14 | B20: =VLOOKUP(A:A,'COG NA'!A:B,2,FALSE) -> 0 | E20: =VLOOKUP($A:$A,'COG NA'!$A:$G,5,FALSE) -> 0 | F20: =VLOOKUP($A:$A,'COG NA'!$A:$G,6,FALSE) -> 0 | G20: =VLOOKUP($A:$A,'COG NA'!$A:$G,7,FALSE) -> 0 | H20: =SUM(E20:G20) -> 0 | J20: ='14'!$C$64 -> 0 | K20: ='14'!$G$64 -> 0 | L20: ='14'!$L$64 -> 0 | M20: ='14'!$S$64 -> 0 | N20: ='14'!$M$64 -> 0 | R20: ='14'!$V$39 -> 0 | S20: ='14'!$V$40 -> 0 | T20: ='14'!$V$41 -> 0 | U20: ='14'!$V$44 -> 0 | V20: ='14'!$V$42 -> 0 | W20: ='14'!$V$43 -> 0 | X20: ='14'!$V$46 -> 0 | Y20: ='14'!$V$47 -> 0 | Z20: ='14'!$V$48 -> 0 | AA20: ='14'!$V$49 -> 0 | AB20: ='14'!$V$50 -> 0 | AC20: ='14'!$V$51 -> 0 | AD20: ='14'!V$52+'14'!V$53 -> 0 | AE20: =(R20+S20)-SUM(T20:AC20) -> 0
A21: 15 | B21: =VLOOKUP(A:A,'COG NA'!A:B,2,FALSE) -> 0 | E21: =VLOOKUP($A:$A,'COG NA'!$A:$G,5,FALSE) -> 0 | F21: =VLOOKUP($A:$A,'COG NA'!$A:$G,6,FALSE) -> 0 | G21: =VLOOKUP($A:$A,'COG NA'!$A:$G,7,FALSE) -> 0 | H21: =SUM(E21:G21) -> 0 | J21: ='15'!$C$64 -> 0 | K21: ='15'!$G$64 -> 0 | L21: ='15'!$L$64 -> 0 | M21: ='15'!$S$64 -> 0 | N21: ='15'!$M$64 -> 0 | R21: ='15'!$V$39 -> 0 | S21: ='15'!$V$40 -> 0 | T21: ='15'!$V$41 -> 0 | U21: ='15'!$V$44 -> 0 | V21: ='15'!$V$42 -> 0 | W21: ='15'!$V$43 -> 0 | X21: ='15'!$V$46 -> 0 | Y21: ='15'!$V$47 -> 0 | Z21: ='15'!$V$48 -> 0 | AA21: ='15'!$V$49 -> 0 | AB21: ='15'!$V$50 -> 0 | AC21: ='15'!$V$51 -> 0 | AD21: ='15'!V$52+'15'!V$53 -> 0 | AE21: =(R21+S21)-SUM(T21:AC21) -> 0
A22: 16 | B22: =VLOOKUP(A:A,'COG NA'!A:B,2,FALSE) -> 0 | E22: =VLOOKUP($A:$A,'COG NA'!$A:$G,5,FALSE) -> 0 | F22: =VLOOKUP($A:$A,'COG NA'!$A:$G,6,FALSE) -> 0 | G22: =VLOOKUP($A:$A,'COG NA'!$A:$G,7,FALSE) -> 0 | H22: =SUM(E22:G22) -> 0 | J22: ='16'!$C$64 -> 0 | K22: ='16'!$G$64 -> 0 | L22: ='16'!$L$64 -> 0 | M22: ='16'!$S$64 -> 0 | N22: ='16'!$M$64 -> 0 | R22: ='16'!$V$39 -> 0 | S22: ='16'!$V$40 -> 0 | T22: ='16'!$V$41 -> 0 | U22: ='16'!$V$44 -> 0 | V22: ='16'!$V$42 -> 0 | W22: ='16'!$V$43 -> 0 | X22: ='16'!$V$46 -> 0 | Y22: ='16'!$V$47 -> 0 | Z22: ='16'!$V$48 -> 0 | AA22: ='16'!$V$49 -> 0 | AB22: ='16'!$V$50 -> 0 | AC22: ='16'!$V$51 -> 0 | AD22: ='16'!V$52+'16'!V$53 -> 0 | AE22: =(R22+S22)-SUM(T22:AC22) -> 0
A23: 17 | B23: =VLOOKUP(A:A,'COG NA'!A:B,2,FALSE) -> 0 | E23: =VLOOKUP($A:$A,'COG NA'!$A:$G,5,FALSE) -> 0 | F23: =VLOOKUP($A:$A,'COG NA'!$A:$G,6,FALSE) -> 0 | G23: =VLOOKUP($A:$A,'COG NA'!$A:$G,7,FALSE) -> 0 | H23: =SUM(E23:G23) -> 0 | J23: ='17'!$C$64 -> 0 | K23: ='17'!$G$64 -> 0 | L23: ='17'!$L$64 -> 0 | M23: ='17'!$S$64 -> 0 | N23: ='17'!$M$64 -> 0 | R23: ='17'!$V$39 -> 0 | S23: ='17'!$V$40 -> 0 | T23: ='17'!$V$41 -> 0 | U23: ='17'!$V$44 -> 0 | V23: ='17'!$V$42 -> 0 | W23: ='17'!$V$43 -> 0 | X23: ='17'!$V$46 -> 0 | Y23: ='17'!$V$47 -> 0 | Z23: ='17'!$V$48 -> 0 | AA23: ='17'!$V$49 -> 0 | AB23: ='17'!$V$50 -> 0 | AC23: ='17'!$V$51 -> 0 | AD23: ='17'!V$52+'17'!V$53 -> 0 | AE23: =(R23+S23)-SUM(T23:AC23) -> 0
A24: 18 | B24: =VLOOKUP(A:A,'COG NA'!A:B,2,FALSE) -> 0 | E24: =VLOOKUP($A:$A,'COG NA'!$A:$G,5,FALSE) -> 0 | F24: =VLOOKUP($A:$A,'COG NA'!$A:$G,6,FALSE) -> 0 | G24: =VLOOKUP($A:$A,'COG NA'!$A:$G,7,FALSE) -> 0 | H24: =SUM(E24:G24) -> 0 | J24: ='18'!$C$64 -> 0 | K24: ='18'!$G$64 -> 0 | L24: ='18'!$L$64 -> 0 | M24: ='18'!$S$64 -> 0 | N24: ='18'!$M$64 -> 0 | R24: ='18'!$V$39 -> 0 | S24: ='18'!$V$40 -> 0 | T24: ='18'!$V$41 -> 0 | U24: ='18'!$V$44 -> 0 | V24: ='18'!$V$42 -> 0 | W24: ='18'!$V$43 -> 0 | X24: ='18'!$V$46 -> 0 | Y24: ='18'!$V$47 -> 0 | Z24: ='18'!$V$48 -> 0 | AA24: ='18'!$V$49 -> 0 | AB24: ='18'!$V$50 -> 0 | AC24: ='18'!$V$51 -> 0 | AD24: ='18'!V$52+'18'!V$53 -> 0 | AE24: =(R24+S24)-SUM(T24:AC24) -> 0
A25: 19 | B25: =VLOOKUP(A:A,'COG NA'!A:B,2,FALSE) -> 0 | E25: =VLOOKUP($A:$A,'COG NA'!$A:$G,5,FALSE) -> 0 | F25: =VLOOKUP($A:$A,'COG NA'!$A:$G,6,FALSE) -> 0 | G25: =VLOOKUP($A:$A,'COG NA'!$A:$G,7,FALSE) -> 0 | H25: =SUM(E25:G25) -> 0 | J25: ='19'!$C$64 -> 0 | K25: ='19'!$G$64 -> 0 | L25: ='19'!$L$64 -> 0 | M25: ='19'!$S$64 -> 0 | N25: ='19'!$M$64 -> 0 | R25: ='19'!$V$39 -> 0 | S25: ='19'!$V$40 -> 0 | T25: ='19'!$V$41 -> 0 | U25: ='19'!$V$44 -> 0 | V25: ='19'!$V$42 -> 0 | W25: ='19'!$V$43 -> 0 | X25: ='19'!$V$46 -> 0 | Y25: ='19'!$V$47 -> 0 | Z25: ='19'!$V$48 -> 0 | AA25: ='19'!$V$49 -> 0 | AB25: ='19'!$V$50 -> 0 | AC25: ='19'!$V$51 -> 0 | AD25: ='19'!V$52+'19'!V$53 -> 0 | AE25: =(R25+S25)-SUM(T25:AC25) -> 0
A26: 20 | B26: =VLOOKUP(A:A,'COG NA'!A:B,2,FALSE) -> 0 | E26: =VLOOKUP($A:$A,'COG NA'!$A:$G,5,FALSE) -> 0 | F26: =VLOOKUP($A:$A,'COG NA'!$A:$G,6,FALSE) -> 0 | G26: =VLOOKUP($A:$A,'COG NA'!$A:$G,7,FALSE) -> 0 | H26: =SUM(E26:G26) -> 0 | J26: ='20'!$C$64 -> 0 | K26: ='20'!$G$64 -> 0 | L26: ='20'!$L$64 -> 0 | M26: ='20'!$S$64 -> 0 | N26: ='20'!$M$64 -> 0 | R26: ='20'!$V$39 -> 0 | S26: ='20'!$V$40 -> 0 | T26: ='20'!$V$41 -> 0 | U26: ='20'!$V$44 -> 0 | V26: ='20'!$V$42 -> 0 | W26: ='20'!$V$43 -> 0 | X26: ='20'!$V$46 -> 0 | Y26: ='20'!$V$47 -> 0 | Z26: ='20'!$V$48 -> 0 | AA26: ='20'!$V$49 -> 0 | AB26: ='20'!$V$50 -> 0 | AC26: ='20'!$V$51 -> 0 | AD26: ='20'!V$52+'20'!V$53 -> 0 | AE26: =(R26+S26)-SUM(T26:AC26) -> 0
A27: 21 | B27: =VLOOKUP(A:A,'COG NA'!A:B,2,FALSE) -> 0 | E27: =VLOOKUP($A:$A,'COG NA'!$A:$G,5,FALSE) -> 0 | F27: =VLOOKUP($A:$A,'COG NA'!$A:$G,6,FALSE) -> 0 | G27: =VLOOKUP($A:$A,'COG NA'!$A:$G,7,FALSE) -> 0 | H27: =SUM(E27:G27) -> 0 | J27: ='21'!$C$64 -> 0 | K27: ='21'!$G$64 -> 0 | L27: ='21'!$L$64 -> 0 | M27: ='21'!$S$64 -> 0 | N27: ='21'!$M$64 -> 0 | R27: ='21'!$V$39 -> 0 | S27: ='21'!$V$40 -> 0 | T27: ='21'!$V$41 -> 0 | U27: ='21'!$V$44 -> 0 | V27: ='21'!$V$42 -> 0 | W27: ='21'!$V$43 -> 0 | X27: ='21'!$V$46 -> 0 | Y27: ='21'!$V$47 -> 0 | Z27: ='21'!$V$48 -> 0 | AA27: ='21'!$V$49 -> 0 | AB27: ='21'!$V$50 -> 0 | AC27: ='21'!$V$51 -> 0 | AD27: ='21'!V$52+'21'!V$53 -> 0 | AE27: =(R27+S27)-SUM(T27:AC27) -> 0
A28: 22 | B28: =VLOOKUP(A:A,'COG NA'!A:B,2,FALSE) -> 0 | E28: =VLOOKUP($A:$A,'COG NA'!$A:$G,5,FALSE) -> 0 | F28: =VLOOKUP($A:$A,'COG NA'!$A:$G,6,FALSE) -> 0 | G28: =VLOOKUP($A:$A,'COG NA'!$A:$G,7,FALSE) -> 0 | H28: =SUM(E28:G28) -> 0 | J28: ='22'!$C$64 -> 0 | K28: ='22'!$G$64 -> 0 | L28: ='22'!$L$64 -> 0 | M28: ='22'!$S$64 -> 0 | N28: ='22'!$M$64 -> 0 | R28: ='22'!$V$39 -> 0 | S28: ='22'!$V$40 -> 0 | T28: ='22'!$V$41 -> 0 | U28: ='22'!$V$44 -> 0 | V28: ='22'!$V$42 -> 0 | W28: ='22'!$V$43 -> 0 | X28: ='22'!$V$46 -> 0 | Y28: ='22'!$V$47 -> 0 | Z28: ='22'!$V$48 -> 0 | AA28: ='22'!$V$49 -> 0 | AB28: ='22'!$V$50 -> 0 | AC28: ='22'!$V$51 -> 0 | AD28: ='22'!V$52+'22'!V$53 -> 0 | AE28: =(R28+S28)-SUM(T28:AC28) -> 0
A29: 23 | B29: =VLOOKUP(A:A,'COG NA'!A:B,2,FALSE) -> 0 | E29: =VLOOKUP($A:$A,'COG NA'!$A:$G,5,FALSE) -> 0 | F29: =VLOOKUP($A:$A,'COG NA'!$A:$G,6,FALSE) -> 0 | G29: =VLOOKUP($A:$A,'COG NA'!$A:$G,7,FALSE) -> 0 | H29: =SUM(E29:G29) -> 0 | J29: ='23'!$C$64 -> 0 | K29: ='23'!$G$64 -> 0 | L29: ='23'!$L$64 -> 0 | M29: ='23'!$S$64 -> 0 | N29: ='23'!$M$64 -> 0 | R29: ='23'!$V$39 -> 0 | S29: ='23'!$V$40 -> 0 | T29: ='23'!$V$41 -> 0 | U29: ='23'!$V$44 -> 0 | V29: ='23'!$V$42 -> 0 | W29: ='23'!$V$43 -> 0 | X29: ='23'!$V$46 -> 0 | Y29: ='23'!$V$47 -> 0 | Z29: ='23'!$V$48 -> 0 | AA29: ='23'!$V$49 -> 0 | AB29: ='23'!$V$50 -> 0 | AC29: ='23'!$V$51 -> 0 | AD29: ='23'!V$52+'23'!V$53 -> 0 | AE29: =(R29+S29)-SUM(T29:AC29) -> 0
A30: 24 | B30: =VLOOKUP(A:A,'COG NA'!A:B,2,FALSE) -> 0 | E30: =VLOOKUP($A:$A,'COG NA'!$A:$G,5,FALSE) -> 0 | F30: =VLOOKUP($A:$A,'COG NA'!$A:$G,6,FALSE) -> 0 | G30: =VLOOKUP($A:$A,'COG NA'!$A:$G,7,FALSE) -> 0 | H30: =SUM(E30:G30) -> 0 | J30: ='24'!$C$64 -> 0 | K30: ='24'!$G$64 -> 0 | L30: ='24'!$L$64 -> 0 | M30: ='24'!$S$64 -> 0 | N30: ='24'!$M$64 -> 0 | R30: ='24'!$V$39 -> 0 | S30: ='24'!$V$40 -> 0 | T30: ='24'!$V$41 -> 0 | U30: ='24'!$V$44 -> 0 | V30: ='24'!$V$42 -> 0 | W30: ='24'!$V$43 -> 0 | X30: ='24'!$V$46 -> 0 | Y30: ='24'!$V$47 -> 0 | Z30: ='24'!$V$48 -> 0 | AA30: ='24'!$V$49 -> 0 | AB30: ='24'!$V$50 -> 0 | AC30: ='24'!$V$51 -> 0 | AD30: ='24'!V$52+'24'!V$53 -> 0 | AE30: =(R30+S30)-SUM(T30:AC30) -> 0
A31: 25 | B31: =VLOOKUP(A:A,'COG NA'!A:B,2,FALSE) -> 0 | E31: =VLOOKUP($A:$A,'COG NA'!$A:$G,5,FALSE) -> 0 | F31: =VLOOKUP($A:$A,'COG NA'!$A:$G,6,FALSE) -> 0 | G31: =VLOOKUP($A:$A,'COG NA'!$A:$G,7,FALSE) -> 0 | H31: =SUM(E31:G31) -> 0 | J31: ='25'!$C$64 -> 0 | K31: ='25'!$G$64 -> 0 | L31: ='25'!$L$64 -> 0 | M31: ='25'!$S$64 -> 0 | N31: ='25'!$M$64 -> 0 | R31: ='25'!$V$39 -> 0 | S31: ='25'!$V$40 -> 0 | T31: ='25'!$V$41 -> 0 | U31: ='25'!$V$44 -> 0 | V31: ='25'!$V$42 -> 0 | W31: ='25'!$V$43 -> 0 | X31: ='25'!$V$46 -> 0 | Y31: ='25'!$V$47 -> 0 | Z31: ='25'!$V$48 -> 0 | AA31: ='25'!$V$49 -> 0 | AB31: ='25'!$V$50 -> 0 | AC31: ='25'!$V$51 -> 0 | AD31: ='25'!V$52+'25'!V$53 -> 0 | AE31: =(R31+S31)-SUM(T31:AC31) -> 0
A32: 26 | B32: =VLOOKUP(A:A,'COG NA'!A:B,2,FALSE) -> 0 | E32: =VLOOKUP($A:$A,'COG NA'!$A:$G,5,FALSE) -> 0 | F32: =VLOOKUP($A:$A,'COG NA'!$A:$G,6,FALSE) -> 0 | G32: =VLOOKUP($A:$A,'COG NA'!$A:$G,7,FALSE) -> 0 | H32: =SUM(E32:G32) -> 0 | J32: ='26'!$C$64 -> 0 | K32: ='26'!$G$64 -> 0 | L32: ='26'!$L$64 -> 0 | M32: ='26'!$S$64 -> 0 | N32: ='26'!$M$64 -> 0 | R32: ='26'!$V$39 -> 0 | S32: ='26'!$V$40 -> 0 | T32: ='26'!$V$41 -> 0 | U32: ='26'!$V$44 -> 0 | V32: ='26'!$V$42 -> 0 | W32: ='26'!$V$43 -> 0 | X32: ='26'!$V$46 -> 0 | Y32: ='26'!$V$47 -> 0 | Z32: ='26'!$V$48 -> 0 | AA32: ='26'!$V$49 -> 0 | AB32: ='26'!$V$50 -> 0 | AC32: ='26'!$V$51 -> 0 | AD32: ='26'!V$52+'26'!V$53 -> 0 | AE32: =(R32+S32)-SUM(T32:AC32) -> 0
A33: 27 | B33: =VLOOKUP(A:A,'COG NA'!A:B,2,FALSE) -> 0 | E33: =VLOOKUP($A:$A,'COG NA'!$A:$G,5,FALSE) -> 0 | F33: =VLOOKUP($A:$A,'COG NA'!$A:$G,6,FALSE) -> 0 | G33: =VLOOKUP($A:$A,'COG NA'!$A:$G,7,FALSE) -> 0 | H33: =SUM(E33:G33) -> 0 | J33: ='27'!$C$64 -> 0 | K33: ='27'!$G$64 -> 0 | L33: ='27'!$L$64 -> 0 | M33: ='27'!$S$64 -> 0 | N33: ='27'!$M$64 -> 0 | R33: ='27'!$V$39 -> 0 | S33: ='27'!$V$40 -> 0 | T33: ='27'!$V$41 -> 0 | U33: ='27'!$V$44 -> 0 | V33: ='27'!$V$42 -> 0 | W33: ='27'!$V$43 -> 0 | X33: ='27'!$V$46 -> 0 | Y33: ='27'!$V$47 -> 0 | Z33: ='27'!$V$48 -> 0 | AA33: ='27'!$V$49 -> 0 | AB33: ='27'!$V$50 -> 0 | AC33: ='27'!$V$51 -> 0 | AD33: ='27'!V$52+'27'!V$53 -> 0 | AE33: =(R33+S33)-SUM(T33:AC33) -> 0
A34: 28 | B34: =VLOOKUP(A:A,'COG NA'!A:B,2,FALSE) -> 0 | E34: =VLOOKUP($A:$A,'COG NA'!$A:$G,5,FALSE) -> 0 | F34: =VLOOKUP($A:$A,'COG NA'!$A:$G,6,FALSE) -> 0 | G34: =VLOOKUP($A:$A,'COG NA'!$A:$G,7,FALSE) -> 0 | H34: =SUM(E34:G34) -> 0 | J34: ='28'!$C$64 -> 0 | K34: ='28'!$G$64 -> 0 | L34: ='28'!$L$64 -> 0 | M34: ='28'!$S$64 -> 0 | N34: ='28'!$M$64 -> 0 | R34: ='28'!$V$39 -> 0 | S34: ='28'!$V$40 -> 0 | T34: ='28'!$V$41 -> 0 | U34: ='28'!$V$44 -> 0 | V34: ='28'!$V$42 -> 0 | W34: ='28'!$V$43 -> 0 | X34: ='28'!$V$46 -> 0 | Y34: ='28'!$V$47 -> 0 | Z34: ='28'!$V$48 -> 0 | AA34: ='28'!$V$49 -> 0 | AB34: ='28'!$V$50 -> 0 | AC34: ='28'!$V$51 -> 0 | AD34: ='28'!V$52+'28'!V$53 -> 0 | AE34: =(R34+S34)-SUM(T34:AC34) -> 0
A35: 29 | B35: =VLOOKUP(A:A,'COG NA'!A:B,2,FALSE) -> 0 | E35: =VLOOKUP($A:$A,'COG NA'!$A:$G,5,FALSE) -> 0 | F35: =VLOOKUP($A:$A,'COG NA'!$A:$G,6,FALSE) -> 0 | G35: =VLOOKUP($A:$A,'COG NA'!$A:$G,7,FALSE) -> 0 | H35: =SUM(E35:G35) -> 0 | J35: ='29'!$C$64 -> 0 | K35: ='29'!$G$64 -> 0 | L35: ='29'!$L$64 -> 0 | M35: ='29'!$S$64 -> 0 | N35: ='29'!$M$64 -> 0 | R35: ='29'!$V$39 -> 0 | S35: ='29'!$V$40 -> 0 | T35: ='29'!$V$41 -> 0 | U35: ='29'!$V$44 -> 0 | V35: ='29'!$V$42 -> 0 | W35: ='29'!$V$43 -> 0 | X35: ='29'!$V$46 -> 0 | Y35: ='29'!$V$47 -> 0 | Z35: ='29'!$V$48 -> 0 | AA35: ='29'!$V$49 -> 0 | AB35: ='29'!$V$50 -> 0 | AC35: ='29'!$V$51 -> 0 | AD35: ='29'!V$52+'29'!V$53 -> 0 | AE35: =(R35+S35)-SUM(T35:AC35) -> 0
A36: 30 | B36: =VLOOKUP(A:A,'COG NA'!A:B,2,FALSE) -> 0 | E36: =VLOOKUP($A:$A,'COG NA'!$A:$G,5,FALSE) -> 0 | F36: =VLOOKUP($A:$A,'COG NA'!$A:$G,6,FALSE) -> 0 | G36: =VLOOKUP($A:$A,'COG NA'!$A:$G,7,FALSE) -> 0 | H36: =SUM(E36:G36) -> 0 | J36: ='30'!$C$64 -> 0 | K36: ='30'!$G$64 -> 0 | L36: ='30'!$L$64 -> 0 | M36: ='30'!$S$64 -> 0 | N36: ='30'!$M$64 -> 0 | R36: ='30'!$V$39 -> 0 | S36: ='30'!$V$40 -> 0 | T36: ='30'!$V$41 -> 0 | U36: ='30'!$V$44 -> 0 | V36: ='30'!$V$42 -> 0 | W36: ='30'!$V$43 -> 0 | X36: ='30'!$V$46 -> 0 | Y36: ='30'!$V$47 -> 0 | Z36: ='30'!$V$48 -> 0 | AA36: ='30'!$V$49 -> 0 | AB36: ='30'!$V$50 -> 0 | AC36: ='30'!$V$51 -> 0 | AD36: ='30'!V$52+'30'!V$53 -> 0 | AE36: =(R36+S36)-SUM(T36:AC36) -> 0
A37: 31 | B37: =VLOOKUP(A:A,'COG NA'!A:B,2,FALSE) -> 0 | E37: =VLOOKUP($A:$A,'COG NA'!$A:$G,5,FALSE) -> 0 | F37: =VLOOKUP($A:$A,'COG NA'!$A:$G,6,FALSE) -> 0 | G37: =VLOOKUP($A:$A,'COG NA'!$A:$G,7,FALSE) -> 0 | H37: =SUM(E37:G37) -> 0 | J37: ='31'!$C$64 -> 0 | K37: ='31'!$G$64 -> 0 | L37: ='31'!$L$64 -> 0 | M37: ='31'!$S$64 -> 0 | N37: ='31'!$M$64 -> 0 | R37: ='31'!$V$39 -> 0 | S37: ='31'!$V$40 -> 0 | T37: ='31'!$V$41 -> 0 | U37: ='31'!$V$44 -> 0 | V37: ='31'!$V$42 -> 0 | W37: ='31'!$V$43 -> 0 | X37: ='31'!$V$46 -> 0 | Y37: ='31'!$V$47 -> 0 | Z37: ='31'!$V$48 -> 0 | AA37: ='31'!$V$49 -> 0 | AB37: ='31'!$V$50 -> 0 | AC37: ='31'!$V$51 -> 0 | AD37: ='31'!V$52+'31'!V$53 -> 0 | AE37: =(R37+S37)-SUM(T37:AC37) -> 0
A38: 32 | B38: =VLOOKUP(A:A,'COG NA'!A:B,2,FALSE) -> 0 | E38: =VLOOKUP($A:$A,'COG NA'!$A:$G,5,FALSE) -> 0 | F38: =VLOOKUP($A:$A,'COG NA'!$A:$G,6,FALSE) -> 0 | G38: =VLOOKUP($A:$A,'COG NA'!$A:$G,7,FALSE) -> 0 | H38: =SUM(E38:G38) -> 0 | J38: ='32'!$C$64 -> 0 | K38: ='32'!$G$64 -> 0 | L38: ='32'!$L$64 -> 0 | M38: ='32'!$S$64 -> 0 | N38: ='32'!$M$64 -> 0 | R38: ='32'!$V$39 -> 0 | S38: ='32'!$V$40 -> 0 | T38: ='32'!$V$41 -> 0 | U38: ='32'!$V$44 -> 0 | V38: ='32'!$V$42 -> 0 | W38: ='32'!$V$43 -> 0 | X38: ='32'!$V$46 -> 0 | Y38: ='32'!$V$47 -> 0 | Z38: ='32'!$V$48 -> 0 | AA38: ='32'!$V$49 -> 0 | AB38: ='32'!$V$50 -> 0 | AC38: ='32'!$V$51 -> 0 | AD38: ='32'!V$52+'32'!V$53 -> 0 | AE38: =(R38+S38)-SUM(T38:AC38) -> 0
A39: 33 | B39: =VLOOKUP(A:A,'COG NA'!A:B,2,FALSE) -> 0 | E39: =VLOOKUP($A:$A,'COG NA'!$A:$G,5,FALSE) -> 0 | F39: =VLOOKUP($A:$A,'COG NA'!$A:$G,6,FALSE) -> 0 | G39: =VLOOKUP($A:$A,'COG NA'!$A:$G,7,FALSE) -> 0 | H39: =SUM(E39:G39) -> 0 | J39: ='33'!$C$64 -> 0 | K39: ='33'!$G$64 -> 0 | L39: ='33'!$L$64 -> 0 | M39: ='33'!$S$64 -> 0 | N39: ='33'!$M$64 -> 0 | R39: ='33'!$V$39 -> 0 | S39: ='33'!$V$40 -> 0 | T39: ='33'!$V$41 -> 0 | U39: ='33'!$V$44 -> 0 | V39: ='33'!$V$42 -> 0 | W39: ='33'!$V$43 -> 0 | X39: ='33'!$V$46 -> 0 | Y39: ='33'!$V$47 -> 0 | Z39: ='33'!$V$48 -> 0 | AA39: ='33'!$V$49 -> 0 | AB39: ='33'!$V$50 -> 0 | AC39: ='33'!$V$51 -> 0 | AD39: ='33'!V$52+'33'!V$53 -> 0 | AE39: =(R39+S39)-SUM(T39:AC39) -> 0
A40: 34 | B40: =VLOOKUP(A:A,'COG NA'!A:B,2,FALSE) -> 0 | E40: =VLOOKUP($A:$A,'COG NA'!$A:$G,5,FALSE) -> 0 | F40: =VLOOKUP($A:$A,'COG NA'!$A:$G,6,FALSE) -> 0 | G40: =VLOOKUP($A:$A,'COG NA'!$A:$G,7,FALSE) -> 0 | H40: =SUM(E40:G40) -> 0 | J40: ='34'!$C$64 -> 0 | K40: ='34'!$G$64 -> 0 | L40: ='34'!$L$64 -> 0 | M40: ='34'!$S$64 -> 0 | N40: ='34'!$M$64 -> 0 | R40: ='34'!$V$39 -> 0 | S40: ='34'!$V$40 -> 0 | T40: ='34'!$V$41 -> 0 | U40: ='34'!$V$44 -> 0 | V40: ='34'!$V$42 -> 0 | W40: ='34'!$V$43 -> 0 | X40: ='34'!$V$46 -> 0 | Y40: ='34'!$V$47 -> 0 | Z40: ='34'!$V$48 -> 0 | AA40: ='34'!$V$49 -> 0 | AB40: ='34'!$V$50 -> 0 | AC40: ='34'!$V$51 -> 0 | AD40: ='34'!V$52+'34'!V$53 -> 0 | AE40: =(R40+S40)-SUM(T40:AC40) -> 0
A41: 35 | B41: =VLOOKUP(A:A,'COG NA'!A:B,2,FALSE) -> 0 | E41: =VLOOKUP($A:$A,'COG NA'!$A:$G,5,FALSE) -> 0 | F41: =VLOOKUP($A:$A,'COG NA'!$A:$G,6,FALSE) -> 0 | G41: =VLOOKUP($A:$A,'COG NA'!$A:$G,7,FALSE) -> 0 | H41: =SUM(E41:G41) -> 0 | J41: ='35'!$C$64 -> 0 | K41: ='35'!$G$64 -> 0 | L41: ='35'!$L$64 -> 0 | M41: ='35'!$S$64 -> 0 | N41: ='35'!$M$64 -> 0 | R41: ='35'!$V$39 -> 0 | S41: ='35'!$V$40 -> 0 | T41: ='35'!$V$41 -> 0 | U41: ='35'!$V$44 -> 0 | V41: ='35'!$V$42 -> 0 | W41: ='35'!$V$43 -> 0 | X41: ='35'!$V$46 -> 0 | Y41: ='35'!$V$47 -> 0 | Z41: ='35'!$V$48 -> 0 | AA41: ='35'!$V$49 -> 0 | AB41: ='35'!$V$50 -> 0 | AC41: ='35'!$V$51 -> 0 | AD41: ='35'!V$52+'35'!V$53 -> 0 | AE41: =(R41+S41)-SUM(T41:AC41) -> 0
A42: 36 | B42: =VLOOKUP(A:A,'COG NA'!A:B,2,FALSE) -> 0 | E42: =VLOOKUP($A:$A,'COG NA'!$A:$G,5,FALSE) -> 0 | F42: =VLOOKUP($A:$A,'COG NA'!$A:$G,6,FALSE) -> 0 | G42: =VLOOKUP($A:$A,'COG NA'!$A:$G,7,FALSE) -> 0 | H42: =SUM(E42:G42) -> 0 | J42: ='36'!$C$64 -> 0 | K42: ='36'!$G$64 -> 0 | L42: ='36'!$L$64 -> 0 | M42: ='36'!$S$64 -> 0 | N42: ='36'!$M$64 -> 0 | R42: ='36'!$V$39 -> 0 | S42: ='36'!$V$40 -> 0 | T42: ='36'!$V$41 -> 0 | U42: ='36'!$V$44 -> 0 | V42: ='36'!$V$42 -> 0 | W42: ='36'!$V$43 -> 0 | X42: ='36'!$V$46 -> 0 | Y42: ='36'!$V$47 -> 0 | Z42: ='36'!$V$48 -> 0 | AA42: ='36'!$V$49 -> 0 | AB42: ='36'!$V$50 -> 0 | AC42: ='36'!$V$51 -> 0 | AD42: ='36'!V$52+'36'!V$53 -> 0 | AE42: =(R42+S42)-SUM(T42:AC42) -> 0
A43: 37 | B43: =VLOOKUP(A:A,'COG NA'!A:B,2,FALSE) -> 0 | E43: =VLOOKUP($A:$A,'COG NA'!$A:$G,5,FALSE) -> 0 | F43: =VLOOKUP($A:$A,'COG NA'!$A:$G,6,FALSE) -> 0 | G43: =VLOOKUP($A:$A,'COG NA'!$A:$G,7,FALSE) -> 0 | H43: =SUM(E43:G43) -> 0 | J43: ='37'!$C$64 -> 0 | K43: ='37'!$G$64 -> 0 | L43: ='37'!$L$64 -> 0 | M43: ='37'!$S$64 -> 0 | N43: ='37'!$M$64 -> 0 | R43: ='37'!$V$39 -> 0 | S43: ='37'!$V$40 -> 0 | T43: ='37'!$V$41 -> 0 | U43: ='37'!$V$44 -> 0 | V43: ='37'!$V$42 -> 0 | W43: ='37'!$V$43 -> 0 | X43: ='37'!$V$46 -> 0 | Y43: ='37'!$V$47 -> 0 | Z43: ='37'!$V$48 -> 0 | AA43: ='37'!$V$49 -> 0 | AB43: ='37'!$V$50 -> 0 | AC43: ='37'!$V$51 -> 0 | AD43: ='37'!V$52+'37'!V$53 -> 0 | AE43: =(R43+S43)-SUM(T43:AC43) -> 0
A44: 38 | B44: =VLOOKUP(A:A,'COG NA'!A:B,2,FALSE) -> 0 | E44: =VLOOKUP($A:$A,'COG NA'!$A:$G,5,FALSE) -> 0 | F44: =VLOOKUP($A:$A,'COG NA'!$A:$G,6,FALSE) -> 0 | G44: =VLOOKUP($A:$A,'COG NA'!$A:$G,7,FALSE) -> 0 | H44: =SUM(E44:G44) -> 0 | J44: ='38'!$C$64 -> 0 | K44: ='38'!$G$64 -> 0 | L44: ='38'!$L$64 -> 0 | M44: ='38'!$S$64 -> 0 | N44: ='38'!$M$64 -> 0 | R44: ='38'!$V$39 -> 0 | S44: ='38'!$V$40 -> 0 | T44: ='38'!$V$41 -> 0 | U44: ='38'!$V$44 -> 0 | V44: ='38'!$V$42 -> 0 | W44: ='38'!$V$43 -> 0 | X44: ='38'!$V$46 -> 0 | Y44: ='38'!$V$47 -> 0 | Z44: ='38'!$V$48 -> 0 | AA44: ='38'!$V$49 -> 0 | AB44: ='38'!$V$50 -> 0 | AC44: ='38'!$V$51 -> 0 | AD44: ='38'!V$52+'38'!V$53 -> 0 | AE44: =(R44+S44)-SUM(T44:AC44) -> 0
A45: 39 | B45: =VLOOKUP(A:A,'COG NA'!A:B,2,FALSE) -> 0 | E45: =VLOOKUP($A:$A,'COG NA'!$A:$G,5,FALSE) -> 0 | F45: =VLOOKUP($A:$A,'COG NA'!$A:$G,6,FALSE) -> 0 | G45: =VLOOKUP($A:$A,'COG NA'!$A:$G,7,FALSE) -> 0 | H45: =SUM(E45:G45) -> 0 | J45: ='39'!$C$64 -> 0 | K45: ='39'!$G$64 -> 0 | L45: ='39'!$L$64 -> 0 | M45: ='39'!$S$64 -> 0 | N45: ='39'!$M$64 -> 0 | R45: ='39'!$V$39 -> 0 | S45: ='39'!$V$40 -> 0 | T45: ='39'!$V$41 -> 0 | U45: ='39'!$V$44 -> 0 | V45: ='39'!$V$42 -> 0 | W45: ='39'!$V$43 -> 0 | X45: ='39'!$V$46 -> 0 | Y45: ='39'!$V$47 -> 0 | Z45: ='39'!$V$48 -> 0 | AA45: ='39'!$V$49 -> 0 | AB45: ='39'!$V$50 -> 0 | AC45: ='39'!$V$51 -> 0 | AD45: ='39'!V$52+'39'!V$53 -> 0 | AE45: =(R45+S45)-SUM(T45:AC45) -> 0
A46: 40 | B46: =VLOOKUP(A:A,'COG NA'!A:B,2,FALSE) -> 0 | E46: =VLOOKUP($A:$A,'COG NA'!$A:$G,5,FALSE) -> 0 | F46: =VLOOKUP($A:$A,'COG NA'!$A:$G,6,FALSE) -> 0 | G46: =VLOOKUP($A:$A,'COG NA'!$A:$G,7,FALSE) -> 0 | H46: =SUM(E46:G46) -> 0 | J46: ='40'!$C$64 -> 0 | K46: ='40'!$G$64 -> 0 | L46: ='40'!$L$64 -> 0 | M46: ='40'!$S$64 -> 0 | N46: ='40'!$M$64 -> 0 | R46: ='40'!$V$39 -> 0 | S46: ='40'!$V$40 -> 0 | T46: ='40'!$V$41 -> 0 | U46: ='40'!$V$44 -> 0 | V46: ='40'!$V$42 -> 0 | W46: ='40'!$V$43 -> 0 | X46: ='40'!$V$46 -> 0 | Y46: ='40'!$V$47 -> 0 | Z46: ='40'!$V$48 -> 0 | AA46: ='40'!$V$49 -> 0 | AB46: ='40'!$V$50 -> 0 | AC46: ='40'!$V$51 -> 0 | AD46: ='40'!V$52+'40'!V$53 -> 0 | AE46: =(R46+S46)-SUM(T46:AC46) -> 0
A47: 41 | B47: =VLOOKUP(A:A,'COG NA'!A:B,2,FALSE) -> 0 | E47: =VLOOKUP($A:$A,'COG NA'!$A:$G,5,FALSE) -> 0 | F47: =VLOOKUP($A:$A,'COG NA'!$A:$G,6,FALSE) -> 0 | G47: =VLOOKUP($A:$A,'COG NA'!$A:$G,7,FALSE) -> 0 | H47: =SUM(E47:G47) -> 0 | J47: ='41'!$C$64 -> 0 | K47: ='41'!$G$64 -> 0 | L47: ='41'!$L$64 -> 0 | M47: ='41'!$S$64 -> 0 | N47: ='41'!$M$64 -> 0 | R47: ='41'!$V$39 -> 0 | S47: ='41'!$V$40 -> 0 | T47: ='41'!$V$41 -> 0 | U47: ='41'!$V$44 -> 0 | V47: ='41'!$V$42 -> 0 | W47: ='41'!$V$43 -> 0 | X47: ='41'!$V$46 -> 0 | Y47: ='41'!$V$47 -> 0 | Z47: ='41'!$V$48 -> 0 | AA47: ='41'!$V$49 -> 0 | AB47: ='41'!$V$50 -> 0 | AC47: ='41'!$V$51 -> 0 | AD47: ='41'!V$52+'41'!V$53 -> 0 | AE47: =(R47+S47)-SUM(T47:AC47) -> 0
A48: 42 | B48: =VLOOKUP(A:A,'COG NA'!A:B,2,FALSE) -> 0 | E48: =VLOOKUP($A:$A,'COG NA'!$A:$G,5,FALSE) -> 0 | F48: =VLOOKUP($A:$A,'COG NA'!$A:$G,6,FALSE) -> 0 | G48: =VLOOKUP($A:$A,'COG NA'!$A:$G,7,FALSE) -> 0 | H48: =SUM(E48:G48) -> 0 | J48: ='42'!$C$64 -> 0 | K48: ='42'!$G$64 -> 0 | L48: ='42'!$L$64 -> 0 | M48: ='42'!$S$64 -> 0 | N48: ='42'!$M$64 -> 0 | R48: ='42'!$V$39 -> 0 | S48: ='42'!$V$40 -> 0 | T48: ='42'!$V$41 -> 0 | U48: ='42'!$V$44 -> 0 | V48: ='42'!$V$42 -> 0 | W48: ='42'!$V$43 -> 0 | X48: ='42'!$V$46 -> 0 | Y48: ='42'!$V$47 -> 0 | Z48: ='42'!$V$48 -> 0 | AA48: ='42'!$V$49 -> 0 | AB48: ='42'!$V$50 -> 0 | AC48: ='42'!$V$51 -> 0 | AD48: ='42'!V$52+'42'!V$53 -> 0 | AE48: =(R48+S48)-SUM(T48:AC48) -> 0
A49: 43 | B49: =VLOOKUP(A:A,'COG NA'!A:B,2,FALSE) -> 0 | E49: =VLOOKUP($A:$A,'COG NA'!$A:$G,5,FALSE) -> 0 | F49: =VLOOKUP($A:$A,'COG NA'!$A:$G,6,FALSE) -> 0 | G49: =VLOOKUP($A:$A,'COG NA'!$A:$G,7,FALSE) -> 0 | H49: =SUM(E49:G49) -> 0 | J49: ='43'!$C$64 -> 0 | K49: ='43'!$G$64 -> 0 | L49: ='43'!$L$64 -> 0 | M49: ='43'!$S$64 -> 0 | N49: ='43'!$M$64 -> 0 | R49: ='43'!$V$39 -> 0 | S49: ='43'!$V$40 -> 0 | T49: ='43'!$V$41 -> 0 | U49: ='43'!$V$44 -> 0 | V49: ='43'!$V$42 -> 0 | W49: ='43'!$V$43 -> 0 | X49: ='43'!$V$46 -> 0 | Y49: ='43'!$V$47 -> 0 | Z49: ='43'!$V$48 -> 0 | AA49: ='43'!$V$49 -> 0 | AB49: ='43'!$V$50 -> 0 | AC49: ='43'!$V$51 -> 0 | AD49: ='43'!V$52+'43'!V$53 -> 0 | AE49: =(R49+S49)-SUM(T49:AC49) -> 0
A50: 44 | B50: =VLOOKUP(A:A,'COG NA'!A:B,2,FALSE) -> 0 | E50: =VLOOKUP($A:$A,'COG NA'!$A:$G,5,FALSE) -> 0 | F50: =VLOOKUP($A:$A,'COG NA'!$A:$G,6,FALSE) -> 0 | G50: =VLOOKUP($A:$A,'COG NA'!$A:$G,7,FALSE) -> 0 | H50: =SUM(E50:G50) -> 0 | J50: ='44'!$C$64 -> 0 | K50: ='44'!$G$64 -> 0 | L50: ='44'!$L$64 -> 0 | M50: ='44'!$S$64 -> 0 | N50: ='44'!$M$64 -> 0 | R50: ='44'!$V$39 -> 0 | S50: ='44'!$V$40 -> 0 | T50: ='44'!$V$41 -> 0 | U50: ='44'!$V$44 -> 0 | V50: ='44'!$V$42 -> 0 | W50: ='44'!$V$43 -> 0 | X50: ='44'!$V$46 -> 0 | Y50: ='44'!$V$47 -> 0 | Z50: ='44'!$V$48 -> 0 | AA50: ='44'!$V$49 -> 0 | AB50: ='44'!$V$50 -> 0 | AC50: ='44'!$V$51 -> 0 | AD50: ='44'!V$52+'44'!V$53 -> 0 | AE50: =(R50+S50)-SUM(T50:AC50) -> 0
A51: 45 | B51: =VLOOKUP(A:A,'COG NA'!A:B,2,FALSE) -> 0 | E51: =VLOOKUP($A:$A,'COG NA'!$A:$G,5,FALSE) -> 0 | F51: =VLOOKUP($A:$A,'COG NA'!$A:$G,6,FALSE) -> 0 | G51: =VLOOKUP($A:$A,'COG NA'!$A:$G,7,FALSE) -> 0 | H51: =SUM(E51:G51) -> 0 | J51: ='45'!$C$64 -> 0 | K51: ='45'!$G$64 -> 0 | L51: ='45'!$L$64 -> 0 | M51: ='45'!$S$64 -> 0 | N51: ='45'!$M$64 -> 0 | R51: ='45'!$V$39 -> 0 | S51: ='45'!$V$40 -> 0 | T51: ='45'!$V$41 -> 0 | U51: ='45'!$V$44 -> 0 | V51: ='45'!$V$42 -> 0 | W51: ='45'!$V$43 -> 0 | X51: ='45'!$V$46 -> 0 | Y51: ='45'!$V$47 -> 0 | Z51: ='45'!$V$48 -> 0 | AA51: ='45'!$V$49 -> 0 | AB51: ='45'!$V$50 -> 0 | AC51: ='45'!$V$51 -> 0 | AD51: ='45'!V$52+'45'!V$53 -> 0 | AE51: =(R51+S51)-SUM(T51:AC51) -> 0
A52: 46 | B52: =VLOOKUP(A:A,'COG NA'!A:B,2,FALSE) -> 0 | E52: =VLOOKUP($A:$A,'COG NA'!$A:$G,5,FALSE) -> 0 | F52: =VLOOKUP($A:$A,'COG NA'!$A:$G,6,FALSE) -> 0 | G52: =VLOOKUP($A:$A,'COG NA'!$A:$G,7,FALSE) -> 0 | H52: =SUM(E52:G52) -> 0 | J52: ='46'!$C$64 -> 0 | K52: ='46'!$G$64 -> 0 | L52: ='46'!$L$64 -> 0 | M52: ='46'!$S$64 -> 0 | N52: ='46'!$M$64 -> 0 | R52: ='46'!$V$39 -> 0 | S52: ='46'!$V$40 -> 0 | T52: ='46'!$V$41 -> 0 | U52: ='46'!$V$44 -> 0 | V52: ='46'!$V$42 -> 0 | W52: ='46'!$V$43 -> 0 | X52: ='46'!$V$46 -> 0 | Y52: ='46'!$V$47 -> 0 | Z52: ='46'!$V$48 -> 0 | AA52: ='46'!$V$49 -> 0 | AB52: ='46'!$V$50 -> 0 | AC52: ='46'!$V$51 -> 0 | AD52: ='46'!V$52+'46'!V$53 -> 0 | AE52: =(R52+S52)-SUM(T52:AC52) -> 0
A53: 47 | B53: =VLOOKUP(A:A,'COG NA'!A:B,2,FALSE) -> 0 | E53: =VLOOKUP($A:$A,'COG NA'!$A:$G,5,FALSE) -> 0 | F53: =VLOOKUP($A:$A,'COG NA'!$A:$G,6,FALSE) -> 0 | G53: =VLOOKUP($A:$A,'COG NA'!$A:$G,7,FALSE) -> 0 | H53: =SUM(E53:G53) -> 0 | J53: ='47'!$C$64 -> 0 | K53: ='47'!$G$64 -> 0 | L53: ='47'!$L$64 -> 0 | M53: ='47'!$S$64 -> 0 | N53: ='47'!$M$64 -> 0 | R53: ='47'!$V$39 -> 0 | S53: ='47'!$V$40 -> 0 | T53: ='47'!$V$41 -> 0 | U53: ='47'!$V$44 -> 0 | V53: ='47'!$V$42 -> 0 | W53: ='47'!$V$43 -> 0 | X53: ='47'!$V$46 -> 0 | Y53: ='47'!$V$47 -> 0 | Z53: ='47'!$V$48 -> 0 | AA53: ='47'!$V$49 -> 0 | AB53: ='47'!$V$50 -> 0 | AC53: ='47'!$V$51 -> 0 | AD53: ='47'!V$52+'47'!V$53 -> 0 | AE53: =(R53+S53)-SUM(T53:AC53) -> 0
A54: 48 | B54: =VLOOKUP(A:A,'COG NA'!A:B,2,FALSE) -> 0 | E54: =VLOOKUP($A:$A,'COG NA'!$A:$G,5,FALSE) -> 0 | F54: =VLOOKUP($A:$A,'COG NA'!$A:$G,6,FALSE) -> 0 | G54: =VLOOKUP($A:$A,'COG NA'!$A:$G,7,FALSE) -> 0 | H54: =SUM(E54:G54) -> 0 | J54: ='48'!$C$64 -> 0 | K54: ='48'!$G$64 -> 0 | L54: ='48'!$L$64 -> 0 | M54: ='48'!$S$64 -> 0 | N54: ='48'!$M$64 -> 0 | R54: ='48'!$V$39 -> 0 | S54: ='48'!$V$40 -> 0 | T54: ='48'!$V$41 -> 0 | U54: ='48'!$V$44 -> 0 | V54: ='48'!$V$42 -> 0 | W54: ='48'!$V$43 -> 0 | X54: ='48'!$V$46 -> 0 | Y54: ='48'!$V$47 -> 0 | Z54: ='48'!$V$48 -> 0 | AA54: ='48'!$V$49 -> 0 | AB54: ='48'!$V$50 -> 0 | AC54: ='48'!$V$51 -> 0 | AD54: ='48'!V$52+'48'!V$53 -> 0 | AE54: =(R54+S54)-SUM(T54:AC54) -> 0
A55: 49 | B55: =VLOOKUP(A:A,'COG NA'!A:B,2,FALSE) -> 0 | E55: =VLOOKUP($A:$A,'COG NA'!$A:$G,5,FALSE) -> 0 | F55: =VLOOKUP($A:$A,'COG NA'!$A:$G,6,FALSE) -> 0 | G55: =VLOOKUP($A:$A,'COG NA'!$A:$G,7,FALSE) -> 0 | H55: =SUM(E55:G55) -> 0 | J55: ='49'!$C$64 -> 0 | K55: ='49'!$G$64 -> 0 | L55: ='49'!$L$64 -> 0 | M55: ='49'!$S$64 -> 0 | N55: ='49'!$M$64 -> 0 | R55: ='49'!$V$39 -> 0 | S55: ='49'!$V$40 -> 0 | T55: ='49'!$V$41 -> 0 | U55: ='49'!$V$44 -> 0 | V55: ='49'!$V$42 -> 0 | W55: ='49'!$V$43 -> 0 | X55: ='49'!$V$46 -> 0 | Y55: ='49'!$V$47 -> 0 | Z55: ='49'!$V$48 -> 0 | AA55: ='49'!$V$49 -> 0 | AB55: ='49'!$V$50 -> 0 | AC55: ='49'!$V$51 -> 0 | AD55: ='49'!V$52+'49'!V$53 -> 0 | AE55: =(R55+S55)-SUM(T55:AC55) -> 0
A56: 50 | B56: =VLOOKUP(A:A,'COG NA'!A:B,2,FALSE) -> 0 | E56: =VLOOKUP($A:$A,'COG NA'!$A:$G,5,FALSE) -> 0 | F56: =VLOOKUP($A:$A,'COG NA'!$A:$G,6,FALSE) -> 0 | G56: =VLOOKUP($A:$A,'COG NA'!$A:$G,7,FALSE) -> 0 | H56: =SUM(E56:G56) -> 0 | J56: ='50'!$C$64 -> 0 | K56: ='50'!$G$64 -> 0 | L56: ='50'!$L$64 -> 0 | M56: ='50'!$S$64 -> 0 | N56: ='50'!$M$64 -> 0 | R56: ='50'!$V$39 -> 0 | S56: ='50'!$V$40 -> 0 | T56: ='50'!$V$41 -> 0 | U56: ='50'!$V$44 -> 0 | V56: ='50'!$V$42 -> 0 | W56: ='50'!$V$43 -> 0 | X56: ='50'!$V$46 -> 0 | Y56: ='50'!$V$47 -> 0 | Z56: ='50'!$V$48 -> 0 | AA56: ='50'!$V$49 -> 0 | AB56: ='50'!$V$50 -> 0 | AC56: ='50'!$V$51 -> 0 | AD56: ='50'!V$52+'50'!V$53 -> 0 | AE56: =(R56+S56)-SUM(T56:AC56) -> 0
A57: 51 | B57: GHOSRX903646OT | C57: PLUSHIE PAPA V PURPLE | D57: FARSTAR | E57: =VLOOKUP($A:$A,'COG NA'!$A:$G,5,FALSE) -> 0 | F57: =VLOOKUP($A:$A,'COG NA'!$A:$G,6,FALSE) -> 0 | G57: =VLOOKUP($A:$A,'COG NA'!$A:$G,7,FALSE) -> 10 | H57: =SUM(E57:G57) -> 10 | J57: ='PLUSHIE PURPLE'!$C$64 -> 0 | K57: ='PLUSHIE PURPLE'!$G$64 -> 0 | L57: ='PLUSHIE PURPLE'!$L$64 -> 6752 | M57: ='PLUSHIE PURPLE'!$S$64 -> 2336 | N57: ='PLUSHIE PURPLE'!$M$64 -> 0 | R57: ='PLUSHIE PURPLE'!$V$39 -> 0 | S57: ='PLUSHIE PURPLE'!$V$40 -> 9088 | T57: ='PLUSHIE PURPLE'!$V$41 -> 0 | U57: ='PLUSHIE PURPLE'!$V$44 -> 0 | V57: ='PLUSHIE PURPLE'!$V$42 -> 0 | W57: ='PLUSHIE PURPLE'!$V$43 -> 0 | X57: ='PLUSHIE PURPLE'!$V$46 -> 0 | Y57: ='PLUSHIE PURPLE'!$V$47 -> 0 | Z57: ='PLUSHIE PURPLE'!$V$48 -> 0 | AA57: ='PLUSHIE PURPLE'!$V$49 -> 0 | AB57: ='PLUSHIE PURPLE'!$V$50 -> 6752 | AC57: ='PLUSHIE PURPLE'!$V$51 -> 0 | AD57: ='PLUSHIE PURPLE'!V$52+'PLUSHIE PURPLE'!V$53 -> 2336 | AE57: =(R57+S57)-SUM(T57:AC57) -> 2336
A58: 52 | B58: GHOSRX103922GR | C58: MASK PAPA V RHINESTONE | D58: FARSTAR | E58: =VLOOKUP($A:$A,'COG NA'!$A:$G,5,FALSE) -> 0 | F58: =VLOOKUP($A:$A,'COG NA'!$A:$G,6,FALSE) -> 0 | G58: =VLOOKUP($A:$A,'COG NA'!$A:$G,7,FALSE) -> 12 | H58: =SUM(E58:G58) -> 12 | J58: ='MASK RHINESTONE'!$C$64 -> 0 | K58: ='MASK RHINESTONE'!$G$64 -> 0 | L58: ='MASK RHINESTONE'!$L$64 -> 0 | M58: ='MASK RHINESTONE'!$S$64 -> 0 | N58: ='MASK RHINESTONE'!$M$64 -> 0 | R58: ='MASK RHINESTONE'!$V$39 -> 0 | S58: ='MASK RHINESTONE'!$V$40 -> 0 | T58: ='MASK RHINESTONE'!$V$41 -> 0 | U58: ='MASK RHINESTONE'!$V$44 -> 0 | V58: ='MASK RHINESTONE'!$V$42 -> 0 | W58: ='MASK RHINESTONE'!$V$43 -> 0 | X58: ='MASK RHINESTONE'!$V$46 -> 0 | Y58: ='MASK RHINESTONE'!$V$47 -> 0 | Z58: ='MASK RHINESTONE'!$V$48 -> 0 | AA58: ='MASK RHINESTONE'!$V$49 -> 0 | AB58: ='MASK RHINESTONE'!$V$50 -> 0 | AC58: ='MASK RHINESTONE'!$V$51 -> 0 | AD58: ='MASK RHINESTONE'!V$52+'MASK RHINESTONE'!V$53 -> 0 | AE58: =(R58+S58)-SUM(T58:AC58) -> 0
A59: 53 | B59: GHOSRX103259OT | C59: CLEAR SLING BAG-SILVER LOGO | D59: FARSTAR | E59: =VLOOKUP($A:$A,'COG NA'!$A:$G,5,FALSE) -> 0 | F59: =VLOOKUP($A:$A,'COG NA'!$A:$G,6,FALSE) -> 0 | G59: =VLOOKUP($A:$A,'COG NA'!$A:$G,7,FALSE) -> 3.8 | H59: =SUM(E59:G59) -> 3.8 | J59: ='CLEAR SLING BG'!$C$64 -> 0 | K59: ='CLEAR SLING BG'!$G$64 -> 0 | L59: ='CLEAR SLING BG'!$L$64 -> 0 | M59: ='CLEAR SLING BG'!$S$64 -> 0 | N59: ='CLEAR SLING BG'!$M$64 -> 0 | R59: ='CLEAR SLING BG'!$V$39 -> 1497 | S59: ='CLEAR SLING BG'!$V$40 -> 0 | T59: ='CLEAR SLING BG'!$V$41 -> 0 | U59: ='CLEAR SLING BG'!$V$44 -> 0 | V59: ='CLEAR SLING BG'!$V$42 -> 0 | W59: ='CLEAR SLING BG'!$V$43 -> 0 | X59: ='CLEAR SLING BG'!$V$46 -> 0 | Y59: ='CLEAR SLING BG'!$V$47 -> 0 | Z59: ='CLEAR SLING BG'!$V$48 -> 0 | AA59: ='CLEAR SLING BG'!$V$49 -> 0 | AB59: ='CLEAR SLING BG'!$V$50 -> 0 | AC59: ='CLEAR SLING BG'!$V$51 -> 0 | AD59: ='CLEAR SLING BG'!V$52+'CLEAR SLING BG'!V$53 -> 1497 | AE59: =(R59+S59)-SUM(T59:AC59) -> 1497
A60: 54 | B60: GHOSRX103935BK | C60: KEYCHAIN PAPA V TOPHAT | D60: FARSTAR | E60: =VLOOKUP($A:$A,'COG NA'!$A:$G,5,FALSE) -> 0 | F60: =VLOOKUP($A:$A,'COG NA'!$A:$G,6,FALSE) -> 0 | G60: =VLOOKUP($A:$A,'COG NA'!$A:$G,7,FALSE) -> 1.8 | H60: =SUM(E60:G60) -> 1.8 | J60: ='KEYCHAIN PAPA V TOPHAT'!$C$64 -> 0 | K60: ='KEYCHAIN PAPA V TOPHAT'!$G$64 -> 0 | L60: ='KEYCHAIN PAPA V TOPHAT'!$L$64 -> 0 | M60: ='KEYCHAIN PAPA V TOPHAT'!$S$64 -> 0 | N60: ='KEYCHAIN PAPA V TOPHAT'!$M$64 -> 0 | R60: ='KEYCHAIN PAPA V TOPHAT'!$V$39 -> 0 | S60: ='KEYCHAIN PAPA V TOPHAT'!$V$40 -> 0 | T60: ='KEYCHAIN PAPA V TOPHAT'!$V$41 -> 0 | U60: ='KEYCHAIN PAPA V TOPHAT'!$V$44 -> 0 | V60: ='KEYCHAIN PAPA V TOPHAT'!$V$42 -> 0 | W60: ='KEYCHAIN PAPA V TOPHAT'!$V$43 -> 0 | X60: ='KEYCHAIN PAPA V TOPHAT'!$V$46 -> 0 | Y60: ='KEYCHAIN PAPA V TOPHAT'!$V$47 -> 0 | Z60: ='KEYCHAIN PAPA V TOPHAT'!$V$48 -> 0 | AA60: ='KEYCHAIN PAPA V TOPHAT'!$V$49 -> 0 | AB60: ='KEYCHAIN PAPA V TOPHAT'!$V$50 -> 0 | AC60: ='KEYCHAIN PAPA V TOPHAT'!$V$51 -> 0 | AD60: ='KEYCHAIN PAPA V TOPHAT'!V$52+'KEYCHAIN PAPA V TOPHAT'!V$53 -> 0 | AE60: =(R60+S60)-SUM(T60:AC60) -> 0
A61: 55 | B61: GHOSRX103936GR | C61: PIN SILVER GRUCIFIX | D61: FARSTAR | E61: =VLOOKUP($A:$A,'COG NA'!$A:$G,5,FALSE) -> 0 | F61: =VLOOKUP($A:$A,'COG NA'!$A:$G,6,FALSE) -> 0 | G61: =VLOOKUP($A:$A,'COG NA'!$A:$G,7,FALSE) -> 1.3 | H61: =SUM(E61:G61) -> 1.3 | J61: ='PIN PAPA V GRUCIFIX'!$C$64 -> 0 | K61: ='PIN PAPA V GRUCIFIX'!$G$64 -> 0 | L61: ='PIN PAPA V GRUCIFIX'!$L$64 -> 0 | M61: ='PIN PAPA V GRUCIFIX'!$S$64 -> 0 | N61: ='PIN PAPA V GRUCIFIX'!$M$64 -> 0 | R61: ='PIN PAPA V GRUCIFIX'!$V$39 -> 0 | S61: ='PIN PAPA V GRUCIFIX'!$V$40 -> 0 | T61: ='PIN PAPA V GRUCIFIX'!$V$41 -> 0 | U61: ='PIN PAPA V GRUCIFIX'!$V$44 -> 0 | V61: ='PIN PAPA V GRUCIFIX'!$V$42 -> 0 | W61: ='PIN PAPA V GRUCIFIX'!$V$43 -> 0 | X61: ='PIN PAPA V GRUCIFIX'!$V$46 -> 0 | Y61: ='PIN PAPA V GRUCIFIX'!$V$47 -> 0 | Z61: ='PIN PAPA V GRUCIFIX'!$V$48 -> 0 | AA61: ='PIN PAPA V GRUCIFIX'!$V$49 -> 0 | AB61: ='PIN PAPA V GRUCIFIX'!$V$50 -> 0 | AC61: ='PIN PAPA V GRUCIFIX'!$V$51 -> 0 | AD61: ='PIN PAPA V GRUCIFIX'!V$52+'PIN PAPA V GRUCIFIX'!V$53 -> 0 | AE61: =(R61+S61)-SUM(T61:AC61) -> 0
A62: 56 | B62: GHOSRX204004OT | C62: COIN | D62: ZACK THE MAKER | E62: =VLOOKUP($A:$A,'COG NA'!$A:$G,5,FALSE) -> 0 | F62: =VLOOKUP($A:$A,'COG NA'!$A:$G,6,FALSE) -> 0 | G62: =VLOOKUP($A:$A,'COG NA'!$A:$G,7,FALSE) -> 0 | H62: =SUM(E62:G62) -> 0 | J62: =COIN!$C$64 -> 0 | K62: =COIN!$G$64 -> 0 | L62: =COIN!$L$64 -> 0 | M62: =COIN!$S$64 -> 0 | N62: =COIN!$M$64 -> 0 | R62: =COIN!$V$39 -> 0 | S62: =COIN!$V$40 -> 0 | T62: =COIN!$V$41 -> 0 | U62: =COIN!$V$44 -> 0 | V62: =COIN!$V$42 -> 0 | W62: =COIN!$V$43 -> 0 | X62: =COIN!$V$46 -> 0 | Y62: =COIN!$V$47 -> 0 | Z62: =COIN!$V$48 -> 0 | AA62: =COIN!$V$49 -> 0 | AB62: =COIN!$V$50 -> 0 | AC62: =COIN!$V$51 -> 0 | AD62: =COIN!V$52+COIN!V$53 -> 0 | AE62: =(R62+S62)-SUM(T62:AC62) -> 0
A63: 57 | B63: GHOSRX103932BK | C63: SNAPBACK CAP PAPA WINGS | D63: WELL SUCCEED | E63: =VLOOKUP($A:$A,'COG NA'!$A:$G,5,FALSE) -> 0 | F63: =VLOOKUP($A:$A,'COG NA'!$A:$G,6,FALSE) -> 0 | G63: =VLOOKUP($A:$A,'COG NA'!$A:$G,7,FALSE) -> 4.25 | H63: =SUM(E63:G63) -> 4.25 | J63: ='SNAPBACK CAP'!$C$64 -> 0 | K63: ='SNAPBACK CAP'!$G$64 -> 0 | L63: ='SNAPBACK CAP'!$L$64 -> 0 | M63: ='SNAPBACK CAP'!$S$64 -> 0 | N63: ='SNAPBACK CAP'!$M$64 -> 0 | R63: ='SNAPBACK CAP'!$V$39 -> 0 | S63: ='SNAPBACK CAP'!$V$40 -> 5000 | T63: ='SNAPBACK CAP'!$V$41 -> 0 | U63: ='SNAPBACK CAP'!$V$44 -> 0 | V63: ='SNAPBACK CAP'!$V$42 -> 0 | W63: ='SNAPBACK CAP'!$V$43 -> 0 | X63: ='SNAPBACK CAP'!$V$46 -> 0 | Y63: ='SNAPBACK CAP'!$V$47 -> 0 | Z63: ='SNAPBACK CAP'!$V$48 -> 0 | AA63: ='SNAPBACK CAP'!$V$49 -> 0 | AB63: ='SNAPBACK CAP'!$V$50 -> 0 | AC63: ='SNAPBACK CAP'!$V$51 -> 0 | AD63: ='SNAPBACK CAP'!V$52+'SNAPBACK CAP'!V$53 -> 5000 | AE63: =(R63+S63)-SUM(T63:AC63) -> 5000
A64: 58 | B64: GHOSRX103934PU | C64: ROSARY ROSE BEAD | D64: FARSTAR | E64: =VLOOKUP($A:$A,'COG NA'!$A:$G,5,FALSE) -> 0 | F64: =VLOOKUP($A:$A,'COG NA'!$A:$G,6,FALSE) -> 0 | G64: =VLOOKUP($A:$A,'COG NA'!$A:$G,7,FALSE) -> 6.3 | H64: =SUM(E64:G64) -> 6.3 | J64: ='ROSARY ROSE BEAD'!$C$64 -> 0 | K64: ='ROSARY ROSE BEAD'!$G$64 -> 0 | L64: ='ROSARY ROSE BEAD'!$L$64 -> 0 | M64: ='ROSARY ROSE BEAD'!$S$64 -> 0 | N64: ='ROSARY ROSE BEAD'!$M$64 -> 0 | R64: ='ROSARY ROSE BEAD'!$V$39 -> 0 | S64: ='ROSARY ROSE BEAD'!$V$40 -> 0 | T64: ='ROSARY ROSE BEAD'!$V$41 -> 0 | U64: ='ROSARY ROSE BEAD'!$V$44 -> 0 | V64: ='ROSARY ROSE BEAD'!$V$42 -> 0 | W64: ='ROSARY ROSE BEAD'!$V$43 -> 0 | X64: ='ROSARY ROSE BEAD'!$V$46 -> 0 | Y64: ='ROSARY ROSE BEAD'!$V$47 -> 0 | Z64: ='ROSARY ROSE BEAD'!$V$48 -> 0 | AA64: ='ROSARY ROSE BEAD'!$V$49 -> 0 | AB64: ='ROSARY ROSE BEAD'!$V$50 -> 0 | AC64: ='ROSARY ROSE BEAD'!$V$51 -> 0 | AD64: ='ROSARY ROSE BEAD'!V$52+'ROSARY ROSE BEAD'!V$53 -> 0 | AE64: =(R64+S64)-SUM(T64:AC64) -> 0
A65: 59 | B65: GHOSNS103814BK | C65: PROGRAM | D65: VANDALAY | E65: =VLOOKUP($A:$A,'COG NA'!$A:$G,5,FALSE) -> 0 | F65: =VLOOKUP($A:$A,'COG NA'!$A:$G,6,FALSE) -> 0 | G65: =VLOOKUP($A:$A,'COG NA'!$A:$G,7,FALSE) -> 3.85 | H65: =SUM(E65:G65) -> 3.85 | J65: =PROGRAM!$C$64 -> 0 | K65: =PROGRAM!$G$64 -> 0 | L65: =PROGRAM!$L$64 -> 0 | M65: =PROGRAM!$S$64 -> 0 | N65: =PROGRAM!$M$64 -> 0 | R65: =PROGRAM!$V$39 -> 0 | S65: =PROGRAM!$V$40 -> 0 | T65: =PROGRAM!$V$41 -> 0 | U65: =PROGRAM!$V$44 -> 0 | V65: =PROGRAM!$V$42 -> 0 | W65: =PROGRAM!$V$43 -> 0 | X65: =PROGRAM!$V$46 -> 0 | Y65: =PROGRAM!$V$47 -> 0 | Z65: =PROGRAM!$V$48 -> 0 | AA65: =PROGRAM!$V$49 -> 0 | AB65: =PROGRAM!$V$50 -> 0 | AC65: =PROGRAM!$V$51 -> 0 | AD65: =PROGRAM!V$52+PROGRAM!V$53 -> 0 | AE65: =(R65+S65)-SUM(T65:AC65) -> 0
A66: 60 | E66: =VLOOKUP($A:$A,'COG NA'!$A:$G,5,FALSE) -> 0 | F66: =VLOOKUP($A:$A,'COG NA'!$A:$G,6,FALSE) -> 0 | G66: =VLOOKUP($A:$A,'COG NA'!$A:$G,7,FALSE) -> 3.6 | H66: =SUM(E66:G66) -> 3.6 | J66: ='60'!$C$64 -> 0 | K66: ='60'!$G$64 -> 0 | L66: ='60'!$L$64 -> 0 | M66: ='60'!$S$64 -> 0 | N66: ='60'!$M$64 -> 0 | R66: ='60'!$V$39 -> 0 | S66: ='60'!$V$40 -> 0 | T66: ='60'!$V$41 -> 0 | U66: ='60'!$V$44 -> 0 | V66: ='60'!$V$42 -> 0 | W66: ='60'!$V$43 -> 0 | X66: ='60'!$V$46 -> 0 | Y66: ='60'!$V$47 -> 0 | Z66: ='60'!$V$48 -> 0 | AA66: ='60'!$V$49 -> 0 | AB66: ='60'!$V$50 -> 0 | AC66: ='60'!$V$51 -> 0 | AD66: ='60'!V$52+'60'!V$53 -> 0 | AE66: =(R66+S66)-SUM(T66:AC66) -> 0
A67: 61 | E67: =VLOOKUP($A:$A,'COG NA'!$A:$G,5,FALSE) -> 0 | F67: =VLOOKUP($A:$A,'COG NA'!$A:$G,6,FALSE) -> 0 | G67: =VLOOKUP($A:$A,'COG NA'!$A:$G,7,FALSE) -> 1.5 | H67: =SUM(E67:G67) -> 1.5 | J67: ='61'!$C$64 -> 0 | K67: ='61'!$G$64 -> 0 | L67: ='61'!$L$64 -> 0 | M67: ='61'!$S$64 -> 0 | N67: ='61'!$M$64 -> 0 | R67: ='61'!$V$39 -> 0 | S67: ='61'!$V$40 -> 0 | T67: ='61'!$V$41 -> 0 | U67: ='61'!$V$44 -> 0 | V67: ='61'!$V$42 -> 0 | W67: ='61'!$V$43 -> 0 | X67: ='61'!$V$46 -> 0 | Y67: ='61'!$V$47 -> 0 | Z67: ='61'!$V$48 -> 0 | AA67: ='61'!$V$49 -> 0 | AB67: ='61'!$V$50 -> 0 | AC67: ='61'!$V$51 -> 0 | AD67: ='61'!V$52+'61'!V$53 -> 0 | AE67: =(R67+S67)-SUM(T67:AC67) -> 0
A68: 62 | E68: =VLOOKUP($A:$A,'COG NA'!$A:$G,5,FALSE) -> 0 | F68: =VLOOKUP($A:$A,'COG NA'!$A:$G,6,FALSE) -> 0 | G68: =VLOOKUP($A:$A,'COG NA'!$A:$G,7,FALSE) -> 2.05 | H68: =SUM(E68:G68) -> 2.05 | J68: ='62'!$C$64 -> 0 | K68: ='62'!$G$64 -> 0 | L68: ='62'!$L$64 -> 0 | M68: ='62'!$S$64 -> 0 | N68: ='62'!$M$64 -> 0 | R68: ='62'!$V$39 -> 0 | S68: ='62'!$V$40 -> 0 | T68: ='62'!$V$41 -> 0 | U68: ='62'!$V$44 -> 0 | V68: ='62'!$V$42 -> 0 | W68: ='62'!$V$43 -> 0 | X68: ='62'!$V$46 -> 0 | Y68: ='62'!$V$47 -> 0 | Z68: ='62'!$V$48 -> 0 | AA68: ='62'!$V$49 -> 0 | AB68: ='62'!$V$50 -> 0 | AC68: ='62'!$V$51 -> 0 | AD68: ='62'!V$52+'62'!V$53 -> 0 | AE68: =(R68+S68)-SUM(T68:AC68) -> 0
A69: 63 | E69: =VLOOKUP($A:$A,'COG NA'!$A:$G,5,FALSE) -> 0 | F69: =VLOOKUP($A:$A,'COG NA'!$A:$G,6,FALSE) -> 0 | G69: =VLOOKUP($A:$A,'COG NA'!$A:$G,7,FALSE) -> 0 | H69: =SUM(E69:G69) -> 0 | J69: ='63'!$C$64 -> 0 | K69: ='63'!$G$64 -> 0 | L69: ='63'!$L$64 -> 0 | M69: ='63'!$S$64 -> 0 | N69: ='63'!$M$64 -> 0 | R69: ='63'!$V$39 -> 0 | S69: ='63'!$V$40 -> 0 | T69: ='63'!$V$41 -> 0 | U69: ='63'!$V$44 -> 0 | V69: ='63'!$V$42 -> 0 | W69: ='63'!$V$43 -> 0 | X69: ='63'!$V$46 -> 0 | Y69: ='63'!$V$47 -> 0 | Z69: ='63'!$V$48 -> 0 | AA69: ='63'!$V$49 -> 0 | AB69: ='63'!$V$50 -> 0 | AC69: ='63'!$V$51 -> 0 | AD69: ='63'!V$52+'63'!V$53 -> 0 | AE69: =(R69+S69)-SUM(T69:AC69) -> 0
A70: 64 | E70: =VLOOKUP($A:$A,'COG NA'!$A:$G,5,FALSE) -> 0 | F70: =VLOOKUP($A:$A,'COG NA'!$A:$G,6,FALSE) -> 0 | G70: =VLOOKUP($A:$A,'COG NA'!$A:$G,7,FALSE) -> 16.89 | H70: =SUM(E70:G70) -> 16.89 | J70: ='64'!$C$64 -> 0 | K70: ='64'!$G$64 -> 0 | L70: ='64'!$L$64 -> 0 | M70: ='64'!$S$64 -> 0 | N70: ='64'!$M$64 -> 0 | R70: ='64'!$V$39 -> 0 | S70: ='64'!$V$40 -> 0 | T70: ='64'!$V$41 -> 0 | U70: ='64'!$V$44 -> 0 | V70: ='64'!$V$42 -> 0 | W70: ='64'!$V$43 -> 0 | X70: ='64'!$V$46 -> 0 | Y70: ='64'!$V$47 -> 0 | Z70: ='64'!$V$48 -> 0 | AA70: ='64'!$V$49 -> 0 | AB70: ='64'!$V$50 -> 0 | AC70: ='64'!$V$51 -> 0 | AD70: ='64'!V$52+'64'!V$53 -> 0 | AE70: =(R70+S70)-SUM(T70:AC70) -> 0
A71: 65 | E71: =VLOOKUP($A:$A,'COG NA'!$A:$G,5,FALSE) -> 0 | F71: =VLOOKUP($A:$A,'COG NA'!$A:$G,6,FALSE) -> 0 | G71: =VLOOKUP($A:$A,'COG NA'!$A:$G,7,FALSE) -> 4.25 | H71: =SUM(E71:G71) -> 4.25 | J71: ='65'!$C$64 -> 0 | K71: ='65'!$G$64 -> 0 | L71: ='65'!$L$64 -> 0 | M71: ='65'!$S$64 -> 0 | N71: ='65'!$M$64 -> 0 | R71: ='65'!$V$39 -> 0 | S71: ='65'!$V$40 -> 0 | T71: ='65'!$V$41 -> 0 | U71: ='65'!$V$44 -> 0 | V71: ='65'!$V$42 -> 0 | W71: ='65'!$V$43 -> 0 | X71: ='65'!$V$46 -> 0 | Y71: ='65'!$V$47 -> 0 | Z71: ='65'!$V$48 -> 0 | AA71: ='65'!$V$49 -> 0 | AB71: ='65'!$V$50 -> 0 | AC71: ='65'!$V$51 -> 0 | AD71: ='65'!V$52+'65'!V$53 -> 0 | AE71: =(R71+S71)-SUM(T71:AC71) -> 0
A72: 66 | E72: =VLOOKUP($A:$A,'COG NA'!$A:$G,5,FALSE) -> 0 | F72: =VLOOKUP($A:$A,'COG NA'!$A:$G,6,FALSE) -> 0 | G72: =VLOOKUP($A:$A,'COG NA'!$A:$G,7,FALSE) -> 2 | H72: =SUM(E72:G72) -> 2 | J72: ='66'!$C$64 -> 0 | K72: ='66'!$G$64 -> 0 | L72: ='66'!$L$64 -> 0 | M72: ='66'!$S$64 -> 0 | N72: ='66'!$M$64 -> 0 | R72: ='66'!$V$39 -> 0 | S72: ='66'!$V$40 -> 0 | T72: ='66'!$V$41 -> 0 | U72: ='66'!$V$44 -> 0 | V72: ='66'!$V$42 -> 0 | W72: ='66'!$V$43 -> 0 | X72: ='66'!$V$46 -> 0 | Y72: ='66'!$V$47 -> 0 | Z72: ='66'!$V$48 -> 0 | AA72: ='66'!$V$49 -> 0 | AB72: ='66'!$V$50 -> 0 | AC72: ='66'!$V$51 -> 0 | AD72: ='66'!V$52+'66'!V$53 -> 0 | AE72: =(R72+S72)-SUM(T72:AC72) -> 0
A73: 67 | B73: GHOSRX103241BK | C73: CHOKER PAPA V | D73: FARSTAR | E73: =VLOOKUP($A:$A,'COG NA'!$A:$G,5,FALSE) -> 0 | F73: =VLOOKUP($A:$A,'COG NA'!$A:$G,6,FALSE) -> 0 | G73: =VLOOKUP($A:$A,'COG NA'!$A:$G,7,FALSE) -> 2 | H73: =SUM(E73:G73) -> 2 | J73: ='67'!$C$64 -> 0 | K73: ='67'!$G$64 -> 0 | L73: ='67'!$L$64 -> 0 | M73: ='67'!$S$64 -> 0 | N73: ='67'!$M$64 -> 0 | R73: ='67'!$V$39 -> 0 | S73: ='67'!$V$40 -> 0 | T73: ='67'!$V$41 -> 0 | U73: ='67'!$V$44 -> 0 | V73: ='67'!$V$42 -> 0 | W73: ='67'!$V$43 -> 0 | X73: ='67'!$V$46 -> 0 | Y73: ='67'!$V$47 -> 0 | Z73: ='67'!$V$48 -> 0 | AA73: ='67'!$V$49 -> 0 | AB73: ='67'!$V$50 -> 0 | AC73: ='67'!$V$51 -> 0 | AD73: ='67'!V$52+'67'!V$53 -> 0 | AE73: =(R73+S73)-SUM(T73:AC73) -> 0
A74: 68 | B74: GHOSRX203254GR | C74: KEYCHAIN SKELETON GRUCIFIX | D74: FARSTAR | E74: =VLOOKUP($A:$A,'COG NA'!$A:$G,5,FALSE) -> 0 | F74: =VLOOKUP($A:$A,'COG NA'!$A:$G,6,FALSE) -> 0 | G74: =VLOOKUP($A:$A,'COG NA'!$A:$G,7,FALSE) -> 2 | H74: =SUM(E74:G74) -> 2 | J74: ='68'!$C$64 -> 0 | K74: ='68'!$G$64 -> 0 | L74: ='68'!$L$64 -> 0 | M74: ='68'!$S$64 -> 0 | N74: ='68'!$M$64 -> 0 | R74: ='68'!$V$39 -> 0 | S74: ='68'!$V$40 -> 0 | T74: ='68'!$V$41 -> 0 | U74: ='68'!$V$44 -> 0 | V74: ='68'!$V$42 -> 0 | W74: ='68'!$V$43 -> 0 | X74: ='68'!$V$46 -> 0 | Y74: ='68'!$V$47 -> 0 | Z74: ='68'!$V$48 -> 0 | AA74: ='68'!$V$49 -> 0 | AB74: ='68'!$V$50 -> 0 | AC74: ='68'!$V$51 -> 0 | AD74: ='68'!V$52+'68'!V$53 -> 0 | AE74: =(R74+S74)-SUM(T74:AC74) -> 0
A75: 69 | B75: GHOSRX903403OT | C75: PATCH SET OF 3 | D75: FARSTAR | E75: =VLOOKUP($A:$A,'COG NA'!$A:$G,5,FALSE) -> 0 | F75: =VLOOKUP($A:$A,'COG NA'!$A:$G,6,FALSE) -> 0 | G75: =VLOOKUP($A:$A,'COG NA'!$A:$G,7,FALSE) -> 11.59 | H75: =SUM(E75:G75) -> 11.59 | J75: ='69'!$C$64 -> 0 | K75: ='69'!$G$64 -> 0 | L75: ='69'!$L$64 -> 0 | M75: ='69'!$S$64 -> 0 | N75: ='69'!$M$64 -> 0 | R75: ='69'!$V$39 -> 0 | S75: ='69'!$V$40 -> 0 | T75: ='69'!$V$41 -> 0 | U75: ='69'!$V$44 -> 0 | V75: ='69'!$V$42 -> 0 | W75: ='69'!$V$43 -> 0 | X75: ='69'!$V$46 -> 0 | Y75: ='69'!$V$47 -> 0 | Z75: ='69'!$V$48 -> 0 | AA75: ='69'!$V$49 -> 0 | AB75: ='69'!$V$50 -> 0 | AC75: ='69'!$V$51 -> 0 | AD75: ='69'!V$52+'69'!V$53 -> 0 | AE75: =(R75+S75)-SUM(T75:AC75) -> 0
A76: 70 | B76: =VLOOKUP(A:A,'COG NA'!A:B,2,FALSE) -> GHOSRX003611BK | E76: =VLOOKUP($A:$A,'COG NA'!$A:$G,5,FALSE) -> 0 | F76: =VLOOKUP($A:$A,'COG NA'!$A:$G,6,FALSE) -> 0 | G76: =VLOOKUP($A:$A,'COG NA'!$A:$G,7,FALSE) -> 24.1 | H76: =SUM(E76:G76) -> 24.1 | J76: ='70'!$C$64 -> 0 | K76: ='70'!$G$64 -> 0 | L76: ='70'!$L$64 -> 0 | M76: ='70'!$S$64 -> 0 | N76: ='70'!$M$64 -> 0 | R76: ='70'!$V$39 -> 0 | S76: ='70'!$V$40 -> 0 | T76: ='70'!$V$41 -> 0 | U76: ='70'!$V$44 -> 0 | V76: ='70'!$V$42 -> 0 | W76: ='70'!$V$43 -> 0 | X76: ='70'!$V$46 -> 0 | Y76: ='70'!$V$47 -> 0 | Z76: ='70'!$V$48 -> 0 | AA76: ='70'!$V$49 -> 0 | AB76: ='70'!$V$50 -> 0 | AC76: ='70'!$V$51 -> 0 | AD76: ='70'!V$52+'70'!V$53 -> 0 | AE76: =(R76+S76)-SUM(T76:AC76) -> 0
A77: 71 | B77: GHOSRX903408OT | C77: LP SKELETA POLTERGEIST | D77: CONCORD | E77: =VLOOKUP($A:$A,'COG NA'!$A:$G,5,FALSE) -> 0 | F77: =VLOOKUP($A:$A,'COG NA'!$A:$G,6,FALSE) -> 0 | G77: =VLOOKUP($A:$A,'COG NA'!$A:$G,7,FALSE) -> 0 | H77: =SUM(E77:G77) -> 0 | J77: ='71'!$C$64 -> 0 | K77: ='71'!$G$64 -> 0 | L77: ='71'!$L$64 -> 0 | M77: ='71'!$S$64 -> 0 | N77: ='71'!$M$64 -> 0 | R77: ='71'!$V$39 -> 0 | S77: ='71'!$V$40 -> 0 | T77: ='71'!$V$41 -> 0 | U77: ='71'!$V$44 -> 0 | V77: ='71'!$V$42 -> 0 | W77: ='71'!$V$43 -> 0 | X77: ='71'!$V$46 -> 0 | Y77: ='71'!$V$47 -> 0 | Z77: ='71'!$V$48 -> 0 | AA77: ='71'!$V$49 -> 0 | AB77: ='71'!$V$50 -> 0 | AC77: ='71'!$V$51 -> 0 | AD77: ='71'!V$52+'71'!V$53 -> 0 | AE77: =(R77+S77)-SUM(T77:AC77) -> 0
A78: 72 | B78: GHOSNS203369OT | C78: FOILED COMIC BOOK SISTER IMPERATOR # 1 | D78: DARK HORSE COMICS | E78: =VLOOKUP($A:$A,'COG NA'!$A:$G,5,FALSE) -> 0 | F78: =VLOOKUP($A:$A,'COG NA'!$A:$G,6,FALSE) -> 0 | G78: =VLOOKUP($A:$A,'COG NA'!$A:$G,7,FALSE) -> 0 | H78: =SUM(E78:G78) -> 0 | J78: ='72'!$C$64 -> 0 | K78: ='72'!$G$64 -> 0 | L78: ='72'!$L$64 -> 0 | M78: ='72'!$S$64 -> 0 | N78: ='72'!$M$64 -> 0 | R78: ='72'!$V$39 -> 0 | S78: ='72'!$V$40 -> 0 | T78: ='72'!$V$41 -> 0 | U78: ='72'!$V$44 -> 0 | V78: ='72'!$V$42 -> 0 | W78: ='72'!$V$43 -> 0 | X78: ='72'!$V$46 -> 0 | Y78: ='72'!$V$47 -> 0 | Z78: ='72'!$V$48 -> 0 | AA78: ='72'!$V$49 -> 0 | AB78: ='72'!$V$50 -> 0 | AC78: ='72'!$V$51 -> 0 | AD78: ='72'!V$52+'72'!V$53 -> 0 | AE78: =(R78+S78)-SUM(T78:AC78) -> 0
A79: 73 | B79: GHOSNS103619OT | C79: FOILED COMIC BOOK SISTER IMPERATOR #2 | D79: DARK HORSE COMICS | E79: =VLOOKUP($A:$A,'COG NA'!$A:$G,5,FALSE) -> 0 | F79: =VLOOKUP($A:$A,'COG NA'!$A:$G,6,FALSE) -> 0 | G79: =VLOOKUP($A:$A,'COG NA'!$A:$G,7,FALSE) -> 0 | H79: =SUM(E79:G79) -> 0 | J79: ='73'!$C$64 -> 0 | K79: ='73'!$G$64 -> 0 | L79: ='73'!$L$64 -> 0 | M79: ='73'!$S$64 -> 0 | N79: ='73'!$M$64 -> 0 | R79: ='73'!$V$39 -> 0 | S79: ='73'!$V$40 -> 0 | T79: ='73'!$V$41 -> 0 | U79: ='73'!$V$44 -> 0 | V79: ='73'!$V$42 -> 0 | W79: ='73'!$V$43 -> 0 | X79: ='73'!$V$46 -> 0 | Y79: ='73'!$V$47 -> 0 | Z79: ='73'!$V$48 -> 0 | AA79: ='73'!$V$49 -> 0 | AB79: ='73'!$V$50 -> 0 | AC79: ='73'!$V$51 -> 0 | AD79: ='73'!V$52+'73'!V$53 -> 0 | AE79: =(R79+S79)-SUM(T79:AC79) -> 0
A80: 74 | B80: GHOSNS103622OT | C80: FOILED COMIC BOOK SISTER IMPERATOR #3 | D80: DARK HORSE COMICS | E80: =VLOOKUP($A:$A,'COG NA'!$A:$G,5,FALSE) -> 0 | F80: =VLOOKUP($A:$A,'COG NA'!$A:$G,6,FALSE) -> 0 | G80: =VLOOKUP($A:$A,'COG NA'!$A:$G,7,FALSE) -> 0 | H80: =SUM(E80:G80) -> 0 | J80: ='74'!$C$64 -> 0 | K80: ='74'!$G$64 -> 0 | L80: ='74'!$L$64 -> 0 | M80: ='74'!$S$64 -> 0 | N80: ='74'!$M$64 -> 0 | R80: ='74'!$V$39 -> 0 | S80: ='74'!$V$40 -> 0 | T80: ='74'!$V$41 -> 0 | U80: ='74'!$V$44 -> 0 | V80: ='74'!$V$42 -> 0 | W80: ='74'!$V$43 -> 0 | X80: ='74'!$V$46 -> 0 | Y80: ='74'!$V$47 -> 0 | Z80: ='74'!$V$48 -> 0 | AA80: ='74'!$V$49 -> 0 | AB80: ='74'!$V$50 -> 0 | AC80: ='74'!$V$51 -> 0 | AD80: ='74'!V$52+'74'!V$53 -> 0 | AE80: =(R80+S80)-SUM(T80:AC80) -> 0
A81: 75 | B81: GHOSNS103624OT | C81: FOILED COMIC BOOK SISTER IMPERATOR #4 | D81: DARK HORSE COMICS | E81: =VLOOKUP($A:$A,'COG NA'!$A:$G,5,FALSE) -> 0 | F81: =VLOOKUP($A:$A,'COG NA'!$A:$G,6,FALSE) -> 0 | G81: =VLOOKUP($A:$A,'COG NA'!$A:$G,7,FALSE) -> 0 | H81: =SUM(E81:G81) -> 0 | J81: ='75'!$C$64 -> 0 | K81: ='75'!$G$64 -> 0 | L81: ='75'!$L$64 -> 0 | M81: ='75'!$S$64 -> 0 | N81: ='75'!$M$64 -> 0 | R81: ='75'!$V$39 -> 0 | S81: ='75'!$V$40 -> 0 | T81: ='75'!$V$41 -> 0 | U81: ='75'!$V$44 -> 0 | V81: ='75'!$V$42 -> 0 | W81: ='75'!$V$43 -> 0 | X81: ='75'!$V$46 -> 0 | Y81: ='75'!$V$47 -> 0 | Z81: ='75'!$V$48 -> 0 | AA81: ='75'!$V$49 -> 0 | AB81: ='75'!$V$50 -> 0 | AC81: ='75'!$V$51 -> 0 | AD81: ='75'!V$52+'75'!V$53 -> 0 | AE81: =(R81+S81)-SUM(T81:AC81) -> 0
A82: 76 | B82: GHOSRX003470OT | C82: ROLLING STONE MAG & ALBUM | D82: GMSUK | E82: =VLOOKUP($A:$A,'COG NA'!$A:$G,5,FALSE) -> 0 | F82: =VLOOKUP($A:$A,'COG NA'!$A:$G,6,FALSE) -> 0 | G82: =VLOOKUP($A:$A,'COG NA'!$A:$G,7,FALSE) -> 0 | H82: =SUM(E82:G82) -> 0 | J82: ='76'!$C$64 -> 0 | K82: ='76'!$G$64 -> 0 | L82: ='76'!$L$64 -> 0 | M82: ='76'!$S$64 -> 0 | N82: ='76'!$M$64 -> 0 | R82: ='76'!$V$39 -> 0 | S82: ='76'!$V$40 -> 0 | T82: ='76'!$V$41 -> 0 | U82: ='76'!$V$44 -> 0 | V82: ='76'!$V$42 -> 0 | W82: ='76'!$V$43 -> 0 | X82: ='76'!$V$46 -> 0 | Y82: ='76'!$V$47 -> 0 | Z82: ='76'!$V$48 -> 0 | AA82: ='76'!$V$49 -> 0 | AB82: ='76'!$V$50 -> 0 | AC82: ='76'!$V$51 -> 0 | AD82: ='76'!V$52+'76'!V$53 -> 0 | AE82: =(R82+S82)-SUM(T82:AC82) -> 0
A83: 77 | B83: GHOSRX003611BK | C83: LP SKELETA BLACK VINYL | D83: GMSUK | E83: =VLOOKUP($A:$A,'COG NA'!$A:$G,5,FALSE) -> 0 | F83: =VLOOKUP($A:$A,'COG NA'!$A:$G,6,FALSE) -> 0 | G83: =VLOOKUP($A:$A,'COG NA'!$A:$G,7,FALSE) -> 0 | H83: =SUM(E83:G83) -> 0 | J83: ='77'!$C$64 -> 0 | K83: ='77'!$G$64 -> 0 | L83: ='77'!$L$64 -> 0 | M83: ='77'!$S$64 -> 0 | N83: ='77'!$M$64 -> 0 | R83: ='77'!$V$39 -> 0 | S83: ='77'!$V$40 -> 0 | T83: ='77'!$V$41 -> 0 | U83: ='77'!$V$44 -> 0 | V83: ='77'!$V$42 -> 0 | W83: ='77'!$V$43 -> 0 | X83: ='77'!$V$46 -> 0 | Y83: ='77'!$V$47 -> 0 | Z83: ='77'!$V$48 -> 0 | AA83: ='77'!$V$49 -> 0 | AB83: ='77'!$V$50 -> 0 | AC83: ='77'!$V$51 -> 0 | AD83: ='77'!V$52+'77'!V$53 -> 0 | AE83: =(R83+S83)-SUM(T83:AC83) -> 0
A84: 78 | B84: GHOSCG103805PU | C84: LP PURPLE LENTICULAR (CONSIGNMENT) | D84: CONCORD | E84: =VLOOKUP($A:$A,'COG NA'!$A:$G,5,FALSE) -> 0 | F84: =VLOOKUP($A:$A,'COG NA'!$A:$G,6,FALSE) -> 0 | G84: =VLOOKUP($A:$A,'COG NA'!$A:$G,7,FALSE) -> 0 | H84: =SUM(E84:G84) -> 0 | J84: ='78'!$C$64 -> 0 | K84: ='78'!$G$64 -> 0 | L84: ='78'!$L$64 -> 0 | M84: ='78'!$S$64 -> 0 | N84: ='78'!$M$64 -> 0 | R84: ='78'!$V$39 -> 0 | S84: ='78'!$V$40 -> 0 | T84: ='78'!$V$41 -> 0 | U84: ='78'!$V$44 -> 0 | V84: ='78'!$V$42 -> 0 | W84: ='78'!$V$43 -> 0 | X84: ='78'!$V$46 -> 0 | Y84: ='78'!$V$47 -> 0 | Z84: ='78'!$V$48 -> 0 | AA84: ='78'!$V$49 -> 0 | AB84: ='78'!$V$50 -> 0 | AC84: ='78'!$V$51 -> 0 | AD84: ='78'!V$52+'78'!V$53 -> 0 | AE84: =(R84+S84)-SUM(T84:AC84) -> 0
A85: 79 | B85: GHOSCG103844BK | C85: CASSETTE (CONSIGNMENT) | D85: CONCORD | E85: =VLOOKUP($A:$A,'COG NA'!$A:$G,5,FALSE) -> 0 | F85: =VLOOKUP($A:$A,'COG NA'!$A:$G,6,FALSE) -> 0 | G85: =VLOOKUP($A:$A,'COG NA'!$A:$G,7,FALSE) -> 0 | H85: =SUM(E85:G85) -> 0 | J85: ='79'!$C$64 -> 0 | K85: ='79'!$G$64 -> 0 | L85: ='79'!$L$64 -> 0 | M85: ='79'!$S$64 -> 0 | N85: ='79'!$M$64 -> 0 | R85: ='79'!$V$39 -> 0 | S85: ='79'!$V$40 -> 0 | T85: ='79'!$V$41 -> 0 | U85: ='79'!$V$44 -> 0 | V85: ='79'!$V$42 -> 0 | W85: ='79'!$V$43 -> 0 | X85: ='79'!$V$46 -> 0 | Y85: ='79'!$V$47 -> 0 | Z85: ='79'!$V$48 -> 0 | AA85: ='79'!$V$49 -> 0 | AB85: ='79'!$V$50 -> 0 | AC85: ='79'!$V$51 -> 0 | AD85: ='79'!V$52+'79'!V$53 -> 0 | AE85: =(R85+S85)-SUM(T85:AC85) -> 0
A86: 80 | B86: =VLOOKUP(A:A,'COG NA'!A:B,2,FALSE) -> 0 | E86: =VLOOKUP($A:$A,'COG NA'!$A:$G,5,FALSE) -> 0 | F86: =VLOOKUP($A:$A,'COG NA'!$A:$G,6,FALSE) -> 0 | G86: =VLOOKUP($A:$A,'COG NA'!$A:$G,7,FALSE) -> 0 | H86: =SUM(E86:G86) -> 0 | J86: ='80'!$C$64 -> 0 | K86: ='80'!$G$64 -> 0 | L86: ='80'!$L$64 -> 0 | M86: ='80'!$S$64 -> 0 | N86: ='80'!$M$64 -> 0 | R86: ='80'!$V$39 -> 0 | S86: ='80'!$V$40 -> 0 | T86: ='80'!$V$41 -> 0 | U86: ='80'!$V$44 -> 0 | V86: ='80'!$V$42 -> 0 | W86: ='80'!$V$43 -> 0 | X86: ='80'!$V$46 -> 0 | Y86: ='80'!$V$47 -> 0 | Z86: ='80'!$V$48 -> 0 | AA86: ='80'!$V$49 -> 0 | AB86: ='80'!$V$50 -> 0 | AC86: ='80'!$V$51 -> 0 | AD86: ='80'!V$52+'80'!V$53 -> 0 | AE86: =(R86+S86)-SUM(T86:AC86) -> 0
A87: 81 | B87: =VLOOKUP(A:A,'COG NA'!A:B,2,FALSE) -> 0 | E87: =VLOOKUP($A:$A,'COG NA'!$A:$G,5,FALSE) -> 0 | F87: =VLOOKUP($A:$A,'COG NA'!$A:$G,6,FALSE) -> 0 | G87: =VLOOKUP($A:$A,'COG NA'!$A:$G,7,FALSE) -> 0 | H87: =SUM(E87:G87) -> 0 | J87: ='81'!$C$64 -> 0 | K87: ='81'!$G$64 -> 0 | L87: ='81'!$L$64 -> 0 | M87: ='81'!$S$64 -> 0 | N87: ='81'!$M$64 -> 0 | R87: ='81'!$V$39 -> 0 | S87: ='81'!$V$40 -> 0 | T87: ='81'!$V$41 -> 0 | U87: ='81'!$V$44 -> 0 | V87: ='81'!$V$42 -> 0 | W87: ='81'!$V$43 -> 0 | X87: ='81'!$V$46 -> 0 | Y87: ='81'!$V$47 -> 0 | Z87: ='81'!$V$48 -> 0 | AA87: ='81'!$V$49 -> 0 | AB87: ='81'!$V$50 -> 0 | AC87: ='81'!$V$51 -> 0 | AD87: ='81'!V$52+'81'!V$53 -> 0 | AE87: =(R87+S87)-SUM(T87:AC87) -> 0
A88: 82 | B88: =VLOOKUP(A:A,'COG NA'!A:B,2,FALSE) -> 0 | E88: =VLOOKUP($A:$A,'COG NA'!$A:$G,5,FALSE) -> 0 | F88: =VLOOKUP($A:$A,'COG NA'!$A:$G,6,FALSE) -> 0 | G88: =VLOOKUP($A:$A,'COG NA'!$A:$G,7,FALSE) -> 0 | H88: =SUM(E88:G88) -> 0 | J88: ='82'!$C$64 -> 0 | K88: ='82'!$G$64 -> 0 | L88: ='82'!$L$64 -> 0 | M88: ='82'!$S$64 -> 0 | N88: ='82'!$M$64 -> 0 | R88: ='82'!$V$39 -> 0 | S88: ='82'!$V$40 -> 0 | T88: ='82'!$V$41 -> 0 | U88: ='82'!$V$44 -> 0 | V88: ='82'!$V$42 -> 0 | W88: ='82'!$V$43 -> 0 | X88: ='82'!$V$46 -> 0 | Y88: ='82'!$V$47 -> 0 | Z88: ='82'!$V$48 -> 0 | AA88: ='82'!$V$49 -> 0 | AB88: ='82'!$V$50 -> 0 | AC88: ='82'!$V$51 -> 0 | AD88: ='82'!V$52+'82'!V$53 -> 0 | AE88: =(R88+S88)-SUM(T88:AC88) -> 0
A89: 83 | B89: =VLOOKUP(A:A,'COG NA'!A:B,2,FALSE) -> 0 | E89: =VLOOKUP($A:$A,'COG NA'!$A:$G,5,FALSE) -> 0 | F89: =VLOOKUP($A:$A,'COG NA'!$A:$G,6,FALSE) -> 0 | G89: =VLOOKUP($A:$A,'COG NA'!$A:$G,7,FALSE) -> 0 | H89: =SUM(E89:G89) -> 0 | J89: ='83'!$C$64 -> 0 | K89: ='83'!$G$64 -> 0 | L89: ='83'!$L$64 -> 0 | M89: ='83'!$S$64 -> 0 | N89: ='83'!$M$64 -> 0 | R89: ='83'!$V$39 -> 0 | S89: ='83'!$V$40 -> 0 | T89: ='83'!$V$41 -> 0 | U89: ='83'!$V$44 -> 0 | V89: ='83'!$V$42 -> 0 | W89: ='83'!$V$43 -> 0 | X89: ='83'!$V$46 -> 0 | Y89: ='83'!$V$47 -> 0 | Z89: ='83'!$V$48 -> 0 | AA89: ='83'!$V$49 -> 0 | AB89: ='83'!$V$50 -> 0 | AC89: ='83'!$V$51 -> 0 | AD89: ='83'!V$52+'83'!V$53 -> 0 | AE89: =(R89+S89)-SUM(T89:AC89) -> 0
A90: 84 | B90: =VLOOKUP(A:A,'COG NA'!A:B,2,FALSE) -> 0 | E90: =VLOOKUP($A:$A,'COG NA'!$A:$G,5,FALSE) -> 0 | F90: =VLOOKUP($A:$A,'COG NA'!$A:$G,6,FALSE) -> 0 | G90: =VLOOKUP($A:$A,'COG NA'!$A:$G,7,FALSE) -> 0 | H90: =SUM(E90:G90) -> 0 | J90: ='84'!$C$64 -> 0 | K90: ='84'!$G$64 -> 0 | L90: ='84'!$L$64 -> 0 | M90: ='84'!$S$64 -> 0 | N90: ='84'!$M$64 -> 0 | R90: ='84'!$V$39 -> 0 | S90: ='84'!$V$40 -> 0 | T90: ='84'!$V$41 -> 0 | U90: ='84'!$V$44 -> 0 | V90: ='84'!$V$42 -> 0 | W90: ='84'!$V$43 -> 0 | X90: ='84'!$V$46 -> 0 | Y90: ='84'!$V$47 -> 0 | Z90: ='84'!$V$48 -> 0 | AA90: ='84'!$V$49 -> 0 | AB90: ='84'!$V$50 -> 0 | AC90: ='84'!$V$51 -> 0 | AD90: ='84'!V$52+'84'!V$53 -> 0 | AE90: =(R90+S90)-SUM(T90:AC90) -> 0
A91: 85 | B91: =VLOOKUP(A:A,'COG NA'!A:B,2,FALSE) -> 0 | E91: =VLOOKUP($A:$A,'COG NA'!$A:$G,5,FALSE) -> 0 | F91: =VLOOKUP($A:$A,'COG NA'!$A:$G,6,FALSE) -> 0 | G91: =VLOOKUP($A:$A,'COG NA'!$A:$G,7,FALSE) -> 0 | H91: =SUM(E91:G91) -> 0 | J91: ='85'!$C$64 -> 0 | K91: ='85'!$G$64 -> 0 | L91: ='85'!$L$64 -> 0 | M91: ='85'!$S$64 -> 0 | N91: ='85'!$M$64 -> 0 | R91: ='85'!$V$39 -> 0 | S91: ='85'!$V$40 -> 0 | T91: ='85'!$V$41 -> 0 | U91: ='85'!$V$44 -> 0 | V91: ='85'!$V$42 -> 0 | W91: ='85'!$V$43 -> 0 | X91: ='85'!$V$46 -> 0 | Y91: ='85'!$V$47 -> 0 | Z91: ='85'!$V$48 -> 0 | AA91: ='85'!$V$49 -> 0 | AB91: ='85'!$V$50 -> 0 | AC91: ='85'!$V$51 -> 0 | AD91: ='85'!V$52+'85'!V$53 -> 0 | AE91: =(R91+S91)-SUM(T91:AC91) -> 0
A92: 86 | B92: =VLOOKUP(A:A,'COG NA'!A:B,2,FALSE) -> 0 | E92: =VLOOKUP($A:$A,'COG NA'!$A:$G,5,FALSE) -> 0 | F92: =VLOOKUP($A:$A,'COG NA'!$A:$G,6,FALSE) -> 0 | G92: =VLOOKUP($A:$A,'COG NA'!$A:$G,7,FALSE) -> 0 | H92: =SUM(E92:G92) -> 0 | J92: ='86'!$C$64 -> 0 | K92: ='86'!$G$64 -> 0 | L92: ='86'!$L$64 -> 0 | M92: ='86'!$S$64 -> 0 | N92: ='86'!$M$64 -> 0 | R92: ='86'!$V$39 -> 0 | S92: ='86'!$V$40 -> 0 | T92: ='86'!$V$41 -> 0 | U92: ='86'!$V$44 -> 0 | V92: ='86'!$V$42 -> 0 | W92: ='86'!$V$43 -> 0 | X92: ='86'!$V$46 -> 0 | Y92: ='86'!$V$47 -> 0 | Z92: ='86'!$V$48 -> 0 | AA92: ='86'!$V$49 -> 0 | AB92: ='86'!$V$50 -> 0 | AC92: ='86'!$V$51 -> 0 | AD92: ='86'!V$52+'86'!V$53 -> 0 | AE92: =(R92+S92)-SUM(T92:AC92) -> 0
A93: 87 | B93: =VLOOKUP(A:A,'COG NA'!A:B,2,FALSE) -> 0 | E93: =VLOOKUP($A:$A,'COG NA'!$A:$G,5,FALSE) -> 0 | F93: =VLOOKUP($A:$A,'COG NA'!$A:$G,6,FALSE) -> 0 | G93: =VLOOKUP($A:$A,'COG NA'!$A:$G,7,FALSE) -> 0 | H93: =SUM(E93:G93) -> 0 | J93: ='87'!$C$64 -> 0 | K93: ='87'!$G$64 -> 0 | L93: ='87'!$L$64 -> 0 | M93: ='87'!$S$64 -> 0 | N93: ='87'!$M$64 -> 0 | R93: ='87'!$V$39 -> 0 | S93: ='87'!$V$40 -> 0 | T93: ='87'!$V$41 -> 0 | U93: ='87'!$V$44 -> 0 | V93: ='87'!$V$42 -> 0 | W93: ='87'!$V$43 -> 0 | X93: ='87'!$V$46 -> 0 | Y93: ='87'!$V$47 -> 0 | Z93: ='87'!$V$48 -> 0 | AA93: ='87'!$V$49 -> 0 | AB93: ='87'!$V$50 -> 0 | AC93: ='87'!$V$51 -> 0 | AD93: ='87'!V$52+'87'!V$53 -> 0 | AE93: =(R93+S93)-SUM(T93:AC93) -> 0
A94: 88 | B94: =VLOOKUP(A:A,'COG NA'!A:B,2,FALSE) -> 0 | E94: =VLOOKUP($A:$A,'COG NA'!$A:$G,5,FALSE) -> 0 | F94: =VLOOKUP($A:$A,'COG NA'!$A:$G,6,FALSE) -> 0 | G94: =VLOOKUP($A:$A,'COG NA'!$A:$G,7,FALSE) -> 0 | H94: =SUM(E94:G94) -> 0 | J94: ='88'!$C$64 -> 0 | K94: ='88'!$G$64 -> 0 | L94: ='88'!$L$64 -> 0 | M94: ='88'!$S$64 -> 0 | N94: ='88'!$M$64 -> 0 | R94: ='88'!$V$39 -> 0 | S94: ='88'!$V$40 -> 0 | T94: ='88'!$V$41 -> 0 | U94: ='88'!$V$44 -> 0 | V94: ='88'!$V$42 -> 0 | W94: ='88'!$V$43 -> 0 | X94: ='88'!$V$46 -> 0 | Y94: ='88'!$V$47 -> 0 | Z94: ='88'!$V$48 -> 0 | AA94: ='88'!$V$49 -> 0 | AB94: ='88'!$V$50 -> 0 | AC94: ='88'!$V$51 -> 0 | AD94: ='88'!V$52+'88'!V$53 -> 0 | AE94: =(R94+S94)-SUM(T94:AC94) -> 0
A95: 89 | B95: =VLOOKUP(A:A,'COG NA'!A:B,2,FALSE) -> 0 | E95: =VLOOKUP($A:$A,'COG NA'!$A:$G,5,FALSE) -> 0 | F95: =VLOOKUP($A:$A,'COG NA'!$A:$G,6,FALSE) -> 0 | G95: =VLOOKUP($A:$A,'COG NA'!$A:$G,7,FALSE) -> 0 | H95: =SUM(E95:G95) -> 0 | J95: ='89'!$C$64 -> 0 | K95: ='89'!$G$64 -> 0 | L95: ='89'!$L$64 -> 0 | M95: ='89'!$S$64 -> 0 | N95: ='89'!$M$64 -> 0 | R95: ='89'!$V$39 -> 0 | S95: ='89'!$V$40 -> 0 | T95: ='89'!$V$41 -> 0 | U95: ='89'!$V$44 -> 0 | V95: ='89'!$V$42 -> 0 | W95: ='89'!$V$43 -> 0 | X95: ='89'!$V$46 -> 0 | Y95: ='89'!$V$47 -> 0 | Z95: ='89'!$V$48 -> 0 | AA95: ='89'!$V$49 -> 0 | AB95: ='89'!$V$50 -> 0 | AC95: ='89'!$V$51 -> 0 | AD95: ='89'!V$52+'89'!V$53 -> 0 | AE95: =(R95+S95)-SUM(T95:AC95) -> 0
A96: 90 | B96: =VLOOKUP(A:A,'COG NA'!A:B,2,FALSE) -> 0 | E96: =VLOOKUP($A:$A,'COG NA'!$A:$G,5,FALSE) -> 0 | F96: =VLOOKUP($A:$A,'COG NA'!$A:$G,6,FALSE) -> 0 | G96: =VLOOKUP($A:$A,'COG NA'!$A:$G,7,FALSE) -> 0 | H96: =SUM(E96:G96) -> 0 | J96: ='90'!$C$64 -> 0 | K96: ='90'!$G$64 -> 0 | L96: ='90'!$L$64 -> 0 | M96: ='90'!$S$64 -> 0 | N96: ='90'!$M$64 -> 0 | R96: ='90'!$V$39 -> 0 | S96: ='90'!$V$40 -> 0 | T96: ='90'!$V$41 -> 0 | U96: ='90'!$V$44 -> 0 | V96: ='90'!$V$42 -> 0 | W96: ='90'!$V$43 -> 0 | X96: ='90'!$V$46 -> 0 | Y96: ='90'!$V$47 -> 0 | Z96: ='90'!$V$48 -> 0 | AA96: ='90'!$V$49 -> 0 | AB96: ='90'!$V$50 -> 0 | AC96: ='90'!$V$51 -> 0 | AD96: ='90'!V$52+'90'!V$53 -> 0 | AE96: =(R96+S96)-SUM(T96:AC96) -> 0
A97: 91 | B97: =VLOOKUP(A:A,'COG NA'!A:B,2,FALSE) -> 0 | E97: =VLOOKUP($A:$A,'COG NA'!$A:$G,5,FALSE) -> 0 | F97: =VLOOKUP($A:$A,'COG NA'!$A:$G,6,FALSE) -> 0 | G97: =VLOOKUP($A:$A,'COG NA'!$A:$G,7,FALSE) -> 0 | H97: =SUM(E97:G97) -> 0 | J97: ='91'!$C$64 -> 0 | K97: ='91'!$G$64 -> 0 | L97: ='91'!$L$64 -> 0 | M97: ='91'!$S$64 -> 0 | N97: ='91'!$M$64 -> 0 | R97: ='91'!$V$39 -> 0 | S97: ='91'!$V$40 -> 0 | T97: ='91'!$V$41 -> 0 | U97: ='91'!$V$44 -> 0 | V97: ='91'!$V$42 -> 0 | W97: ='91'!$V$43 -> 0 | X97: ='91'!$V$46 -> 0 | Y97: ='91'!$V$47 -> 0 | Z97: ='91'!$V$48 -> 0 | AA97: ='91'!$V$49 -> 0 | AB97: ='91'!$V$50 -> 0 | AC97: ='91'!$V$51 -> 0 | AD97: ='91'!V$52+'91'!V$53 -> 0 | AE97: =(R97+S97)-SUM(T97:AC97) -> 0
A98: 92 | B98: =VLOOKUP(A:A,'COG NA'!A:B,2,FALSE) -> 0 | E98: =VLOOKUP($A:$A,'COG NA'!$A:$G,5,FALSE) -> 0 | F98: =VLOOKUP($A:$A,'COG NA'!$A:$G,6,FALSE) -> 0 | G98: =VLOOKUP($A:$A,'COG NA'!$A:$G,7,FALSE) -> 0 | H98: =SUM(E98:G98) -> 0 | J98: ='92'!$C$64 -> 0 | K98: ='92'!$G$64 -> 0 | L98: ='92'!$L$64 -> 0 | M98: ='92'!$S$64 -> 0 | N98: ='92'!$M$64 -> 0 | R98: ='92'!$V$39 -> 0 | S98: ='92'!$V$40 -> 0 | T98: ='92'!$V$41 -> 0 | U98: ='92'!$V$44 -> 0 | V98: ='92'!$V$42 -> 0 | W98: ='92'!$V$43 -> 0 | X98: ='92'!$V$46 -> 0 | Y98: ='92'!$V$47 -> 0 | Z98: ='92'!$V$48 -> 0 | AA98: ='92'!$V$49 -> 0 | AB98: ='92'!$V$50 -> 0 | AC98: ='92'!$V$51 -> 0 | AD98: ='92'!V$52+'92'!V$53 -> 0 | AE98: =(R98+S98)-SUM(T98:AC98) -> 0
A99: 93 | B99: =VLOOKUP(A:A,'COG NA'!A:B,2,FALSE) -> 0 | E99: =VLOOKUP($A:$A,'COG NA'!$A:$G,5,FALSE) -> 0 | F99: =VLOOKUP($A:$A,'COG NA'!$A:$G,6,FALSE) -> 0 | G99: =VLOOKUP($A:$A,'COG NA'!$A:$G,7,FALSE) -> 0 | H99: =SUM(E99:G99) -> 0 | J99: ='93'!$C$64 -> 0 | K99: ='93'!$G$64 -> 0 | L99: ='93'!$L$64 -> 0 | M99: ='93'!$S$64 -> 0 | N99: ='93'!$M$64 -> 0 | R99: ='93'!$V$39 -> 0 | S99: ='93'!$V$40 -> 0 | T99: ='93'!$V$41 -> 0 | U99: ='93'!$V$44 -> 0 | V99: ='93'!$V$42 -> 0 | W99: ='93'!$V$43 -> 0 | X99: ='93'!$V$46 -> 0 | Y99: ='93'!$V$47 -> 0 | Z99: ='93'!$V$48 -> 0 | AA99: ='93'!$V$49 -> 0 | AB99: ='93'!$V$50 -> 0 | AC99: ='93'!$V$51 -> 0 | AD99: ='93'!V$52+'93'!V$53 -> 0 | AE99: =(R99+S99)-SUM(T99:AC99) -> 0
A100: 94 | B100: =VLOOKUP(A:A,'COG NA'!A:B,2,FALSE) -> 0 | E100: =VLOOKUP($A:$A,'COG NA'!$A:$G,5,FALSE) -> 0 | F100: =VLOOKUP($A:$A,'COG NA'!$A:$G,6,FALSE) -> 0 | G100: =VLOOKUP($A:$A,'COG NA'!$A:$G,7,FALSE) -> 0 | H100: =SUM(E100:G100) -> 0 | J100: ='94'!$C$64 -> 0 | K100: ='94'!$G$64 -> 0 | L100: ='94'!$L$64 -> 0 | M100: ='94'!$S$64 -> 0 | N100: ='94'!$M$64 -> 0 | R100: ='94'!$V$39 -> 0 | S100: ='94'!$V$40 -> 0 | T100: ='94'!$V$41 -> 0 | U100: ='94'!$V$44 -> 0 | V100: ='94'!$V$42 -> 0 | W100: ='94'!$V$43 -> 0 | X100: ='94'!$V$46 -> 0 | Y100: ='94'!$V$47 -> 0 | Z100: ='94'!$V$48 -> 0 | AA100: ='94'!$V$49 -> 0 | AB100: ='94'!$V$50 -> 0 | AC100: ='94'!$V$51 -> 0 | AD100: ='94'!V$52+'94'!V$53 -> 0 | AE100: =(R100+S100)-SUM(T100:AC100) -> 0
A101: 95 | B101: =VLOOKUP(A:A,'COG NA'!A:B,2,FALSE) -> 0 | E101: =VLOOKUP($A:$A,'COG NA'!$A:$G,5,FALSE) -> 0 | F101: =VLOOKUP($A:$A,'COG NA'!$A:$G,6,FALSE) -> 0 | G101: =VLOOKUP($A:$A,'COG NA'!$A:$G,7,FALSE) -> 0 | H101: =SUM(E101:G101) -> 0 | J101: ='95'!$C$64 -> 0 | K101: ='95'!$G$64 -> 0 | L101: ='95'!$L$64 -> 0 | M101: ='95'!$S$64 -> 0 | N101: ='95'!$M$64 -> 0 | R101: ='95'!$V$39 -> 0 | S101: ='95'!$V$40 -> 0 | T101: ='95'!$V$41 -> 0 | U101: ='95'!$V$44 -> 0 | V101: ='95'!$V$42 -> 0 | W101: ='95'!$V$43 -> 0 | X101: ='95'!$V$46 -> 0 | Y101: ='95'!$V$47 -> 0 | Z101: ='95'!$V$48 -> 0 | AA101: ='95'!$V$49 -> 0 | AB101: ='95'!$V$50 -> 0 | AC101: ='95'!$V$51 -> 0 | AD101: ='95'!V$52+'95'!V$53 -> 0 | AE101: =(R101+S101)-SUM(T101:AC101) -> 0
...

Sheet BUDGET
A1: GLOBAL MERCHANDISING SERVICES, INC
A2: TOUR BUDGET - NORTH AMERICA
A4: ARTIST | B4: =Inventory!C3 -> GHOST | I4: BRAND MANAGER
A5: TERRITORY | B5: NORTH AMERICA | I5: CURRENCY | K5: USD
A6: TOUR START/LOAD IN DATE | I6: FIRST SHOW CITY
A7: TOUR FINISH/LOUD OUT DATE | I7: LAST SHOW CITY
A8: TOUR DAYS | B8: =B7-B6 -> 0 | I8: TRANSPORT - RECOUP | K8: YES
A9: ROAD MANAGER - GMS | B9: YES | I9: SECURITY - RECOUP | K9: YES
A11: TOUR ASSUMPTIONS | B11: USA | E11: CANADA | H11: FESTIVALS | K11: TOUR TOTAL
A13: TOTAL CAPACITY | K13: =E13+B13+H13 -> 0
A14: PROJ.ATTENDANCE | B14: 1 | E14: 1 | H14: 1 | K14: =IFERROR(K15/K13,0) -> 0
A15: PROJ.ATTENDANCE | B15: =B13*B14 -> 0 | E15: =E13*E14 -> 0 | H15: =H13*H14 -> 0 | K15: =E15+B15+H15 -> 0
A16: TOUR STAFF | K16: =B16 -> 0
A17: NO.OF SHOWS | K17: =E17+B17+H17 -> 0
A18: P/HEAD | K18: =IFERROR(K20/K15,0) -> 0
A20: GROSS SALES | B20: =B18*B15 -> 0 | E20: =E18*E15 -> 0 | H20: =H18*H15 -> 0 | K20: =E20+B20+H20 -> 0
A21: CREDIT CARD % | B21: 1 | E21: 1 | H21: 1 | K21: =IFERROR(K22/K20,0) -> 0
A22: CREDT CARD AMOUNT | B22: =B20*B21 -> 0 | E22: =E20*E21 -> 0 | H22: =H20*H21 -> 0 | K22: =E22+B22+H22 -> 0
A23: TAX: | B23: =B20*C23/(1+C23) -> 0 | C23: 0.08 | E23: =E20*F23/(1+F23) -> 0 | F23: 0.13 | H23: =H20*I23/(1+I23) -> 0 | I23: 0.08 | K23: =E23+B23+H23 -> 0 | L23: =IF(K23=0,0,K23/$K$24) -> 0
A24: NET SALES | B24: =B20-B23 -> 0 | E24: =E20-E23 -> 0 | H24: =H20-H23 -> 0 | K24: =E24+B24+H24 -> 0
A27: TOUR COSTS - ON NET | B27: =B11 -> USA | E27: =E11 -> CANADA | H27: =H11 -> FESTIVALS | K27: =K11 -> TOUR TOTAL
A29: COST OF GOODS | B29: =ROUND((B$24*C29),2) -> 0 | C29: 0 | E29: =ROUND((E$24*F29),2) -> 0 | F29: 0 | H29: =ROUND((H$24*I29),2) -> 0 | I29: 0 | K29: =B29+E29+H29 -> 0 | L29: =IF(K29=0,0,K29/$K$24) -> 0
A30: COST OF GOODS - UPLIFT | B30: =ROUND(B29*C30,2) -> 0 | C30: 0 | E30: =ROUND(E29*F30,2) -> 0 | F30: 0 | H30: =ROUND(H29*I30,2) -> 0 | I30: 0 | K30: =B30+E30+H30 -> 0 | L30: =IF(K30=0,0,K30/$K$24) -> 0
A31: HALL FEES | B31: =ROUND((B$24*C31),2) -> 0 | C31: 0 | E31: =ROUND((E$24*F31),2) -> 0 | F31: 0 | H31: =ROUND((H$24*I31),2) -> 0 | I31: 0 | K31: =B31+E31+H31 -> 0 | L31: =IF(K31=0,0,K31/$K$24) -> 0
A32: VENDORS | B32: =ROUND((B$24*C32),2) -> 0 | C32: 0 | E32: =ROUND((E$24*F32),2) -> 0 | F32: 0 | H32: =ROUND((H$24*I32),2) -> 0 | I32: 0 | K32: =B32+E32+H32 -> 0 | L32: =IF(K32=0,0,K32/$K$24) -> 0
A33: CREDIT CARD FEES | B33: =ROUND(((B$24*B21)*C33),2) -> 0 | C33: 0 | E33: =ROUND(((E$24*E21)*F33),2) -> 0 | F33: 0 | H33: =ROUND(((H$24*H21)*I33),2) -> 0 | I33: 0 | K33: =B33+E33+H33 -> 0 | L33: =IF(K33=0,0,K33/$K$24) -> 0
A34: BOOTLEG SECURITY & LEGAL | B34: =IF($K$9="YES",0,ROUND((B$24*C34),2)) -> 0 | C34: 0 | E34: =IF($K$9="YES",0,ROUND((E$24*F34),2)) -> 0 | F34: 0 | H34: =IF($K$9="YES",0,ROUND((H$24*I34),2)) -> 0 | I34: 0 | K34: =B34+E34+H34 -> 0 | L34: =IF(K34=0,0,K34/$K$24) -> 0
A35: FREIGHT COST | B35: =ROUND((B$24*C35),2) -> 0 | C35: 0 | E35: =ROUND((E$24*F35),2) -> 0 | F35: 0 | H35: =ROUND((H$24*I35),2) -> 0 | I35: 0 | K35: =B35+E35+H35 -> 0 | L35: =IF(K35=0,0,K35/$K$24) -> 0
A36: DUTIES/TAXES | B36: =ROUND((B$29*C36),2) -> 0 | C36: 0 | E36: =ROUND((E$29*F36),2) -> 0 | F36: 0 | H36: =ROUND((H$29*I36),2) -> 0 | I36: 0 | K36: =B36+E36+H36 -> 0 | L36: =IF(K36=0,0,K36/$K$24) -> 0
A37: ROAD EXPENSES | B37: =IF($K$8="YES",B68-SUM(B63:B66),B68) -> 0 | C37: =IF(B37=0,0,B37/B24) -> 0 | E37: =IF($K$8="YES",E68-SUM(E63:E66),E68) -> 0 | F37: =IF(E37=0,0,E37/E24) -> 0 | H37: =IF($K$8="YES",H68-SUM(H63:H66),H68) -> 0 | I37: =IF(H37=0,0,H37/H24) -> 0 | K37: =B37+E37+H37 -> 0 | L37: =IF(K37=0,0,K37/$K$24) -> 0
A38: ADMIN FEE | B38: =ROUND((B$24*C38),2) -> 0 | C38: 0.03 | E38: =ROUND((E$24*F38),2) -> 0 | F38: 0.03 | H38: =ROUND((H$24*I38),2) -> 0 | I38: 0.03 | K38: =B38+E38+H38 -> 0 | L38: =IF(K38=0,0,K38/$K$24) -> 0
A39: TRANSPORT - RECOUPABLE | B39: =IF($K$8="YES",SUM(B63:B66),0) -> 0 | C39: =IF(B39=0,0,B39/B24) -> 0 | E39: =IF($K$8="YES",SUM(E63:E66),0) -> 0 | F39: =IF(E39=0,0,E39/E24) -> 0 | H39: =IF($K$8="YES",SUM(H63:H66),0) -> 0 | I39: =IF(H39=0,0,H39/H24) -> 0 | K39: =B39+E39+H39 -> 0 | L39: =IF(K39=0,0,K39/$K$24) -> 0
A40: SECURITY - RECOUPABLE | B40: =IF($K$9="YES",ROUND((B$24*C40),2),0) -> 0 | C40: =C34 -> 0 | E40: =IF($K$9="YES",ROUND((E$24*F40),2),0) -> 0 | F40: =F34 -> 0 | H40: =IF($K$9="YES",ROUND((H$24*I40),2),0) -> 0 | I40: =I34 -> 0 | K40: =B40+E40+H40 -> 0 | L40: =IF(K40=0,0,K40/$K$24) -> 0
A42: TOTAL TOUR COSTS | B42: =SUM(B29:B38) -> 0 | C42: =IF(B42=0,0,B42/B24) -> 0 | E42: =SUM(E29:E38) -> 0 | F42: =IF(E42=0,0,E42/E24) -> 0 | H42: =SUM(H29:H38) -> 0 | I42: =IF(H42=0,0,H42/H24) -> 0 | K42: =SUM(K29:K38) -> 0 | L42: =IF(K42=0,0,K42/K24) -> 0
A43: PROFIT | B43: =B24-B42 -> 0 | C43: =IF(B43=0,0,B43/B24) -> 0 | E43: =E24-E42 -> 0 | F43: =IF(E43=0,0,E43/E24) -> 0 | H43: =H24-H42 -> 0 | I43: =IF(H43=0,0,H43/H24) -> 0 | K43: =B43+E43+H43 -> 0 | L43: =IF(K43=0,0,K43/K24) -> 0
A44: ARTIST | B44: =B43*C44 -> 0 | C44: 0.8 | E44: =E43*F44 -> 0 | F44: 0.8 | H44: =H43*I44 -> 0 | I44: 0.8 | K44: =B44+E44+H44 -> 0 | L44: =IF(K44=0,0,K44/K43) -> 0
A45: GLOBAL | B45: =B43*C45 -> 0 | C45: =1-C44 -> 0.2 | E45: =E43*F45 -> 0 | F45: =1-F44 -> 0.2 | H45: =H43*I45 -> 0 | I45: =1-I44 -> 0.2 | K45: =B45+E45+H45 -> 0 | L45: =IF(K45=0,0,K45/K43) -> 0
A48: ROAD EXPENSES BREAKDOWN | B48: =B11 -> USA | E48: =E11 -> CANADA | H48: =H11 -> FESTIVALS | K48: =K11 -> TOUR TOTAL
A50: DAYS | B50: 0 | E50: 0 | H50: 0 | K50: =B50+E50+H50 -> 0
A51: HOTELS | B51: 0 | E51: 0 | H51: 0 | K51: =B51+E51+H51 -> 0
A52: NO. OF STAFF | B52: =B16 -> 0 | C52: RATE | E52: =E16 -> 0 | F52: RATE | H52: =H16 -> 0 | I52: RATE
A54: TOUR MANAGER | B54: =C54*B50 -> 0 | E54: =F54*E50 -> 0 | H54: =I54*H50 -> 0 | K54: =B54+E54+H54 -> 0
A55: ASSISTANT MANAGER | B55: =C55*B50 -> 0 | C55: 0 | E55: =F55*E50 -> 0 | F55: 0 | H55: =I55*H50 -> 0 | K55: =B55+E55+H55 -> 0
A56: PAYROLL COSTS | B56: =(B55+B54)*C56 -> 0 | C56: =IF(B9="YES",8.5%,1%) -> 0.085 | E56: =(E55+E54)*F56 -> 0 | F56: =IF(B9="YES",8.5%,2%) -> 0.085 | H56: =(H55+H54)*I56 -> 0 | I56: =IF(B9="YES",8.5%,2%) -> 0.085 | K56: =B56+E56+H56 -> 0
A57: P/DIEMS | B57: =C57*B52*B50 -> 0 | E57: =F57*E52*E50 -> 0 | H57: =I57*H50 -> 0 | I57: 0 | K57: =B57+E57+H57 -> 0
A58: ADDITIONAL STAFF | B58: =C58*B50 -> 0 | E58: 0 | H58: 0 | K58: =B58+E58+H58 -> 0
A59: =("HOTEL - "&K51&" NIGHTS") -> HOTEL - 0 NIGHTS | B59: =C59*B51 -> 0 | C59: 0 | E59: =F59*E51 -> 0 | F59: 0 | H59: =I59*H51 -> 0 | I59: 0 | K59: =B59+E59+H59 -> 0
A60: TAXI/TRAVEL | B60: 0 | E60: 0 | H60: 0 | K60: =B60+E60+H60 -> 0
A61: PHONE / COMPUTER | B61: =C61*B50 -> 0 | C61: 0 | E61: =F61*E50 -> 0 | F61: 0 | H61: =I61*H50 -> 0 | I61: 0 | K61: =B61+E61+H61 -> 0
A62: MISCELLANEOUS | B62: 0 | E62: 0 | H62: 0 | K62: =B62+E62+H62 -> 0
A63: TRUCK RENTAL | B63: =C63*B50 -> 0 | E63: =F63*E50 -> 0 | H63: =I63*H50 -> 0 | K63: =B63+E63+H63 -> 0
A64: INS & GREEN CARD | B64: 0 | E64: 0 | H64: 0 | K64: =B64+E64+H64 -> 0
A65: FUEL | B65: 0 | E65: 0 | H65: 0 | K65: =B65+E65+H65 -> 0
A66: TOLLS | B66: 0 | E66: 0 | H66: 0 | K66: =B66+E66+H66 -> 0
A68: TOTAL ROAD EXPENSES | B68: =SUM(B54:B67) -> 0 | E68: =SUM(E54:E67) -> 0 | H68: =SUM(H54:H67) -> 0 | K68: =SUM(K54:K67) -> 0

Sheet COG NA
A1: GLOBAL MERCHANDISING SERVICES, INC.
A2: 46027
A3: TOUR COST OF GOODS SCHEDULE - NORTH AMERICA in USD
A6: Brand Manager: | C6: KAYLA
A7: Enter sales tax rate: | C7: 0
A8: Enter specials rate: | C8: N/A | E8: CLOSE WHEN PDFing and SENDING TO CLIENT
A9: APPAREL | Q9: APPAREL - ADJUSTED PRICE FOR SPECIAL
A10: ITEM # | B10: SKU # | C10: DESCRIPTION | D10: SIZE | E10: BLANK | F10: PRINT | G10: FULL PACKAGE | H10: COG | I10: COG 2 | J10: TOTAL COG | K10: SUGGESTED PRICE | L10: =("TAX @ " &C7) -> TAX @ 0 | M10: AFTER TAX ADJ. GROSS | N10: PRODUCT COST % (A.T.G.) | O10: SPECIAL YES/NO | Q10: SPECIAL ITEM PRICE | R10: =L10 -> TAX @ 0 | S10: AFTER TAX ADJ. GROSS | T10: SPECIAL COST % (A.T.G.) | U10: SPECIAL YES/NO
A11: 1 | B11: GHOSNS903311BK | C11: BATWING HOODY | D11: SM-XL | E11: 0 | F11: 0 | G11: 28.5 | H11: =SUM(E11:G11) -> 28.5 | I11: 0 | J11: =SUM(H11:I11) -> 28.5 | K11: 125 | L11: =$C$7 -> 0 | M11: =K11-IF(K11<>0,K11-(K11/(1+L11)),0) -> 125 | N11: =IFERROR(J11/M11,0) -> 0.228 | O11: =IF(N11>$C$8,"YES","NO") -> NO | Q11: 0 | R11: =$C$7 -> 0 | S11: =Q11-IF(Q11<>0,Q11-(Q11/(1+R11)),0) -> 0 | T11: =IFERROR(J11/S11,0) -> 0 | U11: =IF(T11>$C$8,"YES","NO") -> NO
D12: 2XL | E12: 0 | F12: 0 | G12: 28.5 | H12: =SUM(E12:G12) -> 28.5 | I12: 0 | J12: =SUM(H12:I12) -> 28.5 | K12: 125 | L12: =$C$7 -> 0 | M12: =K12-IF(K12<>0,K12-(K12/(1+L12)),0) -> 125 | N12: =IFERROR(J12/M12,0) -> 0.228 | O12: =IF(N12>$C$8,"YES","NO") -> NO | Q12: 0 | R12: =$C$7 -> 0 | S12: =Q12-IF(Q12<>0,Q12-(Q12/(1+R12)),0) -> 0 | T12: =IFERROR(J12/S12,0) -> 0 | U12: =IF(T12>$C$8,"YES","NO") -> NO
D13: 3XL | E13: 0 | F13: 0 | G13: 28.5 | H13: =SUM(E13:G13) -> 28.5 | I13: 0 | J13: =SUM(H13:I13) -> 28.5 | K13: 125 | L13: =$C$7 -> 0 | M13: =K13-IF(K13<>0,K13-(K13/(1+L13)),0) -> 125 | N13: =IFERROR(J13/M13,0) -> 0.228 | O13: =IF(N13>$C$8,"YES","NO") -> NO | Q13: 0 | R13: =$C$7 -> 0 | S13: =Q13-IF(Q13<>0,Q13-(Q13/(1+R13)),0) -> 0 | T13: =IFERROR(J13/S13,0) -> 0 | U13: =IF(T13>$C$8,"YES","NO") -> NO
D14: 4XL | E14: 0 | F14: 0 | G14: 0 | H14: =SUM(E14:G14) -> 0 | I14: 0 | J14: =SUM(H14:I14) -> 0 | K14: 0 | L14: =$C$7 -> 0 | M14: =K14-IF(K14<>0,K14-(K14/(1+L14)),0) -> 0 | N14: =IFERROR(J14/M14,0) -> 0 | O14: =IF(N14>$C$8,"YES","NO") -> NO | Q14: 0 | R14: =$C$7 -> 0 | S14: =Q14-IF(Q14<>0,Q14-(Q14/(1+R14)),0) -> 0 | T14: =IFERROR(J14/S14,0) -> 0 | U14: =IF(T14>$C$8,"YES","NO") -> NO
A15: =A11+1 -> 2 | B15: GHOSRX203275BK | C15: SHORTS BLK/ WHT PAPA V CLAWS | D15: SM-XL | E15: 0 | F15: 0 | G15: 5.8 | H15: =SUM(E15:G15) -> 5.8 | I15: 0 | J15: =SUM(H15:I15) -> 5.8 | K15: 50 | L15: =$C$7 -> 0 | M15: =K15-IF(K15<>0,K15-(K15/(1+L15)),0) -> 50 | N15: =IFERROR(J15/M15,0) -> 0.116 | O15: =IF(N15>$C$8,"YES","NO") -> NO | Q15: 0 | R15: =$C$7 -> 0 | S15: =Q15-IF(Q15<>0,Q15-(Q15/(1+R15)),0) -> 0 | T15: =IFERROR(J15/S15,0) -> 0 | U15: =IF(T15>$C$8,"YES","NO") -> NO
D16: 2XL | E16: 0 | F16: 0 | G16: 5.8 | H16: =SUM(E16:G16) -> 5.8 | I16: 0 | J16: =SUM(H16:I16) -> 5.8 | K16: 50 | L16: =$C$7 -> 0 | M16: =K16-IF(K16<>0,K16-(K16/(1+L16)),0) -> 50 | N16: =IFERROR(J16/M16,0) -> 0.116 | O16: =IF(N16>$C$8,"YES","NO") -> NO | Q16: 0 | R16: =$C$7 -> 0 | S16: =Q16-IF(Q16<>0,Q16-(Q16/(1+R16)),0) -> 0 | T16: =IFERROR(J16/S16,0) -> 0 | U16: =IF(T16>$C$8,"YES","NO") -> NO
D17: 3XL | E17: 0 | F17: 0 | G17: 5.8 | H17: =SUM(E17:G17) -> 5.8 | I17: 0 | J17: =SUM(H17:I17) -> 5.8 | K17: 50 | L17: =$C$7 -> 0 | M17: =K17-IF(K17<>0,K17-(K17/(1+L17)),0) -> 50 | N17: =IFERROR(J17/M17,0) -> 0.116 | O17: =IF(N17>$C$8,"YES","NO") -> NO | Q17: 0 | R17: =$C$7 -> 0 | S17: =Q17-IF(Q17<>0,Q17-(Q17/(1+R17)),0) -> 0 | T17: =IFERROR(J17/S17,0) -> 0 | U17: =IF(T17>$C$8,"YES","NO") -> NO
D18: 4XL | E18: 0 | F18: 0 | G18: 0 | H18: =SUM(E18:G18) -> 0 | I18: 0 | J18: =SUM(H18:I18) -> 0 | K18: 0 | L18: =$C$7 -> 0 | M18: =K18-IF(K18<>0,K18-(K18/(1+L18)),0) -> 0 | N18: =IFERROR(J18/M18,0) -> 0 | O18: =IF(N18>$C$8,"YES","NO") -> NO | Q18: 0 | R18: =$C$7 -> 0 | S18: =Q18-IF(Q18<>0,Q18-(Q18/(1+R18)),0) -> 0 | T18: =IFERROR(J18/S18,0) -> 0 | U18: =IF(T18>$C$8,"YES","NO") -> NO
A19: =A15+1 -> 3 | B19: GHOSRX204001BK | C19: BLACK T SKELETOUR 26 ITIN | D19: SM-XL | E19: 0 | F19: 0 | G19: 5.83 | H19: =SUM(E19:G19) -> 5.83 | I19: 0 | J19: =SUM(H19:I19) -> 5.83 | K19: 50 | L19: =$C$7 -> 0 | M19: =K19-IF(K19<>0,K19-(K19/(1+L19)),0) -> 50 | N19: =IFERROR(J19/M19,0) -> 0.1166 | O19: =IF(N19>$C$8,"YES","NO") -> NO | Q19: 0 | R19: =$C$7 -> 0 | S19: =Q19-IF(Q19<>0,Q19-(Q19/(1+R19)),0) -> 0 | T19: =IFERROR(J19/S19,0) -> 0 | U19: =IF(T19>$C$8,"YES","NO") -> NO
D20: 2XL | E20: 0 | F20: 0 | G20: 8.09 | H20: =SUM(E20:G20) -> 8.09 | I20: 0 | J20: =SUM(H20:I20) -> 8.09 | K20: 50 | L20: =$C$7 -> 0 | M20: =K20-IF(K20<>0,K20-(K20/(1+L20)),0) -> 50 | N20: =IFERROR(J20/M20,0) -> 0.1618 | O20: =IF(N20>$C$8,"YES","NO") -> NO | Q20: 0 | R20: =$C$7 -> 0 | S20: =Q20-IF(Q20<>0,Q20-(Q20/(1+R20)),0) -> 0 | T20: =IFERROR(J20/S20,0) -> 0 | U20: =IF(T20>$C$8,"YES","NO") -> NO
D21: 3XL | E21: 0 | F21: 0 | G21: 9.46 | H21: =SUM(E21:G21) -> 9.46 | I21: 0 | J21: =SUM(H21:I21) -> 9.46 | K21: 50 | L21: =$C$7 -> 0 | M21: =K21-IF(K21<>0,K21-(K21/(1+L21)),0) -> 50 | N21: =IFERROR(J21/M21,0) -> 0.1892 | O21: =IF(N21>$C$8,"YES","NO") -> NO | Q21: 0 | R21: =$C$7 -> 0 | S21: =Q21-IF(Q21<>0,Q21-(Q21/(1+R21)),0) -> 0 | T21: =IFERROR(J21/S21,0) -> 0 | U21: =IF(T21>$C$8,"YES","NO") -> NO
D22: 4XL | E22: 0 | F22: 0 | G22: 0 | H22: =SUM(E22:G22) -> 0 | I22: 0 | J22: =SUM(H22:I22) -> 0 | K22: 0 | L22: =$C$7 -> 0 | M22: =K22-IF(K22<>0,K22-(K22/(1+L22)),0) -> 0 | N22: =IFERROR(J22/M22,0) -> 0 | O22: =IF(N22>$C$8,"YES","NO") -> NO | Q22: 0 | R22: =$C$7 -> 0 | S22: =Q22-IF(Q22<>0,Q22-(Q22/(1+R22)),0) -> 0 | T22: =IFERROR(J22/S22,0) -> 0 | U22: =IF(T22>$C$8,"YES","NO") -> NO
A23: =A19+1 -> 4 | B23: GHOSRX204000BK | C23: BLACK T BAT BRAIN 26 ITIN | D23: SM-XL | E23: 0 | F23: 0 | G23: 5.83 | H23: =SUM(E23:G23) -> 5.83 | I23: 0 | J23: =SUM(H23:I23) -> 5.83 | K23: 50 | L23: =$C$7 -> 0 | M23: =K23-IF(K23<>0,K23-(K23/(1+L23)),0) -> 50 | N23: =IFERROR(J23/M23,0) -> 0.1166 | O23: =IF(N23>$C$8,"YES","NO") -> NO | Q23: 0 | R23: =$C$7 -> 0 | S23: =Q23-IF(Q23<>0,Q23-(Q23/(1+R23)),0) -> 0 | T23: =IFERROR(J23/S23,0) -> 0 | U23: =IF(T23>$C$8,"YES","NO") -> NO
D24: 2XL | E24: 0 | F24: 0 | G24: 8.09 | H24: =SUM(E24:G24) -> 8.09 | I24: 0 | J24: =SUM(H24:I24) -> 8.09 | K24: 50 | L24: =$C$7 -> 0 | M24: =K24-IF(K24<>0,K24-(K24/(1+L24)),0) -> 50 | N24: =IFERROR(J24/M24,0) -> 0.1618 | O24: =IF(N24>$C$8,"YES","NO") -> NO | Q24: 0 | R24: =$C$7 -> 0 | S24: =Q24-IF(Q24<>0,Q24-(Q24/(1+R24)),0) -> 0 | T24: =IFERROR(J24/S24,0) -> 0 | U24: =IF(T24>$C$8,"YES","NO") -> NO
D25: 3XL | E25: 0 | F25: 0 | G25: 9.46 | H25: =SUM(E25:G25) -> 9.46 | I25: 0 | J25: =SUM(H25:I25) -> 9.46 | K25: 50 | L25: =$C$7 -> 0 | M25: =K25-IF(K25<>0,K25-(K25/(1+L25)),0) -> 50 | N25: =IFERROR(J25/M25,0) -> 0.1892 | O25: =IF(N25>$C$8,"YES","NO") -> NO | Q25: 0 | R25: =$C$7 -> 0 | S25: =Q25-IF(Q25<>0,Q25-(Q25/(1+R25)),0) -> 0 | T25: =IFERROR(J25/S25,0) -> 0 | U25: =IF(T25>$C$8,"YES","NO") -> NO
D26: 4XL | E26: 0 | F26: 0 | G26: 0 | H26: =SUM(E26:G26) -> 0 | I26: 0 | J26: =SUM(H26:I26) -> 0 | K26: 0 | L26: =$C$7 -> 0 | M26: =K26-IF(K26<>0,K26-(K26/(1+L26)),0) -> 0 | N26: =IFERROR(J26/M26,0) -> 0 | O26: =IF(N26>$C$8,"YES","NO") -> NO | Q26: 0 | R26: =$C$7 -> 0 | S26: =Q26-IF(Q26<>0,Q26-(Q26/(1+R26)),0) -> 0 | T26: =IFERROR(J26/S26,0) -> 0 | U26: =IF(T26>$C$8,"YES","NO") -> NO
A27: =A23+1 -> 5 | B27: GHOSRX204002BK | C27: BLACK T WESTERN EMERITUS 26 ITIN | D27: SM-XL | E27: 0 | F27: 0 | G27: 5.83 | H27: =SUM(E27:G27) -> 5.83 | I27: 0 | J27: =SUM(H27:I27) -> 5.83 | K27: 50 | L27: =$C$7 -> 0 | M27: =K27-IF(K27<>0,K27-(K27/(1+L27)),0) -> 50 | N27: =IFERROR(J27/M27,0) -> 0.1166 | O27: =IF(N27>$C$8,"YES","NO") -> NO | Q27: 0 | R27: =$C$7 -> 0 | S27: =Q27-IF(Q27<>0,Q27-(Q27/(1+R27)),0) -> 0 | T27: =IFERROR(J27/S27,0) -> 0 | U27: =IF(T27>$C$8,"YES","NO") -> NO
D28: 2XL | E28: 0 | F28: 0 | G28: 8.09 | H28: =SUM(E28:G28) -> 8.09 | I28: 0 | J28: =SUM(H28:I28) -> 8.09 | K28: 50 | L28: =$C$7 -> 0 | M28: =K28-IF(K28<>0,K28-(K28/(1+L28)),0) -> 50 | N28: =IFERROR(J28/M28,0) -> 0.1618 | O28: =IF(N28>$C$8,"YES","NO") -> NO | Q28: 0 | R28: =$C$7 -> 0 | S28: =Q28-IF(Q28<>0,Q28-(Q28/(1+R28)),0) -> 0 | T28: =IFERROR(J28/S28,0) -> 0 | U28: =IF(T28>$C$8,"YES","NO") -> NO
D29: 3XL | E29: 0 | F29: 0 | G29: 9.46 | H29: =SUM(E29:G29) -> 9.46 | I29: 0 | J29: =SUM(H29:I29) -> 9.46 | K29: 50 | L29: =$C$7 -> 0 | M29: =K29-IF(K29<>0,K29-(K29/(1+L29)),0) -> 50 | N29: =IFERROR(J29/M29,0) -> 0.1892 | O29: =IF(N29>$C$8,"YES","NO") -> NO | Q29: 0 | R29: =$C$7 -> 0 | S29: =Q29-IF(Q29<>0,Q29-(Q29/(1+R29)),0) -> 0 | T29: =IFERROR(J29/S29,0) -> 0 | U29: =IF(T29>$C$8,"YES","NO") -> NO
D30: 4XL | E30: 0 | F30: 0 | G30: 0 | H30: =SUM(E30:G30) -> 0 | I30: 0 | J30: =SUM(H30:I30) -> 0 | K30: 0 | L30: =$C$7 -> 0 | M30: =K30-IF(K30<>0,K30-(K30/(1+L30)),0) -> 0 | N30: =IFERROR(J30/M30,0) -> 0 | O30: =IF(N30>$C$8,"YES","NO") -> NO | Q30: 0 | R30: =$C$7 -> 0 | S30: =Q30-IF(Q30<>0,Q30-(Q30/(1+R30)),0) -> 0 | T30: =IFERROR(J30/S30,0) -> 0 | U30: =IF(T30>$C$8,"YES","NO") -> NO
A31: =A27+1 -> 6 | B31: GHOSRX103437OT | C31: CRYSTAL WASHED T AT THE GATES | D31: SM-XL | E31: 0 | F31: 0 | G31: 8.71 | H31: =SUM(E31:G31) -> 8.71 | I31: 0 | J31: =SUM(H31:I31) -> 8.71 | K31: 60 | L31: =$C$7 -> 0 | M31: =K31-IF(K31<>0,K31-(K31/(1+L31)),0) -> 60 | N31: =IFERROR(J31/M31,0) -> 0.14516667 | O31: =IF(N31>$C$8,"YES","NO") -> NO | Q31: 0 | R31: =$C$7 -> 0 | S31: =Q31-IF(Q31<>0,Q31-(Q31/(1+R31)),0) -> 0 | T31: =IFERROR(J31/S31,0) -> 0 | U31: =IF(T31>$C$8,"YES","NO") -> NO
D32: 2XL | E32: 0 | F32: 0 | G32: 11.27 | H32: =SUM(E32:G32) -> 11.27 | I32: 0 | J32: =SUM(H32:I32) -> 11.27 | K32: 60 | L32: =$C$7 -> 0 | M32: =K32-IF(K32<>0,K32-(K32/(1+L32)),0) -> 60 | N32: =IFERROR(J32/M32,0) -> 0.18783333 | O32: =IF(N32>$C$8,"YES","NO") -> NO | Q32: 0 | R32: =$C$7 -> 0 | S32: =Q32-IF(Q32<>0,Q32-(Q32/(1+R32)),0) -> 0 | T32: =IFERROR(J32/S32,0) -> 0 | U32: =IF(T32>$C$8,"YES","NO") -> NO
D33: 3XL | E33: 0 | F33: 0 | G33: 12.13 | H33: =SUM(E33:G33) -> 12.13 | I33: 0 | J33: =SUM(H33:I33) -> 12.13 | K33: 60 | L33: =$C$7 -> 0 | M33: =K33-IF(K33<>0,K33-(K33/(1+L33)),0) -> 60 | N33: =IFERROR(J33/M33,0) -> 0.20216667 | O33: =IF(N33>$C$8,"YES","NO") -> NO | Q33: 0 | R33: =$C$7 -> 0 | S33: =Q33-IF(Q33<>0,Q33-(Q33/(1+R33)),0) -> 0 | T33: =IFERROR(J33/S33,0) -> 0 | U33: =IF(T33>$C$8,"YES","NO") -> NO
D34: 4XL | E34: 0 | F34: 0 | G34: 0 | H34: =SUM(E34:G34) -> 0 | I34: 0 | J34: =SUM(H34:I34) -> 0 | K34: 0 | L34: =$C$7 -> 0 | M34: =K34-IF(K34<>0,K34-(K34/(1+L34)),0) -> 0 | N34: =IFERROR(J34/M34,0) -> 0 | O34: =IF(N34>$C$8,"YES","NO") -> NO | Q34: 0 | R34: =$C$7 -> 0 | S34: =Q34-IF(Q34<>0,Q34-(Q34/(1+R34)),0) -> 0 | T34: =IFERROR(J34/S34,0) -> 0 | U34: =IF(T34>$C$8,"YES","NO") -> NO
A35: =A31+1 -> 7 | B35: GHOSRX103998BK | C35: BLACK T PAPA COOPER | D35: SM-XL | E35: 0 | F35: 0 | G35: 0 | H35: =SUM(E35:G35) -> 0 | I35: 0 | J35: =SUM(H35:I35) -> 0 | K35: 50 | L35: =$C$7 -> 0 | M35: =K35-IF(K35<>0,K35-(K35/(1+L35)),0) -> 50 | N35: =IFERROR(J35/M35,0) -> 0 | O35: =IF(N35>$C$8,"YES","NO") -> NO | Q35: 0 | R35: =$C$7 -> 0 | S35: =Q35-IF(Q35<>0,Q35-(Q35/(1+R35)),0) -> 0 | T35: =IFERROR(J35/S35,0) -> 0 | U35: =IF(T35>$C$8,"YES","NO") -> NO
D36: 2XL | E36: 0 | F36: 0 | G36: 0 | H36: =SUM(E36:G36) -> 0 | I36: 0 | J36: =SUM(H36:I36) -> 0 | K36: 50 | L36: =$C$7 -> 0 | M36: =K36-IF(K36<>0,K36-(K36/(1+L36)),0) -> 50 | N36: =IFERROR(J36/M36,0) -> 0 | O36: =IF(N36>$C$8,"YES","NO") -> NO | Q36: 0 | R36: =$C$7 -> 0 | S36: =Q36-IF(Q36<>0,Q36-(Q36/(1+R36)),0) -> 0 | T36: =IFERROR(J36/S36,0) -> 0 | U36: =IF(T36>$C$8,"YES","NO") -> NO
D37: 3XL | E37: 0 | F37: 0 | G37: 0 | H37: =SUM(E37:G37) -> 0 | I37: 0 | J37: =SUM(H37:I37) -> 0 | K37: 50 | L37: =$C$7 -> 0 | M37: =K37-IF(K37<>0,K37-(K37/(1+L37)),0) -> 50 | N37: =IFERROR(J37/M37,0) -> 0 | O37: =IF(N37>$C$8,"YES","NO") -> NO | Q37: 0 | R37: =$C$7 -> 0 | S37: =Q37-IF(Q37<>0,Q37-(Q37/(1+R37)),0) -> 0 | T37: =IFERROR(J37/S37,0) -> 0 | U37: =IF(T37>$C$8,"YES","NO") -> NO
D38: 4XL | E38: 0 | F38: 0 | G38: 0 | H38: =SUM(E38:G38) -> 0 | I38: 0 | J38: =SUM(H38:I38) -> 0 | K38: 0 | L38: =$C$7 -> 0 | M38: =K38-IF(K38<>0,K38-(K38/(1+L38)),0) -> 0 | N38: =IFERROR(J38/M38,0) -> 0 | O38: =IF(N38>$C$8,"YES","NO") -> NO | Q38: 0 | R38: =$C$7 -> 0 | S38: =Q38-IF(Q38<>0,Q38-(Q38/(1+R38)),0) -> 0 | T38: =IFERROR(J38/S38,0) -> 0 | U38: =IF(T38>$C$8,"YES","NO") -> NO
A39: =A35+1 -> 8 | B39: GHOSRX103999OT | C39: WOMENS CROP RAGLAN CHAMBER OF CHILLS | D39: SM-XL | E39: 9.05 | F39: 1.45 | G39: 0 | H39: =SUM(E39:G39) -> 10.5 | I39: 0 | J39: =SUM(H39:I39) -> 10.5 | K39: 50 | L39: =$C$7 -> 0 | M39: =K39-IF(K39<>0,K39-(K39/(1+L39)),0) -> 50 | N39: =IFERROR(J39/M39,0) -> 0.21 | O39: =IF(N39>$C$8,"YES","NO") -> NO | Q39: 0 | R39: =$C$7 -> 0 | S39: =Q39-IF(Q39<>0,Q39-(Q39/(1+R39)),0) -> 0 | T39: =IFERROR(J39/S39,0) -> 0 | U39: =IF(T39>$C$8,"YES","NO") -> NO
D40: 2XL | E40: 0 | F40: 0 | G40: 0 | H40: =SUM(E40:G40) -> 0 | I40: 0 | J40: =SUM(H40:I40) -> 0 | K40: 0 | L40: =$C$7 -> 0 | M40: =K40-IF(K40<>0,K40-(K40/(1+L40)),0) -> 0 | N40: =IFERROR(J40/M40,0) -> 0 | O40: =IF(N40>$C$8,"YES","NO") -> NO | Q40: 0 | R40: =$C$7 -> 0 | S40: =Q40-IF(Q40<>0,Q40-(Q40/(1+R40)),0) -> 0 | T40: =IFERROR(J40/S40,0) -> 0 | U40: =IF(T40>$C$8,"YES","NO") -> NO
D41: 3XL | E41: 0 | F41: 0 | G41: 0 | H41: =SUM(E41:G41) -> 0 | I41: 0 | J41: =SUM(H41:I41) -> 0 | K41: 0 | L41: =$C$7 -> 0 | M41: =K41-IF(K41<>0,K41-(K41/(1+L41)),0) -> 0 | N41: =IFERROR(J41/M41,0) -> 0 | O41: =IF(N41>$C$8,"YES","NO") -> NO | Q41: 0 | R41: =$C$7 -> 0 | S41: =Q41-IF(Q41<>0,Q41-(Q41/(1+R41)),0) -> 0 | T41: =IFERROR(J41/S41,0) -> 0 | U41: =IF(T41>$C$8,"YES","NO") -> NO
D42: 4XL | E42: 0 | F42: 0 | G42: 0 | H42: =SUM(E42:G42) -> 0 | I42: 0 | J42: =SUM(H42:I42) -> 0 | K42: 0 | L42: =$C$7 -> 0 | M42: =K42-IF(K42<>0,K42-(K42/(1+L42)),0) -> 0 | N42: =IFERROR(J42/M42,0) -> 0 | O42: =IF(N42>$C$8,"YES","NO") -> NO | Q42: 0 | R42: =$C$7 -> 0 | S42: =Q42-IF(Q42<>0,Q42-(Q42/(1+R42)),0) -> 0 | T42: =IFERROR(J42/S42,0) -> 0 | U42: =IF(T42>$C$8,"YES","NO") -> NO
A43: =A39+1 -> 9 | B43: GHOSRX203401BK | C43: BLACK PO HOODIE SKELETON | D43: SM-XL | E43: 8.25 | F43: 2.95 | G43: 0 | H43: =SUM(E43:G43) -> 11.2 | I43: 0 | J43: =SUM(H43:I43) -> 11.2 | K43: 80 | L43: =$C$7 -> 0 | M43: =K43-IF(K43<>0,K43-(K43/(1+L43)),0) -> 80 | N43: =IFERROR(J43/M43,0) -> 0.14 | O43: =IF(N43>$C$8,"YES","NO") -> NO | Q43: 0 | R43: =$C$7 -> 0 | S43: =Q43-IF(Q43<>0,Q43-(Q43/(1+R43)),0) -> 0 | T43: =IFERROR(J43/S43,0) -> 0 | U43: =IF(T43>$C$8,"YES","NO") -> NO
D44: 2XL | E44: 9 | F44: 2.95 | G44: 0 | H44: =SUM(E44:G44) -> 11.95 | I44: 0 | J44: =SUM(H44:I44) -> 11.95 | K44: 80 | L44: =$C$7 -> 0 | M44: =K44-IF(K44<>0,K44-(K44/(1+L44)),0) -> 80 | N44: =IFERROR(J44/M44,0) -> 0.149375 | O44: =IF(N44>$C$8,"YES","NO") -> NO | Q44: 0 | R44: =$C$7 -> 0 | S44: =Q44-IF(Q44<>0,Q44-(Q44/(1+R44)),0) -> 0 | T44: =IFERROR(J44/S44,0) -> 0 | U44: =IF(T44>$C$8,"YES","NO") -> NO
D45: 3XL | E45: 9 | F45: 2.95 | G45: 0 | H45: =SUM(E45:G45) -> 11.95 | I45: 0 | J45: =SUM(H45:I45) -> 11.95 | K45: 80 | L45: =$C$7 -> 0 | M45: =K45-IF(K45<>0,K45-(K45/(1+L45)),0) -> 80 | N45: =IFERROR(J45/M45,0) -> 0.149375 | O45: =IF(N45>$C$8,"YES","NO") -> NO | Q45: 0 | R45: =$C$7 -> 0 | S45: =Q45-IF(Q45<>0,Q45-(Q45/(1+R45)),0) -> 0 | T45: =IFERROR(J45/S45,0) -> 0 | U45: =IF(T45>$C$8,"YES","NO") -> NO
D46: 4XL | E46: 0 | F46: 0 | G46: 0 | H46: =SUM(E46:G46) -> 0 | I46: 0 | J46: =SUM(H46:I46) -> 0 | K46: 0 | L46: =$C$7 -> 0 | M46: =K46-IF(K46<>0,K46-(K46/(1+L46)),0) -> 0 | N46: =IFERROR(J46/M46,0) -> 0 | O46: =IF(N46>$C$8,"YES","NO") -> NO | Q46: 0 | R46: =$C$7 -> 0 | S46: =Q46-IF(Q46<>0,Q46-(Q46/(1+R46)),0) -> 0 | T46: =IFERROR(J46/S46,0) -> 0 | U46: =IF(T46>$C$8,"YES","NO") -> NO
A47: =A43+1 -> 10 | D47: SM-XL | E47: 0 | F47: 0 | G47: 0 | H47: =SUM(E47:G47) -> 0 | I47: 0 | J47: =SUM(H47:I47) -> 0 | K47: 0 | L47: =$C$7 -> 0 | M47: =K47-IF(K47<>0,K47-(K47/(1+L47)),0) -> 0 | N47: =IFERROR(J47/M47,0) -> 0 | O47: =IF(N47>$C$8,"YES","NO") -> NO | Q47: 0 | R47: =$C$7 -> 0 | S47: =Q47-IF(Q47<>0,Q47-(Q47/(1+R47)),0) -> 0 | T47: =IFERROR(J47/S47,0) -> 0 | U47: =IF(T47>$C$8,"YES","NO") -> NO
D48: 2XL | E48: 0 | F48: 0 | G48: 0 | H48: =SUM(E48:G48) -> 0 | I48: 0 | J48: =SUM(H48:I48) -> 0 | K48: 0 | L48: =$C$7 -> 0 | M48: =K48-IF(K48<>0,K48-(K48/(1+L48)),0) -> 0 | N48: =IFERROR(J48/M48,0) -> 0 | O48: =IF(N48>$C$8,"YES","NO") -> NO | Q48: 0 | R48: =$C$7 -> 0 | S48: =Q48-IF(Q48<>0,Q48-(Q48/(1+R48)),0) -> 0 | T48: =IFERROR(J48/S48,0) -> 0 | U48: =IF(T48>$C$8,"YES","NO") -> NO
D49: 3XL | E49: 0 | F49: 0 | G49: 0 | H49: =SUM(E49:G49) -> 0 | I49: 0 | J49: =SUM(H49:I49) -> 0 | K49: 0 | L49: =$C$7 -> 0 | M49: =K49-IF(K49<>0,K49-(K49/(1+L49)),0) -> 0 | N49: =IFERROR(J49/M49,0) -> 0 | O49: =IF(N49>$C$8,"YES","NO") -> NO | Q49: 0 | R49: =$C$7 -> 0 | S49: =Q49-IF(Q49<>0,Q49-(Q49/(1+R49)),0) -> 0 | T49: =IFERROR(J49/S49,0) -> 0 | U49: =IF(T49>$C$8,"YES","NO") -> NO
D50: 4XL | E50: 0 | F50: 0 | G50: 0 | H50: =SUM(E50:G50) -> 0 | I50: 0 | J50: =SUM(H50:I50) -> 0 | K50: 0 | L50: =$C$7 -> 0 | M50: =K50-IF(K50<>0,K50-(K50/(1+L50)),0) -> 0 | N50: =IFERROR(J50/M50,0) -> 0 | O50: =IF(N50>$C$8,"YES","NO") -> NO | Q50: 0 | R50: =$C$7 -> 0 | S50: =Q50-IF(Q50<>0,Q50-(Q50/(1+R50)),0) -> 0 | T50: =IFERROR(J50/S50,0) -> 0 | U50: =IF(T50>$C$8,"YES","NO") -> NO
A51: =A47+1 -> 11 | D51: SM-XL | E51: 0 | F51: 0 | G51: 0 | H51: =SUM(E51:G51) -> 0 | I51: 0 | J51: =SUM(H51:I51) -> 0 | K51: 0 | L51: =$C$7 -> 0 | M51: =K51-IF(K51<>0,K51-(K51/(1+L51)),0) -> 0 | N51: =IFERROR(J51/M51,0) -> 0 | O51: =IF(N51>$C$8,"YES","NO") -> NO | Q51: 0 | R51: =$C$7 -> 0 | S51: =Q51-IF(Q51<>0,Q51-(Q51/(1+R51)),0) -> 0 | T51: =IFERROR(J51/S51,0) -> 0 | U51: =IF(T51>$C$8,"YES","NO") -> NO
D52: 2XL | E52: 0 | F52: 0 | G52: 0 | H52: =SUM(E52:G52) -> 0 | I52: 0 | J52: =SUM(H52:I52) -> 0 | K52: 0 | L52: =$C$7 -> 0 | M52: =K52-IF(K52<>0,K52-(K52/(1+L52)),0) -> 0 | N52: =IFERROR(J52/M52,0) -> 0 | O52: =IF(N52>$C$8,"YES","NO") -> NO | Q52: 0 | R52: =$C$7 -> 0 | S52: =Q52-IF(Q52<>0,Q52-(Q52/(1+R52)),0) -> 0 | T52: =IFERROR(J52/S52,0) -> 0 | U52: =IF(T52>$C$8,"YES","NO") -> NO
D53: 3XL | E53: 0 | F53: 0 | G53: 0 | H53: =SUM(E53:G53) -> 0 | I53: 0 | J53: =SUM(H53:I53) -> 0 | K53: 0 | L53: =$C$7 -> 0 | M53: =K53-IF(K53<>0,K53-(K53/(1+L53)),0) -> 0 | N53: =IFERROR(J53/M53,0) -> 0 | O53: =IF(N53>$C$8,"YES","NO") -> NO | Q53: 0 | R53: =$C$7 -> 0 | S53: =Q53-IF(Q53<>0,Q53-(Q53/(1+R53)),0) -> 0 | T53: =IFERROR(J53/S53,0) -> 0 | U53: =IF(T53>$C$8,"YES","NO") -> NO
D54: 4XL | E54: 0 | F54: 0 | G54: 0 | H54: =SUM(E54:G54) -> 0 | I54: 0 | J54: =SUM(H54:I54) -> 0 | K54: 0 | L54: =$C$7 -> 0 | M54: =K54-IF(K54<>0,K54-(K54/(1+L54)),0) -> 0 | N54: =IFERROR(J54/M54,0) -> 0 | O54: =IF(N54>$C$8,"YES","NO") -> NO | Q54: 0 | R54: =$C$7 -> 0 | S54: =Q54-IF(Q54<>0,Q54-(Q54/(1+R54)),0) -> 0 | T54: =IFERROR(J54/S54,0) -> 0 | U54: =IF(T54>$C$8,"YES","NO") -> NO
A55: =A51+1 -> 12 | D55: SM-XL | E55: 0 | F55: 0 | G55: 0 | H55: =SUM(E55:G55) -> 0 | I55: 0 | J55: =SUM(H55:I55) -> 0 | K55: 0 | L55: =$C$7 -> 0 | M55: =K55-IF(K55<>0,K55-(K55/(1+L55)),0) -> 0 | N55: =IFERROR(J55/M55,0) -> 0 | O55: =IF(N55>$C$8,"YES","NO") -> NO | Q55: 0 | R55: =$C$7 -> 0 | S55: =Q55-IF(Q55<>0,Q55-(Q55/(1+R55)),0) -> 0 | T55: =IFERROR(J55/S55,0) -> 0 | U55: =IF(T55>$C$8,"YES","NO") -> NO
D56: 2XL | E56: 0 | F56: 0 | G56: 0 | H56: =SUM(E56:G56) -> 0 | I56: 0 | J56: =SUM(H56:I56) -> 0 | K56: 0 | L56: =$C$7 -> 0 | M56: =K56-IF(K56<>0,K56-(K56/(1+L56)),0) -> 0 | N56: =IFERROR(J56/M56,0) -> 0 | O56: =IF(N56>$C$8,"YES","NO") -> NO | Q56: 0 | R56: =$C$7 -> 0 | S56: =Q56-IF(Q56<>0,Q56-(Q56/(1+R56)),0) -> 0 | T56: =IFERROR(J56/S56,0) -> 0 | U56: =IF(T56>$C$8,"YES","NO") -> NO
D57: 3XL | E57: 0 | F57: 0 | G57: 0 | H57: =SUM(E57:G57) -> 0 | I57: 0 | J57: =SUM(H57:I57) -> 0 | K57: 0 | L57: =$C$7 -> 0 | M57: =K57-IF(K57<>0,K57-(K57/(1+L57)),0) -> 0 | N57: =IFERROR(J57/M57,0) -> 0 | O57: =IF(N57>$C$8,"YES","NO") -> NO | Q57: 0 | R57: =$C$7 -> 0 | S57: =Q57-IF(Q57<>0,Q57-(Q57/(1+R57)),0) -> 0 | T57: =IFERROR(J57/S57,0) -> 0 | U57: =IF(T57>$C$8,"YES","NO") -> NO
D58: 4XL | E58: 0 | F58: 0 | G58: 0 | H58: =SUM(E58:G58) -> 0 | I58: 0 | J58: =SUM(H58:I58) -> 0 | K58: 0 | L58: =$C$7 -> 0 | M58: =K58-IF(K58<>0,K58-(K58/(1+L58)),0) -> 0 | N58: =IFERROR(J58/M58,0) -> 0 | O58: =IF(N58>$C$8,"YES","NO") -> NO | Q58: 0 | R58: =$C$7 -> 0 | S58: =Q58-IF(Q58<>0,Q58-(Q58/(1+R58)),0) -> 0 | T58: =IFERROR(J58/S58,0) -> 0 | U58: =IF(T58>$C$8,"YES","NO") -> NO
A59: =A55+1 -> 13 | D59: SM-XL | E59: 0 | F59: 0 | G59: 0 | H59: =SUM(E59:G59) -> 0 | I59: 0 | J59: =SUM(H59:I59) -> 0 | K59: 0 | L59: =$C$7 -> 0 | M59: =K59-IF(K59<>0,K59-(K59/(1+L59)),0) -> 0 | N59: =IFERROR(J59/M59,0) -> 0 | O59: =IF(N59>$C$8,"YES","NO") -> NO | Q59: 0 | R59: =$C$7 -> 0 | S59: =Q59-IF(Q59<>0,Q59-(Q59/(1+R59)),0) -> 0 | T59: =IFERROR(J59/S59,0) -> 0 | U59: =IF(T59>$C$8,"YES","NO") -> NO
D60: 2XL | E60: 0 | F60: 0 | G60: 0 | H60: =SUM(E60:G60) -> 0 | I60: 0 | J60: =SUM(H60:I60) -> 0 | K60: 0 | L60: =$C$7 -> 0 | M60: =K60-IF(K60<>0,K60-(K60/(1+L60)),0) -> 0 | N60: =IFERROR(J60/M60,0) -> 0 | O60: =IF(N60>$C$8,"YES","NO") -> NO | Q60: 0 | R60: =$C$7 -> 0 | S60: =Q60-IF(Q60<>0,Q60-(Q60/(1+R60)),0) -> 0 | T60: =IFERROR(J60/S60,0) -> 0 | U60: =IF(T60>$C$8,"YES","NO") -> NO
D61: 3XL | E61: 0 | F61: 0 | G61: 0 | H61: =SUM(E61:G61) -> 0 | I61: 0 | J61: =SUM(H61:I61) -> 0 | K61: 0 | L61: =$C$7 -> 0 | M61: =K61-IF(K61<>0,K61-(K61/(1+L61)),0) -> 0 | N61: =IFERROR(J61/M61,0) -> 0 | O61: =IF(N61>$C$8,"YES","NO") -> NO | Q61: 0 | R61: =$C$7 -> 0 | S61: =Q61-IF(Q61<>0,Q61-(Q61/(1+R61)),0) -> 0 | T61: =IFERROR(J61/S61,0) -> 0 | U61: =IF(T61>$C$8,"YES","NO") -> NO
D62: 4XL | E62: 0 | F62: 0 | G62: 0 | H62: =SUM(E62:G62) -> 0 | I62: 0 | J62: =SUM(H62:I62) -> 0 | K62: 0 | L62: =$C$7 -> 0 | M62: =K62-IF(K62<>0,K62-(K62/(1+L62)),0) -> 0 | N62: =IFERROR(J62/M62,0) -> 0 | O62: =IF(N62>$C$8,"YES","NO") -> NO | Q62: 0 | R62: =$C$7 -> 0 | S62: =Q62-IF(Q62<>0,Q62-(Q62/(1+R62)),0) -> 0 | T62: =IFERROR(J62/S62,0) -> 0 | U62: =IF(T62>$C$8,"YES","NO") -> NO
A63: =A59+1 -> 14 | D63: SM-XL | E63: 0 | F63: 0 | G63: 0 | H63: =SUM(E63:G63) -> 0 | I63: 0 | J63: =SUM(H63:I63) -> 0 | K63: 0 | L63: =$C$7 -> 0 | M63: =K63-IF(K63<>0,K63-(K63/(1+L63)),0) -> 0 | N63: =IFERROR(J63/M63,0) -> 0 | O63: =IF(N63>$C$8,"YES","NO") -> NO | Q63: 0 | R63: =$C$7 -> 0 | S63: =Q63-IF(Q63<>0,Q63-(Q63/(1+R63)),0) -> 0 | T63: =IFERROR(J63/S63,0) -> 0 | U63: =IF(T63>$C$8,"YES","NO") -> NO
D64: 2XL | E64: 0 | F64: 0 | G64: 0 | H64: =SUM(E64:G64) -> 0 | I64: 0 | J64: =SUM(H64:I64) -> 0 | K64: 0 | L64: =$C$7 -> 0 | M64: =K64-IF(K64<>0,K64-(K64/(1+L64)),0) -> 0 | N64: =IFERROR(J64/M64,0) -> 0 | O64: =IF(N64>$C$8,"YES","NO") -> NO | Q64: 0 | R64: =$C$7 -> 0 | S64: =Q64-IF(Q64<>0,Q64-(Q64/(1+R64)),0) -> 0 | T64: =IFERROR(J64/S64,0) -> 0 | U64: =IF(T64>$C$8,"YES","NO") -> NO
D65: 3XL | E65: 0 | F65: 0 | G65: 0 | H65: =SUM(E65:G65) -> 0 | I65: 0 | J65: =SUM(H65:I65) -> 0 | K65: 0 | L65: =$C$7 -> 0 | M65: =K65-IF(K65<>0,K65-(K65/(1+L65)),0) -> 0 | N65: =IFERROR(J65/M65,0) -> 0 | O65: =IF(N65>$C$8,"YES","NO") -> NO | Q65: 0 | R65: =$C$7 -> 0 | S65: =Q65-IF(Q65<>0,Q65-(Q65/(1+R65)),0) -> 0 | T65: =IFERROR(J65/S65,0) -> 0 | U65: =IF(T65>$C$8,"YES","NO") -> NO
D66: 4XL | E66: 0 | F66: 0 | G66: 0 | H66: =SUM(E66:G66) -> 0 | I66: 0 | J66: =SUM(H66:I66) -> 0 | K66: 0 | L66: =$C$7 -> 0 | M66: =K66-IF(K66<>0,K66-(K66/(1+L66)),0) -> 0 | N66: =IFERROR(J66/M66,0) -> 0 | O66: =IF(N66>$C$8,"YES","NO") -> NO | Q66: 0 | R66: =$C$7 -> 0 | S66: =Q66-IF(Q66<>0,Q66-(Q66/(1+R66)),0) -> 0 | T66: =IFERROR(J66/S66,0) -> 0 | U66: =IF(T66>$C$8,"YES","NO") -> NO
A67: =A63+1 -> 15 | D67: SM-XL | E67: 0 | F67: 0 | G67: 0 | H67: =SUM(E67:G67) -> 0 | I67: 0 | J67: =SUM(H67:I67) -> 0 | K67: 0 | L67: =$C$7 -> 0 | M67: =K67-IF(K67<>0,K67-(K67/(1+L67)),0) -> 0 | N67: =IFERROR(J67/M67,0) -> 0 | O67: =IF(N67>$C$8,"YES","NO") -> NO | Q67: 0 | R67: =$C$7 -> 0 | S67: =Q67-IF(Q67<>0,Q67-(Q67/(1+R67)),0) -> 0 | T67: =IFERROR(J67/S67,0) -> 0 | U67: =IF(T67>$C$8,"YES","NO") -> NO
D68: 2XL | E68: 0 | F68: 0 | G68: 0 | H68: =SUM(E68:G68) -> 0 | I68: 0 | J68: =SUM(H68:I68) -> 0 | K68: 0 | L68: =$C$7 -> 0 | M68: =K68-IF(K68<>0,K68-(K68/(1+L68)),0) -> 0 | N68: =IFERROR(J68/M68,0) -> 0 | O68: =IF(N68>$C$8,"YES","NO") -> NO | Q68: 0 | R68: =$C$7 -> 0 | S68: =Q68-IF(Q68<>0,Q68-(Q68/(1+R68)),0) -> 0 | T68: =IFERROR(J68/S68,0) -> 0 | U68: =IF(T68>$C$8,"YES","NO") -> NO
D69: 3XL | E69: 0 | F69: 0 | G69: 0 | H69: =SUM(E69:G69) -> 0 | I69: 0 | J69: =SUM(H69:I69) -> 0 | K69: 0 | L69: =$C$7 -> 0 | M69: =K69-IF(K69<>0,K69-(K69/(1+L69)),0) -> 0 | N69: =IFERROR(J69/M69,0) -> 0 | O69: =IF(N69>$C$8,"YES","NO") -> NO | Q69: 0 | R69: =$C$7 -> 0 | S69: =Q69-IF(Q69<>0,Q69-(Q69/(1+R69)),0) -> 0 | T69: =IFERROR(J69/S69,0) -> 0 | U69: =IF(T69>$C$8,"YES","NO") -> NO
D70: 4XL | E70: 0 | F70: 0 | G70: 0 | H70: =SUM(E70:G70) -> 0 | I70: 0 | J70: =SUM(H70:I70) -> 0 | K70: 0 | L70: =$C$7 -> 0 | M70: =K70-IF(K70<>0,K70-(K70/(1+L70)),0) -> 0 | N70: =IFERROR(J70/M70,0) -> 0 | O70: =IF(N70>$C$8,"YES","NO") -> NO | Q70: 0 | R70: =$C$7 -> 0 | S70: =Q70-IF(Q70<>0,Q70-(Q70/(1+R70)),0) -> 0 | T70: =IFERROR(J70/S70,0) -> 0 | U70: =IF(T70>$C$8,"YES","NO") -> NO
A71: =A67+1 -> 16 | D71: SM-XL | E71: 0 | F71: 0 | G71: 0 | H71: =SUM(E71:G71) -> 0 | I71: 0 | J71: =SUM(H71:I71) -> 0 | K71: 0 | L71: =$C$7 -> 0 | M71: =K71-IF(K71<>0,K71-(K71/(1+L71)),0) -> 0 | N71: =IFERROR(J71/M71,0) -> 0 | O71: =IF(N71>$C$8,"YES","NO") -> NO | Q71: 0 | R71: =$C$7 -> 0 | S71: =Q71-IF(Q71<>0,Q71-(Q71/(1+R71)),0) -> 0 | T71: =IFERROR(J71/S71,0) -> 0 | U71: =IF(T71>$C$8,"YES","NO") -> NO
D72: 2XL | E72: 0 | F72: 0 | G72: 0 | H72: =SUM(E72:G72) -> 0 | I72: 0 | J72: =SUM(H72:I72) -> 0 | K72: 0 | L72: =$C$7 -> 0 | M72: =K72-IF(K72<>0,K72-(K72/(1+L72)),0) -> 0 | N72: =IFERROR(J72/M72,0) -> 0 | O72: =IF(N72>$C$8,"YES","NO") -> NO | Q72: 0 | R72: =$C$7 -> 0 | S72: =Q72-IF(Q72<>0,Q72-(Q72/(1+R72)),0) -> 0 | T72: =IFERROR(J72/S72,0) -> 0 | U72: =IF(T72>$C$8,"YES","NO") -> NO
D73: 3XL | E73: 0 | F73: 0 | G73: 0 | H73: =SUM(E73:G73) -> 0 | I73: 0 | J73: =SUM(H73:I73) -> 0 | K73: 0 | L73: =$C$7 -> 0 | M73: =K73-IF(K73<>0,K73-(K73/(1+L73)),0) -> 0 | N73: =IFERROR(J73/M73,0) -> 0 | O73: =IF(N73>$C$8,"YES","NO") -> NO | Q73: 0 | R73: =$C$7 -> 0 | S73: =Q73-IF(Q73<>0,Q73-(Q73/(1+R73)),0) -> 0 | T73: =IFERROR(J73/S73,0) -> 0 | U73: =IF(T73>$C$8,"YES","NO") -> NO
D74: 4XL | E74: 0 | F74: 0 | G74: 0 | H74: =SUM(E74:G74) -> 0 | I74: 0 | J74: =SUM(H74:I74) -> 0 | K74: 0 | L74: =$C$7 -> 0 | M74: =K74-IF(K74<>0,K74-(K74/(1+L74)),0) -> 0 | N74: =IFERROR(J74/M74,0) -> 0 | O74: =IF(N74>$C$8,"YES","NO") -> NO | Q74: 0 | R74: =$C$7 -> 0 | S74: =Q74-IF(Q74<>0,Q74-(Q74/(1+R74)),0) -> 0 | T74: =IFERROR(J74/S74,0) -> 0 | U74: =IF(T74>$C$8,"YES","NO") -> NO
A75: =A71+1 -> 17 | D75: SM-XL | E75: 0 | F75: 0 | G75: 0 | H75: =SUM(E75:G75) -> 0 | I75: 0 | J75: =SUM(H75:I75) -> 0 | K75: 0 | L75: =$C$7 -> 0 | M75: =K75-IF(K75<>0,K75-(K75/(1+L75)),0) -> 0 | N75: =IFERROR(J75/M75,0) -> 0 | O75: =IF(N75>$C$8,"YES","NO") -> NO | Q75: 0 | R75: =$C$7 -> 0 | S75: =Q75-IF(Q75<>0,Q75-(Q75/(1+R75)),0) -> 0 | T75: =IFERROR(J75/S75,0) -> 0 | U75: =IF(T75>$C$8,"YES","NO") -> NO
D76: 2XL | E76: 0 | F76: 0 | G76: 0 | H76: =SUM(E76:G76) -> 0 | I76: 0 | J76: =SUM(H76:I76) -> 0 | K76: 0 | L76: =$C$7 -> 0 | M76: =K76-IF(K76<>0,K76-(K76/(1+L76)),0) -> 0 | N76: =IFERROR(J76/M76,0) -> 0 | O76: =IF(N76>$C$8,"YES","NO") -> NO | Q76: 0 | R76: =$C$7 -> 0 | S76: =Q76-IF(Q76<>0,Q76-(Q76/(1+R76)),0) -> 0 | T76: =IFERROR(J76/S76,0) -> 0 | U76: =IF(T76>$C$8,"YES","NO") -> NO
D77: 3XL | E77: 0 | F77: 0 | G77: 0 | H77: =SUM(E77:G77) -> 0 | I77: 0 | J77: =SUM(H77:I77) -> 0 | K77: 0 | L77: =$C$7 -> 0 | M77: =K77-IF(K77<>0,K77-(K77/(1+L77)),0) -> 0 | N77: =IFERROR(J77/M77,0) -> 0 | O77: =IF(N77>$C$8,"YES","NO") -> NO | Q77: 0 | R77: =$C$7 -> 0 | S77: =Q77-IF(Q77<>0,Q77-(Q77/(1+R77)),0) -> 0 | T77: =IFERROR(J77/S77,0) -> 0 | U77: =IF(T77>$C$8,"YES","NO") -> NO
D78: 4XL | E78: 0 | F78: 0 | G78: 0 | H78: =SUM(E78:G78) -> 0 | I78: 0 | J78: =SUM(H78:I78) -> 0 | K78: 0 | L78: =$C$7 -> 0 | M78: =K78-IF(K78<>0,K78-(K78/(1+L78)),0) -> 0 | N78: =IFERROR(J78/M78,0) -> 0 | O78: =IF(N78>$C$8,"YES","NO") -> NO | Q78: 0 | R78: =$C$7 -> 0 | S78: =Q78-IF(Q78<>0,Q78-(Q78/(1+R78)),0) -> 0 | T78: =IFERROR(J78/S78,0) -> 0 | U78: =IF(T78>$C$8,"YES","NO") -> NO
A79: =A75+1 -> 18 | D79: SM-XL | E79: 0 | F79: 0 | G79: 0 | H79: =SUM(E79:G79) -> 0 | I79: 0 | J79: =SUM(H79:I79) -> 0 | K79: 0 | L79: =$C$7 -> 0 | M79: =K79-IF(K79<>0,K79-(K79/(1+L79)),0) -> 0 | N79: =IFERROR(J79/M79,0) -> 0 | O79: =IF(N79>$C$8,"YES","NO") -> NO | Q79: 0 | R79: =$C$7 -> 0 | S79: =Q79-IF(Q79<>0,Q79-(Q79/(1+R79)),0) -> 0 | T79: =IFERROR(J79/S79,0) -> 0 | U79: =IF(T79>$C$8,"YES","NO") -> NO
D80: 2XL | E80: 0 | F80: 0 | G80: 0 | H80: =SUM(E80:G80) -> 0 | I80: 0 | J80: =SUM(H80:I80) -> 0 | K80: 0 | L80: =$C$7 -> 0 | M80: =K80-IF(K80<>0,K80-(K80/(1+L80)),0) -> 0 | N80: =IFERROR(J80/M80,0) -> 0 | O80: =IF(N80>$C$8,"YES","NO") -> NO | Q80: 0 | R80: =$C$7 -> 0 | S80: =Q80-IF(Q80<>0,Q80-(Q80/(1+R80)),0) -> 0 | T80: =IFERROR(J80/S80,0) -> 0 | U80: =IF(T80>$C$8,"YES","NO") -> NO
D81: 3XL | E81: 0 | F81: 0 | G81: 0 | H81: =SUM(E81:G81) -> 0 | I81: 0 | J81: =SUM(H81:I81) -> 0 | K81: 0 | L81: =$C$7 -> 0 | M81: =K81-IF(K81<>0,K81-(K81/(1+L81)),0) -> 0 | N81: =IFERROR(J81/M81,0) -> 0 | O81: =IF(N81>$C$8,"YES","NO") -> NO | Q81: 0 | R81: =$C$7 -> 0 | S81: =Q81-IF(Q81<>0,Q81-(Q81/(1+R81)),0) -> 0 | T81: =IFERROR(J81/S81,0) -> 0 | U81: =IF(T81>$C$8,"YES","NO") -> NO
D82: 4XL | E82: 0 | F82: 0 | G82: 0 | H82: =SUM(E82:G82) -> 0 | I82: 0 | J82: =SUM(H82:I82) -> 0 | K82: 0 | L82: =$C$7 -> 0 | M82: =K82-IF(K82<>0,K82-(K82/(1+L82)),0) -> 0 | N82: =IFERROR(J82/M82,0) -> 0 | O82: =IF(N82>$C$8,"YES","NO") -> NO | Q82: 0 | R82: =$C$7 -> 0 | S82: =Q82-IF(Q82<>0,Q82-(Q82/(1+R82)),0) -> 0 | T82: =IFERROR(J82/S82,0) -> 0 | U82: =IF(T82>$C$8,"YES","NO") -> NO
A83: =A79+1 -> 19 | D83: SM-XL | E83: 0 | F83: 0 | G83: 0 | H83: =SUM(E83:G83) -> 0 | I83: 0 | J83: =SUM(H83:I83) -> 0 | K83: 0 | L83: =$C$7 -> 0 | M83: =K83-IF(K83<>0,K83-(K83/(1+L83)),0) -> 0 | N83: =IFERROR(J83/M83,0) -> 0 | O83: =IF(N83>$C$8,"YES","NO") -> NO | Q83: 0 | R83: =$C$7 -> 0 | S83: =Q83-IF(Q83<>0,Q83-(Q83/(1+R83)),0) -> 0 | T83: =IFERROR(J83/S83,0) -> 0 | U83: =IF(T83>$C$8,"YES","NO") -> NO
D84: 2XL | E84: 0 | F84: 0 | G84: 0 | H84: =SUM(E84:G84) -> 0 | I84: 0 | J84: =SUM(H84:I84) -> 0 | K84: 0 | L84: =$C$7 -> 0 | M84: =K84-IF(K84<>0,K84-(K84/(1+L84)),0) -> 0 | N84: =IFERROR(J84/M84,0) -> 0 | O84: =IF(N84>$C$8,"YES","NO") -> NO | Q84: 0 | R84: =$C$7 -> 0 | S84: =Q84-IF(Q84<>0,Q84-(Q84/(1+R84)),0) -> 0 | T84: =IFERROR(J84/S84,0) -> 0 | U84: =IF(T84>$C$8,"YES","NO") -> NO
D85: 3XL | E85: 0 | F85: 0 | G85: 0 | H85: =SUM(E85:G85) -> 0 | I85: 0 | J85: =SUM(H85:I85) -> 0 | K85: 0 | L85: =$C$7 -> 0 | M85: =K85-IF(K85<>0,K85-(K85/(1+L85)),0) -> 0 | N85: =IFERROR(J85/M85,0) -> 0 | O85: =IF(N85>$C$8,"YES","NO") -> NO | Q85: 0 | R85: =$C$7 -> 0 | S85: =Q85-IF(Q85<>0,Q85-(Q85/(1+R85)),0) -> 0 | T85: =IFERROR(J85/S85,0) -> 0 | U85: =IF(T85>$C$8,"YES","NO") -> NO
D86: 4XL | E86: 0 | F86: 0 | G86: 0 | H86: =SUM(E86:G86) -> 0 | I86: 0 | J86: =SUM(H86:I86) -> 0 | K86: 0 | L86: =$C$7 -> 0 | M86: =K86-IF(K86<>0,K86-(K86/(1+L86)),0) -> 0 | N86: =IFERROR(J86/M86,0) -> 0 | O86: =IF(N86>$C$8,"YES","NO") -> NO | Q86: 0 | R86: =$C$7 -> 0 | S86: =Q86-IF(Q86<>0,Q86-(Q86/(1+R86)),0) -> 0 | T86: =IFERROR(J86/S86,0) -> 0 | U86: =IF(T86>$C$8,"YES","NO") -> NO
A87: =A83+1 -> 20 | D87: SM-XL | E87: 0 | F87: 0 | G87: 0 | H87: =SUM(E87:G87) -> 0 | I87: 0 | J87: =SUM(H87:I87) -> 0 | K87: 0 | L87: =$C$7 -> 0 | M87: =K87-IF(K87<>0,K87-(K87/(1+L87)),0) -> 0 | N87: =IFERROR(J87/M87,0) -> 0 | O87: =IF(N87>$C$8,"YES","NO") -> NO | Q87: 0 | R87: =$C$7 -> 0 | S87: =Q87-IF(Q87<>0,Q87-(Q87/(1+R87)),0) -> 0 | T87: =IFERROR(J87/S87,0) -> 0 | U87: =IF(T87>$C$8,"YES","NO") -> NO
D88: 2XL | E88: 0 | F88: 0 | G88: 0 | H88: =SUM(E88:G88) -> 0 | I88: 0 | J88: =SUM(H88:I88) -> 0 | K88: 0 | L88: =$C$7 -> 0 | M88: =K88-IF(K88<>0,K88-(K88/(1+L88)),0) -> 0 | N88: =IFERROR(J88/M88,0) -> 0 | O88: =IF(N88>$C$8,"YES","NO") -> NO | Q88: 0 | R88: =$C$7 -> 0 | S88: =Q88-IF(Q88<>0,Q88-(Q88/(1+R88)),0) -> 0 | T88: =IFERROR(J88/S88,0) -> 0 | U88: =IF(T88>$C$8,"YES","NO") -> NO
D89: 3XL | E89: 0 | F89: 0 | G89: 0 | H89: =SUM(E89:G89) -> 0 | I89: 0 | J89: =SUM(H89:I89) -> 0 | K89: 0 | L89: =$C$7 -> 0 | M89: =K89-IF(K89<>0,K89-(K89/(1+L89)),0) -> 0 | N89: =IFERROR(J89/M89,0) -> 0 | O89: =IF(N89>$C$8,"YES","NO") -> NO | Q89: 0 | R89: =$C$7 -> 0 | S89: =Q89-IF(Q89<>0,Q89-(Q89/(1+R89)),0) -> 0 | T89: =IFERROR(J89/S89,0) -> 0 | U89: =IF(T89>$C$8,"YES","NO") -> NO
D90: 4XL | E90: 0 | F90: 0 | G90: 0 | H90: =SUM(E90:G90) -> 0 | I90: 0 | J90: =SUM(H90:I90) -> 0 | K90: 0 | L90: =$C$7 -> 0 | M90: =K90-IF(K90<>0,K90-(K90/(1+L90)),0) -> 0 | N90: =IFERROR(J90/M90,0) -> 0 | O90: =IF(N90>$C$8,"YES","NO") -> NO | Q90: 0 | R90: =$C$7 -> 0 | S90: =Q90-IF(Q90<>0,Q90-(Q90/(1+R90)),0) -> 0 | T90: =IFERROR(J90/S90,0) -> 0 | U90: =IF(T90>$C$8,"YES","NO") -> NO
A91: =A87+1 -> 21 | D91: SM-XL | E91: 0 | F91: 0 | G91: 0 | H91: =SUM(E91:G91) -> 0 | I91: 0 | J91: =SUM(H91:I91) -> 0 | K91: 0 | L91: =$C$7 -> 0 | M91: =K91-IF(K91<>0,K91-(K91/(1+L91)),0) -> 0 | N91: =IFERROR(J91/M91,0) -> 0 | O91: =IF(N91>$C$8,"YES","NO") -> NO | Q91: 0 | R91: =$C$7 -> 0 | S91: =Q91-IF(Q91<>0,Q91-(Q91/(1+R91)),0) -> 0 | T91: =IFERROR(J91/S91,0) -> 0 | U91: =IF(T91>$C$8,"YES","NO") -> NO
D92: 2XL | E92: 0 | F92: 0 | G92: 0 | H92: =SUM(E92:G92) -> 0 | I92: 0 | J92: =SUM(H92:I92) -> 0 | K92: 0 | L92: =$C$7 -> 0 | M92: =K92-IF(K92<>0,K92-(K92/(1+L92)),0) -> 0 | N92: =IFERROR(J92/M92,0) -> 0 | O92: =IF(N92>$C$8,"YES","NO") -> NO | Q92: 0 | R92: =$C$7 -> 0 | S92: =Q92-IF(Q92<>0,Q92-(Q92/(1+R92)),0) -> 0 | T92: =IFERROR(J92/S92,0) -> 0 | U92: =IF(T92>$C$8,"YES","NO") -> NO
D93: 3XL | E93: 0 | F93: 0 | G93: 0 | H93: =SUM(E93:G93) -> 0 | I93: 0 | J93: =SUM(H93:I93) -> 0 | K93: 0 | L93: =$C$7 -> 0 | M93: =K93-IF(K93<>0,K93-(K93/(1+L93)),0) -> 0 | N93: =IFERROR(J93/M93,0) -> 0 | O93: =IF(N93>$C$8,"YES","NO") -> NO | Q93: 0 | R93: =$C$7 -> 0 | S93: =Q93-IF(Q93<>0,Q93-(Q93/(1+R93)),0) -> 0 | T93: =IFERROR(J93/S93,0) -> 0 | U93: =IF(T93>$C$8,"YES","NO") -> NO
D94: 4XL | E94: 0 | F94: 0 | G94: 0 | H94: =SUM(E94:G94) -> 0 | I94: 0 | J94: =SUM(H94:I94) -> 0 | K94: 0 | L94: =$C$7 -> 0 | M94: =K94-IF(K94<>0,K94-(K94/(1+L94)),0) -> 0 | N94: =IFERROR(J94/M94,0) -> 0 | O94: =IF(N94>$C$8,"YES","NO") -> NO | Q94: 0 | R94: =$C$7 -> 0 | S94: =Q94-IF(Q94<>0,Q94-(Q94/(1+R94)),0) -> 0 | T94: =IFERROR(J94/S94,0) -> 0 | U94: =IF(T94>$C$8,"YES","NO") -> NO
A95: =A91+1 -> 22 | D95: SM-XL | E95: 0 | F95: 0 | G95: 0 | H95: =SUM(E95:G95) -> 0 | I95: 0 | J95: =SUM(H95:I95) -> 0 | K95: 0 | L95: =$C$7 -> 0 | M95: =K95-IF(K95<>0,K95-(K95/(1+L95)),0) -> 0 | N95: =IFERROR(J95/M95,0) -> 0 | O95: =IF(N95>$C$8,"YES","NO") -> NO | Q95: 0 | R95: =$C$7 -> 0 | S95: =Q95-IF(Q95<>0,Q95-(Q95/(1+R95)),0) -> 0 | T95: =IFERROR(J95/S95,0) -> 0 | U95: =IF(T95>$C$8,"YES","NO") -> NO
D96: 2XL | E96: 0 | F96: 0 | G96: 0 | H96: =SUM(E96:G96) -> 0 | I96: 0 | J96: =SUM(H96:I96) -> 0 | K96: 0 | L96: =$C$7 -> 0 | M96: =K96-IF(K96<>0,K96-(K96/(1+L96)),0) -> 0 | N96: =IFERROR(J96/M96,0) -> 0 | O96: =IF(N96>$C$8,"YES","NO") -> NO | Q96: 0 | R96: =$C$7 -> 0 | S96: =Q96-IF(Q96<>0,Q96-(Q96/(1+R96)),0) -> 0 | T96: =IFERROR(J96/S96,0) -> 0 | U96: =IF(T96>$C$8,"YES","NO") -> NO
D97: 3XL | E97: 0 | F97: 0 | G97: 0 | H97: =SUM(E97:G97) -> 0 | I97: 0 | J97: =SUM(H97:I97) -> 0 | K97: 0 | L97: =$C$7 -> 0 | M97: =K97-IF(K97<>0,K97-(K97/(1+L97)),0) -> 0 | N97: =IFERROR(J97/M97,0) -> 0 | O97: =IF(N97>$C$8,"YES","NO") -> NO | Q97: 0 | R97: =$C$7 -> 0 | S97: =Q97-IF(Q97<>0,Q97-(Q97/(1+R97)),0) -> 0 | T97: =IFERROR(J97/S97,0) -> 0 | U97: =IF(T97>$C$8,"YES","NO") -> NO
D98: 4XL | E98: 0 | F98: 0 | G98: 0 | H98: =SUM(E98:G98) -> 0 | I98: 0 | J98: =SUM(H98:I98) -> 0 | K98: 0 | L98: =$C$7 -> 0 | M98: =K98-IF(K98<>0,K98-(K98/(1+L98)),0) -> 0 | N98: =IFERROR(J98/M98,0) -> 0 | O98: =IF(N98>$C$8,"YES","NO") -> NO | Q98: 0 | R98: =$C$7 -> 0 | S98: =Q98-IF(Q98<>0,Q98-(Q98/(1+R98)),0) -> 0 | T98: =IFERROR(J98/S98,0) -> 0 | U98: =IF(T98>$C$8,"YES","NO") -> NO
A99: =A95+1 -> 23 | D99: SM-XL | E99: 0 | F99: 0 | G99: 0 | H99: =SUM(E99:G99) -> 0 | I99: 0 | J99: =SUM(H99:I99) -> 0 | K99: 0 | L99: =$C$7 -> 0 | M99: =K99-IF(K99<>0,K99-(K99/(1+L99)),0) -> 0 | N99: =IFERROR(J99/M99,0) -> 0 | O99: =IF(N99>$C$8,"YES","NO") -> NO | Q99: 0 | R99: =$C$7 -> 0 | S99: =Q99-IF(Q99<>0,Q99-(Q99/(1+R99)),0) -> 0 | T99: =IFERROR(J99/S99,0) -> 0 | U99: =IF(T99>$C$8,"YES","NO") -> NO
D100: 2XL | E100: 0 | F100: 0 | G100: 0 | H100: =SUM(E100:G100) -> 0 | I100: 0 | J100: =SUM(H100:I100) -> 0 | K100: 0 | L100: =$C$7 -> 0 | M100: =K100-IF(K100<>0,K100-(K100/(1+L100)),0) -> 0 | N100: =IFERROR(J100/M100,0) -> 0 | O100: =IF(N100>$C$8,"YES","NO") -> NO | Q100: 0 | R100: =$C$7 -> 0 | S100: =Q100-IF(Q100<>0,Q100-(Q100/(1+R100)),0) -> 0 | T100: =IFERROR(J100/S100,0) -> 0 | U100: =IF(T100>$C$8,"YES","NO") -> NO
D101: 3XL | E101: 0 | F101: 0 | G101: 0 | H101: =SUM(E101:G101) -> 0 | I101: 0 | J101: =SUM(H101:I101) -> 0 | K101: 0 | L101: =$C$7 -> 0 | M101: =K101-IF(K101<>0,K101-(K101/(1+L101)),0) -> 0 | N101: =IFERROR(J101/M101,0) -> 0 | O101: =IF(N101>$C$8,"YES","NO") -> NO | Q101: 0 | R101: =$C$7 -> 0 | S101: =Q101-IF(Q101<>0,Q101-(Q101/(1+R101)),0) -> 0 | T101: =IFERROR(J101/S101,0) -> 0 | U101: =IF(T101>$C$8,"YES","NO") -> NO
D102: 4XL | E102: 0 | F102: 0 | G102: 0 | H102: =SUM(E102:G102) -> 0 | I102: 0 | J102: =SUM(H102:I102) -> 0 | K102: 0 | L102: =$C$7 -> 0 | M102: =K102-IF(K102<>0,K102-(K102/(1+L102)),0) -> 0 | N102: =IFERROR(J102/M102,0) -> 0 | O102: =IF(N102>$C$8,"YES","NO") -> NO | Q102: 0 | R102: =$C$7 -> 0 | S102: =Q102-IF(Q102<>0,Q102-(Q102/(1+R102)),0) -> 0 | T102: =IFERROR(J102/S102,0) -> 0 | U102: =IF(T102>$C$8,"YES","NO") -> NO
...

Sheet Selling Prices
A1: Tour Inventory
B3: Tour | C3: =Inventory!C3 -> GHOST
B4: Tour Date | C4: =Inventory!C4 -> JAN-FEB 2026
D6: USD | E6: CAD
B7: NAV Item Code | C7: Product Description | D7: Selling Price | E7: Selling Price | F7: Selling Price | G7: Selling Price
A8: 1 | B8: =Inventory!B7 -> GHOSNS903311BK | C8: =Inventory!C7 -> BATWING HOODY | D8: ='Projection Sheet'!D15 -> 125
A9: 2 | B9: =Inventory!B8 -> GHOSRX203275BK | C9: =Inventory!C8 -> SHORTS BLACK/ WHT PAPA V COSTUME CLAWS | D9: ='Projection Sheet'!D16 -> 45
A10: 3 | B10: =Inventory!B9 -> GHOSRX204001BK | C10: =Inventory!C9 -> BLACK T SKELETOUR 26 ITIN | D10: ='Projection Sheet'!D17 -> 50
A11: 4 | B11: =Inventory!B10 -> GHOSRX204000BK | C11: =Inventory!C10 -> BLACK T BAT BRAIN 26 ITIN | D11: ='Projection Sheet'!D18 -> 50
A12: 5 | B12: =Inventory!B11 -> GHOSRX204002BK | C12: =Inventory!C11 -> BLACK T WESTERN EMERITUS 26 ITIN | D12: ='Projection Sheet'!D19 -> 50
A13: 6 | B13: =Inventory!B12 -> GHOSRX103437OT | C13: =Inventory!C12 -> CRYSTAL WASHED T AT THE GATES | D13: ='Projection Sheet'!D20 -> 60
A14: 7 | B14: =Inventory!B13 -> GHOSRX103998BK | C14: =Inventory!C13 -> BLACK T PAPA COOPER | D14: ='Projection Sheet'!D21 -> 50
A15: 8 | B15: =Inventory!B14 -> GHOSRX103999OT | C15: =Inventory!C14 -> WOMENS CROP RAGLAN CHAMBER OF CHILLS | D15: ='Projection Sheet'!D22 -> 50
A16: 9 | B16: =Inventory!B15 -> GHOSRX203401BK | C16: =Inventory!C15 -> BLACK PO HOODIE SKELETON | D16: ='Projection Sheet'!D23 -> 80
A17: 10 | B17: =Inventory!B16 -> 0 | C17: =Inventory!C16 -> 0 | D17: ='Projection Sheet'!D24 -> 1
A18: 11 | B18: =Inventory!B17 -> 0 | C18: =Inventory!C17 -> 0 | D18: ='Projection Sheet'!D25 -> 1
A19: 12 | B19: =Inventory!B18 -> 0 | C19: =Inventory!C18 -> 0 | D19: ='Projection Sheet'!D26 -> 1
... A67: 60 | B67: =Inventory!B66 -> 0 | C67: =Inventory!C66 -> 0 | D67: ='Projection Sheet'!D74 -> 1
A68: 61 | B68: =Inventory!B67 -> 0 | C68: =Inventory!C67 -> 0 | D68: ='Projection Sheet'!D75 -> 1
A69: 62 | B69: =Inventory!B68 -> 0 | C69: =Inventory!C68 -> 0 | D69: ='Projection Sheet'!D76 -> 1
A70: 63 | B70: =Inventory!B69 -> 0 | C70: =Inventory!C69 -> 0 | D70: ='Projection Sheet'!D77 -> 1
A71: 64 | B71: =Inventory!B70 -> 0 | C71: =Inventory!C70 -> 0 | D71: ='Projection Sheet'!D78 -> 1
A72: 65 | B72: =Inventory!B71 -> 0 | C72: =Inventory!C71 -> 0 | D72: ='Projection Sheet'!D79 -> 1
A73: 66 | B73: =Inventory!B72 -> 0 | C73: =Inventory!C72 -> 0 | D73: ='Projection Sheet'!D80 -> 1
A74: 67 | B74: =Inventory!B73 -> GHOSRX103241BK | C74: =Inventory!C73 -> CHOKER PAPA V | D74: ='Projection Sheet'!D81 -> 30
A75: 68 | B75: =Inventory!B74 -> GHOSRX203254GR | C75: =Inventory!C74 -> KEYCHAIN SKELETON GRUCIFIX | D75: ='Projection Sheet'!D82 -> 15
A76: 69 | B76: =Inventory!B75 -> GHOSRX903403OT | C76: =Inventory!C75 -> PATCH SET OF 3 | D76: ='Projection Sheet'!D83 -> 20
A77: 70 | B77: =Inventory!B76 -> GHOSRX003611BK | C77: =Inventory!C76 -> 0 | D77: ='Projection Sheet'!D84 -> 1
A78: 71 | B78: =Inventory!B77 -> GHOSRX903408OT | C78: =Inventory!C77 -> LP SKELETA POLTERGEIST | D78: ='Projection Sheet'!D85 -> 40
A79: 72 | B79: =Inventory!B78 -> GHOSNS203369OT | C79: =Inventory!C78 -> FOILED COMIC BOOK SISTER IMPERATOR # 1 | D79: ='Projection Sheet'!D86 -> 30
... A82: 75 | B82: =Inventory!B81 -> GHOSNS103624OT | C82: =Inventory!C81 -> FOILED COMIC BOOK SISTER IMPERATOR #4 | D82: ='Projection Sheet'!D89 -> 15
A83: 76 | B83: =Inventory!B82 -> GHOSRX003470OT | C83: =Inventory!C82 -> ROLLING STONE MAG & ALBUM | D83: ='Projection Sheet'!#REF! -> #REF!
A84: 77 | B84: =Inventory!B83 -> GHOSRX003611BK | C84: =Inventory!C83 -> LP SKELETA BLACK VINYL | D84: ='Projection Sheet'!#REF! -> #REF!
A85: 78 | B85: =Inventory!B84 -> GHOSCG103805PU | C85: =Inventory!C84 -> LP PURPLE LENTICULAR (CONSIGNMENT) | D85: ='Projection Sheet'!#REF! -> #REF!
A86: 79 | B86: =Inventory!B85 -> GHOSCG103844BK | C86: =Inventory!C85 -> CASSETTE (CONSIGNMENT) | D86: ='Projection Sheet'!#REF! -> #REF!
A87: 80 | B87: =Inventory!B86 -> 0 | C87: =Inventory!C86 -> 0 | D87: ='Projection Sheet'!#REF! -> #REF!
A88: 81 | B88: =Inventory!B87 -> 0 | C88: =Inventory!C87 -> 0 | D88: ='Projection Sheet'!#REF! -> #REF!
A89: 82 | B89: =Inventory!B88 -> 0 | C89: =Inventory!C88 -> 0 | D89: ='Projection Sheet'!#REF! -> #REF!
A90: 83 | B90: =Inventory!B89 -> 0 | C90: =Inventory!C89 -> 0 | D90: ='Projection Sheet'!#REF! -> #REF!
A91: 84 | B91: =Inventory!B90 -> 0 | C91: =Inventory!C90 -> 0 | D91: ='Projection Sheet'!#REF! -> #REF!
A92: 85 | B92: =Inventory!B91 -> 0 | C92: =Inventory!C91 -> 0 | D92: ='Projection Sheet'!#REF! -> #REF!
A93: 86 | B93: =Inventory!B92 -> 0 | C93: =Inventory!C92 -> 0 | D93: ='Projection Sheet'!#REF! -> #REF!
A94: 87 | B94: =Inventory!B93 -> 0 | C94: =Inventory!C93 -> 0 | D94: ='Projection Sheet'!#REF! -> #REF!
... A107: 100 | B107: =Inventory!B106 -> 0 | C107: =Inventory!C106 -> 0 | D107: ='Projection Sheet'!#REF! -> #REF!

Sheet Projection Sheet
F2: SM | G2: MED | H2: LG | I2: XL | J2: 2X | K2: 3X | L2: TOTAL | N2: TOUR STOCK | O2: ORDER QTY | P2: TOTAL | Q2: SIZE | R2: SIZE % | S2: AMOUNT | T2: LESS TOUR INV | U2: ORDER QTY | X2: TS | Y2: LADIES | Z2: LS | AA2: ZIP | AB2: SHORT
L3: =SUM(F3:K3) -> 0 | N3: 0 | O3: 2160 | P3: =N3+O3 -> 2160 | Q3: SM | R3: 0.09 | S3: =P3*R3 -> 194.4 | T3: 0 | U3: =S3-T3 -> 194.4 | X3: 0.05 | Y3: 0.21 | Z3: 0.04 | AA3: 0.04 | AB3: 0.17
L4: =SUM(F4:K4) -> 0 | P4: =P3 -> 2160 | Q4: MED | R4: 0.23 | S4: =P4*R4 -> 496.8 | T4: 0 | U4: =S4-T4 -> 496.8 | X4: 0.12 | Y4: 0.3 | Z4: 0.17 | AA4: 0.17 | AB4: 0.25
L5: =SUM(F5:K5) -> 0 | P5: =P3 -> 2160 | Q5: LG | R5: 0.28 | S5: =P5*R5 -> 604.8 | T5: 0 | U5: =S5-T5 -> 604.8 | X5: 0.27 | Y5: 0.26 | Z5: 0.24 | AA5: 0.24 | AB5: 0.25 | AG5: DATE | AH5: CITY | AI5: ST | AJ5: VENUE | AK5: CAPACITY | AL5: SOLD | AM5: EXPECT | AO5: PH | AP5: GROSS
B6: DATE: | C6: 45944 | L6: =SUM(F6:K6) -> 0 | P6: =P3 -> 2160 | Q6: XL | R6: 0.2 | S6: =P6*R6 -> 432 | T6: 0 | U6: =S6-T6 -> 432 | X6: 0.27 | Y6: 0.23 | Z6: 0.26 | AA6: 0.26 | AB6: 0.21 | AG6: ='Tour Dates'!A4 -> 46043 | AH6: ='Tour Dates'!B4 -> ORLANDO | AI6: ='Tour Dates'!C4 -> FL | AJ6: ='Tour Dates'!D4 -> KIA CENTER | AK6: 9061 | AL6: 6589 | AM6: 7500 | AO6: 35 | AP6: =AM6*AO6 -> 262500
B7: BAND: | C7: =Inventory!C3 -> GHOST | L7: =SUM(F7:K7) -> 0 | P7: =P5 -> 2160 | Q7: 2X | R7: 0.14 | S7: =P7*R7 -> 302.4 | T7: 0 | U7: =S7-T7 -> 302.4 | X7: 0.19 | Y7: 0 | Z7: 0.18 | AA7: 0.18 | AB7: 0.13 | AG7: ='Tour Dates'!A5 -> 46044 | AH7: ='Tour Dates'!B5 -> JACKSONVILLE | AI7: ='Tour Dates'!C5 -> FL | AJ7: ='Tour Dates'!D5 -> VYSTAR MEMORIAL ARENA | AK7: 5265 | AL7: 3275 | AM7: 3750 | AO7: 35 | AP7: =AM7*AO7 -> 131250
B8: TOUR: | C8: North America | L8: =SUM(F8:K8) -> 0 | P8: =P5 -> 2160 | Q8: 3X | R8: 0.06 | S8: =P8*R8 -> 129.6 | T8: 0 | U8: =S8-T8 -> 129.6 | X8: 0.1 | Y8: 0 | Z8: 0.09 | AA8: 0.09 | AB8: 0 | AG8: ='Tour Dates'!A6 -> 46046 | AH8: ='Tour Dates'!B6 -> KNOXVILLE | AI8: ='Tour Dates'!C6 -> TN | AJ8: ='Tour Dates'!D6 -> THOMPSON-BOLING ARENA | AK8: 9698 | AL8: 6720 | AM8: 7000 | AO8: 35 | AP8: =AM8*AO8 -> 245000
B9: # OF SHOWS: | C9: 20 | R9: =SUM(R3:R8) -> 1 | T9: =SUM(T3:T8) -> 0 | U9: =SUM(U3:U8) -> 2160 | X9: 0 | Y9: 0 | Z9: 0.02 | AA9: 0.02 | AB9: 0 | AG9: ='Tour Dates'!A7 -> 46047 | AH9: ='Tour Dates'!B7 -> CHARLOTTE | AI9: ='Tour Dates'!C7 -> NC | AJ9: ='Tour Dates'!D7 -> SPECTRUM CENTER | AK9: 10355 | AL9: 6464 | AM9: 7500 | AO9: 35 | AP9: =AM9*AO9 -> 262500
B10: ATTENDANCE: | C10: =AM46 -> 134885 | X10: =SUM(X3:X9) -> 1 | Y10: =SUM(Y3:Y9) -> 1 | Z10: =SUM(Z3:Z9) -> 1 | AA10: =SUM(AA3:AA9) -> 1 | AB10: =SUM(AB3:AB9) -> 1.01 | AG10: ='Tour Dates'!A8 -> 46048 | AH10: ='Tour Dates'!B8 -> GREENVILLE | AI10: ='Tour Dates'!C8 -> SC | AJ10: ='Tour Dates'!D8 -> BON SECOURS ARENA | AK10: 5978 | AL10: 3321 | AM10: 3800 | AO10: 35 | AP10: =AM10*AO10 -> 133000
AG11: ='Tour Dates'!A9 -> 46050 | AH11: ='Tour Dates'!B9 -> UNCASVILLE | AI11: ='Tour Dates'!C9 -> CT | AJ11: ='Tour Dates'!D9 -> MOHEGAN SUN ARENA | AK11: 4835 | AL11: 4818 | AM11: 4835 | AO11: 35 | AP11: =AM11*AO11 -> 169225
D12: EXP. GROSS | E12: =C10*E13 -> 3372125 | F12: =C10*F13 -> 4046550 | G12: =C10*G13 -> 4316320 | H12: =C10*H13 -> 4855860 | I12: STOCK | J12: STOCK | K12: STOCK | L12: STOCK | M12: STOCK | N12: STOCK | O12: PO's | P12: PRODUCT OVER (+) or UNDER (-) | T12: BLANKS | U12: PRINTER | V12: SM | W12: MED | X12: LG | Y12: XL | Z12: 2X | AA12: 3X | AB12: TOTAL | AC12: DUE | AD12: BLANK PO | AE12: PRINT PO | AG12: ='Tour Dates'!A10 -> 46052 | AH12: ='Tour Dates'!B10 -> MONTREAL | AI12: ='Tour Dates'!C10 -> QC | AJ12: ='Tour Dates'!D10 -> BELL CENTRE | AK12: 12268 | AL12: 8978 | AM12: 10000 | AO12: 25 | AP12: =AM12*AO12 -> 250000
C13: =SUM(C15:C89) -> 0.99 | D13: PRICE/P.H. | E13: 25 | F13: 30 | G13: 32 | H13: 36 | I13: TOUR | J13: CITY-A | K13: CITY-B | L13: MEXICO | M13: WEB | N13: ANAHEIM | O13: ON ORDER | P13: =E13 -> 25 | Q13: =F13 -> 30 | R13: =G13 -> 32 | S13: =H13 -> 36 | AG13: ='Tour Dates'!A11 -> 46053 | AH13: ='Tour Dates'!B11 -> TORONTO | AI13: ='Tour Dates'!C11 -> ON | AJ13: ='Tour Dates'!D11 -> SCOTIABANK ARENA | AK13: 11715 | AL13: 9785 | AM13: 11000 | AO13: 30 | AP13: =AM13*AO13 -> 330000
A14: SKU # | B14: DESIGN | C14: % GROSS | AG14: ='Tour Dates'!A12 -> 46055 | AH14: ='Tour Dates'!B12 -> COLUMBUS | AI14: ='Tour Dates'!C12 -> OH | AJ14: ='Tour Dates'!D12 -> NATIONWIDE ARENA | AK14: 9654 | AL14: 5612 | AM14: 6500 | AO14: 35 | AP14: =AM14*AO14 -> 227500
A15: =Inventory!B7 -> GHOSNS903311BK | B15: =Inventory!C7 -> BATWING HOODY | C15: 0.105 | D15: 125 | E15: =E12/D15*C15 -> 2832.585 | F15: =F12/D15*C15 -> 3399.102 | G15: =G12/D15*C15 -> 3625.7088 | H15: =H12/D15*C15 -> 4078.9224 | I15: 0 | J15: 0 | K15: 0 | L15: 0 | M15: 0 | N15: 0 | O15: 6000 | P15: =I15+J15+K15+L15+M15+N15+O15-E15 -> 3167.415 | Q15: =I15+J15+K15+L15+M15+N15+O15-F15 -> 2600.898 | R15: =I15+J15+K15+L15+M15+N15+O15-G15 -> 2374.2912 | S15: =I15+J15+K15+L15+M15+N15+O15-H15 -> 1921.0776 | T15: CUSTOM | U15: =Inventory!D7 -> FARSTAR | V15: 500 | W15: 1200 | X15: 1800 | Y15: 1300 | Z15: 800 | AA15: 400 | AB15: =SUM(V15:AA15) -> 6000 | AC15: 45986 | AG15: ='Tour Dates'!A13 -> 46057 | AH15: ='Tour Dates'!B13 -> CINCINNATI | AI15: ='Tour Dates'!C13 -> OH | AJ15: ='Tour Dates'!D13 -> HERITAGE BANK CENTER | AK15: 7861 | AL15: 4787 | AM15: 5500 | AO15: 35 | AP15: =AM15*AO15 -> 192500
A16: =Inventory!B8 -> GHOSRX203275BK | B16: =Inventory!C8 -> SHORTS BLACK/ WHT PAPA V COSTUME CLAWS | C16: 0.04 | D16: 45 | E16: =E12/D16*C16 -> 2997.4444 | F16: =F12/D16*C16 -> 3596.9333 | G16: =G12/D16*C16 -> 3836.7289 | H16: =H12/D16*C16 -> 4316.32 | I16: 0 | J16: 0 | K16: 0 | L16: 0 | M16: 0 | N16: 706 | O16: 4500 | P16: =I16+J16+K16+L16+M16+N16+O16-E16 -> 2208.5556 | Q16: =I16+J16+K16+L16+M16+N16+O16-F16 -> 1609.0667 | R16: =I16+J16+K16+L16+M16+N16+O16-G16 -> 1369.2711 | S16: =I16+J16+K16+L16+M16+N16+O16-H16 -> 889.68 | T16: CUSTOM | U16: =Inventory!D8 -> FARSTAR | V16: 650 | W16: 1000 | X16: 1200 | Y16: 1000 | Z16: 650 | AA16: 0 | AB16: =SUM(V16:AA16) -> 4500 | AC16: 45986 | AG16: ='Tour Dates'!A14 -> 46058 | AH16: ='Tour Dates'!B14 -> PEORIA | AI16: ='Tour Dates'!C14 -> IL | AJ16: ='Tour Dates'!D14 -> CIVIC CENTER ARENA | AK16: 7612 | AL16: 4601 | AM16: 5500 | AO16: 35 | AP16: =AM16*AO16 -> 192500
A17: =Inventory!B9 -> GHOSRX204001BK | B17: =Inventory!C9 -> BLACK T SKELETOUR 26 ITIN | C17: 0.12 | D17: 50 | E17: =E12/D17*C17 -> 8093.1 | F17: =F12/D17*C17 -> 9711.72 | G17: =G12/D17*C17 -> 10359.168 | H17: =H12/D17*C17 -> 11654.064 | I17: 0 | J17: 0 | K17: 0 | L17: 0 | M17: 0 | N17: 0 | O17: 7200 | P17: =I17+J17+K17+L17+M17+N17+O17-E17 -> -893.1 | Q17: =I17+J17+K17+L17+M17+N17+O17-F17 -> -2511.72 | R17: =I17+J17+K17+L17+M17+N17+O17-G17 -> -3159.168 | S17: =I17+J17+K17+L17+M17+N17+O17-H17 -> -4454.064 | T17: FULL PACKAGE 30S | U17: =Inventory!D9 -> CULTURE | V17: 576 | W17: 1440 | X17: 2016 | Y17: 1800 | Z17: 864 | AA17: 504 | AB17: =SUM(V17:AA17) -> 7200 | AC17: 46038 | AG17: ='Tour Dates'!A15 -> 46060 | AH17: ='Tour Dates'!B15 -> TULSA | AI17: ='Tour Dates'!C15 -> OK | AJ17: ='Tour Dates'!D15 -> BOK CENTER | AK17: 7524 | AL17: 5252 | AM17: 6000 | AO17: 35 | AP17: =AM17*AO17 -> 210000
A18: =Inventory!B10 -> GHOSRX204000BK | B18: =Inventory!C10 -> BLACK T BAT BRAIN 26 ITIN | C18: 0.14 | D18: 50 | E18: =E12/D18*C18 -> 9441.95 | F18: =F12/D18*C18 -> 11330.34 | G18: =G12/D18*C18 -> 12085.696 | H18: =H12/D18*C18 -> 13596.408 | I18: 0 | J18: 0 | K18: 0 | L18: 0 | M18: 0 | N18: 0 | O18: 7200 | P18: =I18+J18+K18+L18+M18+N18+O18-E18 -> -2241.95 | Q18: =I18+J18+K18+L18+M18+N18+O18-F18 -> -4130.34 | R18: =I18+J18+K18+L18+M18+N18+O18-G18 -> -4885.696 | S18: =I18+J18+K18+L18+M18+N18+O18-H18 -> -6396.408 | T18: FULL PACKAGE 30S | U18: =Inventory!D10 -> CULTURE | V18: 576 | W18: 1440 | X18: 2016 | Y18: 1800 | Z18: 864 | AA18: 504 | AB18: =SUM(V18:AA18) -> 7200 | AC18: 46038 | AG18: ='Tour Dates'!A16 -> 46063 | AH18: ='Tour Dates'!B16 -> SALT LAKE CITY | AI18: ='Tour Dates'!C16 -> UT | AJ18: ='Tour Dates'!D16 -> DELTA CENTER | AK18: 7729 | AL18: 5170 | AM18: 7000 | AO18: 35 | AP18: =AM18*AO18 -> 245000
A19: =Inventory!B11 -> GHOSRX204002BK | B19: =Inventory!C11 -> BLACK T WESTERN EMERITUS 26 ITIN | C19: 0.14 | D19: 50 | E19: =E12/D19*C19 -> 9441.95 | F19: =F12/D19*C19 -> 11330.34 | G19: =G12/D19*C19 -> 12085.696 | H19: =H12/D19*C19 -> 13596.408 | I19: 0 | J19: 0 | K19: 0 | L19: 0 | M19: 0 | N19: 0 | O19: 7200 | P19: =I19+J19+K19+L19+M19+N19+O19-E19 -> -2241.95 | Q19: =I19+J19+K19+L19+M19+N19+O19-F19 -> -4130.34 | R19: =I19+J19+K19+L19+M19+N19+O19-G19 -> -4885.696 | S19: =I19+J19+K19+L19+M19+N19+O19-H19 -> -6396.408 | T19: FULL PACKAGE 30S | U19: =Inventory!D11 -> CULTURE | V19: 576 | W19: 1440 | X19: 2016 | Y19: 1800 | Z19: 864 | AA19: 504 | AB19: =SUM(V19:AA19) -> 7200 | AC19: 46038 | AG19: ='Tour Dates'!A17 -> 46065 | AH19: ='Tour Dates'!B17 -> SPOKANE | AI19: ='Tour Dates'!C17 -> WA | AJ19: ='Tour Dates'!D17 -> SPOKANE ARENA | AK19: 4578 | AL19: 2424 | AM19: 3500 | AO19: 35 | AP19: =AM19*AO19 -> 122500
A20: =Inventory!B12 -> GHOSRX103437OT | B20: =Inventory!C12 -> CRYSTAL WASHED T AT THE GATES | C20: 0.04 | D20: 60 | E20: =E12/D20*C20 -> 2248.0833 | F20: =F12/D20*C20 -> 2697.7 | G20: =G12/D20*C20 -> 2877.5467 | H20: =H12/D20*C20 -> 3237.24 | I20: 0 | J20: 0 | K20: 0 | L20: 0 | M20: 0 | N20: 0 | O20: 1872 | P20: =I20+J20+K20+L20+M20+N20+O20-E20 -> -376.08333 | Q20: =I20+J20+K20+L20+M20+N20+O20-F20 -> -825.7 | R20: =I20+J20+K20+L20+M20+N20+O20-G20 -> -1005.5467 | S20: =I20+J20+K20+L20+M20+N20+O20-H20 -> -1365.24 | T20: COLORTONE 390 | U20: =Inventory!D12 -> CULTURE | V20: 216 | W20: 360 | X20: 504 | Y20: 432 | Z20: 216 | AA20: 144 | AB20: =SUM(V20:AA20) -> 1872 | AC20: 46038 | AG20: ='Tour Dates'!A18 -> 46067 | AH20: ='Tour Dates'!B18 -> VANCOUVER | AI20: ='Tour Dates'!C18 -> BC | AJ20: ='Tour Dates'!D18 -> ROGERS ARENA | AK20: 10794 | AL20: 7063 | AM20: 8000 | AO20: 35 | AP20: =AM20*AO20 -> 280000
A21: =Inventory!B13 -> GHOSRX103998BK | B21: =Inventory!C13 -> BLACK T PAPA COOPER | C21: 0.02 | D21: 50 | E21: =E12/D21*C21 -> 1348.85 | F21: =F12/D21*C21 -> 1618.62 | G21: =G12/D21*C21 -> 1726.528 | H21: =H12/D21*C21 -> 1942.344 | I21: 0 | J21: 0 | K21: 0 | L21: 0 | M21: 0 | N21: 0 | O21: 1104 | P21: =I21+J21+K21+L21+M21+N21+O21-E21 -> -244.85 | Q21: =I21+J21+K21+L21+M21+N21+O21-F21 -> -514.62 | R21: =I21+J21+K21+L21+M21+N21+O21-G21 -> -622.528 | S21: =I21+J21+K21+L21+M21+N21+O21-H21 -> -838.344 | T21: FULL PACKAGE 30S | U21: =Inventory!D13 -> GAVINA | V21: 144 | W21: 216 | X21: 288 | Y21: 240 | Z21: 144 | AA21: 72 | AB21: =SUM(V21:AA21) -> 1104 | AC21: 46038 | AG21: ='Tour Dates'!A19 -> 46068 | AH21: ='Tour Dates'!B19 -> SEATTLE | AI21: ='Tour Dates'!C19 -> WA | AJ21: ='Tour Dates'!D19 -> CLIMATE PLEDGE ARENA | AK21: 10074 | AL21: 6642 | AM21: 8500 | AO21: 35 | AP21: =AM21*AO21 -> 297500
A22: =Inventory!B14 -> GHOSRX103999OT | B22: =Inventory!C14 -> WOMENS CROP RAGLAN CHAMBER OF CHILLS | C22: 0.02 | D22: 50 | E22: =E12/D22*C22 -> 1348.85 | F22: =F12/D22*C22 -> 1618.62 | G22: =G12/D22*C22 -> 1726.528 | H22: =H12/D22*C22 -> 1942.344 | I22: 0 | J22: 0 | K22: 0 | L22: 0 | M22: 0 | N22: 0 | O22: 936 | P22: =I22+J22+K22+L22+M22+N22+O22-E22 -> -412.85 | Q22: =I22+J22+K22+L22+M22+N22+O22-F22 -> -682.62 | R22: =I22+J22+K22+L22+M22+N22+O22-G22 -> -790.528 | S22: =I22+J22+K22+L22+M22+N22+O22-H22 -> -1006.344 | T22: BC 1200 | U22: =Inventory!D14 -> GAVINA | V22: 216 | W22: 288 | X22: 216 | Y22: 216 | Z22: 0 | AA22: 0 | AB22: =SUM(V22:AA22) -> 936 | AC22: 46038 | AG22: ='Tour Dates'!A20 -> 46070 | AH22: ='Tour Dates'!B20 -> PORTLAND | AI22: ='Tour Dates'!C20 -> OR | AJ22: ='Tour Dates'!D20 -> MODA CENTER | AK22: 7818 | AL22: 5176 | AM22: 6000 | AO22: 35 | AP22: =AM22*AO22 -> 210000
A23: =Inventory!B15 -> GHOSRX203401BK | B23: =Inventory!C15 -> BLACK PO HOODIE SKELETON | C23: 0.06 | D23: 80 | E23: =E12/D23*C23 -> 2529.0938 | F23: =F12/D23*C23 -> 3034.9125 | G23: =G12/D23*C23 -> 3237.24 | H23: =H12/D23*C23 -> 3641.895 | I23: 0 | J23: 0 | K23: 0 | L23: 0 | M23: 0 | N23: 57 | O23: 2136 | P23: =I23+J23+K23+L23+M23+N23+O23-E23 -> -336.09375 | Q23: =I23+J23+K23+L23+M23+N23+O23-F23 -> -841.9125 | R23: =I23+J23+K23+L23+M23+N23+O23-G23 -> -1044.24 | S23: =I23+J23+K23+L23+M23+N23+O23-H23 -> -1448.895 | T23: INDSS4500 | U23: =Inventory!D15 -> GAVINA | V23: 192 | W23: 504 | X23: 576 | Y23: 432 | Z23: 288 | AA23: 144 | AB23: =SUM(V23:AA23) -> 2136 | AC23: 46038 | AG23: ='Tour Dates'!A21 -> 46073 | AH23: ='Tour Dates'!B21 -> SACRAMENTO | AI23: ='Tour Dates'!C21 -> CA | AJ23: ='Tour Dates'!D21 -> GOLDEN 1 CENTER | AK23: 10424 | AL23: 6634 | AM23: 7500 | AO23: 35 | AP23: =AM23*AO23 -> 262500
A24: =Inventory!B16 -> 0 | B24: =Inventory!C16 -> 0 | C24: 0 | D24: 1 | E24: =E12/D24*C24 -> 0 | F24: =F12/D24*C24 -> 0 | G24: =G12/D24*C24 -> 0 | H24: =H12/D24*C24 -> 0 | I24: 0 | J24: 0 | K24: 0 | L24: 0 | M24: 0 | N24: 0 | O24: 0 | P24: =I24+J24+K24+L24+M24+N24+O24-E24 -> 0 | Q24: =I24+J24+K24+L24+M24+N24+O24-F24 -> 0 | R24: =I24+J24+K24+L24+M24+N24+O24-G24 -> 0 | S24: =I24+J24+K24+L24+M24+N24+O24-H24 -> 0 | U24: =Inventory!D16 -> 0 | AB24: =SUM(V24:AA24) -> 0 | AG24: ='Tour Dates'!A22 -> 46074 | AH24: ='Tour Dates'!B22 -> ANAHEIM | AI24: ='Tour Dates'!C22 -> CA | AJ24: ='Tour Dates'!D22 -> HONDA CENTER | AK24: 9423 | AL24: 7644 | AM24: 9000 | AO24: 35 | AP24: =AM24*AO24 -> 315000
A25: =Inventory!B17 -> 0 | B25: =Inventory!C17 -> 0 | C25: 0 | D25: 1 | E25: =E12/D25*C25 -> 0 | F25: =F12/D25*C25 -> 0 | G25: =G12/D25*C25 -> 0 | H25: =H12/D25*C25 -> 0 | I25: 0 | J25: 0 | K25: 0 | L25: 0 | M25: 0 | N25: 0 | O25: 0 | P25: =I25+J25+K25+L25+M25+N25+O25-E25 -> 0 | Q25: =I25+J25+K25+L25+M25+N25+O25-F25 -> 0 | R25: =I25+J25+K25+L25+M25+N25+O25-G25 -> 0 | S25: =I25+J25+K25+L25+M25+N25+O25-H25 -> 0 | U25: =Inventory!D17 -> 0 | AB25: =SUM(V25:AA25) -> 0 | AG25: ='Tour Dates'!A23 -> 46076 | AH25: ='Tour Dates'!B23 -> INGLEWOOD | AI25: ='Tour Dates'!C23 -> CA | AJ25: ='Tour Dates'!D23 -> INTUIT DOME | AK25: 8462 | AL25: 4227 | AM25: 6500 | AO25: 35 | AP25: =AM25*AO25 -> 227500
A26: =Inventory!B18 -> 0 | B26: =Inventory!C18 -> 0 | C26: 0 | D26: 1 | E26: =E12/D26*C26 -> 0 | F26: =F12/D26*C26 -> 0 | G26: =G12/D26*C26 -> 0 | H26: =H12/D26*C26 -> 0 | I26: 0 | J26: 0 | K26: 0 | L26: 0 | M26: 0 | N26: 0 | O26: 0 | P26: =I26+J26+K26+L26+M26+N26+O26-E26 -> 0 | Q26: =I26+J26+K26+L26+M26+N26+O26-F26 -> 0 | R26: =I26+J26+K26+L26+M26+N26+O26-G26 -> 0 | S26: =I26+J26+K26+L26+M26+N26+O26-H26 -> 0 | U26: =Inventory!D18 -> 0 | AB26: =SUM(V26:AA26) -> 0 | AG26: ='Tour Dates'!A24 -> 0 | AH26: ='Tour Dates'!B24 -> 0 | AI26: ='Tour Dates'!C24 -> 0 | AJ26: ='Tour Dates'!D24 -> 0 | AK26: 0 | AL26: 0 | AM26: 0 | AO26: 0 | AP26: =AM26*AO26 -> 0
A27: =Inventory!B19 -> 0 | B27: =Inventory!C19 -> 0 | C27: 0 | D27: 1 | E27: =E12/D27*C27 -> 0 | F27: =F12/D27*C27 -> 0 | G27: =G12/D27*C27 -> 0 | H27: =H12/D27*C27 -> 0 | I27: 0 | J27: 0 | K27: 0 | L27: 0 | M27: 0 | N27: 0 | O27: 0 | P27: =I27+J27+K27+L27+M27+N27+O27-E27 -> 0 | Q27: =I27+J27+K27+L27+M27+N27+O27-F27 -> 0 | R27: =I27+J27+K27+L27+M27+N27+O27-G27 -> 0 | S27: =I27+J27+K27+L27+M27+N27+O27-H27 -> 0 | U27: =Inventory!D19 -> 0 | AB27: =SUM(V27:AA27) -> 0 | AG27: ='Tour Dates'!A25 -> 0 | AH27: ='Tour Dates'!B25 -> 0 | AI27: ='Tour Dates'!C25 -> 0 | AJ27: ='Tour Dates'!D25 -> 0 | AK27: 0 | AL27: 0 | AM27: 0 | AO27: 0 | AP27: =AM27*AO27 -> 0
A28: =Inventory!B20 -> 0 | B28: =Inventory!C20 -> 0 | C28: 0 | D28: 1 | E28: =E12/D28*C28 -> 0 | F28: =F12/D28*C28 -> 0 | G28: =G12/D28*C28 -> 0 | H28: =H12/D28*C28 -> 0 | I28: 0 | J28: 0 | K28: 0 | L28: 0 | M28: 0 | N28: 0 | O28: 0 | P28: =I28+J28+K28+L28+M28+N28+O28-E28 -> 0 | Q28: =I28+J28+K28+L28+M28+N28+O28-F28 -> 0 | R28: =I28+J28+K28+L28+M28+N28+O28-G28 -> 0 | S28: =I28+J28+K28+L28+M28+N28+O28-H28 -> 0 | U28: =Inventory!D20 -> 0 | AB28: =SUM(V28:AA28) -> 0 | AG28: ='Tour Dates'!A26 -> 0 | AH28: ='Tour Dates'!B26 -> 0 | AI28: ='Tour Dates'!C26 -> 0 | AJ28: ='Tour Dates'!D26 -> 0 | AK28: 0 | AL28: 0 | AM28: 0 | AO28: 0 | AP28: =AM28*AO28 -> 0
A29: =Inventory!B21 -> 0 | B29: =Inventory!C21 -> 0 | C29: 0 | D29: 1 | E29: =E12/D29*C29 -> 0 | F29: =F12/D29*C29 -> 0 | G29: =G12/D29*C29 -> 0 | H29: =H12/D29*C29 -> 0 | I29: 0 | J29: 0 | K29: 0 | L29: 0 | M29: 0 | N29: 0 | O29: 0 | P29: =I29+J29+K29+L29+M29+N29+O29-E29 -> 0 | Q29: =I29+J29+K29+L29+M29+N29+O29-F29 -> 0 | R29: =I29+J29+K29+L29+M29+N29+O29-G29 -> 0 | S29: =I29+J29+K29+L29+M29+N29+O29-H29 -> 0 | U29: =Inventory!D21 -> 0 | AB29: =SUM(V29:AA29) -> 0 | AG29: ='Tour Dates'!A27 -> 0 | AH29: ='Tour Dates'!B27 -> 0 | AI29: ='Tour Dates'!C27 -> 0 | AJ29: ='Tour Dates'!D27 -> 0 | AK29: 0 | AL29: 0 | AM29: 0 | AO29: 0 | AP29: =AM29*AO29 -> 0
A30: =Inventory!B22 -> 0 | B30: =Inventory!C22 -> 0 | C30: 0 | D30: 1 | E30: =E12/D30*C30 -> 0 | F30: =F12/D30*C30 -> 0 | G30: =G12/D30*C30 -> 0 | H30: =H12/D30*C30 -> 0 | I30: 0 | J30: 0 | K30: 0 | L30: 0 | M30: 0 | N30: 0 | O30: 0 | P30: =I30+J30+K30+L30+M30+N30+O30-E30 -> 0 | Q30: =I30+J30+K30+L30+M30+N30+O30-F30 -> 0 | R30: =I30+J30+K30+L30+M30+N30+O30-G30 -> 0 | S30: =I30+J30+K30+L30+M30+N30+O30-H30 -> 0 | U30: =Inventory!D22 -> 0 | AB30: =SUM(V30:AA30) -> 0 | AG30: ='Tour Dates'!A28 -> 0 | AH30: ='Tour Dates'!B28 -> 0 | AI30: ='Tour Dates'!C28 -> 0 | AJ30: ='Tour Dates'!D28 -> 0 | AK30: 0 | AL30: 0 | AM30: 0 | AO30: 0 | AP30: =AM30*AO30 -> 0
A31: =Inventory!B23 -> 0 | B31: =Inventory!C23 -> 0 | C31: 0 | D31: 1 | E31: =E12/D31*C31 -> 0 | F31: =F12/D31*C31 -> 0 | G31: =G12/D31*C31 -> 0 | H31: =H12/D31*C31 -> 0 | I31: 0 | J31: 0 | K31: 0 | L31: 0 | M31: 0 | N31: 0 | O31: 0 | P31: =I31+J31+K31+L31+M31+N31+O31-E31 -> 0 | Q31: =I31+J31+K31+L31+M31+N31+O31-F31 -> 0 | R31: =I31+J31+K31+L31+M31+N31+O31-G31 -> 0 | S31: =I31+J31+K31+L31+M31+N31+O31-H31 -> 0 | U31: =Inventory!D23 -> 0 | AB31: =SUM(V31:AA31) -> 0 | AG31: ='Tour Dates'!A29 -> 0 | AH31: ='Tour Dates'!B29 -> 0 | AI31: ='Tour Dates'!C29 -> 0 | AJ31: ='Tour Dates'!D29 -> 0 | AK31: 0 | AL31: 0 | AM31: 0 | AO31: 0 | AP31: =AM31*AO31 -> 0
A32: =Inventory!B24 -> 0 | B32: =Inventory!C24 -> 0 | C32: 0 | D32: 1 | E32: =E12/D32*C32 -> 0 | F32: =F12/D32*C32 -> 0 | G32: =G12/D32*C32 -> 0 | H32: =H12/D32*C32 -> 0 | I32: 0 | J32: 0 | K32: 0 | L32: 0 | M32: 0 | N32: 0 | O32: 0 | P32: =I32+J32+K32+L32+M32+N32+O32-E32 -> 0 | Q32: =I32+J32+K32+L32+M32+N32+O32-F32 -> 0 | R32: =I32+J32+K32+L32+M32+N32+O32-G32 -> 0 | S32: =I32+J32+K32+L32+M32+N32+O32-H32 -> 0 | U32: =Inventory!D24 -> 0 | AB32: =SUM(V32:AA32) -> 0 | AG32: ='Tour Dates'!A30 -> 0 | AH32: ='Tour Dates'!B30 -> 0 | AI32: ='Tour Dates'!C30 -> 0 | AJ32: ='Tour Dates'!D30 -> 0 | AK32: 0 | AL32: 0 | AM32: 0 | AO32: 0 | AP32: =AM32*AO32 -> 0
A33: =Inventory!B25 -> 0 | B33: =Inventory!C25 -> 0 | C33: 0 | D33: 1 | E33: =E12/D33*C33 -> 0 | F33: =F12/D33*C33 -> 0 | G33: =G12/D33*C33 -> 0 | H33: =H12/D33*C33 -> 0 | I33: 0 | J33: 0 | K33: 0 | L33: 0 | M33: 0 | N33: 0 | O33: 0 | P33: =I33+J33+K33+L33+M33+N33+O33-E33 -> 0 | Q33: =I33+J33+K33+L33+M33+N33+O33-F33 -> 0 | R33: =I33+J33+K33+L33+M33+N33+O33-G33 -> 0 | S33: =I33+J33+K33+L33+M33+N33+O33-H33 -> 0 | U33: =Inventory!D25 -> 0 | AB33: =SUM(V33:AA33) -> 0 | AG33: ='Tour Dates'!A31 -> 0 | AH33: ='Tour Dates'!B31 -> 0 | AI33: ='Tour Dates'!C31 -> 0 | AJ33: ='Tour Dates'!D31 -> 0 | AK33: 0 | AL33: 0 | AM33: 0 | AO33: 0 | AP33: =AM33*AO33 -> 0
A34: =Inventory!B26 -> 0 | B34: =Inventory!C26 -> 0 | C34: 0 | D34: 1 | E34: =E12/D34*C34 -> 0 | F34: =F12/D34*C34 -> 0 | G34: =G12/D34*C34 -> 0 | H34: =H12/D34*C34 -> 0 | I34: 0 | J34: 0 | K34: 0 | L34: 0 | M34: 0 | N34: 0 | O34: 0 | P34: =I34+J34+K34+L34+M34+N34+O34-E34 -> 0 | Q34: =I34+J34+K34+L34+M34+N34+O34-F34 -> 0 | R34: =I34+J34+K34+L34+M34+N34+O34-G34 -> 0 | S34: =I34+J34+K34+L34+M34+N34+O34-H34 -> 0 | U34: =Inventory!D26 -> 0 | AB34: =SUM(V34:AA34) -> 0 | AG34: ='Tour Dates'!A32 -> 0 | AH34: ='Tour Dates'!B32 -> 0 | AI34: ='Tour Dates'!C32 -> 0 | AJ34: ='Tour Dates'!D32 -> 0 | AK34: 0 | AL34: 0 | AM34: 0 | AO34: 0 | AP34: =AM34*AO34 -> 0
A35: =Inventory!B27 -> 0 | B35: =Inventory!C27 -> 0 | C35: 0 | D35: 1 | E35: =E12/D35*C35 -> 0 | F35: =F12/D35*C35 -> 0 | G35: =G12/D35*C35 -> 0 | H35: =H12/D35*C35 -> 0 | I35: 0 | J35: 0 | K35: 0 | L35: 0 | M35: 0 | N35: 0 | O35: 0 | P35: =I35+J35+K35+L35+M35+N35+O35-E35 -> 0 | Q35: =I35+J35+K35+L35+M35+N35+O35-F35 -> 0 | R35: =I35+J35+K35+L35+M35+N35+O35-G35 -> 0 | S35: =I35+J35+K35+L35+M35+N35+O35-H35 -> 0 | U35: =Inventory!D27 -> 0 | AB35: =SUM(V35:AA35) -> 0 | AG35: ='Tour Dates'!A33 -> 0 | AH35: ='Tour Dates'!B33 -> 0 | AI35: ='Tour Dates'!C33 -> 0 | AJ35: ='Tour Dates'!D33 -> 0 | AK35: 0 | AL35: 0 | AM35: 0 | AO35: 0 | AP35: =AM35*AO35 -> 0
A36: =Inventory!B28 -> 0 | B36: =Inventory!C28 -> 0 | C36: 0 | D36: 1 | E36: =E12/D36*C36 -> 0 | F36: =F12/D36*C36 -> 0 | G36: =G12/D36*C36 -> 0 | H36: =H12/D36*C36 -> 0 | I36: 0 | J36: 0 | K36: 0 | L36: 0 | M36: 0 | N36: 0 | O36: 0 | P36: =I36+J36+K36+L36+M36+N36+O36-E36 -> 0 | Q36: =I36+J36+K36+L36+M36+N36+O36-F36 -> 0 | R36: =I36+J36+K36+L36+M36+N36+O36-G36 -> 0 | S36: =I36+J36+K36+L36+M36+N36+O36-H36 -> 0 | U36: =Inventory!D28 -> 0 | AB36: =SUM(V36:AA36) -> 0 | AG36: ='Tour Dates'!A34 -> 0 | AH36: ='Tour Dates'!B34 -> 0 | AI36: ='Tour Dates'!C34 -> 0 | AJ36: ='Tour Dates'!D34 -> 0 | AK36: 0 | AL36: 0 | AM36: 0 | AO36: 0 | AP36: =AM36*AO36 -> 0
A37: =Inventory!B29 -> 0 | B37: =Inventory!C29 -> 0 | C37: 0 | D37: 1 | E37: =E12/D37*C37 -> 0 | F37: =F12/D37*C37 -> 0 | G37: =G12/D37*C37 -> 0 | H37: =H12/D37*C37 -> 0 | I37: 0 | J37: 0 | K37: 0 | L37: 0 | M37: 0 | N37: 0 | O37: 0 | P37: =I37+J37+K37+L37+M37+N37+O37-E37 -> 0 | Q37: =I37+J37+K37+L37+M37+N37+O37-F37 -> 0 | R37: =I37+J37+K37+L37+M37+N37+O37-G37 -> 0 | S37: =I37+J37+K37+L37+M37+N37+O37-H37 -> 0 | U37: =Inventory!D29 -> 0 | AB37: =SUM(V37:AA37) -> 0 | AG37: ='Tour Dates'!A35 -> 0 | AH37: ='Tour Dates'!B35 -> 0 | AI37: ='Tour Dates'!C35 -> 0 | AJ37: ='Tour Dates'!D35 -> 0 | AK37: 0 | AL37: 0 | AM37: 0 | AO37: 0 | AP37: =AM37*AO37 -> 0
A38: =Inventory!B30 -> 0 | B38: =Inventory!C30 -> 0 | C38: 0 | D38: 1 | E38: =E12/D38*C38 -> 0 | F38: =F12/D38*C38 -> 0 | G38: =G12/D38*C38 -> 0 | H38: =H12/D38*C38 -> 0 | I38: 0 | J38: 0 | K38: 0 | L38: 0 | M38: 0 | N38: 0 | O38: 0 | P38: =I38+J38+K38+L38+M38+N38+O38-E38 -> 0 | Q38: =I38+J38+K38+L38+M38+N38+O38-F38 -> 0 | R38: =I38+J38+K38+L38+M38+N38+O38-G38 -> 0 | S38: =I38+J38+K38+L38+M38+N38+O38-H38 -> 0 | U38: =Inventory!D30 -> 0 | AB38: =SUM(V38:AA38) -> 0 | AG38: ='Tour Dates'!A36 -> 0 | AH38: ='Tour Dates'!B36 -> 0 | AI38: ='Tour Dates'!C36 -> 0 | AJ38: ='Tour Dates'!D36 -> 0 | AK38: 0 | AL38: 0 | AM38: 0 | AO38: 0 | AP38: =AM38*AO38 -> 0
A39: =Inventory!B31 -> 0 | B39: =Inventory!C31 -> 0 | C39: 0 | D39: 1 | E39: =E12/D39*C39 -> 0 | F39: =F12/D39*C39 -> 0 | G39: =G12/D39*C39 -> 0 | H39: =H12/D39*C39 -> 0 | I39: 0 | J39: 0 | K39: 0 | L39: 0 | M39: 0 | N39: 0 | O39: 0 | P39: =I39+J39+K39+L39+M39+N39+O39-E39 -> 0 | Q39: =I39+J39+K39+L39+M39+N39+O39-F39 -> 0 | R39: =I39+J39+K39+L39+M39+N39+O39-G39 -> 0 | S39: =I39+J39+K39+L39+M39+N39+O39-H39 -> 0 | U39: =Inventory!D31 -> 0 | AB39: =SUM(V39:AA39) -> 0 | AG39: ='Tour Dates'!A37 -> 0 | AH39: ='Tour Dates'!B37 -> 0 | AI39: ='Tour Dates'!C37 -> 0 | AJ39: ='Tour Dates'!D37 -> 0 | AK39: 0 | AL39: 0 | AM39: 0 | AO39: 0 | AP39: =AM39*AO39 -> 0
A40: =Inventory!B32 -> 0 | B40: =Inventory!C32 -> 0 | C40: 0 | D40: 1 | E40: =E12/D40*C40 -> 0 | F40: =F12/D40*C40 -> 0 | G40: =G12/D40*C40 -> 0 | H40: =H12/D40*C40 -> 0 | I40: 0 | J40: 0 | K40: 0 | L40: 0 | M40: 0 | N40: 0 | O40: 0 | P40: =I40+J40+K40+L40+M40+N40+O40-E40 -> 0 | Q40: =I40+J40+K40+L40+M40+N40+O40-F40 -> 0 | R40: =I40+J40+K40+L40+M40+N40+O40-G40 -> 0 | S40: =I40+J40+K40+L40+M40+N40+O40-H40 -> 0 | U40: =Inventory!D32 -> 0 | AB40: =SUM(V40:AA40) -> 0 | AG40: ='Tour Dates'!A38 -> 0 | AH40: ='Tour Dates'!B38 -> 0 | AI40: ='Tour Dates'!C38 -> 0 | AJ40: ='Tour Dates'!D38 -> 0 | AK40: 0 | AL40: 0 | AM40: 0 | AO40: 0 | AP40: =AM40*AO40 -> 0
A41: =Inventory!B33 -> 0 | B41: =Inventory!C33 -> 0 | C41: 0 | D41: 1 | E41: =E12/D41*C41 -> 0 | F41: =F12/D41*C41 -> 0 | G41: =G12/D41*C41 -> 0 | H41: =H12/D41*C41 -> 0 | I41: 0 | J41: 0 | K41: 0 | L41: 0 | M41: 0 | N41: 0 | O41: 0 | P41: =I41+J41+K41+L41+M41+N41+O41-E41 -> 0 | Q41: =I41+J41+K41+L41+M41+N41+O41-F41 -> 0 | R41: =I41+J41+K41+L41+M41+N41+O41-G41 -> 0 | S41: =I41+J41+K41+L41+M41+N41+O41-H41 -> 0 | U41: =Inventory!D33 -> 0 | AB41: =SUM(V41:AA41) -> 0 | AG41: ='Tour Dates'!A39 -> 0 | AH41: ='Tour Dates'!B39 -> 0 | AI41: ='Tour Dates'!C39 -> 0 | AJ41: ='Tour Dates'!D39 -> 0 | AK41: 0 | AL41: 0 | AM41: 0 | AO41: 0 | AP41: =AM41*AO41 -> 0
A42: =Inventory!B34 -> 0 | B42: =Inventory!C34 -> 0 | C42: 0 | D42: 1 | E42: =E12/D42*C42 -> 0 | F42: =F12/D42*C42 -> 0 | G42: =G12/D42*C42 -> 0 | H42: =H12/D42*C42 -> 0 | I42: 0 | J42: 0 | K42: 0 | L42: 0 | M42: 0 | N42: 0 | O42: 0 | P42: =I42+J42+K42+L42+M42+N42+O42-E42 -> 0 | Q42: =I42+J42+K42+L42+M42+N42+O42-F42 -> 0 | R42: =I42+J42+K42+L42+M42+N42+O42-G42 -> 0 | S42: =I42+J42+K42+L42+M42+N42+O42-H42 -> 0 | U42: =Inventory!D34 -> 0 | AB42: =SUM(V42:AA42) -> 0 | AG42: ='Tour Dates'!A40 -> 0 | AH42: ='Tour Dates'!B40 -> 0 | AI42: ='Tour Dates'!C40 -> 0 | AJ42: ='Tour Dates'!D40 -> 0 | AK42: 0 | AL42: 0 | AM42: 0 | AO42: 0 | AP42: =AM42*AO42 -> 0
A43: =Inventory!B35 -> 0 | B43: =Inventory!C35 -> 0 | C43: 0 | D43: 1 | E43: =E12/D43*C43 -> 0 | F43: =F12/D43*C43 -> 0 | G43: =G12/D43*C43 -> 0 | H43: =H12/D43*C43 -> 0 | I43: 0 | J43: 0 | K43: 0 | L43: 0 | M43: 0 | N43: 0 | O43: 0 | P43: =I43+J43+K43+L43+M43+N43+O43-E43 -> 0 | Q43: =I43+J43+K43+L43+M43+N43+O43-F43 -> 0 | R43: =I43+J43+K43+L43+M43+N43+O43-G43 -> 0 | S43: =I43+J43+K43+L43+M43+N43+O43-H43 -> 0 | U43: =Inventory!D35 -> 0 | AB43: =SUM(V43:AA43) -> 0 | AG43: ='Tour Dates'!A41 -> 0 | AH43: ='Tour Dates'!B41 -> 0 | AI43: ='Tour Dates'!C41 -> 0 | AJ43: ='Tour Dates'!D41 -> 0 | AK43: 0 | AL43: 0 | AM43: 0 | AO43: 0 | AP43: =AM43*AO43 -> 0
A44: =Inventory!B36 -> 0 | B44: =Inventory!C36 -> 0 | C44: 0 | D44: 1 | E44: =E12/D44*C44 -> 0 | F44: =F12/D44*C44 -> 0 | G44: =G12/D44*C44 -> 0 | H44: =H12/D44*C44 -> 0 | I44: 0 | J44: 0 | K44: 0 | L44: 0 | M44: 0 | N44: 0 | O44: 0 | P44: =I44+J44+K44+L44+M44+N44+O44-E44 -> 0 | Q44: =I44+J44+K44+L44+M44+N44+O44-F44 -> 0 | R44: =I44+J44+K44+L44+M44+N44+O44-G44 -> 0 | S44: =I44+J44+K44+L44+M44+N44+O44-H44 -> 0 | U44: =Inventory!D36 -> 0 | AB44: =SUM(V44:AA44) -> 0 | AG44: ='Tour Dates'!A42 -> 0 | AH44: ='Tour Dates'!B42 -> 0 | AI44: ='Tour Dates'!C42 -> 0 | AJ44: ='Tour Dates'!D42 -> 0 | AK44: 0 | AL44: 0 | AM44: 0 | AO44: 0 | AP44: =AM44*AO44 -> 0
A45: =Inventory!B37 -> 0 | B45: =Inventory!C37 -> 0 | C45: 0 | D45: 1 | E45: =E12/D45*C45 -> 0 | F45: =F12/D45*C45 -> 0 | G45: =G12/D45*C45 -> 0 | H45: =H12/D45*C45 -> 0 | I45: 0 | J45: 0 | K45: 0 | L45: 0 | M45: 0 | N45: 0 | O45: 0 | P45: =I45+J45+K45+L45+M45+N45+O45-E45 -> 0 | Q45: =I45+J45+K45+L45+M45+N45+O45-F45 -> 0 | R45: =I45+J45+K45+L45+M45+N45+O45-G45 -> 0 | S45: =I45+J45+K45+L45+M45+N45+O45-H45 -> 0 | U45: =Inventory!D37 -> 0 | AB45: =SUM(V45:AA45) -> 0 | AG45: ='Tour Dates'!A43 -> 0 | AH45: ='Tour Dates'!B43 -> 0 | AI45: ='Tour Dates'!C43 -> 0 | AJ45: ='Tour Dates'!D43 -> 0 | AK45: 0 | AL45: 0 | AM45: 0 | AO45: 0 | AP45: =AM45*AO45 -> 0
A46: =Inventory!B38 -> 0 | B46: =Inventory!C38 -> 0 | C46: 0 | D46: 1 | E46: =E12/D46*C46 -> 0 | F46: =F12/D46*C46 -> 0 | G46: =G12/D46*C46 -> 0 | H46: =H12/D46*C46 -> 0 | I46: 0 | J46: 0 | K46: 0 | L46: 0 | M46: 0 | N46: 0 | O46: 0 | P46: =I46+J46+K46+L46+M46+N46+O46-E46 -> 0 | Q46: =I46+J46+K46+L46+M46+N46+O46-F46 -> 0 | R46: =I46+J46+K46+L46+M46+N46+O46-G46 -> 0 | S46: =I46+J46+K46+L46+M46+N46+O46-H46 -> 0 | U46: =Inventory!D38 -> 0 | AB46: =SUM(V46:AA46) -> 0 | AK46: =SUM(AK6:AK45) -> 171128 | AL46: =SUM(AL6:AL40) -> 115182 | AM46: =SUM(AM6:AM40) -> 134885 | AO46: =AP46/AM46 -> 33.850873 | AP46: =SUM(AP6:AP45) -> 4565975
A47: =Inventory!B39 -> 0 | B47: =Inventory!C39 -> 0 | C47: 0 | D47: 1 | E47: =E12/D47*C47 -> 0 | F47: =F12/D47*C47 -> 0 | G47: =G12/D47*C47 -> 0 | H47: =H12/D47*C47 -> 0 | I47: 0 | J47: 0 | K47: 0 | L47: 0 | M47: 0 | N47: 0 | O47: 0 | P47: =I47+J47+K47+L47+M47+N47+O47-E47 -> 0 | Q47: =I47+J47+K47+L47+M47+N47+O47-F47 -> 0 | R47: =I47+J47+K47+L47+M47+N47+O47-G47 -> 0 | S47: =I47+J47+K47+L47+M47+N47+O47-H47 -> 0 | U47: =Inventory!D39 -> 0 | AB47: =SUM(V47:AA47) -> 0 | AL47: =AL46/AK46 -> 0.67307513 | AM47: =AM46/AK46 -> 0.78821116
A48: =Inventory!B40 -> 0 | B48: =Inventory!C40 -> 0 | C48: 0 | D48: 1 | E48: =E12/D48*C48 -> 0 | F48: =F12/D48*C48 -> 0 | G48: =G12/D48*C48 -> 0 | H48: =H12/D48*C48 -> 0 | I48: 0 | J48: 0 | K48: 0 | L48: 0 | M48: 0 | N48: 0 | O48: 0 | P48: =I48+J48+K48+L48+M48+N48+O48-E48 -> 0 | Q48: =I48+J48+K48+L48+M48+N48+O48-F48 -> 0 | R48: =I48+J48+K48+L48+M48+N48+O48-G48 -> 0 | S48: =I48+J48+K48+L48+M48+N48+O48-H48 -> 0 | U48: =Inventory!D40 -> 0 | AB48: =SUM(V48:AA48) -> 0
A49: =Inventory!B41 -> 0 | B49: =Inventory!C41 -> 0 | C49: 0 | D49: 1 | E49: =E12/D49*C49 -> 0 | F49: =F12/D49*C49 -> 0 | G49: =G12/D49*C49 -> 0 | H49: =H12/D49*C49 -> 0 | I49: 0 | J49: 0 | K49: 0 | L49: 0 | M49: 0 | N49: 0 | O49: 0 | P49: =I49+J49+K49+L49+M49+N49+O49-E49 -> 0 | Q49: =I49+J49+K49+L49+M49+N49+O49-F49 -> 0 | R49: =I49+J49+K49+L49+M49+N49+O49-G49 -> 0 | S49: =I49+J49+K49+L49+M49+N49+O49-H49 -> 0 | U49: =Inventory!D41 -> 0 | AB49: =SUM(V49:AA49) -> 0
A50: =Inventory!B42 -> 0 | B50: =Inventory!C42 -> 0 | C50: 0 | D50: 1 | E50: =E12/D50*C50 -> 0 | F50: =F12/D50*C50 -> 0 | G50: =G12/D50*C50 -> 0 | H50: =H12/D50*C50 -> 0 | I50: 0 | J50: 0 | K50: 0 | L50: 0 | M50: 0 | N50: 0 | O50: 0 | P50: =I50+J50+K50+L50+M50+N50+O50-E50 -> 0 | Q50: =I50+J50+K50+L50+M50+N50+O50-F50 -> 0 | R50: =I50+J50+K50+L50+M50+N50+O50-G50 -> 0 | S50: =I50+J50+K50+L50+M50+N50+O50-H50 -> 0 | U50: =Inventory!D42 -> 0 | AB50: =SUM(V50:AA50) -> 0
A51: =Inventory!B43 -> 0 | B51: =Inventory!C43 -> 0 | C51: 0 | D51: 1 | E51: =E12/D51*C51 -> 0 | F51: =F12/D51*C51 -> 0 | G51: =G12/D51*C51 -> 0 | H51: =H12/D51*C51 -> 0 | I51: 0 | J51: 0 | K51: 0 | L51: 0 | M51: 0 | N51: 0 | O51: 0 | P51: =I51+J51+K51+L51+M51+N51+O51-E51 -> 0 | Q51: =I51+J51+K51+L51+M51+N51+O51-F51 -> 0 | R51: =I51+J51+K51+L51+M51+N51+O51-G51 -> 0 | S51: =I51+J51+K51+L51+M51+N51+O51-H51 -> 0 | U51: =Inventory!D43 -> 0 | AB51: =SUM(V51:AA51) -> 0
A52: =Inventory!B44 -> 0 | B52: =Inventory!C44 -> 0 | C52: 0 | D52: 1 | E52: =E12/D52*C52 -> 0 | F52: =F12/D52*C52 -> 0 | G52: =G12/D52*C52 -> 0 | H52: =H12/D52*C52 -> 0 | I52: 0 | J52: 0 | K52: 0 | L52: 0 | M52: 0 | N52: 0 | O52: 0 | P52: =I52+J52+K52+L52+M52+N52+O52-E52 -> 0 | Q52: =I52+J52+K52+L52+M52+N52+O52-F52 -> 0 | R52: =I52+J52+K52+L52+M52+N52+O52-G52 -> 0 | S52: =I52+J52+K52+L52+M52+N52+O52-H52 -> 0 | U52: =Inventory!D44 -> 0 | AB52: =SUM(V52:AA52) -> 0
A53: =Inventory!B45 -> 0 | B53: =Inventory!C45 -> 0 | C53: 0 | D53: 1 | E53: =E12/D53*C53 -> 0 | F53: =F12/D53*C53 -> 0 | G53: =G12/D53*C53 -> 0 | H53: =H12/D53*C53 -> 0 | I53: 0 | J53: 0 | K53: 0 | L53: 0 | M53: 0 | N53: 0 | O53: 0 | P53: =I53+J53+K53+L53+M53+N53+O53-E53 -> 0 | Q53: =I53+J53+K53+L53+M53+N53+O53-F53 -> 0 | R53: =I53+J53+K53+L53+M53+N53+O53-G53 -> 0 | S53: =I53+J53+K53+L53+M53+N53+O53-H53 -> 0 | U53: =Inventory!D45 -> 0 | AB53: =SUM(V53:AA53) -> 0
A54: =Inventory!B46 -> 0 | B54: =Inventory!C46 -> 0 | C54: 0 | D54: 1 | E54: =E12/D54*C54 -> 0 | F54: =F12/D54*C54 -> 0 | G54: =G12/D54*C54 -> 0 | H54: =H12/D54*C54 -> 0 | I54: 0 | J54: 0 | K54: 0 | L54: 0 | M54: 0 | N54: 0 | O54: 0 | P54: =I54+J54+K54+L54+M54+N54+O54-E54 -> 0 | Q54: =I54+J54+K54+L54+M54+N54+O54-F54 -> 0 | R54: =I54+J54+K54+L54+M54+N54+O54-G54 -> 0 | S54: =I54+J54+K54+L54+M54+N54+O54-H54 -> 0 | U54: =Inventory!D46 -> 0 | AB54: =SUM(V54:AA54) -> 0
A55: =Inventory!B47 -> 0 | B55: =Inventory!C47 -> 0 | C55: 0 | D55: 1 | E55: =E12/D55*C55 -> 0 | F55: =F12/D55*C55 -> 0 | G55: =G12/D55*C55 -> 0 | H55: =H12/D55*C55 -> 0 | I55: 0 | J55: 0 | K55: 0 | L55: 0 | M55: 0 | N55: 0 | O55: 0 | P55: =I55+J55+K55+L55+M55+N55+O55-E55 -> 0 | Q55: =I55+J55+K55+L55+M55+N55+O55-F55 -> 0 | R55: =I55+J55+K55+L55+M55+N55+O55-G55 -> 0 | S55: =I55+J55+K55+L55+M55+N55+O55-H55 -> 0 | U55: =Inventory!D47 -> 0 | AB55: =SUM(V55:AA55) -> 0
A56: =Inventory!B48 -> 0 | B56: =Inventory!C48 -> 0 | C56: 0 | D56: 1 | E56: =E12/D56*C56 -> 0 | F56: =F12/D56*C56 -> 0 | G56: =G12/D56*C56 -> 0 | H56: =H12/D56*C56 -> 0 | I56: 0 | J56: 0 | K56: 0 | L56: 0 | M56: 0 | N56: 0 | O56: 0 | P56: =I56+J56+K56+L56+M56+N56+O56-E56 -> 0 | Q56: =I56+J56+K56+L56+M56+N56+O56-F56 -> 0 | R56: =I56+J56+K56+L56+M56+N56+O56-G56 -> 0 | S56: =I56+J56+K56+L56+M56+N56+O56-H56 -> 0 | U56: =Inventory!D48 -> 0 | AB56: =SUM(V56:AA56) -> 0
A57: =Inventory!B49 -> 0 | B57: =Inventory!C49 -> 0 | C57: 0 | D57: 1 | E57: =E12/D57*C57 -> 0 | F57: =F12/D57*C57 -> 0 | G57: =G12/D57*C57 -> 0 | H57: =H12/D57*C57 -> 0 | I57: 0 | J57: 0 | K57: 0 | L57: 0 | M57: 0 | N57: 0 | O57: 0 | P57: =I57+J57+K57+L57+M57+N57+O57-E57 -> 0 | Q57: =I57+J57+K57+L57+M57+N57+O57-F57 -> 0 | R57: =I57+J57+K57+L57+M57+N57+O57-G57 -> 0 | S57: =I57+J57+K57+L57+M57+N57+O57-H57 -> 0 | U57: =Inventory!D49 -> 0 | AB57: =SUM(V57:AA57) -> 0
A58: =Inventory!B50 -> 0 | B58: =Inventory!C50 -> 0 | C58: 0 | D58: 1 | E58: =E12/D58*C58 -> 0 | F58: =F12/D58*C58 -> 0 | G58: =G12/D58*C58 -> 0 | H58: =H12/D58*C58 -> 0 | I58: 0 | J58: 0 | K58: 0 | L58: 0 | M58: 0 | N58: 0 | O58: 0 | P58: =I58+J58+K58+L58+M58+N58+O58-E58 -> 0 | Q58: =I58+J58+K58+L58+M58+N58+O58-F58 -> 0 | R58: =I58+J58+K58+L58+M58+N58+O58-G58 -> 0 | S58: =I58+J58+K58+L58+M58+N58+O58-H58 -> 0 | U58: =Inventory!D50 -> 0 | AB58: =SUM(V58:AA58) -> 0
A59: =Inventory!B51 -> 0 | B59: =Inventory!C51 -> 0 | C59: 0 | D59: 1 | E59: =E$12/D59*C59 -> 0 | F59: =F$12/D59*C59 -> 0 | G59: =G$12/D59*C59 -> 0 | H59: =H$12/D59*C59 -> 0 | I59: 0 | J59: 0 | K59: 0 | L59: 0 | M59: 0 | N59: 0 | O59: 0 | P59: =I59+J59+K59+L59+M59+N59+O59-E59 -> 0 | Q59: =I59+J59+K59+L59+M59+N59+O59-F59 -> 0 | R59: =I59+J59+K59+L59+M59+N59+O59-G59 -> 0 | S59: =I59+J59+K59+L59+M59+N59+O59-H59 -> 0 | U59: =Inventory!D51 -> 0 | AB59: =SUM(V59:AA59) -> 0
A60: =Inventory!B52 -> 0 | B60: =Inventory!C52 -> 0 | C60: 0 | D60: 1 | E60: =E$12/D60*C60 -> 0 | F60: =F$12/D60*C60 -> 0 | G60: =G$12/D60*C60 -> 0 | H60: =H$12/D60*C60 -> 0 | I60: 0 | J60: 0 | K60: 0 | L60: 0 | M60: 0 | N60: 0 | O60: 0 | P60: =I60+J60+K60+L60+M60+N60+O60-E60 -> 0 | Q60: =I60+J60+K60+L60+M60+N60+O60-F60 -> 0 | R60: =I60+J60+K60+L60+M60+N60+O60-G60 -> 0 | S60: =I60+J60+K60+L60+M60+N60+O60-H60 -> 0 | U60: =Inventory!D52 -> 0 | AB60: =SUM(V60:AA60) -> 0
A61: =Inventory!B53 -> 0 | B61: =Inventory!C53 -> 0 | C61: 0 | D61: 1 | E61: =E$12/D61*C61 -> 0 | F61: =F$12/D61*C61 -> 0 | G61: =G$12/D61*C61 -> 0 | H61: =H$12/D61*C61 -> 0 | I61: 0 | J61: 0 | K61: 0 | L61: 0 | M61: 0 | N61: 0 | O61: 0 | P61: =I61+J61+K61+L61+M61+N61+O61-E61 -> 0 | Q61: =I61+J61+K61+L61+M61+N61+O61-F61 -> 0 | R61: =I61+J61+K61+L61+M61+N61+O61-G61 -> 0 | S61: =I61+J61+K61+L61+M61+N61+O61-H61 -> 0 | U61: =Inventory!D53 -> 0 | AB61: =SUM(V61:AA61) -> 0
A62: =Inventory!B54 -> 0 | B62: =Inventory!C54 -> 0 | C62: 0 | D62: 1 | E62: =E$12/D62*C62 -> 0 | F62: =F$12/D62*C62 -> 0 | G62: =G$12/D62*C62 -> 0 | H62: =H$12/D62*C62 -> 0 | I62: 0 | J62: 0 | K62: 0 | L62: 0 | M62: 0 | N62: 0 | O62: 0 | P62: =I62+J62+K62+L62+M62+N62+O62-E62 -> 0 | Q62: =I62+J62+K62+L62+M62+N62+O62-F62 -> 0 | R62: =I62+J62+K62+L62+M62+N62+O62-G62 -> 0 | S62: =I62+J62+K62+L62+M62+N62+O62-H62 -> 0 | U62: =Inventory!D54 -> 0 | AB62: =SUM(V62:AA62) -> 0
A63: =Inventory!B55 -> 0 | B63: =Inventory!C55 -> 0 | C63: 0 | D63: 1 | E63: =E$12/D63*C63 -> 0 | F63: =F$12/D63*C63 -> 0 | G63: =G$12/D63*C63 -> 0 | H63: =H$12/D63*C63 -> 0 | I63: 0 | J63: 0 | K63: 0 | L63: 0 | M63: 0 | N63: 0 | O63: 0 | P63: =I63+J63+K63+L63+M63+N63+O63-E63 -> 0 | Q63: =I63+J63+K63+L63+M63+N63+O63-F63 -> 0 | R63: =I63+J63+K63+L63+M63+N63+O63-G63 -> 0 | S63: =I63+J63+K63+L63+M63+N63+O63-H63 -> 0 | U63: =Inventory!D55 -> 0 | AB63: =SUM(V63:AA63) -> 0
A64: =Inventory!B56 -> 0 | B64: =Inventory!C56 -> 0 | C64: 0 | D64: 1 | E64: =E$12/D64*C64 -> 0 | F64: =F$12/D64*C64 -> 0 | G64: =G$12/D64*C64 -> 0 | H64: =H$12/D64*C64 -> 0 | I64: 0 | J64: 0 | K64: 0 | L64: 0 | M64: 0 | N64: 0 | O64: 0 | P64: =I64+J64+K64+L64+M64+N64+O64-E64 -> 0 | Q64: =I64+J64+K64+L64+M64+N64+O64-F64 -> 0 | R64: =I64+J64+K64+L64+M64+N64+O64-G64 -> 0 | S64: =I64+J64+K64+L64+M64+N64+O64-H64 -> 0 | U64: =Inventory!D56 -> 0 | AB64: =SUM(V64:AA64) -> 0
A65: =Inventory!B57 -> GHOSRX903646OT | B65: =Inventory!C57 -> PLUSHIE PAPA V PURPLE | C65: 0.09 | D65: 50 | E65: =E$12/D65*C65 -> 6069.825 | F65: =F$12/D65*C65 -> 7283.79 | G65: =G$12/D65*C65 -> 7769.376 | H65: =H$12/D65*C65 -> 8740.548 | I65: 0 | J65: 0 | K65: 0 | L65: 0 | M65: 0 | N65: 0 | O65: 9000 | P65: =I65+J65+K65+L65+M65+N65+O65-E65 -> 2930.175 | Q65: =I65+J65+K65+L65+M65+N65+O65-F65 -> 1716.21 | R65: =I65+J65+K65+L65+M65+N65+O65-G65 -> 1230.624 | S65: =I65+J65+K65+L65+M65+N65+O65-H65 -> 259.452 | T65: CUSTOM | U65: =Inventory!D57 -> FARSTAR | AB65: 9000 | AC65: 45986
A66: =Inventory!B58 -> GHOSRX103922GR | B66: =Inventory!C58 -> MASK PAPA V RHINESTONE | C66: 0.02 | D66: 75 | E66: =E$12/D66*C66 -> 899.23333 | F66: =F$12/D66*C66 -> 1079.08 | G66: =G$12/D66*C66 -> 1151.0187 | H66: =H$12/D66*C66 -> 1294.896 | I66: 0 | J66: 0 | K66: 0 | L66: 0 | M66: 0 | N66: 0 | O66: 1500 | P66: =I66+J66+K66+L66+M66+N66+O66-E66 -> 600.76667 | Q66: =I66+J66+K66+L66+M66+N66+O66-F66 -> 420.92 | R66: =I66+J66+K66+L66+M66+N66+O66-G66 -> 348.98133 | S66: =I66+J66+K66+L66+M66+N66+O66-H66 -> 205.104 | U66: =Inventory!D58 -> FARSTAR | AB66: =SUM(V66:AA66) -> 0
A67: =Inventory!B59 -> GHOSRX103259OT | B67: =Inventory!C59 -> CLEAR SLING BAG-SILVER LOGO | C67: 0.01 | D67: 40 | E67: =E$12/D67*C67 -> 843.03125 | F67: =F$12/D67*C67 -> 1011.6375 | G67: =G$12/D67*C67 -> 1079.08 | H67: =H$12/D67*C67 -> 1213.965 | I67: 0 | J67: 0 | K67: 0 | L67: 0 | M67: 0 | N67: 1497 | O67: 0 | P67: =I67+J67+K67+L67+M67+N67+O67-E67 -> 653.96875 | Q67: =I67+J67+K67+L67+M67+N67+O67-F67 -> 485.3625 | R67: =I67+J67+K67+L67+M67+N67+O67-G67 -> 417.92 | S67: =I67+J67+K67+L67+M67+N67+O67-H67 -> 283.035 | U67: =Inventory!D59 -> FARSTAR | AB67: =SUM(V67:AA67) -> 0
A68: =Inventory!B60 -> GHOSRX103935BK | B68: =Inventory!C60 -> KEYCHAIN PAPA V TOPHAT | C68: 0.015 | D68: 20 | E68: =E$12/D68*C68 -> 2529.0938 | F68: =F$12/D68*C68 -> 3034.9125 | G68: =G$12/D68*C68 -> 3237.24 | H68: =H$12/D68*C68 -> 3641.895 | I68: 0 | J68: 0 | K68: 0 | L68: 0 | M68: 0 | N68: 0 | O68: 5000 | P68: =I68+J68+K68+L68+M68+N68+O68-E68 -> 2470.9062 | Q68: =I68+J68+K68+L68+M68+N68+O68-F68 -> 1965.0875 | R68: =I68+J68+K68+L68+M68+N68+O68-G68 -> 1762.76 | S68: =I68+J68+K68+L68+M68+N68+O68-H68 -> 1358.105 | T68: CUSTOM | U68: =Inventory!D60 -> FARSTAR | AB68: 5000 | AC68: 46019
A69: =Inventory!B61 -> GHOSRX103936GR | B69: =Inventory!C61 -> PIN SILVER GRUCIFIX | C69: 0.015 | D69: 20 | E69: =E$12/D69*C69 -> 2529.0938 | F69: =F$12/D69*C69 -> 3034.9125 | G69: =G$12/D69*C69 -> 3237.24 | H69: =H$12/D69*C69 -> 3641.895 | I69: 0 | J69: 0 | K69: 0 | L69: 0 | M69: 0 | N69: 0 | O69: 5000 | P69: =I69+J69+K69+L69+M69+N69+O69-E69 -> 2470.9062 | Q69: =I69+J69+K69+L69+M69+N69+O69-F69 -> 1965.0875 | R69: =I69+J69+K69+L69+M69+N69+O69-G69 -> 1762.76 | S69: =I69+J69+K69+L69+M69+N69+O69-H69 -> 1358.105 | T69: CUSTOM | U69: =Inventory!D61 -> FARSTAR | AB69: 5000 | AC69: 46019
A70: =Inventory!B62 -> GHOSRX204004OT | B70: =Inventory!C62 -> COIN | C70: 0.02 | D70: 30 | E70: =E$12/D70*C70 -> 2248.0833 | F70: =F$12/D70*C70 -> 2697.7 | G70: =G$12/D70*C70 -> 2877.5467 | H70: =H$12/D70*C70 -> 3237.24 | I70: 0 | J70: 0 | K70: 0 | L70: 0 | M70: 0 | N70: 0 | O70: 3000 | P70: =I70+J70+K70+L70+M70+N70+O70-E70 -> 751.91667 | Q70: =I70+J70+K70+L70+M70+N70+O70-F70 -> 302.3 | R70: =I70+J70+K70+L70+M70+N70+O70-G70 -> 122.45333 | S70: =I70+J70+K70+L70+M70+N70+O70-H70 -> -237.24 | T70: CUSTOM | U70: =Inventory!D62 -> ZACK THE MAKER | AB70: 3000 | AC70: 46041
A71: =Inventory!B63 -> GHOSRX103932BK | B71: =Inventory!C63 -> SNAPBACK CAP PAPA WINGS | C71: 0.04 | D71: 40 | E71: =E$12/D71*C71 -> 3372.125 | F71: =F$12/D71*C71 -> 4046.55 | G71: =G$12/D71*C71 -> 4316.32 | H71: =H$12/D71*C71 -> 4855.86 | I71: 0 | J71: 0 | K71: 0 | L71: 0 | M71: 0 | N71: 0 | O71: 5000 | P71: =I71+J71+K71+L71+M71+N71+O71-E71 -> 1627.875 | Q71: =I71+J71+K71+L71+M71+N71+O71-F71 -> 953.45 | R71: =I71+J71+K71+L71+M71+N71+O71-G71 -> 683.68 | S71: =I71+J71+K71+L71+M71+N71+O71-H71 -> 144.14 | T71: CUSTOM | U71: =Inventory!D63 -> WELL SUCCEED | AB71: 5000 | AC71: 46029
A72: =Inventory!B64 -> GHOSRX103934PU | B72: =Inventory!C64 -> ROSARY ROSE BEAD | C72: 0.04 | D72: 40 | E72: =E$12/D72*C72 -> 3372.125 | F72: =F$12/D72*C72 -> 4046.55 | G72: =G$12/D72*C72 -> 4316.32 | H72: =H$12/D72*C72 -> 4855.86 | I72: 0 | J72: 0 | K72: 0 | L72: 0 | M72: 0 | N72: 0 | O72: 5000 | P72: =I72+J72+K72+L72+M72+N72+O72-E72 -> 1627.875 | Q72: =I72+J72+K72+L72+M72+N72+O72-F72 -> 953.45 | R72: =I72+J72+K72+L72+M72+N72+O72-G72 -> 683.68 | S72: =I72+J72+K72+L72+M72+N72+O72-H72 -> 144.14 | T72: CUSTOM | U72: =Inventory!D64 -> FARSTAR | AB72: 5000 | AC72: 46019
A73: =Inventory!B65 -> GHOSNS103814BK | B73: =Inventory!C65 -> PROGRAM | C73: 0.015 | D73: 30 | E73: =E$12/D73*C73 -> 1686.0625 | F73: =F$12/D73*C73 -> 2023.275 | G73: =G$12/D73*C73 -> 2158.16 | H73: =H$12/D73*C73 -> 2427.93 | I73: 0 | J73: 0 | K73: 0 | L73: 686 | M73: 1000 | N73: 0 | O73: 0 | P73: =I73+J73+K73+L73+M73+N73+O73-E73 -> -0.0625 | Q73: =I73+J73+K73+L73+M73+N73+O73-F73 -> -337.275 | R73: =I73+J73+K73+L73+M73+N73+O73-G73 -> -472.16 | S73: =I73+J73+K73+L73+M73+N73+O73-H73 -> -741.93 | U73: =Inventory!D65 -> VANDALAY | AB73: =SUM(V73:AA73) -> 0
A74: =Inventory!B66 -> 0 | B74: =Inventory!C66 -> 0 | C74: 0 | D74: 1 | E74: =E$12/D74*C74 -> 0 | F74: =F$12/D74*C74 -> 0 | G74: =G$12/D74*C74 -> 0 | H74: =H$12/D74*C74 -> 0 | I74: 0 | J74: 0 | K74: 0 | L74: 0 | M74: 0 | N74: 0 | O74: 0 | P74: =I74+J74+K74+L74+M74+N74+O74-E74 -> 0 | Q74: =I74+J74+K74+L74+M74+N74+O74-F74 -> 0 | R74: =I74+J74+K74+L74+M74+N74+O74-G74 -> 0 | S74: =I74+J74+K74+L74+M74+N74+O74-H74 -> 0 | U74: =Inventory!D66 -> 0 | AB74: =SUM(V74:AA74) -> 0
A75: =Inventory!B67 -> 0 | B75: =Inventory!C67 -> 0 | C75: 0 | D75: 1 | E75: =E$12/D75*C75 -> 0 | F75: =F$12/D75*C75 -> 0 | G75: =G$12/D75*C75 -> 0 | H75: =H$12/D75*C75 -> 0 | I75: 0 | J75: 0 | K75: 0 | L75: 0 | M75: 0 | N75: 0 | O75: 0 | P75: =I75+J75+K75+L75+M75+N75+O75-E75 -> 0 | Q75: =I75+J75+K75+L75+M75+N75+O75-F75 -> 0 | R75: =I75+J75+K75+L75+M75+N75+O75-G75 -> 0 | S75: =I75+J75+K75+L75+M75+N75+O75-H75 -> 0 | U75: =Inventory!D67 -> 0 | AB75: =SUM(V75:AA75) -> 0
A76: =Inventory!B68 -> 0 | B76: =Inventory!C68 -> 0 | C76: 0 | D76: 1 | E76: =E$12/D76*C76 -> 0 | F76: =F$12/D76*C76 -> 0 | G76: =G$12/D76*C76 -> 0 | H76: =H$12/D76*C76 -> 0 | I76: 0 | J76: 0 | K76: 0 | L76: 0 | M76: 0 | N76: 0 | O76: 0 | P76: =I76+J76+K76+L76+M76+N76+O76-E76 -> 0 | Q76: =I76+J76+K76+L76+M76+N76+O76-F76 -> 0 | R76: =I76+J76+K76+L76+M76+N76+O76-G76 -> 0 | S76: =I76+J76+K76+L76+M76+N76+O76-H76 -> 0 | U76: =Inventory!D68 -> 0 | AB76: =SUM(V76:AA76) -> 0
A77: =Inventory!B69 -> 0 | B77: =Inventory!C69 -> 0 | C77: 0 | D77: 1 | E77: =E$12/D77*C77 -> 0 | F77: =F$12/D77*C77 -> 0 | G77: =G$12/D77*C77 -> 0 | H77: =H$12/D77*C77 -> 0 | I77: 0 | J77: 0 | K77: 0 | L77: 0 | M77: 0 | N77: 0 | O77: 0 | P77: =I77+J77+K77+L77+M77+N77+O77-E77 -> 0 | Q77: =I77+J77+K77+L77+M77+N77+O77-F77 -> 0 | R77: =I77+J77+K77+L77+M77+N77+O77-G77 -> 0 | S77: =I77+J77+K77+L77+M77+N77+O77-H77 -> 0 | U77: =Inventory!D69 -> 0 | AB77: =SUM(V77:AA77) -> 0
A78: =Inventory!B70 -> 0 | B78: =Inventory!C70 -> 0 | C78: 0 | D78: 1 | E78: =E$12/D78*C78 -> 0 | F78: =F$12/D78*C78 -> 0 | G78: =G$12/D78*C78 -> 0 | H78: =H$12/D78*C78 -> 0 | I78: 0 | J78: 0 | K78: 0 | L78: 0 | M78: 0 | N78: 0 | O78: 0 | P78: =I78+J78+K78+L78+M78+N78+O78-E78 -> 0 | Q78: =I78+J78+K78+L78+M78+N78+O78-F78 -> 0 | R78: =I78+J78+K78+L78+M78+N78+O78-G78 -> 0 | S78: =I78+J78+K78+L78+M78+N78+O78-H78 -> 0 | U78: =Inventory!D70 -> 0 | AB78: =SUM(V78:AA78) -> 0
A79: =Inventory!B71 -> 0 | B79: =Inventory!C71 -> 0 | C79: 0 | D79: 1 | E79: =E$12/D79*C79 -> 0 | F79: =F$12/D79*C79 -> 0 | G79: =G$12/D79*C79 -> 0 | H79: =H$12/D79*C79 -> 0 | I79: 0 | J79: 0 | K79: 0 | L79: 0 | M79: 0 | N79: 0 | O79: 0 | P79: =I79+J79+K79+L79+M79+N79+O79-E79 -> 0 | Q79: =I79+J79+K79+L79+M79+N79+O79-F79 -> 0 | R79: =I79+J79+K79+L79+M79+N79+O79-G79 -> 0 | S79: =I79+J79+K79+L79+M79+N79+O79-H79 -> 0 | U79: =Inventory!D71 -> 0 | AB79: =SUM(V79:AA79) -> 0
A80: =Inventory!B72 -> 0 | B80: =Inventory!C72 -> 0 | C80: 0 | D80: 1 | E80: =E$12/D80*C80 -> 0 | F80: =F$12/D80*C80 -> 0 | G80: =G$12/D80*C80 -> 0 | H80: =H$12/D80*C80 -> 0 | I80: 0 | J80: 0 | K80: 0 | L80: 0 | M80: 0 | N80: 0 | O80: 0 | P80: =I80+J80+K80+L80+M80+N80+O80-E80 -> 0 | Q80: =I80+J80+K80+L80+M80+N80+O80-F80 -> 0 | R80: =I80+J80+K80+L80+M80+N80+O80-G80 -> 0 | S80: =I80+J80+K80+L80+M80+N80+O80-H80 -> 0 | U80: =Inventory!D72 -> 0 | AB80: =SUM(V80:AA80) -> 0
A81: =Inventory!B73 -> GHOSRX103241BK | B81: =Inventory!C73 -> CHOKER PAPA V | C81: 0.0075 | D81: 30 | E81: =E$12/D81*C81 -> 843.03125 | F81: =F$12/D81*C81 -> 1011.6375 | G81: =G$12/D81*C81 -> 1079.08 | H81: =H$12/D81*C81 -> 1213.965 | I81: 0 | J81: 0 | K81: 0 | L81: 0 | M81: 0 | N81: 1511 | O81: 0 | P81: =I81+J81+K81+L81+M81+N81+O81-E81 -> 667.96875 | Q81: =I81+J81+K81+L81+M81+N81+O81-F81 -> 499.3625 | R81: =I81+J81+K81+L81+M81+N81+O81-G81 -> 431.92 | S81: =I81+J81+K81+L81+M81+N81+O81-H81 -> 297.035 | U81: =Inventory!D73 -> FARSTAR | AB81: =SUM(V81:AA81) -> 0
A82: =Inventory!B74 -> GHOSRX203254GR | B82: =Inventory!C74 -> KEYCHAIN SKELETON GRUCIFIX | C82: 0.0075 | D82: 15 | E82: =E$12/D82*C82 -> 1686.0625 | F82: =F$12/D82*C82 -> 2023.275 | G82: =G$12/D82*C82 -> 2158.16 | H82: =H$12/D82*C82 -> 2427.93 | I82: 0 | J82: 0 | K82: 0 | L82: 0 | M82: 0 | N82: 2629 | O82: 0 | P82: =I82+J82+K82+L82+M82+N82+O82-E82 -> 942.9375 | Q82: =I82+J82+K82+L82+M82+N82+O82-F82 -> 605.725 | R82: =I82+J82+K82+L82+M82+N82+O82-G82 -> 470.84 | S82: =I82+J82+K82+L82+M82+N82+O82-H82 -> 201.07 | U82: =Inventory!D74 -> FARSTAR | AB82: =SUM(V82:AA82) -> 0
A83: =Inventory!B75 -> GHOSRX903403OT | B83: =Inventory!C75 -> PATCH SET OF 3 | C83: 0.005 | D83: 20 | E83: =E$12/D83*C83 -> 843.03125 | F83: =F$12/D83*C83 -> 1011.6375 | G83: =G$12/D83*C83 -> 1079.08 | H83: =H$12/D83*C83 -> 1213.965 | I83: 0 | J83: 0 | K83: 0 | L83: 0 | M83: 0 | N83: 1379 | O83: 0 | P83: =I83+J83+K83+L83+M83+N83+O83-E83 -> 535.96875 | Q83: =I83+J83+K83+L83+M83+N83+O83-F83 -> 367.3625 | R83: =I83+J83+K83+L83+M83+N83+O83-G83 -> 299.92 | S83: =I83+J83+K83+L83+M83+N83+O83-H83 -> 165.035 | U83: =Inventory!D75 -> FARSTAR | AB83: =SUM(V83:AA83) -> 0
A84: =Inventory!B76 -> GHOSRX003611BK | B84: =Inventory!C76 -> 0 | C84: 0 | D84: 1 | E84: =E$12/D84*C84 -> 0 | F84: =F$12/D84*C84 -> 0 | G84: =G$12/D84*C84 -> 0 | H84: =H$12/D84*C84 -> 0 | I84: 0 | J84: 0 | K84: 0 | L84: 0 | M84: 0 | N84: 0 | O84: 0 | P84: =I84+J84+K84+L84+M84+N84+O84-E84 -> 0 | Q84: =I84+J84+K84+L84+M84+N84+O84-F84 -> 0 | R84: =I84+J84+K84+L84+M84+N84+O84-G84 -> 0 | S84: =I84+J84+K84+L84+M84+N84+O84-H84 -> 0 | U84: =Inventory!D76 -> 0 | AB84: =SUM(V84:AA84) -> 0
... A88: =Inventory!B80 -> GHOSNS103622OT | B88: =Inventory!C80 -> FOILED COMIC BOOK SISTER IMPERATOR #3 | C88: 0.0025 | D88: 15 | E88: =E$12/D88*C88 -> 562.02083 | F88: =F$12/D88*C88 -> 674.425 | G88: =G$12/D88*C88 -> 719.38667 | H88: =H$12/D88*C88 -> 809.31 | I88: 0 | J88: 0 | K88: 0 | L88: 0 | M88: 0 | N88: 229 | O88: 0 | P88: =I88+J88+K88+L88+M88+N88+O88-E88 -> -333.02083 | Q88: =I88+J88+K88+L88+M88+N88+O88-F88 -> -445.425 | R88: =I88+J88+K88+L88+M88+N88+O88-G88 -> -490.38667 | S88: =I88+J88+K88+L88+M88+N88+O88-H88 -> -580.31 | U88: =Inventory!D80 -> DARK HORSE COMICS | AB88: =SUM(V88:AA88) -> 0
A89: =Inventory!B81 -> GHOSNS103624OT | B89: =Inventory!C81 -> FOILED COMIC BOOK SISTER IMPERATOR #4 | C89: 0.0025 | D89: 15 | E89: =E$12/D89*C89 -> 562.02083 | F89: =F$12/D89*C89 -> 674.425 | G89: =G$12/D89*C89 -> 719.38667 | H89: =H$12/D89*C89 -> 809.31 | I89: 0 | J89: 0 | K89: 0 | L89: 0 | M89: 0 | N89: 244 | O89: 0 | P89: =I89+J89+K89+L89+M89+N89+O89-E89 -> -318.02083 | Q89: =I89+J89+K89+L89+M89+N89+O89-F89 -> -430.425 | R89: =I89+J89+K89+L89+M89+N89+O89-G89 -> -475.38667 | S89: =I89+J89+K89+L89+M89+N89+O89-H89 -> -565.31 | AB89: =SUM(V89:AA89) -> 0
A90: =Inventory!B82 -> GHOSRX003470OT | B90: =Inventory!C82 -> ROLLING STONE MAG & ALBUM | C90: 0.0075 | D90: 30 | E90: =E$12/D90*C90 -> 843.03125 | F90: =F$12/D90*C90 -> 1011.6375 | G90: =G$12/D90*C90 -> 1079.08 | H90: =H$12/D90*C90 -> 1213.965 | I90: 0 | J90: 0 | K90: 0 | L90: 0 | M90: 0 | N90: 549 | O90: 0 | P90: =I90+J90+K90+L90+M90+N90+O90-E90 -> -294.03125 | Q90: =I90+J90+K90+L90+M90+N90+O90-F90 -> -462.6375 | R90: =I90+J90+K90+L90+M90+N90+O90-G90 -> -530.08 | S90: =I90+J90+K90+L90+M90+N90+O90-H90 -> -664.965 | AB90: =SUM(V90:AA90) -> 0
A91: =Inventory!B83 -> GHOSRX003611BK | B91: =Inventory!C83 -> LP SKELETA BLACK VINYL | C91: 0.0025 | D91: 40 | E91: =E$12/D91*C91 -> 210.75781 | F91: =F$12/D91*C91 -> 252.90938 | G91: =G$12/D91*C91 -> 269.77 | H91: =H$12/D91*C91 -> 303.49125 | I91: 0 | J91: 0 | K91: 0 | L91: 0 | M91: 0 | N91: 0 | O91: 0 | P91: =I91+J91+K91+L91+M91+N91+O91-E91 -> -210.75781 | Q91: =I91+J91+K91+L91+M91+N91+O91-F91 -> -252.90938 | R91: =I91+J91+K91+L91+M91+N91+O91-G91 -> -269.77 | S91: =I91+J91+K91+L91+M91+N91+O91-H91 -> -303.49125 | AB91: =SUM(V91:AA91) -> 0
A92: =Inventory!B84 -> GHOSCG103805PU | B92: =Inventory!C84 -> LP PURPLE LENTICULAR (CONSIGNMENT) | C92: 0.01 | D92: 40 | E92: =E$12/D92*C92 -> 843.03125 | F92: =F$12/D92*C92 -> 1011.6375 | G92: =G$12/D92*C92 -> 1079.08 | H92: =H$12/D92*C92 -> 1213.965 | I92: 0 | J92: 0 | K92: 0 | L92: 0 | M92: 0 | N92: 0 | O92: 0 | P92: =I92+J92+K92+L92+M92+N92+O92-E92 -> -843.03125 | Q92: =I92+J92+K92+L92+M92+N92+O92-F92 -> -1011.6375 | R92: =I92+J92+K92+L92+M92+N92+O92-G92 -> -1079.08 | S92: =I92+J92+K92+L92+M92+N92+O92-H92 -> -1213.965 | AB92: =SUM(V92:AA92) -> 0
A93: =Inventory!B85 -> GHOSCG103844BK | B93: =Inventory!C85 -> CASSETTE (CONSIGNMENT) | C93: 0.0025 | D93: 15 | E93: =E$12/D93*C93 -> 562.02083 | F93: =F$12/D93*C93 -> 674.425 | G93: =G$12/D93*C93 -> 719.38667 | H93: =H$12/D93*C93 -> 809.31 | I93: 0 | J93: 0 | K93: 0 | L93: 0 | M93: 0 | N93: 0 | O93: 0 | P93: =I93+J93+K93+L93+M93+N93+O93-E93 -> -562.02083 | Q93: =I93+J93+K93+L93+M93+N93+O93-F93 -> -674.425 | R93: =I93+J93+K93+L93+M93+N93+O93-G93 -> -719.38667 | S93: =I93+J93+K93+L93+M93+N93+O93-H93 -> -809.31 | AB93: =SUM(V93:AA93) -> 0
A94: =Inventory!B86 -> 0 | B94: =Inventory!C86 -> 0 | C94: 0 | D94: 1 | E94: =E$12/D94*C94 -> 0 | F94: =F$12/D94*C94 -> 0 | G94: =G$12/D94*C94 -> 0 | H94: =H$12/D94*C94 -> 0 | I94: 0 | J94: 0 | K94: 0 | L94: 0 | M94: 0 | N94: 0 | O94: 0 | P94: =I94+J94+K94+L94+M94+N94+O94-E94 -> 0 | Q94: =I94+J94+K94+L94+M94+N94+O94-F94 -> 0 | R94: =I94+J94+K94+L94+M94+N94+O94-G94 -> 0 | S94: =I94+J94+K94+L94+M94+N94+O94-H94 -> 0 | AB94: =SUM(V94:AA94) -> 0
A95: =Inventory!B87 -> 0 | B95: =Inventory!C87 -> 0 | C95: 0 | D95: 1 | E95: =E$12/D95*C95 -> 0 | F95: =F$12/D95*C95 -> 0 | G95: =G$12/D95*C95 -> 0 | H95: =H$12/D95*C95 -> 0 | I95: 0 | J95: 0 | K95: 0 | L95: 0 | M95: 0 | N95: 0 | O95: 0 | P95: =I95+J95+K95+L95+M95+N95+O95-E95 -> 0 | Q95: =I95+J95+K95+L95+M95+N95+O95-F95 -> 0 | R95: =I95+J95+K95+L95+M95+N95+O95-G95 -> 0 | S95: =I95+J95+K95+L95+M95+N95+O95-H95 -> 0 | AB95: =SUM(V95:AA95) -> 0
A96: =Inventory!B88 -> 0 | B96: =Inventory!C88 -> 0 | C96: 0 | D96: 1 | E96: =E$12/D96*C96 -> 0 | F96: =F$12/D96*C96 -> 0 | G96: =G$12/D96*C96 -> 0 | H96: =H$12/D96*C96 -> 0 | I96: 0 | J96: 0 | K96: 0 | L96: 0 | M96: 0 | N96: 0 | O96: 0 | P96: =I96+J96+K96+L96+M96+N96+O96-E96 -> 0 | Q96: =I96+J96+K96+L96+M96+N96+O96-F96 -> 0 | R96: =I96+J96+K96+L96+M96+N96+O96-G96 -> 0 | S96: =I96+J96+K96+L96+M96+N96+O96-H96 -> 0 | AB96: =SUM(V96:AA96) -> 0
A97: =Inventory!B89 -> 0 | B97: =Inventory!C89 -> 0 | C97: 0 | D97: 1 | E97: =E$12/D97*C97 -> 0 | F97: =F$12/D97*C97 -> 0 | G97: =G$12/D97*C97 -> 0 | H97: =H$12/D97*C97 -> 0 | I97: 0 | J97: 0 | K97: 0 | L97: 0 | M97: 0 | N97: 0 | O97: 0 | P97: =I97+J97+K97+L97+M97+N97+O97-E97 -> 0 | Q97: =I97+J97+K97+L97+M97+N97+O97-F97 -> 0 | R97: =I97+J97+K97+L97+M97+N97+O97-G97 -> 0 | S97: =I97+J97+K97+L97+M97+N97+O97-H97 -> 0 | AB97: =SUM(V97:AA97) -> 0
A98: =Inventory!B90 -> 0 | B98: =Inventory!C90 -> 0 | C98: 0 | D98: 1 | E98: =E$12/D98*C98 -> 0 | F98: =F$12/D98*C98 -> 0 | G98: =G$12/D98*C98 -> 0 | H98: =H$12/D98*C98 -> 0 | I98: 0 | J98: 0 | K98: 0 | L98: 0 | M98: 0 | N98: 0 | O98: 0 | P98: =I98+J98+K98+L98+M98+N98+O98-E98 -> 0 | Q98: =I98+J98+K98+L98+M98+N98+O98-F98 -> 0 | R98: =I98+J98+K98+L98+M98+N98+O98-G98 -> 0 | S98: =I98+J98+K98+L98+M98+N98+O98-H98 -> 0 | AB98: =SUM(V98:AA98) -> 0
A99: =Inventory!B91 -> 0 | B99: =Inventory!C91 -> 0 | C99: 0 | D99: 1 | E99: =E$12/D99*C99 -> 0 | F99: =F$12/D99*C99 -> 0 | G99: =G$12/D99*C99 -> 0 | H99: =H$12/D99*C99 -> 0 | I99: 0 | J99: 0 | K99: 0 | L99: 0 | M99: 0 | N99: 0 | O99: 0 | P99: =I99+J99+K99+L99+M99+N99+O99-E99 -> 0 | Q99: =I99+J99+K99+L99+M99+N99+O99-F99 -> 0 | R99: =I99+J99+K99+L99+M99+N99+O99-G99 -> 0 | S99: =I99+J99+K99+L99+M99+N99+O99-H99 -> 0 | AB99: =SUM(V99:AA99) -> 0
A100: =Inventory!B92 -> 0 | B100: =Inventory!C92 -> 0 | C100: 0 | D100: 1 | E100: =E$12/D100*C100 -> 0 | F100: =F$12/D100*C100 -> 0 | G100: =G$12/D100*C100 -> 0 | H100: =H$12/D100*C100 -> 0 | I100: 0 | J100: 0 | K100: 0 | L100: 0 | M100: 0 | N100: 0 | O100: 0 | P100: =I100+J100+K100+L100+M100+N100+O100-E100 -> 0 | Q100: =I100+J100+K100+L100+M100+N100+O100-F100 -> 0 | R100: =I100+J100+K100+L100+M100+N100+O100-G100 -> 0 | S100: =I100+J100+K100+L100+M100+N100+O100-H100 -> 0 | AB100: =SUM(V100:AA100) -> 0
... A106: =Inventory!B98 -> 0 | B106: =Inventory!C98 -> 0 | C106: 0 | D106: 1 | E106: =E$12/D106*C106 -> 0 | F106: =F$12/D106*C106 -> 0 | G106: =G$12/D106*C106 -> 0 | H106: =H$12/D106*C106 -> 0 | I106: 0 | J106: 0 | K106: 0 | L106: 0 | M106: 0 | N106: 0 | O106: 0 | P106: =I106+J106+K106+L106+M106+N106+O106-E106 -> 0 | Q106: =I106+J106+K106+L106+M106+N106+O106-F106 -> 0 | R106: =I106+J106+K106+L106+M106+N106+O106-G106 -> 0 | S106: =I106+J106+K106+L106+M106+N106+O106-H106 -> 0 | AB106: =SUM(V106:AA106) -> 0
C107: =SUM(C15:C89) -> 0.99

Sheet BATWNG HOODY
A1: Tour | B1: =Inventory!C3 -> GHOST | D1: Item | E1: =Inventory!C7 -> BATWING HOODY | L1: Cost | M1: =Inventory!H7 -> 28.5 | N1: Supplier | O1: =Inventory!D7 -> FARSTAR | R1: Code | S1: =Inventory!B7 -> GHOSNS903311BK | U1: % of Gross | V1: =M64 -> 0
A3: Date | B3: City | C3: Sales | D3: Band Co | E3: GMS Co | F3: W/Sale | G3: Used | H3: Delivery | I3: +/- | J3: Ship | K3: To | L3: Balance | M3: % | O3: Stock B/F | Q3: Date | R3: Qty Received | S3: To | X3: SM | Y3: MED | Z3: LG | AA3: XL | AB3: 2X | AC3: 3X | AD3: 4X | AE3: TOTAL
A4: =IF('Tour Dates'!A4="","",'Tour Dates'!A4) -> 46043 | B4: =IF('Tour Dates'!B4="","",'Tour Dates'!B4) -> ORLANDO | G4: =SUM(C4:F4) -> 0 | H4: 1837 | L4: =H4-G4-I4-J4 -> 1837 | R4: =AE4 -> 0 | AE4: =SUM(X4:AD4) -> 0
A5: =IF('Tour Dates'!A5="","",'Tour Dates'!A5) -> 46044 | B5: =IF('Tour Dates'!B5="","",'Tour Dates'!B5) -> JACKSONVILLE | G5: =SUM(C5:F5) -> 0 | L5: =L4+H5-G5-I5-J5 -> 1837 | R5: =AE5 -> 0 | AE5: =SUM(X5:AD5) -> 0
A6: =IF('Tour Dates'!A6="","",'Tour Dates'!A6) -> 46046 | B6: =IF('Tour Dates'!B6="","",'Tour Dates'!B6) -> KNOXVILLE | G6: =SUM(C6:F6) -> 0 | L6: =L5+H6-G6-I6-J6 -> 1837 | R6: =AE6 -> 0 | AE6: =SUM(X6:AD6) -> 0
A7: =IF('Tour Dates'!A7="","",'Tour Dates'!A7) -> 46047 | B7: =IF('Tour Dates'!B7="","",'Tour Dates'!B7) -> CHARLOTTE | G7: =SUM(C7:F7) -> 0 | L7: =L6+H7-G7-I7-J7 -> 1837 | R7: =SUM(R4:R6) -> 0 | U7: Invoice Details
A8: =IF('Tour Dates'!A8="","",'Tour Dates'!A8) -> 46048 | B8: =IF('Tour Dates'!B8="","",'Tour Dates'!B8) -> GREENVILLE | G8: =SUM(C8:F8) -> 0 | L8: =L7+H8-G8-I8-J8 -> 1837
A9: =IF('Tour Dates'!A9="","",'Tour Dates'!A9) -> 46050 | B9: =IF('Tour Dates'!B9="","",'Tour Dates'!B9) -> UNCASVILLE | G9: =SUM(C9:F9) -> 0 | H9: 1830 | L9: =L8+H9-G9-I9-J9 -> 3667 | O9: Date | P9: PO Number | Q9: Amount Ordered | R9: Qty Received | S9: To | T9: BOXES | U9: Delivery Note | V9: Inv No | W9: Checked By | X9: SM | Y9: MED | Z9: LG | AA9: XL | AB9: 2X | AC9: 3X | AD9: 4X | AE9: TOTAL
A10: =IF('Tour Dates'!A10="","",'Tour Dates'!A10) -> 46052 | B10: =IF('Tour Dates'!B10="","",'Tour Dates'!B10) -> MONTREAL | G10: =SUM(C10:F10) -> 0 | L10: =L9+H10-G10-I10-J10 -> 3667 | O10: 45944 | P10: 85655 | Q10: 6240 | S10: FULL PACKAGE | X10: 500 | Y10: 1200 | Z10: 1800 | AA10: 1300 | AB10: 800 | AC10: 400 | AD10: 0 | AE10: =SUM(X10:AD10) -> 6000
A11: =IF('Tour Dates'!A11="","",'Tour Dates'!A11) -> 46053 | B11: =IF('Tour Dates'!B11="","",'Tour Dates'!B11) -> TORONTO | G11: =SUM(C11:F11) -> 0 | L11: =L10+H11-G11-I11-J11 -> 3667 | R11: 6240 | S11: HASSETT LAX | T11: 415 | X11: 502 | Y11: 1288 | Z11: 1877 | AA11: 1373 | AB11: 801 | AC11: 399 | AD11: 0 | AE11: =SUM(X11:AD11) -> 6240
A12: =IF('Tour Dates'!A12="","",'Tour Dates'!A12) -> 46055 | B12: =IF('Tour Dates'!B12="","",'Tour Dates'!B12) -> COLUMBUS | G12: =SUM(C12:F12) -> 0 | L12: =L11+H12-G12-I12-J12 -> 3667 | AE12: =SUM(X12:AD12) -> 0
A13: =IF('Tour Dates'!A13="","",'Tour Dates'!A13) -> 46057 | B13: =IF('Tour Dates'!B13="","",'Tour Dates'!B13) -> CINCINNATI | G13: =SUM(C13:F13) -> 0 | L13: =L12+H13-G13-I13-J13 -> 3667 | AE13: =SUM(X13:AD13) -> 0
A14: =IF('Tour Dates'!A14="","",'Tour Dates'!A14) -> 46058 | B14: =IF('Tour Dates'!B14="","",'Tour Dates'!B14) -> PEORIA | G14: =SUM(C14:F14) -> 0 | L14: =L13+H14-G14-I14-J14 -> 3667 | AE14: =SUM(X14:AD14) -> 0
A15: =IF('Tour Dates'!A15="","",'Tour Dates'!A15) -> 46060 | B15: =IF('Tour Dates'!B15="","",'Tour Dates'!B15) -> TULSA | G15: =SUM(C15:F15) -> 0 | L15: =L14+H15-G15-I15-J15 -> 3667 | AE15: =SUM(X15:AD15) -> 0
A16: =IF('Tour Dates'!A16="","",'Tour Dates'!A16) -> 46063 | B16: =IF('Tour Dates'!B16="","",'Tour Dates'!B16) -> SALT LAKE CITY | G16: =SUM(C16:F16) -> 0 | L16: =L15+H16-G16-I16-J16 -> 3667 | AE16: =SUM(X16:AD16) -> 0
A17: =IF('Tour Dates'!A17="","",'Tour Dates'!A17) -> 46065 | B17: =IF('Tour Dates'!B17="","",'Tour Dates'!B17) -> SPOKANE | G17: =SUM(C17:F17) -> 0 | L17: =L16+H17-G17-I17-J17 -> 3667 | AE17: =SUM(X17:AD17) -> 0
A18: =IF('Tour Dates'!A18="","",'Tour Dates'!A18) -> 46067 | B18: =IF('Tour Dates'!B18="","",'Tour Dates'!B18) -> VANCOUVER | G18: =SUM(C18:F18) -> 0 | L18: =L17+H18-G18-I18-J18 -> 3667 | AE18: =SUM(X18:AD18) -> 0
A19: =IF('Tour Dates'!A19="","",'Tour Dates'!A19) -> 46068 | B19: =IF('Tour Dates'!B19="","",'Tour Dates'!B19) -> SEATTLE | G19: =SUM(C19:F19) -> 0 | L19: =L18+H19-G19-I19-J19 -> 3667 | AE19: =SUM(X19:AD19) -> 0
A20: =IF('Tour Dates'!A20="","",'Tour Dates'!A20) -> 46070 | B20: =IF('Tour Dates'!B20="","",'Tour Dates'!B20) -> PORTLAND | G20: =SUM(C20:F20) -> 0 | L20: =L19+H20-G20-I20-J20 -> 3667 | AE20: =SUM(X20:AD20) -> 0
A21: =IF('Tour Dates'!A21="","",'Tour Dates'!A21) -> 46073 | B21: =IF('Tour Dates'!B21="","",'Tour Dates'!B21) -> SACRAMENTO | G21: =SUM(C21:F21) -> 0 | L21: =L20+H21-G21-I21-J21 -> 3667 | AE21: =SUM(X21:AD21) -> 0
A22: =IF('Tour Dates'!A22="","",'Tour Dates'!A22) -> 46074 | B22: =IF('Tour Dates'!B22="","",'Tour Dates'!B22) -> ANAHEIM | G22: =SUM(C22:F22) -> 0 | L22: =L21+H22-G22-I22-J22 -> 3667 | AE22: =SUM(X22:AD22) -> 0
A23: =IF('Tour Dates'!A23="","",'Tour Dates'!A23) -> 46076 | B23: =IF('Tour Dates'!B23="","",'Tour Dates'!B23) -> INGLEWOOD | G23: =SUM(C23:F23) -> 0 | L23: =L22+H23-G23-I23-J23 -> 3667 | AE23: =SUM(X23:AD23) -> 0
... A34: =IF('Tour Dates'!A34="","",'Tour Dates'!A34) | B34: =IF('Tour Dates'!B34="","",'Tour Dates'!B34) | G34: =SUM(C34:F34) -> 0 | L34: =L33+H34-G34-I34-J34 -> 3667 | AE34: =SUM(X34:AD34) -> 0
A35: =IF('Tour Dates'!A35="","",'Tour Dates'!A35) | B35: =IF('Tour Dates'!B35="","",'Tour Dates'!B35) | G35: =SUM(C35:F35) -> 0 | L35: =L34+H35-G35-I35-J35 -> 3667 | O35: Total | Q35: =SUM(Q10:Q34) -> 6240 | R35: =SUM(R10:R34) -> 6240
A36: =IF('Tour Dates'!A36="","",'Tour Dates'!A36) | B36: =IF('Tour Dates'!B36="","",'Tour Dates'!B36) | G36: =SUM(C36:F36) -> 0 | L36: =L35+H36-G36-I36-J36 -> 3667
A37: =IF('Tour Dates'!A37="","",'Tour Dates'!A37) | B37: =IF('Tour Dates'!B37="","",'Tour Dates'!B37) | G37: =SUM(C37:F37) -> 0 | L37: =L36+H37-G37-I37-J37 -> 3667 | O37: Stock Movement | U37: Product Summary
A38: =IF('Tour Dates'!A38="","",'Tour Dates'!A38) | B38: =IF('Tour Dates'!B38="","",'Tour Dates'!B38) | G38: =SUM(C38:F38) -> 0 | L38: =L37+H38-G38-I38-J38 -> 3667
A39: =IF('Tour Dates'!A39="","",'Tour Dates'!A39) | B39: =IF('Tour Dates'!B39="","",'Tour Dates'!B39) | G39: =SUM(C39:F39) -> 0 | L39: =L38+H39-G39-I39-J39 -> 3667 | O39: In | P39: From | Q39: Out | R39: To | S39: Qty | T39: BOXES | U39: Stock B/F | V39: =R7 -> 0 | X39: SM | Y39: MED | Z39: LG | AA39: XL | AB39: 2X | AC39: 3X | AD39: 4X | AE39: TOTAL
A40: =IF('Tour Dates'!A40="","",'Tour Dates'!A40) | B40: =IF('Tour Dates'!B40="","",'Tour Dates'!B40) | G40: =SUM(C40:F40) -> 0 | L40: =L39+H40-G40-I40-J40 -> 3667 | O40: 6240 | P40: CHINA | S40: =O40-Q40 -> 6240 | U40: Stock Purchased | V40: =R35 -> 6240 | X40: 502 | Y40: 1288 | Z40: 1877 | AA40: 1373 | AB40: 801 | AC40: 399 | AD40: 0 | AE40: =SUM(X40:AD40) -> 6240
A41: =IF('Tour Dates'!A41="","",'Tour Dates'!A41) | B41: =IF('Tour Dates'!B41="","",'Tour Dates'!B41) | G41: =SUM(C41:F41) -> 0 | L41: =L40+H41-G41-I41-J41 -> 3667 | Q41: 2494 | R41: OTHER | S41: =S40+O41-Q41 -> 3746 | T41: 163 | U41: Tour Sales | V41: =C64 -> 0 | X41: 289 | Y41: 525 | Z41: 600 | AA41: 600 | AB41: 300 | AC41: 180 | AD41: 0 | AE41: =SUM(X41:AD41) -> 2494
A42: =IF('Tour Dates'!A42="","",'Tour Dates'!A42) | B42: =IF('Tour Dates'!B42="","",'Tour Dates'!B42) | G42: =SUM(C42:F42) -> 0 | L42: =L41+H42-G42-I42-J42 -> 3667 | S42: =S41+O42-Q42 -> 3746 | U42: Band Comps | V42: =D64 -> 0 | AE42: =SUM(X42:AD42) -> 0
A43: =IF('Tour Dates'!A43="","",'Tour Dates'!A43) | B43: =IF('Tour Dates'!B43="","",'Tour Dates'!B43) | G43: =SUM(C43:F43) -> 0 | L43: =L42+H43-G43-I43-J43 -> 3667 | S43: =S42+O43-Q43 -> 3746 | U43: Global Comps | V43: =E64 -> 0 | AE43: =SUM(X43:AD43) -> 0
A44: =IF('Tour Dates'!A44="","",'Tour Dates'!A44) | B44: =IF('Tour Dates'!B44="","",'Tour Dates'!B44) | G44: =SUM(C44:F44) -> 0 | L44: =L43+H44-G44-I44-J44 -> 3667 | S44: =S43+O44-Q44 -> 3746 | U44: W/Sales | V44: =F64 -> 0 | AE44: =SUM(X44:AD44) -> 0
A45: =IF('Tour Dates'!A45="","",'Tour Dates'!A45) | B45: =IF('Tour Dates'!B45="","",'Tour Dates'!B45) | G45: =SUM(C45:F45) -> 0 | L45: =L44+H45-G45-I45-J45 -> 3667 | S45: =S44+O45-Q45 -> 3746 | U45: Total Used | V45: =G64 -> 0 | AE45: =SUM(X45:AD45) -> 0
A46: =IF('Tour Dates'!A46="","",'Tour Dates'!A46) | B46: =IF('Tour Dates'!B46="","",'Tour Dates'!B46) | G46: =SUM(C46:F46) -> 0 | L46: =L45+H46-G46-I46-J46 -> 3667 | S46: =S45+O46-Q46 -> 3746 | U46: +/- | V46: =I64 -> 0 | AE46: =SUM(X46:AD46) -> 0
A47: =IF('Tour Dates'!A47="","",'Tour Dates'!A47) | B47: =IF('Tour Dates'!B47="","",'Tour Dates'!B47) | G47: =SUM(C47:F47) -> 0 | L47: =L46+H47-G47-I47-J47 -> 3667 | S47: =S46+O47-Q47 -> 3746 | U47: Retail | V47: =SUMIF($R$40:$R$63,U47,$Q$40:$Q$63) -> 0 | AE47: =SUM(X47:AD47) -> 0
A48: =IF('Tour Dates'!A48="","",'Tour Dates'!A48) | B48: =IF('Tour Dates'!B48="","",'Tour Dates'!B48) | G48: =SUM(C48:F48) -> 0 | L48: =L47+H48-G48-I48-J48 -> 3667 | S48: =S47+O48-Q48 -> 3746 | U48: Web | V48: =SUMIF($R$40:$R$63,U48,$Q$40:$Q$63) -> 0 | AE48: =SUM(X48:AD48) -> 0
A49: =IF('Tour Dates'!A49="","",'Tour Dates'!A49) | B49: =IF('Tour Dates'!B49="","",'Tour Dates'!B49) | G49: =SUM(C49:F49) -> 0 | L49: =L48+H49-G49-I49-J49 -> 3667 | S49: =S48+O49-Q49 -> 3746 | U49: Global UK | V49: =SUMIF($R$40:$R$63,U49,$Q$40:$Q$63) -> 0 | AE49: =SUM(X49:AD49) -> 0
A50: =IF('Tour Dates'!A50="","",'Tour Dates'!A50) | B50: =IF('Tour Dates'!B50="","",'Tour Dates'!B50) | G50: =SUM(C50:F50) -> 0 | L50: =L49+H50-G50-I50-J50 -> 3667 | S50: =S49+O50-Q50 -> 3746 | U50: Other | V50: =SUMIF($R$40:$R$63,U50,$Q$40:$Q$63) -> 2494 | AE50: =SUM(X50:AD50) -> 0
A51: =IF('Tour Dates'!A51="","",'Tour Dates'!A51) | B51: =IF('Tour Dates'!B51="","",'Tour Dates'!B51) | G51: =SUM(C51:F51) -> 0 | L51: =L50+H51-G51-I51-J51 -> 3667 | S51: =S50+O51-Q51 -> 3746 | U51: Misprint | V51: =SUMIF($R$40:$R$63,U51,$Q$40:$Q$63) -> 0 | AE51: =SUM(X51:AD51) -> 0
A52: =IF('Tour Dates'!A52="","",'Tour Dates'!A52) | B52: =IF('Tour Dates'!B52="","",'Tour Dates'!B52) | G52: =SUM(C52:F52) -> 0 | L52: =L51+H52-G52-I52-J52 -> 3667 | S52: =S51+O52-Q52 -> 3746 | U52: Warehouse | V52: =S64 -> 3746 | AE52: =SUM(X52:AD52) -> 0
A53: =IF('Tour Dates'!A53="","",'Tour Dates'!A53) | B53: =IF('Tour Dates'!B53="","",'Tour Dates'!B53) | G53: =SUM(C53:F53) -> 0 | L53: =L52+H53-G53-I53-J53 -> 3667 | S53: =S52+O53-Q53 -> 3746 | U53: Discrepancy | V53: =(V39+V40)-SUM(V45:W52) -> 0 | AE53: =SUM(X53:AD53) -> 0
A54: =IF('Tour Dates'!A54="","",'Tour Dates'!A54) | B54: =IF('Tour Dates'!B54="","",'Tour Dates'!B54) | G54: =SUM(C54:F54) -> 0 | L54: =L53+H54-G54-I54-J54 -> 3667 | S54: =S53+O54-Q54 -> 3746 | U54: Comments | AE54: =SUM(X54:AD54) -> 0
A55: =IF('Tour Dates'!A55="","",'Tour Dates'!A55) | B55: =IF('Tour Dates'!B55="","",'Tour Dates'!B55) | G55: =SUM(C55:F55) -> 0 | L55: =L54+H55-G55-I55-J55 -> 3667 | S55: =S54+O55-Q55 -> 3746 | AE55: =SUM(X55:AD55) -> 0
A56: =IF('Tour Dates'!A56="","",'Tour Dates'!A56) | B56: =IF('Tour Dates'!B56="","",'Tour Dates'!B56) | G56: =SUM(C56:F56) -> 0 | L56: =L55+H56-G56-I56-J56 -> 3667 | S56: =S55+O56-Q56 -> 3746 | AE56: =SUM(X56:AD56) -> 0
A57: =IF('Tour Dates'!A57="","",'Tour Dates'!A57) | B57: =IF('Tour Dates'!B57="","",'Tour Dates'!B57) | G57: =SUM(C57:F57) -> 0 | L57: =L56+H57-G57-I57-J57 -> 3667 | S57: =S56+O57-Q57 -> 3746 | AE57: =SUM(X57:AD57) -> 0
A58: =IF('Tour Dates'!A58="","",'Tour Dates'!A58) | B58: =IF('Tour Dates'!B58="","",'Tour Dates'!B58) | G58: =SUM(C58:F58) -> 0 | L58: =L57+H58-G58-I58-J58 -> 3667 | S58: =S57+O58-Q58 -> 3746 | AE58: =SUM(X58:AD58) -> 0
A59: =IF('Tour Dates'!A59="","",'Tour Dates'!A59) | B59: =IF('Tour Dates'!B59="","",'Tour Dates'!B59) | G59: =SUM(C59:F59) -> 0 | L59: =L58+H59-G59-I59-J59 -> 3667 | S59: =S58+O59-Q59 -> 3746 | AE59: =SUM(X59:AD59) -> 0
A60: =IF('Tour Dates'!A60="","",'Tour Dates'!A60) | B60: =IF('Tour Dates'!B60="","",'Tour Dates'!B60) | G60: =SUM(C60:F60) -> 0 | L60: =L59+H60-G60-I60-J60 -> 3667 | S60: =S59+O60-Q60 -> 3746 | AE60: =SUM(X60:AD60) -> 0
A61: =IF('Tour Dates'!A61="","",'Tour Dates'!A61) | B61: =IF('Tour Dates'!B61="","",'Tour Dates'!B61) | G61: =SUM(C61:F61) -> 0 | L61: =L60+H61-G61-I61-J61 -> 3667 | S61: =S60+O61-Q61 -> 3746 | AE61: =SUM(X61:AD61) -> 0
A62: =IF('Tour Dates'!A62="","",'Tour Dates'!A62) | B62: =IF('Tour Dates'!B62="","",'Tour Dates'!B62) | G62: =SUM(C62:F62) -> 0 | L62: =L61+H62-G62-I62-J62 -> 3667 | S62: =S61+O62-Q62 -> 3746 | AE62: =SUM(X62:AD62) -> 0
A63: =IF('Tour Dates'!A63="","",'Tour Dates'!A63) | B63: =IF('Tour Dates'!B63="","",'Tour Dates'!B63) | G63: =SUM(C63:F63) -> 0 | L63: =L62+H63-G63-I63-J63 -> 3667 | S63: =S62+O63-Q63 -> 3746 | AE63: =SUM(X63:AD63) -> 0
A64: Total | C64: =SUM(C4:C63) -> 0 | D64: =SUM(D4:D63) -> 0 | E64: =SUM(E4:E63) -> 0 | F64: =SUM(F4:F63) -> 0 | G64: =SUM(G4:G63) -> 0 | H64: =SUM(H4:H63) -> 3667 | I64: =SUM(I4:I63) -> 0 | L64: =L63 -> 3667 | M64: =IFERROR(AVERAGE(M4:M63),0) -> 0 | O64: =SUM(O40:O63) -> 6240 | Q64: =SUM(Q40:Q63) -> 2494 | S64: =S63 -> 3746 | AE64: =SUM(X64:AD64) -> 0

Sheet SHORTS
A1: Tour | B1: =Inventory!C3 -> GHOST | D1: Item | E1: =Inventory!C8 -> SHORTS BLACK/ WHT PAPA V COSTUME CLAWS | L1: Cost | M1: =Inventory!H8 -> 5.8 | N1: Supplier | O1: =Inventory!D8 -> FARSTAR | R1: Code | S1: =Inventory!B8 -> GHOSRX203275BK | U1: % of Gross | V1: =M64 -> 0
A3: Date | B3: City | C3: Sales | D3: Band Co | E3: GMS Co | F3: W/Sale | G3: Used | H3: Delivery | I3: +/- | J3: Ship | K3: To | L3: Balance | M3: % | O3: Stock B/F | Q3: Date | R3: Qty Received | S3: To | X3: SM | Y3: MED | Z3: LG | AA3: XL | AB3: 2X | AC3: 3X | AD3: 4X | AE3: TOTAL
A4: =IF('Tour Dates'!A4="","",'Tour Dates'!A4) -> 46043 | B4: =IF('Tour Dates'!B4="","",'Tour Dates'!B4) -> ORLANDO | G4: =SUM(C4:F4) -> 0 | H4: =706+4652 -> 5358 | L4: =H4-G4-I4-J4 -> 5358 | O4: 2025 TRACKER | Q4: 46309 | R4: =AE4 -> 706 | S4: ORLANDO | X4: 256 | Y4: 311 | Z4: 96 | AA4: 43 | AB4: 0 | AC4: 0 | AD4: 0 | AE4: =SUM(X4:AD4) -> 706
A5: =IF('Tour Dates'!A5="","",'Tour Dates'!A5) -> 46044 | B5: =IF('Tour Dates'!B5="","",'Tour Dates'!B5) -> JACKSONVILLE | G5: =SUM(C5:F5) -> 0 | L5: =L4+H5-G5-I5-J5 -> 5358 | R5: =AE5 -> 0 | AE5: =SUM(X5:AD5) -> 0
A6: =IF('Tour Dates'!A6="","",'Tour Dates'!A6) -> 46046 | B6: =IF('Tour Dates'!B6="","",'Tour Dates'!B6) -> KNOXVILLE | G6: =SUM(C6:F6) -> 0 | L6: =L5+H6-G6-I6-J6 -> 5358 | R6: =AE6 -> 0 | AE6: =SUM(X6:AD6) -> 0
A7: =IF('Tour Dates'!A7="","",'Tour Dates'!A7) -> 46047 | B7: =IF('Tour Dates'!B7="","",'Tour Dates'!B7) -> CHARLOTTE | G7: =SUM(C7:F7) -> 0 | L7: =L6+H7-G7-I7-J7 -> 5358 | R7: =SUM(R4:R6) -> 706 | U7: Invoice Details
A8: =IF('Tour Dates'!A8="","",'Tour Dates'!A8) -> 46048 | B8: =IF('Tour Dates'!B8="","",'Tour Dates'!B8) -> GREENVILLE | G8: =SUM(C8:F8) -> 0 | L8: =L7+H8-G8-I8-J8 -> 5358
A9: =IF('Tour Dates'!A9="","",'Tour Dates'!A9) -> 46050 | B9: =IF('Tour Dates'!B9="","",'Tour Dates'!B9) -> UNCASVILLE | G9: =SUM(C9:F9) -> 0 | L9: =L8+H9-G9-I9-J9 -> 5358 | O9: Date | P9: PO Number | Q9: Amount Ordered | R9: Qty Received | S9: To | T9: BOXES | U9: Delivery Note | V9: Inv No | W9: Checked By | X9: SM | Y9: MED | Z9: LG | AA9: XL | AB9: 2X | AC9: 3X | AD9: 4X | AE9: TOTAL
A10: =IF('Tour Dates'!A10="","",'Tour Dates'!A10) -> 46052 | B10: =IF('Tour Dates'!B10="","",'Tour Dates'!B10) -> MONTREAL | G10: =SUM(C10:F10) -> 0 | L10: =L9+H10-G10-I10-J10 -> 5358 | O10: 45944 | P10: 85655 | Q10: 4652 | X10: 650 | Y10: 1000 | Z10: 1200 | AA10: 1000 | AB10: 650 | AC10: 0 | AE10: =SUM(X10:AD10) -> 4500
A11: =IF('Tour Dates'!A11="","",'Tour Dates'!A11) -> 46053 | B11: =IF('Tour Dates'!B11="","",'Tour Dates'!B11) -> TORONTO | G11: =SUM(C11:F11) -> 0 | L11: =L10+H11-G11-I11-J11 -> 5358 | R11: 4652 | S11: ORLANDO | T11: 46 | X11: 661 | Y11: 1032 | Z11: 1241 | AA11: 1054 | AB11: 664 | AC11: 0 | AD11: 0 | AE11: =SUM(X11:AD11) -> 4652
A12: =IF('Tour Dates'!A12="","",'Tour Dates'!A12) -> 46055 | B12: =IF('Tour Dates'!B12="","",'Tour Dates'!B12) -> COLUMBUS | G12: =SUM(C12:F12) -> 0 | L12: =L11+H12-G12-I12-J12 -> 5358 | AE12: =SUM(X12:AD12) -> 0
A13: =IF('Tour Dates'!A13="","",'Tour Dates'!A13) -> 46057 | B13: =IF('Tour Dates'!B13="","",'Tour Dates'!B13) -> CINCINNATI | G13: =SUM(C13:F13) -> 0 | L13: =L12+H13-G13-I13-J13 -> 5358 | AE13: =SUM(X13:AD13) -> 0
A14: =IF('Tour Dates'!A14="","",'Tour Dates'!A14) -> 46058 | B14: =IF('Tour Dates'!B14="","",'Tour Dates'!B14) -> PEORIA | G14: =SUM(C14:F14) -> 0 | L14: =L13+H14-G14-I14-J14 -> 5358 | AE14: =SUM(X14:AD14) -> 0
A15: =IF('Tour Dates'!A15="","",'Tour Dates'!A15) -> 46060 | B15: =IF('Tour Dates'!B15="","",'Tour Dates'!B15) -> TULSA | G15: =SUM(C15:F15) -> 0 | L15: =L14+H15-G15-I15-J15 -> 5358 | AE15: =SUM(X15:AD15) -> 0
A16: =IF('Tour Dates'!A16="","",'Tour Dates'!A16) -> 46063 | B16: =IF('Tour Dates'!B16="","",'Tour Dates'!B16) -> SALT LAKE CITY | G16: =SUM(C16:F16) -> 0 | L16: =L15+H16-G16-I16-J16 -> 5358 | AE16: =SUM(X16:AD16) -> 0
A17: =IF('Tour Dates'!A17="","",'Tour Dates'!A17) -> 46065 | B17: =IF('Tour Dates'!B17="","",'Tour Dates'!B17) -> SPOKANE | G17: =SUM(C17:F17) -> 0 | L17: =L16+H17-G17-I17-J17 -> 5358 | AE17: =SUM(X17:AD17) -> 0
A18: =IF('Tour Dates'!A18="","",'Tour Dates'!A18) -> 46067 | B18: =IF('Tour Dates'!B18="","",'Tour Dates'!B18) -> VANCOUVER | G18: =SUM(C18:F18) -> 0 | L18: =L17+H18-G18-I18-J18 -> 5358 | AE18: =SUM(X18:AD18) -> 0
A19: =IF('Tour Dates'!A19="","",'Tour Dates'!A19) -> 46068 | B19: =IF('Tour Dates'!B19="","",'Tour Dates'!B19) -> SEATTLE | G19: =SUM(C19:F19) -> 0 | L19: =L18+H19-G19-I19-J19 -> 5358 | AE19: =SUM(X19:AD19) -> 0
A20: =IF('Tour Dates'!A20="","",'Tour Dates'!A20) -> 46070 | B20: =IF('Tour Dates'!B20="","",'Tour Dates'!B20) -> PORTLAND | G20: =SUM(C20:F20) -> 0 | L20: =L19+H20-G20-I20-J20 -> 5358 | AE20: =SUM(X20:AD20) -> 0
A21: =IF('Tour Dates'!A21="","",'Tour Dates'!A21) -> 46073 | B21: =IF('Tour Dates'!B21="","",'Tour Dates'!B21) -> SACRAMENTO | G21: =SUM(C21:F21) -> 0 | L21: =L20+H21-G21-I21-J21 -> 5358 | AE21: =SUM(X21:AD21) -> 0
A22: =IF('Tour Dates'!A22="","",'Tour Dates'!A22) -> 46074 | B22: =IF('Tour Dates'!B22="","",'Tour Dates'!B22) -> ANAHEIM | G22: =SUM(C22:F22) -> 0 | L22: =L21+H22-G22-I22-J22 -> 5358 | AE22: =SUM(X22:AD22) -> 0
A23: =IF('Tour Dates'!A23="","",'Tour Dates'!A23) -> 46076 | B23: =IF('Tour Dates'!B23="","",'Tour Dates'!B23) -> INGLEWOOD | G23: =SUM(C23:F23) -> 0 | L23: =L22+H23-G23-I23-J23 -> 5358 | AE23: =SUM(X23:AD23) -> 0
... A34: =IF('Tour Dates'!A34="","",'Tour Dates'!A34) | B34: =IF('Tour Dates'!B34="","",'Tour Dates'!B34) | G34: =SUM(C34:F34) -> 0 | L34: =L33+H34-G34-I34-J34 -> 5358 | AE34: =SUM(X34:AD34) -> 0
A35: =IF('Tour Dates'!A35="","",'Tour Dates'!A35) | B35: =IF('Tour Dates'!B35="","",'Tour Dates'!B35) | G35: =SUM(C35:F35) -> 0 | L35: =L34+H35-G35-I35-J35 -> 5358 | O35: Total | Q35: =SUM(Q10:Q34) -> 4652 | R35: =SUM(R10:R34) -> 4652
A36: =IF('Tour Dates'!A36="","",'Tour Dates'!A36) | B36: =IF('Tour Dates'!B36="","",'Tour Dates'!B36) | G36: =SUM(C36:F36) -> 0 | L36: =L35+H36-G36-I36-J36 -> 5358
A37: =IF('Tour Dates'!A37="","",'Tour Dates'!A37) | B37: =IF('Tour Dates'!B37="","",'Tour Dates'!B37) | G37: =SUM(C37:F37) -> 0 | L37: =L36+H37-G37-I37-J37 -> 5358 | O37: Stock Movement | U37: Product Summary
A38: =IF('Tour Dates'!A38="","",'Tour Dates'!A38) | B38: =IF('Tour Dates'!B38="","",'Tour Dates'!B38) | G38: =SUM(C38:F38) -> 0 | L38: =L37+H38-G38-I38-J38 -> 5358
A39: =IF('Tour Dates'!A39="","",'Tour Dates'!A39) | B39: =IF('Tour Dates'!B39="","",'Tour Dates'!B39) | G39: =SUM(C39:F39) -> 0 | L39: =L38+H39-G39-I39-J39 -> 5358 | O39: In | P39: From | Q39: Out | R39: To | S39: Qty | U39: Stock B/F | V39: =R7 -> 706 | X39: SM | Y39: MED | Z39: LG | AA39: XL | AB39: 2X | AC39: 3X | AD39: 4X | AE39: TOTAL
A40: =IF('Tour Dates'!A40="","",'Tour Dates'!A40) | B40: =IF('Tour Dates'!B40="","",'Tour Dates'!B40) | G40: =SUM(C40:F40) -> 0 | L40: =L39+H40-G40-I40-J40 -> 5358 | O40: 4652 | P40: CHINA | S40: =O40-Q40 -> 4652 | U40: Stock Purchased | V40: =R35 -> 4652 | AE40: =SUM(X40:AD40) -> 0
A41: =IF('Tour Dates'!A41="","",'Tour Dates'!A41) | B41: =IF('Tour Dates'!B41="","",'Tour Dates'!B41) | G41: =SUM(C41:F41) -> 0 | L41: =L40+H41-G41-I41-J41 -> 5358 | R41: OTHER | S41: =S40+O41-Q41 -> 4652 | U41: Tour Sales | V41: =C64 -> 0 | AE41: =SUM(X41:AD41) -> 0
A42: =IF('Tour Dates'!A42="","",'Tour Dates'!A42) | B42: =IF('Tour Dates'!B42="","",'Tour Dates'!B42) | G42: =SUM(C42:F42) -> 0 | L42: =L41+H42-G42-I42-J42 -> 5358 | R42: OTHER | S42: =S41+O42-Q42 -> 4652 | U42: Band Comps | V42: =D64 -> 0 | AE42: =SUM(X42:AD42) -> 0
A43: =IF('Tour Dates'!A43="","",'Tour Dates'!A43) | B43: =IF('Tour Dates'!B43="","",'Tour Dates'!B43) | G43: =SUM(C43:F43) -> 0 | L43: =L42+H43-G43-I43-J43 -> 5358 | S43: =S42+O43-Q43 -> 4652 | U43: Global Comps | V43: =E64 -> 0 | AE43: =SUM(X43:AD43) -> 0
