Workbook
Name CompanyAddress: [1]Settings!$C$10
Name CompanyName: '[1]Tour Info'!$F$6
Name Rates: [1]Settings!$C$2:$C$7
Name YesNo: [1]Settings!$C$15:$C$16

Sheet Tour Dates
A1: Tour Dates
A3: Date | B3: City | C3: STATE | D3: VENUE | E3: Country
A4: 45847 | B4: Baltimore | C4: MD | D4: CFG Bank Arena | E4: USA
A5: 45849 | B5: Atlanta | C5: GA | D5: State Farm Arena | E5: USA
A6: 45850 | B6: Tampa | C6: FL | D6: Amalie Arena | E6: USA
A7: 45851 | B7: Miami | C7: FL | D7: Kaseya Center | E7: USA
A8: 45853 | B8: Raleigh | C8: NC | D8: Lenovo Center | E8: USA
A9: 45855 | B9: Cleveland | C9: OH | D9: Rocket Mortgage FieldHouse | E9: USA
A10: 45856 | B10: Pittsburgh | C10: PA | D10: PPG Paints Arena | E10: USA
A11: 45857 | B11: Philadelphia | C11: PA | D11: Wells Fargo Center | E11: USA
A12: 45859 | B12: Boston | C12: MA | D12: TD Garden | E12: USA
A13: 45860 | B13: New York | C13: NY | D13: Madison Square Garden | E13: USA
A14: 45862 | B14: Detroit | C14: MI | D14: Little Caesars Arena | E14: USA
A15: 45863 | B15: Louisville | C15: KY | D15: KFC Yum! Center | E15: USA
... A25: 45878 | B25: Las Vegas | C25: NV | D25: MGM Grand Garden Arena | E25: USA
A26: 8/10/2025 | B26: San Diego | C26: CA | D26: Viejas Arena | E26: USA
A27: 8/11/2025 | B27: Phoenix | C27: AZ | D27: Footprint Center | E27: USA
A28: 8/14/2025 | B28: Austin | C28: TX | D28: Moody Center | E28: USA
A29: 8/15/2025 | B29: Fort Worth | C29: TX | D29: Dickies Arena | E29: USA
A30: 8/16/2025 | B30: Houston | C30: TX | D30: Toyota Center | E30: USA

Sheet Inventory
B1: Tour Inventory
B3: Tour | C3: GHOST | D3: GARMENTS x 20 | E3: TRINKETS X 20
B4: Tour Date | C4: SUMMER 2025
E5: Formula | F5: Formula | G5: Formula | J5: QUICK STOCK VIEW | R5: PRODUCT SUMMARY
B6: BC Item Code | C6: Product Description | D6: Supplier | E6: Blank Unit Cost | F6: Print Unit Cost | G6: Full Package | H6: Total Unit Cost | J6: Sales | K6: Used | L6: Road | M6: Ware house | N6: Sales % | P6: End Tour Stock Count | R6: B/F | S6: Purchased | T6: Sold | U6: W/S | V6: Band Comps | W6: GMS Comps | X6: O/U | Y6: Retail | Z6: Web | AA6: Global UK | AB6: Other | AC6: Misprint | AD6: Closing Stock | AE6: Closing Stock
A7: 1 | B7: GHOSRX203729BK | C7: BLACK T SKELETOUR 2025 ITIN | D7: CULTURE | E7: =VLOOKUP($A:$A,'COGS NEW TEMPLATE'!$A:$G,5,FALSE) -> 0 | F7: =VLOOKUP($A:$A,'COGS NEW TEMPLATE'!$A:$G,6,FALSE) -> 0 | G7: =VLOOKUP($A:$A,'COGS NEW TEMPLATE'!$A:$G,7,FALSE) -> 5.7 | H7: =SUM(E7:G7) -> 5.7 | J7: ='BLK T ADMAT ITIN'!$C$64 -> 23973 | K7: ='BLK T ADMAT ITIN'!$G$64 -> 24021 | L7: ='BLK T ADMAT ITIN'!$L$64 -> 0 | M7: ='BLK T ADMAT ITIN'!$S$64 -> 684 | N7: ='BLK T ADMAT ITIN'!$M$64 -> 0.15037037 | R7: ='BLK T ADMAT ITIN'!$V$39 -> 0 | S7: ='BLK T ADMAT ITIN'!$V$40 -> 25108 | T7: ='BLK T ADMAT ITIN'!$V$41 -> 23973 | U7: ='BLK T ADMAT ITIN'!$V$44 -> 8 | V7: ='BLK T ADMAT ITIN'!$V$42 -> 27 | W7: ='BLK T ADMAT ITIN'!$V$43 -> 13 | X7: ='BLK T ADMAT ITIN'!$V$46 -> 133 | Y7: ='BLK T ADMAT ITIN'!$V$47 -> 0 | Z7: ='BLK T ADMAT ITIN'!$V$48 -> 270 | AA7: ='BLK T ADMAT ITIN'!$V$49 -> 0 | AB7: ='BLK T ADMAT ITIN'!$V$50 -> 0 | AC7: ='BLK T ADMAT ITIN'!$V$51 -> 0 | AD7: ='BLK T ADMAT ITIN'!V$52+'BLK T ADMAT ITIN'!V$53 -> 684 | AE7: =(R7+S7)-SUM(T7:AC7) -> 684
A8: 2 | B8: GHOSRX203728BK | C8: BLACK T SKELETA ALBUM COVER 2025 ITIN | D8: CULTURE | E8: =VLOOKUP($A:$A,'COGS NEW TEMPLATE'!$A:$G,5,FALSE) -> 0 | F8: =VLOOKUP($A:$A,'COGS NEW TEMPLATE'!$A:$G,6,FALSE) -> 0 | G8: =VLOOKUP($A:$A,'COGS NEW TEMPLATE'!$A:$G,7,FALSE) -> 5.7 | H8: =SUM(E8:G8) -> 5.7 | J8: ='BLK T SKELETA ITIN'!$C$64 -> 17260 | K8: ='BLK T SKELETA ITIN'!$G$64 -> 17296 | L8: ='BLK T SKELETA ITIN'!$L$64 -> 0 | M8: ='BLK T SKELETA ITIN'!$S$64 -> 58 | N8: ='BLK T SKELETA ITIN'!$M$64 -> 0.10777778 | R8: ='BLK T SKELETA ITIN'!$V$39 -> 0 | S8: ='BLK T SKELETA ITIN'!$V$40 -> 17527 | T8: ='BLK T SKELETA ITIN'!$V$41 -> 17260 | U8: ='BLK T SKELETA ITIN'!$V$44 -> 4 | V8: ='BLK T SKELETA ITIN'!$V$42 -> 22 | W8: ='BLK T SKELETA ITIN'!$V$43 -> 10 | X8: ='BLK T SKELETA ITIN'!$V$46 -> 173 | Y8: ='BLK T SKELETA ITIN'!$V$47 -> 0 | Z8: ='BLK T SKELETA ITIN'!$V$48 -> 0 | AA8: ='BLK T SKELETA ITIN'!$V$49 -> 0 | AB8: ='BLK T SKELETA ITIN'!$V$50 -> 0 | AC8: ='BLK T SKELETA ITIN'!$V$51 -> 0 | AD8: ='BLK T SKELETA ITIN'!V$52+'BLK T SKELETA ITIN'!V$53 -> 58 | AE8: =(R8+S8)-SUM(T8:AC8) -> 58
A9: 3 | B9: GHOSRX203730BK | C9: BLACK T WESTERN EMERITUS 2025 ITIN | D9: CULTURE | E9: =VLOOKUP($A:$A,'COGS NEW TEMPLATE'!$A:$G,5,FALSE) -> 0 | F9: =VLOOKUP($A:$A,'COGS NEW TEMPLATE'!$A:$G,6,FALSE) -> 0 | G9: =VLOOKUP($A:$A,'COGS NEW TEMPLATE'!$A:$G,7,FALSE) -> 5.7 | H9: =SUM(E9:G9) -> 5.7 | J9: ='BLK T EMERITUS ITIN'!$C$64 -> 28239 | K9: ='BLK T EMERITUS ITIN'!$G$64 -> 28281 | L9: ='BLK T EMERITUS ITIN'!$L$64 -> 0 | M9: ='BLK T EMERITUS ITIN'!$S$64 -> 0 | N9: ='BLK T EMERITUS ITIN'!$M$64 -> 0.1762963 | R9: ='BLK T EMERITUS ITIN'!$V$39 -> 0 | S9: ='BLK T EMERITUS ITIN'!$V$40 -> 28590 | T9: ='BLK T EMERITUS ITIN'!$V$41 -> 28239 | U9: ='BLK T EMERITUS ITIN'!$V$44 -> 7 | V9: ='BLK T EMERITUS ITIN'!$V$42 -> 24 | W9: ='BLK T EMERITUS ITIN'!$V$43 -> 11 | X9: ='BLK T EMERITUS ITIN'!$V$46 -> 141 | Y9: ='BLK T EMERITUS ITIN'!$V$47 -> 0 | Z9: ='BLK T EMERITUS ITIN'!$V$48 -> 168 | AA9: ='BLK T EMERITUS ITIN'!$V$49 -> 0 | AB9: ='BLK T EMERITUS ITIN'!$V$50 -> 0 | AC9: ='BLK T EMERITUS ITIN'!$V$51 -> 0 | AD9: ='BLK T EMERITUS ITIN'!V$52+'BLK T EMERITUS ITIN'!V$53 -> 0 | AE9: =(R9+S9)-SUM(T9:AC9) -> 0
A10: 4 | B10: GHOSRX103726BK | C10: BLACK TANK OPUS EPONYMOUS | D10: CULTURE | E10: =VLOOKUP($A:$A,'COGS NEW TEMPLATE'!$A:$G,5,FALSE) -> 0 | F10: =VLOOKUP($A:$A,'COGS NEW TEMPLATE'!$A:$G,6,FALSE) -> 0 | G10: =VLOOKUP($A:$A,'COGS NEW TEMPLATE'!$A:$G,7,FALSE) -> 7.38 | H10: =SUM(E10:G10) -> 7.38 | J10: ='TANK TOP'!$C$64 -> 4001 | K10: ='TANK TOP'!$G$64 -> 4019 | L10: ='TANK TOP'!$L$64 -> 0 | M10: ='TANK TOP'!$S$64 -> 0 | N10: ='TANK TOP'!$M$64 -> 0.025555556 | R10: ='TANK TOP'!$V$39 -> 0 | S10: ='TANK TOP'!$V$40 -> 4179 | T10: ='TANK TOP'!$V$41 -> 4001 | U10: ='TANK TOP'!$V$44 -> 1 | V10: ='TANK TOP'!$V$42 -> 15 | W10: ='TANK TOP'!$V$43 -> 2 | X10: ='TANK TOP'!$V$46 -> 8 | Y10: ='TANK TOP'!$V$47 -> 0 | Z10: ='TANK TOP'!$V$48 -> 152 | AA10: ='TANK TOP'!$V$49 -> 0 | AB10: ='TANK TOP'!$V$50 -> 0 | AC10: ='TANK TOP'!$V$51 -> 0 | AD10: ='TANK TOP'!V$52+'TANK TOP'!V$53 -> 0 | AE10: =(R10+S10)-SUM(T10:AC10) -> 0
A11: 5 | B11: GHOSRX203400BK | C11: LADIES CROP TOP SHOWGHOULS | D11: GMSUK | E11: =VLOOKUP($A:$A,'COGS NEW TEMPLATE'!$A:$G,5,FALSE) -> 0 | F11: =VLOOKUP($A:$A,'COGS NEW TEMPLATE'!$A:$G,6,FALSE) -> 0 | G11: =VLOOKUP($A:$A,'COGS NEW TEMPLATE'!$A:$G,7,FALSE) -> 9.77 | H11: =SUM(E11:G11) -> 9.77 | J11: ='LADIES CROP TOP'!$C$64 -> 3160 | K11: ='LADIES CROP TOP'!$G$64 -> 3167 | L11: ='LADIES CROP TOP'!$L$64 -> 0 | M11: ='LADIES CROP TOP'!$S$64 -> 0 | N11: ='LADIES CROP TOP'!$M$64 -> 0.01962963 | R11: ='LADIES CROP TOP'!$V$39 -> 0 | S11: ='LADIES CROP TOP'!$V$40 -> 3156 | T11: ='LADIES CROP TOP'!$V$41 -> 3160 | U11: ='LADIES CROP TOP'!$V$44 -> 0 | V11: ='LADIES CROP TOP'!$V$42 -> 2 | W11: ='LADIES CROP TOP'!$V$43 -> 5 | X11: ='LADIES CROP TOP'!$V$46 -> -11 | Y11: ='LADIES CROP TOP'!$V$47 -> 0 | Z11: ='LADIES CROP TOP'!$V$48 -> 0 | AA11: ='LADIES CROP TOP'!$V$49 -> 0 | AB11: ='LADIES CROP TOP'!$V$50 -> 0 | AC11: ='LADIES CROP TOP'!$V$51 -> 0 | AD11: ='LADIES CROP TOP'!V$52+'LADIES CROP TOP'!V$53 -> 0 | AE11: =(R11+S11)-SUM(T11:AC11) -> 0
A12: 6 | B12: GHOSRX203727PK | C12: LADIES PINK RAGLAN GARGOYLE | D12: CULTURE | E12: =VLOOKUP($A:$A,'COGS NEW TEMPLATE'!$A:$G,5,FALSE) -> 0 | F12: =VLOOKUP($A:$A,'COGS NEW TEMPLATE'!$A:$G,6,FALSE) -> 0 | G12: =VLOOKUP($A:$A,'COGS NEW TEMPLATE'!$A:$G,7,FALSE) -> 12.29 | H12: =SUM(E12:G12) -> 12.29 | J12: ='LADIES RAGLAN '!$C$64 -> 2939 | K12: ='LADIES RAGLAN '!$G$64 -> 2959 | L12: ='LADIES RAGLAN '!$L$64 -> 0 | M12: ='LADIES RAGLAN '!$S$64 -> 242 | N12: ='LADIES RAGLAN '!$M$64 -> 0.018888889 | R12: ='LADIES RAGLAN '!$V$39 -> 0 | S12: ='LADIES RAGLAN '!$V$40 -> 3307 | T12: ='LADIES RAGLAN '!$V$41 -> 2939 | U12: ='LADIES RAGLAN '!$V$44 -> 1 | V12: ='LADIES RAGLAN '!$V$42 -> 15 | W12: ='LADIES RAGLAN '!$V$43 -> 4 | X12: ='LADIES RAGLAN '!$V$46 -> 6 | Y12: ='LADIES RAGLAN '!$V$47 -> 0 | Z12: ='LADIES RAGLAN '!$V$48 -> 100 | AA12: ='LADIES RAGLAN '!$V$49 -> 0 | AB12: ='LADIES RAGLAN '!$V$50 -> 0 | AC12: ='LADIES RAGLAN '!$V$51 -> 0 | AD12: ='LADIES RAGLAN '!V$52+'LADIES RAGLAN '!V$53 -> 242 | AE12: =(R12+S12)-SUM(T12:AC12) -> 242
A13: 7 | E13: =VLOOKUP($A:$A,'COGS NEW TEMPLATE'!$A:$G,5,FALSE) -> 0 | F13: =VLOOKUP($A:$A,'COGS NEW TEMPLATE'!$A:$G,6,FALSE) -> 0 | G13: =VLOOKUP($A:$A,'COGS NEW TEMPLATE'!$A:$G,7,FALSE) -> 0 | H13: =SUM(E13:G13) -> 0 | J13: ='7'!$C$64 -> 0 | K13: ='7'!$G$64 -> 0 | L13: ='7'!$L$64 -> 0 | M13: ='7'!$S$64 -> 0 | N13: ='7'!$M$64 -> 0 | R13: ='7'!$V$39 -> 0 | S13: ='7'!$V$40 -> 0 | T13: ='7'!$V$41 -> 0 | U13: ='7'!$V$44 -> 0 | V13: ='7'!$V$42 -> 0 | W13: ='7'!$V$43 -> 0 | X13: ='7'!$V$46 -> 0 | Y13: ='7'!$V$47 -> 0 | Z13: ='7'!$V$48 -> 0 | AA13: ='7'!$V$49 -> 0 | AB13: ='7'!$V$50 -> 0 | AC13: ='7'!$V$51 -> 0 | AD13: ='7'!V$52+'7'!V$53 -> 0 | AE13: =(R13+S13)-SUM(T13:AC13) -> 0
A14: 8 | B14: GHOSNS903311BK | C14: BATWING HOODY | D14: FARSTAR | E14: =VLOOKUP($A:$A,'COGS NEW TEMPLATE'!$A:$G,5,FALSE) -> 0 | F14: =VLOOKUP($A:$A,'COGS NEW TEMPLATE'!$A:$G,6,FALSE) -> 0 | G14: =VLOOKUP($A:$A,'COGS NEW TEMPLATE'!$A:$G,7,FALSE) -> 28.5 | H14: =SUM(E14:G14) -> 28.5 | J14: ='BATWING HOODY'!$C$64 -> 6179 | K14: ='BATWING HOODY'!$G$64 -> 6196 | L14: ='BATWING HOODY'!$L$64 -> 0 | M14: ='BATWING HOODY'!$S$69 -> 1093 | N14: ='BATWING HOODY'!$M$64 -> 0.097407407 | R14: ='BATWING HOODY'!$V$44 -> 0 | S14: ='BATWING HOODY'!$V$45 -> 7225 | T14: ='BATWING HOODY'!$V$46 -> 6179 | U14: ='BATWING HOODY'!$V$49 -> 4 | V14: ='BATWING HOODY'!$V$47 -> 11 | W14: ='BATWING HOODY'!$V$48 -> 2 | X14: ='BATWING HOODY'!$V$51 -> -64 | Y14: ='BATWING HOODY'!$V$52 -> 0 | Z14: ='BATWING HOODY'!$V$53 -> 0 | AA14: ='BATWING HOODY'!$V$54 -> 0 | AB14: ='BATWING HOODY'!$V$55 -> 0 | AC14: ='BATWING HOODY'!$V$56 -> 0 | AD14: ='BATWING HOODY'!V$57+'BATWING HOODY'!V$58 -> 1093 | AE14: =(R14+S14)-SUM(T14:AC14) -> 1093
A15: 9 | B15: GHOSRX203401BK | C15: PULLOVER HOODY SKELETON | D15: CULTURE | E15: =VLOOKUP($A:$A,'COGS NEW TEMPLATE'!$A:$G,5,FALSE) -> 0 | F15: =VLOOKUP($A:$A,'COGS NEW TEMPLATE'!$A:$G,6,FALSE) -> 0 | G15: =VLOOKUP($A:$A,'COGS NEW TEMPLATE'!$A:$G,7,FALSE) -> 14.19 | H15: =SUM(E15:G15) -> 14.19 | J15: ='PO HOODY'!$C$64 -> 7347 | K15: ='PO HOODY'!$G$64 -> 7366 | L15: ='PO HOODY'!$L$64 -> 0 | M15: ='PO HOODY'!$S$64 -> 57 | N15: ='PO HOODY'!$M$64 -> 0.074074074 | R15: ='PO HOODY'!$V$39 -> 0 | S15: ='PO HOODY'!$V$40 -> 7518 | T15: ='PO HOODY'!$V$41 -> 7347 | U15: ='PO HOODY'!$V$44 -> 3 | V15: ='PO HOODY'!$V$42 -> 8 | W15: ='PO HOODY'!$V$43 -> 8 | X15: ='PO HOODY'!$V$46 -> 54 | Y15: ='PO HOODY'!$V$47 -> 0 | Z15: ='PO HOODY'!$V$48 -> 41 | AA15: ='PO HOODY'!$V$49 -> 0 | AB15: ='PO HOODY'!$V$50 -> 0 | AC15: ='PO HOODY'!$V$51 -> 0 | AD15: ='PO HOODY'!V$52+'PO HOODY'!V$53 -> 57 | AE15: =(R15+S15)-SUM(T15:AC15) -> 57
A16: 10 | B16: GHOSRX203275BK | C16: SHORTS BLACK/ WHT PAPA V COSTUME CLAWS | D16: CULTURE | E16: =VLOOKUP($A:$A,'COGS NEW TEMPLATE'!$A:$G,5,FALSE) -> 5.5 | F16: =VLOOKUP($A:$A,'COGS NEW TEMPLATE'!$A:$G,6,FALSE) -> 0 | G16: =VLOOKUP($A:$A,'COGS NEW TEMPLATE'!$A:$G,7,FALSE) -> 0 | H16: =SUM(E16:G16) -> 5.5 | J16: ='SHORTS BLK'!$C$64 -> 6578 | K16: ='SHORTS BLK'!$G$64 -> 6586 | L16: ='SHORTS BLK'!$L$64 -> 0 | M16: ='SHORTS BLK'!$S$64 -> 706 | N16: ='SHORTS BLK'!$M$64 -> 0.036666667 | R16: ='SHORTS BLK'!$V$39 -> 0 | S16: ='SHORTS BLK'!$V$40 -> 7476 | T16: ='SHORTS BLK'!$V$41 -> 6578 | U16: ='SHORTS BLK'!$V$44 -> 4 | V16: ='SHORTS BLK'!$V$42 -> 2 | W16: ='SHORTS BLK'!$V$43 -> 2 | X16: ='SHORTS BLK'!$V$46 -> 15 | Y16: ='SHORTS BLK'!$V$47 -> 0 | Z16: ='SHORTS BLK'!$V$48 -> 169 | AA16: ='SHORTS BLK'!$V$49 -> 0 | AB16: ='SHORTS BLK'!$V$50 -> 0 | AC16: ='SHORTS BLK'!$V$51 -> 0 | AD16: ='SHORTS BLK'!V$52+'SHORTS BLK'!V$53 -> 706 | AE16: =(R16+S16)-SUM(T16:AC16) -> 706
A17: 11 | B17: GHOSRX103510OT | C17: TIE DYE T TOP HAT | D17: GMSUK | E17: =VLOOKUP($A:$A,'COGS NEW TEMPLATE'!$A:$G,5,FALSE) -> 0 | F17: =VLOOKUP($A:$A,'COGS NEW TEMPLATE'!$A:$G,6,FALSE) -> 0 | G17: =VLOOKUP($A:$A,'COGS NEW TEMPLATE'!$A:$G,7,FALSE) -> 12.15 | H17: =SUM(E17:G17) -> 12.15 | J17: ='TIE DYE T'!$C$64 -> 2356 | K17: ='TIE DYE T'!$G$64 -> 2357 | L17: ='TIE DYE T'!$L$64 -> 0 | M17: ='TIE DYE T'!$S$64 -> 19 | N17: ='TIE DYE T'!$M$64 -> 0.016796296 | R17: ='TIE DYE T'!$V$39 -> 0 | S17: ='TIE DYE T'!$V$40 -> 2407 | T17: ='TIE DYE T'!$V$41 -> 2356 | U17: ='TIE DYE T'!$V$44 -> 0 | V17: ='TIE DYE T'!$V$42 -> 1 | W17: ='TIE DYE T'!$V$43 -> 0 | X17: ='TIE DYE T'!$V$46 -> 31 | Y17: ='TIE DYE T'!$V$47 -> 0 | Z17: ='TIE DYE T'!$V$48 -> 0 | AA17: ='TIE DYE T'!$V$49 -> 0 | AB17: ='TIE DYE T'!$V$50 -> 0 | AC17: ='TIE DYE T'!$V$51 -> 0 | AD17: ='TIE DYE T'!V$52+'TIE DYE T'!V$53 -> 19 | AE17: =(R17+S17)-SUM(T17:AC17) -> 19
A18: 12 | B18: GHOSRX103437OT | C18: CRYSTAL WASHED T AT THE GATES | D18: CULTURE DAYTONA | E18: =VLOOKUP($A:$A,'COGS NEW TEMPLATE'!$A:$G,5,FALSE) -> 0 | F18: =VLOOKUP($A:$A,'COGS NEW TEMPLATE'!$A:$G,6,FALSE) -> 0 | G18: =VLOOKUP($A:$A,'COGS NEW TEMPLATE'!$A:$G,7,FALSE) -> 8.71 | H18: =SUM(E18:G18) -> 8.71 | J18: ='CRYSTAL WASHED T'!$C$64 -> 6264 | K18: ='CRYSTAL WASHED T'!$G$64 -> 6276 | L18: ='CRYSTAL WASHED T'!$L$64 -> 0 | M18: ='CRYSTAL WASHED T'!$S$64 -> 0 | N18: ='CRYSTAL WASHED T'!$M$64 -> 0.047407407 | R18: ='CRYSTAL WASHED T'!$V$39 -> 0 | S18: ='CRYSTAL WASHED T'!$V$40 -> 6667 | T18: ='CRYSTAL WASHED T'!$V$41 -> 6264 | U18: ='CRYSTAL WASHED T'!$V$44 -> 0 | V18: ='CRYSTAL WASHED T'!$V$42 -> 5 | W18: ='CRYSTAL WASHED T'!$V$43 -> 7 | X18: ='CRYSTAL WASHED T'!$V$46 -> 58 | Y18: ='CRYSTAL WASHED T'!$V$47 -> 0 | Z18: ='CRYSTAL WASHED T'!$V$48 -> 0 | AA18: ='CRYSTAL WASHED T'!$V$49 -> 0 | AB18: ='CRYSTAL WASHED T'!$V$50 -> 333 | AC18: ='CRYSTAL WASHED T'!$V$51 -> 0 | AD18: ='CRYSTAL WASHED T'!V$52+'CRYSTAL WASHED T'!V$53 -> 0 | AE18: =(R18+S18)-SUM(T18:AC18) -> 0
A19: 13 | B19: GHOSRX203738BL | C19: OILWASHED NAVY BLUE T COME TOGETHER | D19: CULTURE DAYTONA | E19: =VLOOKUP($A:$A,'COGS NEW TEMPLATE'!$A:$G,5,FALSE) -> 0 | F19: =VLOOKUP($A:$A,'COGS NEW TEMPLATE'!$A:$G,6,FALSE) -> 0 | G19: =VLOOKUP($A:$A,'COGS NEW TEMPLATE'!$A:$G,7,FALSE) -> 11.15 | H19: =SUM(E19:G19) -> 11.15 | J19: ='OIL WASHED T'!$C$64 -> 2274 | K19: ='OIL WASHED T'!$G$64 -> 2293 | L19: ='OIL WASHED T'!$L$64 -> 0 | M19: ='OIL WASHED T'!$S$64 -> 431 | N19: ='OIL WASHED T'!$M$64 -> 0.016666667 | R19: ='OIL WASHED T'!$V$39 -> 0 | S19: ='OIL WASHED T'!$V$40 -> 2717 | T19: ='OIL WASHED T'!$V$41 -> 2274 | U19: ='OIL WASHED T'!$V$44 -> 0 | V19: ='OIL WASHED T'!$V$42 -> 15 | W19: ='OIL WASHED T'!$V$43 -> 4 | X19: ='OIL WASHED T'!$V$46 -> -7 | Y19: ='OIL WASHED T'!$V$47 -> 0 | Z19: ='OIL WASHED T'!$V$48 -> 0 | AA19: ='OIL WASHED T'!$V$49 -> 0 | AB19: ='OIL WASHED T'!$V$50 -> 0 | AC19: ='OIL WASHED T'!$V$51 -> 0 | AD19: ='OIL WASHED T'!V$52+'OIL WASHED T'!V$53 -> 431 | AE19: =(R19+S19)-SUM(T19:AC19) -> 431
A20: 14 | B20: GHOSRX203570RD | C20: SHORTS RED/WHITE LOGO | D20: CULTURE | E20: =VLOOKUP($A:$A,'COGS NEW TEMPLATE'!$A:$G,5,FALSE) -> 0 | F20: =VLOOKUP($A:$A,'COGS NEW TEMPLATE'!$A:$G,6,FALSE) -> 0 | G20: =VLOOKUP($A:$A,'COGS NEW TEMPLATE'!$A:$G,7,FALSE) -> 12.19 | H20: =SUM(E20:G20) -> 12.19 | J20: ='SHORTS RED'!$C$64 -> 566 | K20: ='SHORTS RED'!$G$64 -> 566 | L20: ='SHORTS RED'!$L$64 -> 0 | M20: ='SHORTS RED'!$S$64 -> 0 | N20: ='SHORTS RED'!$M$64 -> 0.0037037037 | R20: ='SHORTS RED'!$V$39 -> 0 | S20: ='SHORTS RED'!$V$40 -> 574 | T20: ='SHORTS RED'!$V$41 -> 566 | U20: ='SHORTS RED'!$V$44 -> 0 | V20: ='SHORTS RED'!$V$42 -> 0 | W20: ='SHORTS RED'!$V$43 -> 0 | X20: ='SHORTS RED'!$V$46 -> 8 | Y20: ='SHORTS RED'!$V$47 -> 0 | Z20: ='SHORTS RED'!$V$48 -> 0 | AA20: ='SHORTS RED'!$V$49 -> 0 | AB20: ='SHORTS RED'!$V$50 -> 0 | AC20: ='SHORTS RED'!$V$51 -> 0 | AD20: ='SHORTS RED'!V$52+'SHORTS RED'!V$53 -> 0 | AE20: =(R20+S20)-SUM(T20:AC20) -> 0
A21: 15 | B21: GHOSRX203800BK | C21: EVENT T TAMPA | D21: CULTURE DAYTONA | E21: =VLOOKUP($A:$A,'COGS NEW TEMPLATE'!$A:$G,5,FALSE) -> 0 | F21: =VLOOKUP($A:$A,'COGS NEW TEMPLATE'!$A:$G,6,FALSE) -> 0 | G21: =VLOOKUP($A:$A,'COGS NEW TEMPLATE'!$A:$G,7,FALSE) -> 6.2 | H21: =SUM(E21:G21) -> 6.2 | J21: =TAMPA!$C$64 -> 776 | K21: =TAMPA!$G$64 -> 788 | L21: =TAMPA!$L$64 -> 0 | M21: =TAMPA!$S$64 -> 0 | N21: =TAMPA!$M$64 -> 0.0044444444 | R21: =TAMPA!$V$39 -> 0 | S21: =TAMPA!$V$40 -> 788 | T21: =TAMPA!$V$41 -> 776 | U21: =TAMPA!$V$44 -> 0 | V21: =TAMPA!$V$42 -> 12 | W21: =TAMPA!$V$43 -> 0 | X21: =TAMPA!$V$46 -> 0 | Y21: =TAMPA!$V$47 -> 0 | Z21: =TAMPA!$V$48 -> 0 | AA21: =TAMPA!$V$49 -> 0 | AB21: =TAMPA!$V$50 -> 0 | AC21: =TAMPA!$V$51 -> 0 | AD21: =TAMPA!V$52+TAMPA!V$53 -> 0 | AE21: =(R21+S21)-SUM(T21:AC21) -> 0
A22: 16 | B22: GHOSRX203799BK | C22: EVENT T PHILLY | D22: CULTURE | E22: =VLOOKUP($A:$A,'COGS NEW TEMPLATE'!$A:$G,5,FALSE) -> 0 | F22: =VLOOKUP($A:$A,'COGS NEW TEMPLATE'!$A:$G,6,FALSE) -> 0 | G22: =VLOOKUP($A:$A,'COGS NEW TEMPLATE'!$A:$G,7,FALSE) -> 5.7 | H22: =SUM(E22:G22) -> 5.7 | J22: =PHILLY!$C$64 -> 973 | K22: =PHILLY!$G$64 -> 982 | L22: =PHILLY!$L$64 -> 0 | M22: =PHILLY!$S$64 -> 0 | N22: =PHILLY!$M$64 -> 0.0048148148 | R22: =PHILLY!$V$39 -> 0 | S22: =PHILLY!$V$40 -> 1087 | T22: =PHILLY!$V$41 -> 973 | U22: =PHILLY!$V$44 -> 0 | V22: =PHILLY!$V$42 -> 9 | W22: =PHILLY!$V$43 -> 0 | X22: =PHILLY!$V$46 -> 0 | Y22: =PHILLY!$V$47 -> 0 | Z22: =PHILLY!$V$48 -> 96 | AA22: =PHILLY!$V$49 -> 0 | AB22: =PHILLY!$V$50 -> 0 | AC22: =PHILLY!$V$51 -> 0 | AD22: =PHILLY!V$52+PHILLY!V$53 -> 9 | AE22: =(R22+S22)-SUM(T22:AC22) -> 9
A23: 17 | B23: GHOSRX203798BK | C23: EVENT T BOSTON | D23: CULTURE | E23: =VLOOKUP($A:$A,'COGS NEW TEMPLATE'!$A:$G,5,FALSE) -> 0 | F23: =VLOOKUP($A:$A,'COGS NEW TEMPLATE'!$A:$G,6,FALSE) -> 0 | G23: =VLOOKUP($A:$A,'COGS NEW TEMPLATE'!$A:$G,7,FALSE) -> 5.7 | H23: =SUM(E23:G23) -> 5.7 | J23: =BOSTON!$C$64 -> 897 | K23: =BOSTON!$G$64 -> 906 | L23: =BOSTON!$L$64 -> 0 | M23: =BOSTON!$S$64 -> 0 | N23: =BOSTON!$M$64 -> 0.0048148148 | R23: =BOSTON!$V$39 -> 0 | S23: =BOSTON!$V$40 -> 1088 | T23: =BOSTON!$V$41 -> 897 | U23: =BOSTON!$V$44 -> 0 | V23: =BOSTON!$V$42 -> 9 | W23: =BOSTON!$V$43 -> 0 | X23: =BOSTON!$V$46 -> 0 | Y23: =BOSTON!$V$47 -> 0 | Z23: =BOSTON!$V$48 -> 173 | AA23: =BOSTON!$V$49 -> 0 | AB23: =BOSTON!$V$50 -> 0 | AC23: =BOSTON!$V$51 -> 0 | AD23: =BOSTON!V$52+BOSTON!V$53 -> 9 | AE23: =(R23+S23)-SUM(T23:AC23) -> 9
A24: 18 | B24: GHOSRX203801BK | C24: EVENT T NEW YORK | D24: CULTURE | E24: =VLOOKUP($A:$A,'COGS NEW TEMPLATE'!$A:$G,5,FALSE) -> 0 | F24: =VLOOKUP($A:$A,'COGS NEW TEMPLATE'!$A:$G,6,FALSE) -> 0 | G24: =VLOOKUP($A:$A,'COGS NEW TEMPLATE'!$A:$G,7,FALSE) -> 5.7 | H24: =SUM(E24:G24) -> 5.7 | J24: ='NEW YORK'!$C$64 -> 1409 | K24: ='NEW YORK'!$G$64 -> 1433 | L24: ='NEW YORK'!$L$64 -> 0 | M24: ='NEW YORK'!$S$64 -> 0 | N24: ='NEW YORK'!$M$64 -> 0.0066666667 | R24: ='NEW YORK'!$V$39 -> 0 | S24: ='NEW YORK'!$V$40 -> 1440 | T24: ='NEW YORK'!$V$41 -> 1409 | U24: ='NEW YORK'!$V$44 -> 0 | V24: ='NEW YORK'!$V$42 -> 21 | W24: ='NEW YORK'!$V$43 -> 3 | X24: ='NEW YORK'!$V$46 -> 7 | Y24: ='NEW YORK'!$V$47 -> 0 | Z24: ='NEW YORK'!$V$48 -> 0 | AA24: ='NEW YORK'!$V$49 -> 0 | AB24: ='NEW YORK'!$V$50 -> 0 | AC24: ='NEW YORK'!$V$51 -> 0 | AD24: ='NEW YORK'!V$52+'NEW YORK'!V$53 -> 0 | AE24: =(R24+S24)-SUM(T24:AC24) -> 0
A25: 19 | B25: GHOSRX203822BK | C25: EVENT T CHICAGO | D25: CULTURE | E25: =VLOOKUP($A:$A,'COGS NEW TEMPLATE'!$A:$G,5,FALSE) -> 0 | F25: =VLOOKUP($A:$A,'COGS NEW TEMPLATE'!$A:$G,6,FALSE) -> 0 | G25: =VLOOKUP($A:$A,'COGS NEW TEMPLATE'!$A:$G,7,FALSE) -> 5.7 | H25: =SUM(E25:G25) -> 5.7 | J25: =CHICAGO!$C$64 -> 690 | K25: =CHICAGO!$G$64 -> 699 | L25: =CHICAGO!$L$64 -> 0 | M25: =CHICAGO!$S$64 -> 0 | N25: =CHICAGO!$M$64 -> 0.0040740741 | R25: =CHICAGO!$V$39 -> 0 | S25: =CHICAGO!$V$40 -> 1062 | T25: =CHICAGO!$V$41 -> 690 | U25: =CHICAGO!$V$44 -> 0 | V25: =CHICAGO!$V$42 -> 9 | W25: =CHICAGO!$V$43 -> 0 | X25: =CHICAGO!$V$46 -> 0 | Y25: =CHICAGO!$V$47 -> 0 | Z25: =CHICAGO!$V$48 -> 363 | AA25: =CHICAGO!$V$49 -> 0 | AB25: =CHICAGO!$V$50 -> 0 | AC25: =CHICAGO!$V$51 -> 0 | AD25: =CHICAGO!V$52+CHICAGO!V$53 -> 0 | AE25: =(R25+S25)-SUM(T25:AC25) -> 0
A26: 20 | E26: =VLOOKUP($A:$A,'COGS NEW TEMPLATE'!$A:$G,5,FALSE) -> 0 | F26: =VLOOKUP($A:$A,'COGS NEW TEMPLATE'!$A:$G,6,FALSE) -> 0 | G26: =VLOOKUP($A:$A,'COGS NEW TEMPLATE'!$A:$G,7,FALSE) -> 0 | H26: =SUM(E26:G26) -> 0 | J26: ='20'!$C$64 -> 0 | K26: ='20'!$G$64 -> 0 | L26: ='20'!$L$64 -> 0 | M26: ='20'!$S$64 -> 0 | N26: ='20'!$M$64 -> 0 | R26: ='20'!$V$39 -> 0 | S26: ='20'!$V$40 -> 0 | T26: ='20'!$V$41 -> 0 | U26: ='20'!$V$44 -> 0 | V26: ='20'!$V$42 -> 0 | W26: ='20'!$V$43 -> 0 | X26: ='20'!$V$46 -> 0 | Y26: ='20'!$V$47 -> 0 | Z26: ='20'!$V$48 -> 0 | AA26: ='20'!$V$49 -> 0 | AB26: ='20'!$V$50 -> 0 | AC26: ='20'!$V$51 -> 0 | AD26: ='20'!V$52+'20'!V$53 -> 0 | AE26: =(R26+S26)-SUM(T26:AC26) -> 0
A27: 21 | J27: ='21'!$C$64 -> 0 | K27: ='21'!$G$64 -> 0 | L27: ='21'!$L$64 -> 0 | M27: ='21'!$S$64 -> 0 | N27: ='21'!$M$64 -> 0 | R27: ='21'!$V$39 -> 0 | S27: ='21'!$V$40 -> 0 | T27: ='21'!$V$41 -> 0 | U27: ='21'!$V$44 -> 0 | V27: ='21'!$V$42 -> 0 | W27: ='21'!$V$43 -> 0 | X27: ='21'!$V$46 -> 0 | Y27: ='21'!$V$47 -> 0 | Z27: ='21'!$V$48 -> 0 | AA27: ='21'!$V$49 -> 0 | AB27: ='21'!$V$50 -> 0 | AC27: ='21'!$V$51 -> 0 | AD27: ='21'!V$52+'21'!V$53 -> 0 | AE27: =(R27+S27)-SUM(T27:AC27) -> 0
A28: 22 | B28: GHOSNS103665BK | C28: HAT SATANIC PANIC | D28: WELLSUCCEED | E28: =VLOOKUP($A:$A,'COGS NEW TEMPLATE'!$A:$G,5,FALSE) -> 3.92 | F28: =VLOOKUP($A:$A,'COGS NEW TEMPLATE'!$A:$G,6,FALSE) -> 0 | G28: =VLOOKUP($A:$A,'COGS NEW TEMPLATE'!$A:$G,7,FALSE) -> 0 | H28: =SUM(E28:G28) -> 3.92 | J28: =HAT!$C$64 -> 1212 | K28: =HAT!$G$64 -> 1215 | L28: =HAT!$L$64 -> 0 | M28: =HAT!$S$64 -> 0 | N28: =HAT!$M$64 -> 0.0055925926 | R28: =HAT!$V$39 -> 1215 | S28: =HAT!$V$40 -> 0 | T28: =HAT!$V$41 -> 1212 | U28: =HAT!$V$44 -> 0 | V28: =HAT!$V$42 -> 3 | W28: =HAT!$V$43 -> 0 | X28: =HAT!$V$46 -> 0 | Y28: =HAT!$V$47 -> 0 | Z28: =HAT!$V$48 -> 0 | AA28: =HAT!$V$49 -> 0 | AB28: =HAT!$V$50 -> 0 | AC28: =HAT!$V$51 -> 0 | AD28: =HAT!V$52+HAT!V$53 -> 0 | AE28: =(R28+S28)-SUM(T28:AC28) -> 0
A29: 23 | B29: GHOSNS903309GR | C29: MASK BURNT GHOUL | D29: FARSTAR | E29: =VLOOKUP($A:$A,'COGS NEW TEMPLATE'!$A:$G,5,FALSE) -> 4.8 | F29: =VLOOKUP($A:$A,'COGS NEW TEMPLATE'!$A:$G,6,FALSE) -> 0 | G29: =VLOOKUP($A:$A,'COGS NEW TEMPLATE'!$A:$G,7,FALSE) -> 0 | H29: =SUM(E29:G29) -> 4.8 | J29: =MASK!$C$64 -> 3857 | K29: =MASK!$G$64 -> 3861 | L29: =MASK!$L$64 -> 0 | M29: =MASK!$S$64 -> 0 | N29: =MASK!$M$64 -> 0.020740741 | R29: =MASK!$V$39 -> 0 | S29: =MASK!$V$40 -> 4060 | T29: =MASK!$V$41 -> 3857 | U29: =MASK!$V$44 -> 2 | V29: =MASK!$V$42 -> 2 | W29: =MASK!$V$43 -> 0 | X29: =MASK!$V$46 -> 0 | Y29: =MASK!$V$47 -> 0 | Z29: =MASK!$V$48 -> 0 | AA29: =MASK!$V$49 -> 0 | AB29: =MASK!$V$50 -> 199 | AC29: =MASK!$V$51 -> 0 | AD29: =MASK!V$52+MASK!V$53 -> 0 | AE29: =(R29+S29)-SUM(T29:AC29) -> 0
A30: 24 | B30: GHOSNS903279OT | C30: PLUSHIE FRATER IMPERATOR | D30: FARSTAR | E30: =VLOOKUP($A:$A,'COGS NEW TEMPLATE'!$A:$G,5,FALSE) -> 8.9 | F30: =VLOOKUP($A:$A,'COGS NEW TEMPLATE'!$A:$G,6,FALSE) -> 0 | G30: =VLOOKUP($A:$A,'COGS NEW TEMPLATE'!$A:$G,7,FALSE) -> 0 | H30: =SUM(E30:G30) -> 8.9 | J30: =PLUSHIE!$C$64 -> 11108 | K30: =PLUSHIE!$G$64 -> 11118 | L30: =PLUSHIE!$L$64 -> 0 | M30: =PLUSHIE!$S$64 -> 0 | N30: =PLUSHIE!$M$64 -> 0.068888889 | R30: =PLUSHIE!$V$39 -> 0 | S30: =PLUSHIE!$V$40 -> 15998 | T30: =PLUSHIE!$V$41 -> 11108 | U30: =PLUSHIE!$V$44 -> 0 | V30: =PLUSHIE!$V$42 -> 10 | W30: =PLUSHIE!$V$43 -> 0 | X30: =PLUSHIE!$V$46 -> 0 | Y30: =PLUSHIE!$V$47 -> 0 | Z30: =PLUSHIE!$V$48 -> 0 | AA30: =PLUSHIE!$V$49 -> 0 | AB30: =PLUSHIE!$V$50 -> 1640 | AC30: =PLUSHIE!$V$51 -> 0 | AD30: =PLUSHIE!V$52+PLUSHIE!V$53 -> 3240 | AE30: =(R30+S30)-SUM(T30:AC30) -> 3240
A31: 25 | B31: GHOSRX103259OT | C31: CLEAR SLING BAG-SILVER LOGO | D31: FARSTAR | E31: =VLOOKUP($A:$A,'COGS NEW TEMPLATE'!$A:$G,5,FALSE) -> 3.8 | F31: =VLOOKUP($A:$A,'COGS NEW TEMPLATE'!$A:$G,6,FALSE) -> 0 | G31: =VLOOKUP($A:$A,'COGS NEW TEMPLATE'!$A:$G,7,FALSE) -> 0 | H31: =SUM(E31:G31) -> 3.8 | J31: ='CLEAR SLING BAG'!$C$64 -> 1373 | K31: ='CLEAR SLING BAG'!$G$64 -> 1380 | L31: ='CLEAR SLING BAG'!$L$64 -> 0 | M31: ='CLEAR SLING BAG'!$S$64 -> 1522 | N31: ='CLEAR SLING BAG'!$M$64 -> 0.0088888889 | R31: ='CLEAR SLING BAG'!$V$39 -> 0 | S31: ='CLEAR SLING BAG'!$V$40 -> 3319 | T31: ='CLEAR SLING BAG'!$V$41 -> 1373 | U31: ='CLEAR SLING BAG'!$V$44 -> 1 | V31: ='CLEAR SLING BAG'!$V$42 -> 6 | W31: ='CLEAR SLING BAG'!$V$43 -> 0 | X31: ='CLEAR SLING BAG'!$V$46 -> -83 | Y31: ='CLEAR SLING BAG'!$V$47 -> 0 | Z31: ='CLEAR SLING BAG'!$V$48 -> 300 | AA31: ='CLEAR SLING BAG'!$V$49 -> 0 | AB31: ='CLEAR SLING BAG'!$V$50 -> 200 | AC31: ='CLEAR SLING BAG'!$V$51 -> 0 | AD31: ='CLEAR SLING BAG'!V$52+'CLEAR SLING BAG'!V$53 -> 1522 | AE31: =(R31+S31)-SUM(T31:AC31) -> 1522
A32: 26 | B32: GHOSRX103241BK | C32: CHOKER PAPA V | D32: FARSTAR | E32: =VLOOKUP($A:$A,'COGS NEW TEMPLATE'!$A:$G,5,FALSE) -> 3.6 | F32: =VLOOKUP($A:$A,'COGS NEW TEMPLATE'!$A:$G,6,FALSE) -> 0 | G32: =VLOOKUP($A:$A,'COGS NEW TEMPLATE'!$A:$G,7,FALSE) -> 0 | H32: =SUM(E32:G32) -> 3.6 | J32: =CHOKER!$C$64 -> 2043 | K32: =CHOKER!$G$64 -> 2048 | L32: =CHOKER!$L$64 -> 0 | M32: =CHOKER!$S$64 -> 1511 | N32: =CHOKER!$M$64 -> 0.0096296296 | R32: =CHOKER!$V$39 -> 0 | S32: =CHOKER!$V$40 -> 3859 | T32: =CHOKER!$V$41 -> 2043 | U32: =CHOKER!$V$44 -> 0 | V32: =CHOKER!$V$42 -> 4 | W32: =CHOKER!$V$43 -> 1 | X32: =CHOKER!$V$46 -> 0 | Y32: =CHOKER!$V$47 -> 0 | Z32: =CHOKER!$V$48 -> 0 | AA32: =CHOKER!$V$49 -> 0 | AB32: =CHOKER!$V$50 -> 300 | AC32: =CHOKER!$V$51 -> 0 | AD32: =CHOKER!V$52+CHOKER!V$53 -> 1511 | AE32: =(R32+S32)-SUM(T32:AC32) -> 1511
A33: 27 | B33: GHOSRX203254GR | C33: KEYCHAIN SKELETON GRUCIFIX | D33: FARSTAR | E33: =VLOOKUP($A:$A,'COGS NEW TEMPLATE'!$A:$G,5,FALSE) -> 1.5 | F33: =VLOOKUP($A:$A,'COGS NEW TEMPLATE'!$A:$G,6,FALSE) -> 0 | G33: =VLOOKUP($A:$A,'COGS NEW TEMPLATE'!$A:$G,7,FALSE) -> 0 | H33: =SUM(E33:G33) -> 1.5 | J33: =KEYCHAIN!$C$64 -> 7144 | K33: =KEYCHAIN!$G$64 -> 7154 | L33: =KEYCHAIN!$L$64 -> 0 | M33: =KEYCHAIN!$S$64 -> 2629 | N33: =KEYCHAIN!$M$64 -> 0.014444444 | R33: =KEYCHAIN!$V$39 -> 0 | S33: =KEYCHAIN!$V$40 -> 10483 | T33: =KEYCHAIN!$V$41 -> 7144 | U33: =KEYCHAIN!$V$44 -> 0 | V33: =KEYCHAIN!$V$42 -> 5 | W33: =KEYCHAIN!$V$43 -> 5 | X33: =KEYCHAIN!$V$46 -> 100 | Y33: =KEYCHAIN!$V$47 -> 0 | Z33: =KEYCHAIN!$V$48 -> 0 | AA33: =KEYCHAIN!$V$49 -> 0 | AB33: =KEYCHAIN!$V$50 -> 600 | AC33: =KEYCHAIN!$V$51 -> 0 | AD33: =KEYCHAIN!V$52+KEYCHAIN!V$53 -> 2629 | AE33: =(R33+S33)-SUM(T33:AC33) -> 2629
A34: 28 | B34: GHOSRX903403OT | C34: PATCH SET OF 3 | D34: WELLSUCCEED | E34: =VLOOKUP($A:$A,'COGS NEW TEMPLATE'!$A:$G,5,FALSE) -> 2.05 | F34: =VLOOKUP($A:$A,'COGS NEW TEMPLATE'!$A:$G,6,FALSE) -> 0 | G34: =VLOOKUP($A:$A,'COGS NEW TEMPLATE'!$A:$G,7,FALSE) -> 0 | H34: =SUM(E34:G34) -> 2.05 | J34: ='PATCH SET'!$C$64 -> 4925 | K34: ='PATCH SET'!$G$64 -> 4931 | L34: ='PATCH SET'!$L$64 -> 0 | M34: ='PATCH SET'!$S$64 -> 1479 | N34: ='PATCH SET'!$M$64 -> 0.011851852 | R34: ='PATCH SET'!$V$39 -> 0 | S34: ='PATCH SET'!$V$40 -> 6910 | T34: ='PATCH SET'!$V$41 -> 4925 | U34: ='PATCH SET'!$V$44 -> 0 | V34: ='PATCH SET'!$V$42 -> 5 | W34: ='PATCH SET'!$V$43 -> 1 | X34: ='PATCH SET'!$V$46 -> 0 | Y34: ='PATCH SET'!$V$47 -> 0 | Z34: ='PATCH SET'!$V$48 -> 0 | AA34: ='PATCH SET'!$V$49 -> 0 | AB34: ='PATCH SET'!$V$50 -> 500 | AC34: ='PATCH SET'!$V$51 -> 0 | AD34: ='PATCH SET'!V$52+'PATCH SET'!V$53 -> 1479 | AE34: =(R34+S34)-SUM(T34:AC34) -> 1479
A35: 29 | B35: GHOSNS103814BK | C35: TOUR PROGRAM | D35: VANDALAY | E35: =VLOOKUP($A:$A,'COGS NEW TEMPLATE'!$A:$G,5,FALSE) -> 5.59 | F35: =VLOOKUP($A:$A,'COGS NEW TEMPLATE'!$A:$G,6,FALSE) -> 0 | G35: =VLOOKUP($A:$A,'COGS NEW TEMPLATE'!$A:$G,7,FALSE) -> 0 | H35: =SUM(E35:G35) -> 5.59 | J35: ='TOUR PROGRAM'!$C$64 -> 989 | K35: ='TOUR PROGRAM'!$G$64 -> 1118 | L35: ='TOUR PROGRAM'!$L$64 -> 0 | M35: ='TOUR PROGRAM'!$S$64 -> 2230 | N35: ='TOUR PROGRAM'!$M$64 -> 0.0035 | R35: ='TOUR PROGRAM'!$V$39 -> 0 | S35: ='TOUR PROGRAM'!$V$40 -> 5415 | T35: ='TOUR PROGRAM'!$V$41 -> 989 | U35: ='TOUR PROGRAM'!$V$44 -> 0 | V35: ='TOUR PROGRAM'!$V$42 -> 126 | W35: ='TOUR PROGRAM'!$V$43 -> 3 | X35: ='TOUR PROGRAM'!$V$46 -> 2 | Y35: ='TOUR PROGRAM'!$V$47 -> 0 | Z35: ='TOUR PROGRAM'!$V$48 -> 1015 | AA35: ='TOUR PROGRAM'!$V$49 -> 0 | AB35: ='TOUR PROGRAM'!$V$50 -> 1050 | AC35: ='TOUR PROGRAM'!$V$51 -> 0 | AD35: ='TOUR PROGRAM'!V$52+'TOUR PROGRAM'!V$53 -> 2230 | AE35: =(R35+S35)-SUM(T35:AC35) -> 2230
A36: 30 | B36: GHOSRX903408OT | C36: LP SKELETA POLTERGEIST | D36: CONCORD | E36: =VLOOKUP($A:$A,'COGS NEW TEMPLATE'!$A:$G,5,FALSE) -> 16.89 | F36: =VLOOKUP($A:$A,'COGS NEW TEMPLATE'!$A:$G,6,FALSE) -> 0 | G36: =VLOOKUP($A:$A,'COGS NEW TEMPLATE'!$A:$G,7,FALSE) -> 0 | H36: =SUM(E36:G36) -> 16.89 | J36: ='LP SKELETA POLTER'!$C$64 -> 1519 | K36: ='LP SKELETA POLTER'!$G$64 -> 1520 | L36: ='LP SKELETA POLTER'!$L$64 -> 0 | M36: ='LP SKELETA POLTER'!$S$64 -> 330 | N36: ='LP SKELETA POLTER'!$M$64 -> 0.0098148148 | R36: ='LP SKELETA POLTER'!$V$39 -> 0 | S36: ='LP SKELETA POLTER'!$V$40 -> 2000 | T36: ='LP SKELETA POLTER'!$V$41 -> 1519 | U36: ='LP SKELETA POLTER'!$V$44 -> 0 | V36: ='LP SKELETA POLTER'!$V$42 -> 0 | W36: ='LP SKELETA POLTER'!$V$43 -> 1 | X36: ='LP SKELETA POLTER'!$V$46 -> 0 | Y36: ='LP SKELETA POLTER'!$V$47 -> 0 | Z36: ='LP SKELETA POLTER'!$V$48 -> 0 | AA36: ='LP SKELETA POLTER'!$V$49 -> 0 | AB36: ='LP SKELETA POLTER'!$V$50 -> 150 | AC36: ='LP SKELETA POLTER'!$V$51 -> 0 | AD36: ='LP SKELETA POLTER'!V$52+'LP SKELETA POLTER'!V$53 -> 330 | AE36: =(R36+S36)-SUM(T36:AC36) -> 330
A37: 31 | B37: GHOSNS203369OT | C37: FOILED COMIC BOOK SISTER IMPERATOR # 1 | D37: DARK HORSE COMICS | E37: =VLOOKUP($A:$A,'COGS NEW TEMPLATE'!$A:$G,5,FALSE) -> 4.25 | F37: =VLOOKUP($A:$A,'COGS NEW TEMPLATE'!$A:$G,6,FALSE) -> 0 | G37: =VLOOKUP($A:$A,'COGS NEW TEMPLATE'!$A:$G,7,FALSE) -> 0 | H37: =SUM(E37:G37) -> 4.25 | J37: ='COMIC BOOK #1'!$C$64 -> 1303 | K37: ='COMIC BOOK #1'!$G$64 -> 1305 | L37: ='COMIC BOOK #1'!$L$64 -> 0 | M37: ='COMIC BOOK #1'!$S$64 -> 1195 | N37: ='COMIC BOOK #1'!$M$64 -> 0.0071296296 | R37: ='COMIC BOOK #1'!$V$39 -> 0 | S37: ='COMIC BOOK #1'!$V$40 -> 2500 | T37: ='COMIC BOOK #1'!$V$41 -> 1303 | U37: ='COMIC BOOK #1'!$V$44 -> 1 | V37: ='COMIC BOOK #1'!$V$42 -> 0 | W37: ='COMIC BOOK #1'!$V$43 -> 1 | X37: ='COMIC BOOK #1'!$V$46 -> 0 | Y37: ='COMIC BOOK #1'!$V$47 -> 0 | Z37: ='COMIC BOOK #1'!$V$48 -> 0 | AA37: ='COMIC BOOK #1'!$V$49 -> 0 | AB37: ='COMIC BOOK #1'!$V$50 -> 0 | AC37: ='COMIC BOOK #1'!$V$51 -> 0 | AD37: ='COMIC BOOK #1'!V$52+'COMIC BOOK #1'!V$53 -> 1195 | AE37: =(R37+S37)-SUM(T37:AC37) -> 1195
A38: 32 | B38: GHOSNS203533OT | C38: COMIC BOOK SISTER IMPERATOR #2 | D38: DARK HORSE COMICS | E38: =VLOOKUP($A:$A,'COGS NEW TEMPLATE'!$A:$G,5,FALSE) -> 2 | F38: =VLOOKUP($A:$A,'COGS NEW TEMPLATE'!$A:$G,6,FALSE) -> 0 | G38: =VLOOKUP($A:$A,'COGS NEW TEMPLATE'!$A:$G,7,FALSE) -> 0 | H38: =SUM(E38:G38) -> 2 | J38: ='COMIC BOOK #2'!$C$64 -> 301 | K38: ='COMIC BOOK #2'!$G$64 -> 301 | L38: ='COMIC BOOK #2'!$L$64 -> 0 | M38: ='COMIC BOOK #2'!$S$64 -> 0 | N38: ='COMIC BOOK #2'!$M$64 -> 0.0015185185 | R38: ='COMIC BOOK #2'!$V$39 -> 0 | S38: ='COMIC BOOK #2'!$V$40 -> 300 | T38: ='COMIC BOOK #2'!$V$41 -> 301 | U38: ='COMIC BOOK #2'!$V$44 -> 0 | V38: ='COMIC BOOK #2'!$V$42 -> 0 | W38: ='COMIC BOOK #2'!$V$43 -> 0 | X38: ='COMIC BOOK #2'!$V$46 -> -1 | Y38: ='COMIC BOOK #2'!$V$47 -> 0 | Z38: ='COMIC BOOK #2'!$V$48 -> 0 | AA38: ='COMIC BOOK #2'!$V$49 -> 0 | AB38: ='COMIC BOOK #2'!$V$50 -> 0 | AC38: ='COMIC BOOK #2'!$V$51 -> 0 | AD38: ='COMIC BOOK #2'!V$52+'COMIC BOOK #2'!V$53 -> 0 | AE38: =(R38+S38)-SUM(T38:AC38) -> 0
A39: 33 | B39: GHOSNS203534OT | C39: COMIC BOOK SISTER IMPERATOR #3 | D39: DARK HORSE COMICS | E39: =VLOOKUP($A:$A,'COGS NEW TEMPLATE'!$A:$G,5,FALSE) -> 2 | F39: =VLOOKUP($A:$A,'COGS NEW TEMPLATE'!$A:$G,6,FALSE) -> 0 | G39: =VLOOKUP($A:$A,'COGS NEW TEMPLATE'!$A:$G,7,FALSE) -> 0 | H39: =SUM(E39:G39) -> 2 | J39: ='COMIC BOOK #3'!$C$64 -> 299 | K39: ='COMIC BOOK #3'!$G$64 -> 299 | L39: ='COMIC BOOK #3'!$L$64 -> 0 | M39: ='COMIC BOOK #3'!$S$64 -> 0 | N39: ='COMIC BOOK #3'!$M$64 -> 0.0010555556 | R39: ='COMIC BOOK #3'!$V$39 -> 0 | S39: ='COMIC BOOK #3'!$V$40 -> 300 | T39: ='COMIC BOOK #3'!$V$41 -> 299 | U39: ='COMIC BOOK #3'!$V$44 -> 0 | V39: ='COMIC BOOK #3'!$V$42 -> 0 | W39: ='COMIC BOOK #3'!$V$43 -> 0 | X39: ='COMIC BOOK #3'!$V$46 -> 1 | Y39: ='COMIC BOOK #3'!$V$47 -> 0 | Z39: ='COMIC BOOK #3'!$V$48 -> 0 | AA39: ='COMIC BOOK #3'!$V$49 -> 0 | AB39: ='COMIC BOOK #3'!$V$50 -> 0 | AC39: ='COMIC BOOK #3'!$V$51 -> 0 | AD39: ='COMIC BOOK #3'!V$52+'COMIC BOOK #3'!V$53 -> 0 | AE39: =(R39+S39)-SUM(T39:AC39) -> 0
A40: 34 | B40: GHOSNS203535OT | C40: COMIC BOOK SISTER IMPERATOR #4 | D40: DARK HORSE COMICS | E40: =VLOOKUP($A:$A,'COGS NEW TEMPLATE'!$A:$G,5,FALSE) -> 2 | F40: =VLOOKUP($A:$A,'COGS NEW TEMPLATE'!$A:$G,6,FALSE) -> 0 | G40: =VLOOKUP($A:$A,'COGS NEW TEMPLATE'!$A:$G,7,FALSE) -> 0 | H40: =SUM(E40:G40) -> 2 | J40: ='COMIC BOOK #4'!$C$64 -> 297 | K40: ='COMIC BOOK #4'!$G$64 -> 297 | L40: ='COMIC BOOK #4'!$L$64 -> 0 | M40: ='COMIC BOOK #4'!$S$64 -> 0 | N40: ='COMIC BOOK #4'!$M$64 -> 0.0011685185 | R40: ='COMIC BOOK #4'!$V$39 -> 0 | S40: ='COMIC BOOK #4'!$V$40 -> 300 | T40: ='COMIC BOOK #4'!$V$41 -> 297 | U40: ='COMIC BOOK #4'!$V$44 -> 0 | V40: ='COMIC BOOK #4'!$V$42 -> 0 | W40: ='COMIC BOOK #4'!$V$43 -> 0 | X40: ='COMIC BOOK #4'!$V$46 -> 3 | Y40: ='COMIC BOOK #4'!$V$47 -> 0 | Z40: ='COMIC BOOK #4'!$V$48 -> 0 | AA40: ='COMIC BOOK #4'!$V$49 -> 0 | AB40: ='COMIC BOOK #4'!$V$50 -> 0 | AC40: ='COMIC BOOK #4'!$V$51 -> 0 | AD40: ='COMIC BOOK #4'!V$52+'COMIC BOOK #4'!V$53 -> 0 | AE40: =(R40+S40)-SUM(T40:AC40) -> 0
A41: 35 | E41: =VLOOKUP($A:$A,'COGS NEW TEMPLATE'!$A:$G,5,FALSE) -> 0 | F41: =VLOOKUP($A:$A,'COGS NEW TEMPLATE'!$A:$G,6,FALSE) -> 0 | G41: =VLOOKUP($A:$A,'COGS NEW TEMPLATE'!$A:$G,7,FALSE) -> 0 | H41: =SUM(E41:G41) -> 0 | J41: ='35'!$C$64 -> 0 | K41: ='35'!$G$64 -> 0 | L41: ='35'!$L$64 -> 0 | M41: ='35'!$S$64 -> 0 | N41: ='35'!$M$64 -> 0 | R41: ='35'!$V$39 -> 0 | S41: ='35'!$V$40 -> 0 | T41: ='35'!$V$41 -> 0 | U41: ='35'!$V$44 -> 0 | V41: ='35'!$V$42 -> 0 | W41: ='35'!$V$43 -> 0 | X41: ='35'!$V$46 -> 0 | Y41: ='35'!$V$47 -> 0 | Z41: ='35'!$V$48 -> 0 | AA41: ='35'!$V$49 -> 0 | AB41: ='35'!$V$50 -> 0 | AC41: ='35'!$V$51 -> 0 | AD41: ='35'!V$52+'35'!V$53 -> 0 | AE41: =(R41+S41)-SUM(T41:AC41) -> 0
A42: 36 | B42: GHOSNS103619OT | C42: FOILED COMIC BOOK SISTER IMPERATOR #2 | D42: DARK HORSE COMICS | E42: =VLOOKUP($A:$A,'COGS NEW TEMPLATE'!$A:$G,5,FALSE) -> 4.05 | F42: =VLOOKUP($A:$A,'COGS NEW TEMPLATE'!$A:$G,6,FALSE) -> 0 | G42: =VLOOKUP($A:$A,'COGS NEW TEMPLATE'!$A:$G,7,FALSE) -> 0 | H42: =SUM(E42:G42) -> 4.05 | J42: ='FOILED COMIC BOOK #2'!$C$64 -> 643 | K42: ='FOILED COMIC BOOK #2'!$G$64 -> 645 | L42: ='FOILED COMIC BOOK #2'!$L$64 -> 0 | M42: ='FOILED COMIC BOOK #2'!$S$64 -> 164 | N42: ='FOILED COMIC BOOK #2'!$M$64 -> 0.0024074074 | R42: ='FOILED COMIC BOOK #2'!$V$39 -> 0 | S42: ='FOILED COMIC BOOK #2'!$V$40 -> 0 | T42: ='FOILED COMIC BOOK #2'!$V$41 -> 643 | U42: ='FOILED COMIC BOOK #2'!$V$44 -> 1 | V42: ='FOILED COMIC BOOK #2'!$V$42 -> 0 | W42: ='FOILED COMIC BOOK #2'!$V$43 -> 1 | X42: ='FOILED COMIC BOOK #2'!$V$46 -> 11 | Y42: ='FOILED COMIC BOOK #2'!$V$47 -> 0 | Z42: ='FOILED COMIC BOOK #2'!$V$48 -> 0 | AA42: ='FOILED COMIC BOOK #2'!$V$49 -> 0 | AB42: ='FOILED COMIC BOOK #2'!$V$50 -> 180 | AC42: ='FOILED COMIC BOOK #2'!$V$51 -> 0 | AD42: ='FOILED COMIC BOOK #2'!V$52+'FOILED COMIC BOOK #2'!V$53 -> -836 | AE42: =(R42+S42)-SUM(T42:AC42) -> -836
A43: 37 | B43: GHOSNS103622OT | C43: FOILED COMIC BOOK SISTER IMPERATOR #3 | D43: DARK HORSE COMICS | E43: =VLOOKUP($A:$A,'COGS NEW TEMPLATE'!$A:$G,5,FALSE) -> 4.05 | F43: =VLOOKUP($A:$A,'COGS NEW TEMPLATE'!$A:$G,6,FALSE) -> 0 | G43: =VLOOKUP($A:$A,'COGS NEW TEMPLATE'!$A:$G,7,FALSE) -> 0 | H43: =SUM(E43:G43) -> 4.05 | J43: ='FOILED COMIC BOOK #3'!$C$64 -> 589 | K43: ='FOILED COMIC BOOK #3'!$G$64 -> 591 | L43: ='FOILED COMIC BOOK #3'!$L$64 -> 0 | M43: ='FOILED COMIC BOOK #3'!$S$64 -> 229 | N43: ='FOILED COMIC BOOK #3'!$M$64 -> 0.0023148148 | R43: ='FOILED COMIC BOOK #3'!$V$39 -> 0 | S43: ='FOILED COMIC BOOK #3'!$V$40 -> 0 | T43: ='FOILED COMIC BOOK #3'!$V$41 -> 589 | U43: ='FOILED COMIC BOOK #3'!$V$44 -> 1 | V43: ='FOILED COMIC BOOK #3'!$V$42 -> 0 | W43: ='FOILED COMIC BOOK #3'!$V$43 -> 1 | X43: ='FOILED COMIC BOOK #3'!$V$46 -> 0 | Y43: ='FOILED COMIC BOOK #3'!$V$47 -> 0 | Z43: ='FOILED COMIC BOOK #3'!$V$48 -> 0 | AA43: ='FOILED COMIC BOOK #3'!$V$49 -> 0 | AB43: ='FOILED COMIC BOOK #3'!$V$50 -> 180 | AC43: ='FOILED COMIC BOOK #3'!$V$51 -> 0 | AD43: ='FOILED COMIC BOOK #3'!V$52+'FOILED COMIC BOOK #3'!V$53 -> -771 | AE43: =(R43+S43)-SUM(T43:AC43) -> -771
A44: 38 | B44: GHOSNS103624OT | C44: FOILED COMIC BOOK SISTER IMPERATOR #4 | D44: DARK HORSE COMICS | E44: =VLOOKUP($A:$A,'COGS NEW TEMPLATE'!$A:$G,5,FALSE) -> 4.05 | F44: =VLOOKUP($A:$A,'COGS NEW TEMPLATE'!$A:$G,6,FALSE) -> 0 | G44: =VLOOKUP($A:$A,'COGS NEW TEMPLATE'!$A:$G,7,FALSE) -> 0 | H44: =SUM(E44:G44) -> 4.05 | J44: ='FOILED COMIC BOOK #4'!$C$64 -> 574 | K44: ='FOILED COMIC BOOK #4'!$G$64 -> 576 | L44: ='FOILED COMIC BOOK #4'!$L$64 -> 424 | M44: ='FOILED COMIC BOOK #4'!$S$64 -> 244 | N44: ='FOILED COMIC BOOK #4'!$M$64 -> 0.0024074074 | R44: ='FOILED COMIC BOOK #4'!$V$39 -> 0 | S44: ='FOILED COMIC BOOK #4'!$V$40 -> 1000 | T44: ='FOILED COMIC BOOK #4'!$V$41 -> 574 | U44: ='FOILED COMIC BOOK #4'!$V$44 -> 1 | V44: ='FOILED COMIC BOOK #4'!$V$42 -> 0 | W44: ='FOILED COMIC BOOK #4'!$V$43 -> 1 | X44: ='FOILED COMIC BOOK #4'!$V$46 -> 0 | Y44: ='FOILED COMIC BOOK #4'!$V$47 -> 0 | Z44: ='FOILED COMIC BOOK #4'!$V$48 -> 0 | AA44: ='FOILED COMIC BOOK #4'!$V$49 -> 0 | AB44: ='FOILED COMIC BOOK #4'!$V$50 -> 180 | AC44: ='FOILED COMIC BOOK #4'!$V$51 -> 0 | AD44: ='FOILED COMIC BOOK #4'!V$52+'FOILED COMIC BOOK #4'!V$53 -> 244 | AE44: =(R44+S44)-SUM(T44:AC44) -> 244
A45: 39 | B45: GHOSRX003463OT | C45: CD SKELETA | D45: GMSUK | E45: =VLOOKUP($A:$A,'COGS NEW TEMPLATE'!$A:$G,5,FALSE) -> 12.25 | F45: =VLOOKUP($A:$A,'COGS NEW TEMPLATE'!$A:$G,6,FALSE) -> 0 | G45: =VLOOKUP($A:$A,'COGS NEW TEMPLATE'!$A:$G,7,FALSE) -> 0 | H45: =SUM(E45:G45) -> 12.25 | J45: =CD!$C$64 -> 146 | K45: =CD!$G$64 -> 146 | L45: =CD!$L$64 -> 0 | M45: =CD!$S$64 -> 0 | N45: =CD!$M$64 -> 0.00092592593 | R45: =CD!$V$39 -> 0 | S45: =CD!$V$40 -> 0 | T45: =CD!$V$41 -> 146 | U45: =CD!$V$44 -> 0 | V45: =CD!$V$42 -> 0 | W45: =CD!$V$43 -> 0 | X45: =CD!$V$46 -> 0 | Y45: =CD!$V$47 -> 0 | Z45: =CD!$V$48 -> 0 | AA45: =CD!$V$49 -> 0 | AB45: =CD!$V$50 -> 0 | AC45: =CD!$V$51 -> 0 | AD45: =CD!V$52+CD!V$53 -> -146 | AE45: =(R45+S45)-SUM(T45:AC45) -> -146
A46: 40 | B46: GHOSRX003470OT | C46: ROLLING STONE MAG & ALBUM | D46: GMSUK | E46: =VLOOKUP($A:$A,'COGS NEW TEMPLATE'!$A:$G,5,FALSE) -> 11.59 | F46: =VLOOKUP($A:$A,'COGS NEW TEMPLATE'!$A:$G,6,FALSE) -> 0 | G46: =VLOOKUP($A:$A,'COGS NEW TEMPLATE'!$A:$G,7,FALSE) -> 0 | H46: =SUM(E46:G46) -> 11.59 | J46: ='ROLLING STONE'!$C$64 -> 1765 | K46: ='ROLLING STONE'!$G$64 -> 1772 | L46: ='ROLLING STONE'!$L$64 -> 906 | M46: ='ROLLING STONE'!$S$64 -> 531 | N46: ='ROLLING STONE'!$M$64 -> 0.0083333333 | R46: ='ROLLING STONE'!$V$39 -> 0 | S46: ='ROLLING STONE'!$V$40 -> 2678 | T46: ='ROLLING STONE'!$V$41 -> 1765 | U46: ='ROLLING STONE'!$V$44 -> 0 | V46: ='ROLLING STONE'!$V$42 -> 6 | W46: ='ROLLING STONE'!$V$43 -> 1 | X46: ='ROLLING STONE'!$V$46 -> 0 | Y46: ='ROLLING STONE'!$V$47 -> 0 | Z46: ='ROLLING STONE'!$V$48 -> 0 | AA46: ='ROLLING STONE'!$V$49 -> 0 | AB46: ='ROLLING STONE'!$V$50 -> 375 | AC46: ='ROLLING STONE'!$V$51 -> 0 | AD46: ='ROLLING STONE'!V$52+'ROLLING STONE'!V$53 -> 531 | AE46: =(R46+S46)-SUM(T46:AC46) -> 531
A47: 41 | B47: GHOSRX003611BK | C47: LP SKELETA BLACK VINYL | D47: GMSUK | E47: =VLOOKUP($A:$A,'COGS NEW TEMPLATE'!$A:$G,5,FALSE) -> 24.1 | F47: =VLOOKUP($A:$A,'COGS NEW TEMPLATE'!$A:$G,6,FALSE) -> 0 | G47: =VLOOKUP($A:$A,'COGS NEW TEMPLATE'!$A:$G,7,FALSE) -> 0 | H47: =SUM(E47:G47) -> 24.1 | J47: ='BLK STANDARD LP'!$C$64 -> 325 | K47: ='BLK STANDARD LP'!$G$64 -> 325 | L47: ='BLK STANDARD LP'!$L$64 -> 0 | M47: ='BLK STANDARD LP'!$S$64 -> 0 | N47: ='BLK STANDARD LP'!$M$64 -> 0.0019444444 | R47: ='BLK STANDARD LP'!$V$39 -> 0 | S47: ='BLK STANDARD LP'!$V$40 -> 343 | T47: ='BLK STANDARD LP'!$V$41 -> 325 | U47: ='BLK STANDARD LP'!$V$44 -> 0 | V47: ='BLK STANDARD LP'!$V$42 -> 0 | W47: ='BLK STANDARD LP'!$V$43 -> 0 | X47: ='BLK STANDARD LP'!$V$46 -> 18 | Y47: ='BLK STANDARD LP'!$V$47 -> 0 | Z47: ='BLK STANDARD LP'!$V$48 -> 0 | AA47: ='BLK STANDARD LP'!$V$49 -> 0 | AB47: ='BLK STANDARD LP'!$V$50 -> 0 | AC47: ='BLK STANDARD LP'!$V$51 -> 0 | AD47: ='BLK STANDARD LP'!V$52+'BLK STANDARD LP'!V$53 -> 0 | AE47: =(R47+S47)-SUM(T47:AC47) -> 0
A48: 42 | B48: GHOSCG103805PU | C48: LP PURPLE LENTICULAR | D48: CONCORD | H48: =SUM(E48:G48) -> 0 | J48: ='PURPLE LP LENTICULAR'!$C$64 -> 1988 | K48: ='PURPLE LP LENTICULAR'!$G$64 -> 2005 | L48: ='PURPLE LP LENTICULAR'!$L$64 -> 0 | M48: ='PURPLE LP LENTICULAR'!$S$64 -> 0 | N48: ='PURPLE LP LENTICULAR'!$M$64 -> 0.010185185 | R48: ='PURPLE LP LENTICULAR'!$V$39 -> 0 | S48: ='PURPLE LP LENTICULAR'!$V$40 -> 2200 | T48: ='PURPLE LP LENTICULAR'!$V$41 -> 1988 | U48: ='PURPLE LP LENTICULAR'!$V$44 -> 0 | V48: ='PURPLE LP LENTICULAR'!$V$42 -> 16 | W48: ='PURPLE LP LENTICULAR'!$V$43 -> 1 | X48: ='PURPLE LP LENTICULAR'!$V$46 -> -5 | Y48: ='PURPLE LP LENTICULAR'!$V$47 -> 0 | Z48: ='PURPLE LP LENTICULAR'!$V$48 -> 0 | AA48: ='PURPLE LP LENTICULAR'!$V$49 -> 0 | AB48: ='PURPLE LP LENTICULAR'!$V$50 -> 200 | AC48: ='PURPLE LP LENTICULAR'!$V$51 -> 0 | AD48: ='PURPLE LP LENTICULAR'!V$52+'PURPLE LP LENTICULAR'!V$53 -> 0 | AE48: =(R48+S48)-SUM(T48:AC48) -> 0
A49: 43 | B49: GHOSCG103844BK | C49: CASSETTE | D49: CONCORD | H49: =SUM(E49:G49) -> 0 | J49: =CASSETTE!$C$64 -> 514 | K49: =CASSETTE!$G$64 -> 514 | L49: =CASSETTE!$L$64 -> 0 | M49: =CASSETTE!$S$64 -> 0 | N49: =CASSETTE!$M$64 -> 0.0014814815 | R49: =CASSETTE!$V$39 -> 0 | S49: =CASSETTE!$V$40 -> 302 | T49: =CASSETTE!$V$41 -> 514 | U49: =CASSETTE!$V$44 -> 0 | V49: =CASSETTE!$V$42 -> 0 | W49: =CASSETTE!$V$43 -> 0 | X49: =CASSETTE!$V$46 -> 0 | Y49: =CASSETTE!$V$47 -> 0 | Z49: =CASSETTE!$V$48 -> 0 | AA49: =CASSETTE!$V$49 -> 0 | AB49: =CASSETTE!$V$50 -> 288 | AC49: =CASSETTE!$V$51 -> 0 | AD49: =CASSETTE!V$52+CASSETTE!V$53 -> -500 | AE49: =(R49+S49)-SUM(T49:AC49) -> -500
A50: 44 | H50: =SUM(E50:G50) -> 0 | J50: ='44'!$C$64 -> 0 | K50: ='44'!$G$64 -> 0 | L50: ='44'!$L$64 -> 0 | M50: ='44'!$S$64 -> 0 | N50: ='44'!$M$64 -> 0 | R50: ='44'!$V$39 -> 0 | S50: ='44'!$V$40 -> 0 | T50: ='44'!$V$41 -> 0 | U50: ='44'!$V$44 -> 0 | V50: ='44'!$V$42 -> 0 | W50: ='44'!$V$43 -> 0 | X50: ='44'!$V$46 -> 0 | Y50: ='44'!$V$47 -> 0 | Z50: ='44'!$V$48 -> 0 | AA50: ='44'!$V$49 -> 0 | AB50: ='44'!$V$50 -> 0 | AC50: ='44'!$V$51 -> 0 | AD50: ='44'!V$52+'44'!V$53 -> 0 | AE50: =(R50+S50)-SUM(T50:AC50) -> 0
A51: 45 | H51: =SUM(E51:G51) -> 0 | J51: ='45'!$C$64 -> 0 | K51: ='45'!$G$64 -> 0 | L51: ='45'!$L$64 -> 0 | M51: ='45'!$S$64 -> 0 | N51: ='45'!$M$64 -> 0 | R51: ='45'!$V$39 -> 0 | S51: ='45'!$V$40 -> 0 | T51: ='45'!$V$41 -> 0 | U51: ='45'!$V$44 -> 0 | V51: ='45'!$V$42 -> 0 | W51: ='45'!$V$43 -> 0 | X51: ='45'!$V$46 -> 0 | Y51: ='45'!$V$47 -> 0 | Z51: ='45'!$V$48 -> 0 | AA51: ='45'!$V$49 -> 0 | AB51: ='45'!$V$50 -> 0 | AC51: ='45'!$V$51 -> 0 | AD51: ='45'!V$52+'45'!V$53 -> 0 | AE51: =(R51+S51)-SUM(T51:AC51) -> 0
A52: 46 | H52: =SUM(E52:G52) -> 0 | J52: ='46'!$C$64 -> 0 | K52: ='46'!$G$64 -> 0 | L52: ='46'!$L$64 -> 0 | M52: ='46'!$S$64 -> 0 | N52: ='46'!$M$64 -> 0 | R52: ='46'!$V$39 -> 0 | S52: ='46'!$V$40 -> 0 | T52: ='46'!$V$41 -> 0 | U52: ='46'!$V$44 -> 0 | V52: ='46'!$V$42 -> 0 | W52: ='46'!$V$43 -> 0 | X52: ='46'!$V$46 -> 0 | Y52: ='46'!$V$47 -> 0 | Z52: ='46'!$V$48 -> 0 | AA52: ='46'!$V$49 -> 0 | AB52: ='46'!$V$50 -> 0 | AC52: ='46'!$V$51 -> 0 | AD52: ='46'!V$52+'46'!V$53 -> 0 | AE52: =(R52+S52)-SUM(T52:AC52) -> 0
A53: 47 | H53: =SUM(E53:G53) -> 0 | J53: ='47'!$C$64 -> 0 | K53: ='47'!$G$64 -> 0 | L53: ='47'!$L$64 -> 0 | M53: ='47'!$S$64 -> 0 | N53: ='47'!$M$64 -> 0 | R53: ='47'!$V$39 -> 0 | S53: ='47'!$V$40 -> 0 | T53: ='47'!$V$41 -> 0 | U53: ='47'!$V$44 -> 0 | V53: ='47'!$V$42 -> 0 | W53: ='47'!$V$43 -> 0 | X53: ='47'!$V$46 -> 0 | Y53: ='47'!$V$47 -> 0 | Z53: ='47'!$V$48 -> 0 | AA53: ='47'!$V$49 -> 0 | AB53: ='47'!$V$50 -> 0 | AC53: ='47'!$V$51 -> 0 | AD53: ='47'!V$52+'47'!V$53 -> 0 | AE53: =(R53+S53)-SUM(T53:AC53) -> 0
A54: 48 | H54: =SUM(E54:G54) -> 0 | J54: ='48'!$C$64 -> 0 | K54: ='48'!$G$64 -> 0 | L54: ='48'!$L$64 -> 0 | M54: ='48'!$S$64 -> 0 | N54: ='48'!$M$64 -> 0 | R54: ='48'!$V$39 -> 0 | S54: ='48'!$V$40 -> 0 | T54: ='48'!$V$41 -> 0 | U54: ='48'!$V$44 -> 0 | V54: ='48'!$V$42 -> 0 | W54: ='48'!$V$43 -> 0 | X54: ='48'!$V$46 -> 0 | Y54: ='48'!$V$47 -> 0 | Z54: ='48'!$V$48 -> 0 | AA54: ='48'!$V$49 -> 0 | AB54: ='48'!$V$50 -> 0 | AC54: ='48'!$V$51 -> 0 | AD54: ='48'!V$52+'48'!V$53 -> 0 | AE54: =(R54+S54)-SUM(T54:AC54) -> 0
A55: 49 | H55: =SUM(E55:G55) -> 0 | J55: ='49'!$C$64 -> 0 | K55: ='49'!$G$64 -> 0 | L55: ='49'!$L$64 -> 0 | M55: ='49'!$S$64 -> 0 | N55: ='49'!$M$64 -> 0 | R55: ='49'!$V$39 -> 0 | S55: ='49'!$V$40 -> 0 | T55: ='49'!$V$41 -> 0 | U55: ='49'!$V$44 -> 0 | V55: ='49'!$V$42 -> 0 | W55: ='49'!$V$43 -> 0 | X55: ='49'!$V$46 -> 0 | Y55: ='49'!$V$47 -> 0 | Z55: ='49'!$V$48 -> 0 | AA55: ='49'!$V$49 -> 0 | AB55: ='49'!$V$50 -> 0 | AC55: ='49'!$V$51 -> 0 | AD55: ='49'!V$52+'49'!V$53 -> 0 | AE55: =(R55+S55)-SUM(T55:AC55) -> 0
A56: 50 | H56: =SUM(E56:G56) -> 0 | J56: ='50'!$C$64 -> 0 | K56: ='50'!$G$64 -> 0 | L56: ='50'!$L$64 -> 0 | M56: ='50'!$S$64 -> 0 | N56: ='50'!$M$64 -> 0 | R56: ='50'!$V$39 -> 0 | S56: ='50'!$V$40 -> 0 | T56: ='50'!$V$41 -> 0 | U56: ='50'!$V$44 -> 0 | V56: ='50'!$V$42 -> 0 | W56: ='50'!$V$43 -> 0 | X56: ='50'!$V$46 -> 0 | Y56: ='50'!$V$47 -> 0 | Z56: ='50'!$V$48 -> 0 | AA56: ='50'!$V$49 -> 0 | AB56: ='50'!$V$50 -> 0 | AC56: ='50'!$V$51 -> 0 | AD56: ='50'!V$52+'50'!V$53 -> 0 | AE56: =(R56+S56)-SUM(T56:AC56) -> 0
A57: 51 | H57: =SUM(E57:G57) -> 0 | J57: ='51'!$C$64 -> 0 | K57: ='51'!$G$64 -> 0 | L57: ='51'!$L$64 -> 0 | M57: ='51'!$S$64 -> 0 | N57: ='51'!$M$64 -> 0 | R57: ='51'!$V$39 -> 0 | S57: ='51'!$V$40 -> 0 | T57: ='51'!$V$41 -> 0 | U57: ='51'!$V$44 -> 0 | V57: ='51'!$V$42 -> 0 | W57: ='51'!$V$43 -> 0 | X57: ='51'!$V$46 -> 0 | Y57: ='51'!$V$47 -> 0 | Z57: ='51'!$V$48 -> 0 | AA57: ='51'!$V$49 -> 0 | AB57: ='51'!$V$50 -> 0 | AC57: ='51'!$V$51 -> 0 | AD57: ='51'!V$52+'51'!V$53 -> 0 | AE57: =(R57+S57)-SUM(T57:AC57) -> 0
A58: 52 | H58: =SUM(E58:G58) -> 0 | J58: ='52'!$C$64 -> 0 | K58: ='52'!$G$64 -> 0 | L58: ='52'!$L$64 -> 0 | M58: ='52'!$S$64 -> 0 | N58: ='52'!$M$64 -> 0 | R58: ='52'!$V$39 -> 0 | S58: ='52'!$V$40 -> 0 | T58: ='52'!$V$41 -> 0 | U58: ='52'!$V$44 -> 0 | V58: ='52'!$V$42 -> 0 | W58: ='52'!$V$43 -> 0 | X58: ='52'!$V$46 -> 0 | Y58: ='52'!$V$47 -> 0 | Z58: ='52'!$V$48 -> 0 | AA58: ='52'!$V$49 -> 0 | AB58: ='52'!$V$50 -> 0 | AC58: ='52'!$V$51 -> 0 | AD58: ='52'!V$52+'52'!V$53 -> 0 | AE58: =(R58+S58)-SUM(T58:AC58) -> 0
A59: 53 | H59: =SUM(E59:G59) -> 0 | J59: ='53'!$C$64 -> 0 | K59: ='53'!$G$64 -> 0 | L59: ='53'!$L$64 -> 0 | M59: ='53'!$S$64 -> 0 | N59: ='53'!$M$64 -> 0 | R59: ='53'!$V$39 -> 0 | S59: ='53'!$V$40 -> 0 | T59: ='53'!$V$41 -> 0 | U59: ='53'!$V$44 -> 0 | V59: ='53'!$V$42 -> 0 | W59: ='53'!$V$43 -> 0 | X59: ='53'!$V$46 -> 0 | Y59: ='53'!$V$47 -> 0 | Z59: ='53'!$V$48 -> 0 | AA59: ='53'!$V$49 -> 0 | AB59: ='53'!$V$50 -> 0 | AC59: ='53'!$V$51 -> 0 | AD59: ='53'!V$52+'53'!V$53 -> 0 | AE59: =(R59+S59)-SUM(T59:AC59) -> 0
A60: 54 | H60: =SUM(E60:G60) -> 0 | J60: ='54'!$C$64 -> 0 | K60: ='54'!$G$64 -> 0 | L60: ='54'!$L$64 -> 0 | M60: ='54'!$S$64 -> 0 | N60: ='54'!$M$64 -> 0 | R60: ='54'!$V$39 -> 0 | S60: ='54'!$V$40 -> 0 | T60: ='54'!$V$41 -> 0 | U60: ='54'!$V$44 -> 0 | V60: ='54'!$V$42 -> 0 | W60: ='54'!$V$43 -> 0 | X60: ='54'!$V$46 -> 0 | Y60: ='54'!$V$47 -> 0 | Z60: ='54'!$V$48 -> 0 | AA60: ='54'!$V$49 -> 0 | AB60: ='54'!$V$50 -> 0 | AC60: ='54'!$V$51 -> 0 | AD60: ='54'!V$52+'54'!V$53 -> 0 | AE60: =(R60+S60)-SUM(T60:AC60) -> 0
A61: 55 | H61: =SUM(E61:G61) -> 0 | J61: ='55'!$C$64 -> 0 | K61: ='55'!$G$64 -> 0 | L61: ='55'!$L$64 -> 0 | M61: ='55'!$S$64 -> 0 | N61: ='55'!$M$64 -> 0 | R61: ='55'!$V$39 -> 0 | S61: ='55'!$V$40 -> 0 | T61: ='55'!$V$41 -> 0 | U61: ='55'!$V$44 -> 0 | V61: ='55'!$V$42 -> 0 | W61: ='55'!$V$43 -> 0 | X61: ='55'!$V$46 -> 0 | Y61: ='55'!$V$47 -> 0 | Z61: ='55'!$V$48 -> 0 | AA61: ='55'!$V$49 -> 0 | AB61: ='55'!$V$50 -> 0 | AC61: ='55'!$V$51 -> 0 | AD61: ='55'!V$52+'55'!V$53 -> 0 | AE61: =(R61+S61)-SUM(T61:AC61) -> 0
A62: 56 | H62: =SUM(E62:G62) -> 0 | J62: ='56'!$C$64 -> 0 | K62: ='56'!$G$64 -> 0 | L62: ='56'!$L$64 -> 0 | M62: ='56'!$S$64 -> 0 | N62: ='56'!$M$64 -> 0 | R62: ='56'!$V$39 -> 0 | S62: ='56'!$V$40 -> 0 | T62: ='56'!$V$41 -> 0 | U62: ='56'!$V$44 -> 0 | V62: ='56'!$V$42 -> 0 | W62: ='56'!$V$43 -> 0 | X62: ='56'!$V$46 -> 0 | Y62: ='56'!$V$47 -> 0 | Z62: ='56'!$V$48 -> 0 | AA62: ='56'!$V$49 -> 0 | AB62: ='56'!$V$50 -> 0 | AC62: ='56'!$V$51 -> 0 | AD62: ='56'!V$52+'56'!V$53 -> 0 | AE62: =(R62+S62)-SUM(T62:AC62) -> 0
A63: 57 | H63: =SUM(E63:G63) -> 0 | J63: ='57'!$C$64 -> 0 | K63: ='57'!$G$64 -> 0 | L63: ='57'!$L$64 -> 0 | M63: ='57'!$S$64 -> 0 | N63: ='57'!$M$64 -> 0 | R63: ='57'!$V$39 -> 0 | S63: ='57'!$V$40 -> 0 | T63: ='57'!$V$41 -> 0 | U63: ='57'!$V$44 -> 0 | V63: ='57'!$V$42 -> 0 | W63: ='57'!$V$43 -> 0 | X63: ='57'!$V$46 -> 0 | Y63: ='57'!$V$47 -> 0 | Z63: ='57'!$V$48 -> 0 | AA63: ='57'!$V$49 -> 0 | AB63: ='57'!$V$50 -> 0 | AC63: ='57'!$V$51 -> 0 | AD63: ='57'!V$52+'57'!V$53 -> 0 | AE63: =(R63+S63)-SUM(T63:AC63) -> 0
A64: 58 | H64: =SUM(E64:G64) -> 0 | J64: ='58'!$C$64 -> 0 | K64: ='58'!$G$64 -> 0 | L64: ='58'!$L$64 -> 0 | M64: ='58'!$S$64 -> 0 | N64: ='58'!$M$64 -> 0 | R64: ='58'!$V$39 -> 0 | S64: ='58'!$V$40 -> 0 | T64: ='58'!$V$41 -> 0 | U64: ='58'!$V$44 -> 0 | V64: ='58'!$V$42 -> 0 | W64: ='58'!$V$43 -> 0 | X64: ='58'!$V$46 -> 0 | Y64: ='58'!$V$47 -> 0 | Z64: ='58'!$V$48 -> 0 | AA64: ='58'!$V$49 -> 0 | AB64: ='58'!$V$50 -> 0 | AC64: ='58'!$V$51 -> 0 | AD64: ='58'!V$52+'58'!V$53 -> 0 | AE64: =(R64+S64)-SUM(T64:AC64) -> 0
A65: 59 | H65: =SUM(E65:G65) -> 0 | J65: ='59'!$C$64 -> 0 | K65: ='59'!$G$64 -> 0 | L65: ='59'!$L$64 -> 0 | M65: ='59'!$S$64 -> 0 | N65: ='59'!$M$64 -> 0 | R65: ='59'!$V$39 -> 0 | S65: ='59'!$V$40 -> 0 | T65: ='59'!$V$41 -> 0 | U65: ='59'!$V$44 -> 0 | V65: ='59'!$V$42 -> 0 | W65: ='59'!$V$43 -> 0 | X65: ='59'!$V$46 -> 0 | Y65: ='59'!$V$47 -> 0 | Z65: ='59'!$V$48 -> 0 | AA65: ='59'!$V$49 -> 0 | AB65: ='59'!$V$50 -> 0 | AC65: ='59'!$V$51 -> 0 | AD65: ='59'!V$52+'59'!V$53 -> 0 | AE65: =(R65+S65)-SUM(T65:AC65) -> 0
A66: 60 | H66: =SUM(E66:G66) -> 0 | J66: ='60'!$C$64 -> 0 | K66: ='60'!$G$64 -> 0 | L66: ='60'!$L$64 -> 0 | M66: ='60'!$S$64 -> 0 | N66: ='60'!$M$64 -> 0 | R66: ='60'!$V$39 -> 0 | S66: ='60'!$V$40 -> 0 | T66: ='60'!$V$41 -> 0 | U66: ='60'!$V$44 -> 0 | V66: ='60'!$V$42 -> 0 | W66: ='60'!$V$43 -> 0 | X66: ='60'!$V$46 -> 0 | Y66: ='60'!$V$47 -> 0 | Z66: ='60'!$V$48 -> 0 | AA66: ='60'!$V$49 -> 0 | AB66: ='60'!$V$50 -> 0 | AC66: ='60'!$V$51 -> 0 | AD66: ='60'!V$52+'60'!V$53 -> 0 | AE66: =(R66+S66)-SUM(T66:AC66) -> 0
A67: 61 | H67: =SUM(E67:G67) -> 0 | J67: ='61'!$C$64 -> 0 | K67: ='61'!$G$64 -> 0 | L67: ='61'!$L$64 -> 0 | M67: ='61'!$S$64 -> 0 | N67: ='61'!$M$64 -> 0 | R67: ='61'!$V$39 -> 0 | S67: ='61'!$V$40 -> 0 | T67: ='61'!$V$41 -> 0 | U67: ='61'!$V$44 -> 0 | V67: ='61'!$V$42 -> 0 | W67: ='61'!$V$43 -> 0 | X67: ='61'!$V$46 -> 0 | Y67: ='61'!$V$47 -> 0 | Z67: ='61'!$V$48 -> 0 | AA67: ='61'!$V$49 -> 0 | AB67: ='61'!$V$50 -> 0 | AC67: ='61'!$V$51 -> 0 | AD67: ='61'!V$52+'61'!V$53 -> 0 | AE67: =(R67+S67)-SUM(T67:AC67) -> 0
A68: 62 | H68: =SUM(E68:G68) -> 0 | J68: ='62'!$C$64 -> 0 | K68: ='62'!$G$64 -> 0 | L68: ='62'!$L$64 -> 0 | M68: ='62'!$S$64 -> 0 | N68: ='62'!$M$64 -> 0 | R68: ='62'!$V$39 -> 0 | S68: ='62'!$V$40 -> 0 | T68: ='62'!$V$41 -> 0 | U68: ='62'!$V$44 -> 0 | V68: ='62'!$V$42 -> 0 | W68: ='62'!$V$43 -> 0 | X68: ='62'!$V$46 -> 0 | Y68: ='62'!$V$47 -> 0 | Z68: ='62'!$V$48 -> 0 | AA68: ='62'!$V$49 -> 0 | AB68: ='62'!$V$50 -> 0 | AC68: ='62'!$V$51 -> 0 | AD68: ='62'!V$52+'62'!V$53 -> 0 | AE68: =(R68+S68)-SUM(T68:AC68) -> 0
A69: 63 | H69: =SUM(E69:G69) -> 0 | J69: ='63'!$C$64 -> 0 | K69: ='63'!$G$64 -> 0 | L69: ='63'!$L$64 -> 0 | M69: ='63'!$S$64 -> 0 | N69: ='63'!$M$64 -> 0 | R69: ='63'!$V$39 -> 0 | S69: ='63'!$V$40 -> 0 | T69: ='63'!$V$41 -> 0 | U69: ='63'!$V$44 -> 0 | V69: ='63'!$V$42 -> 0 | W69: ='63'!$V$43 -> 0 | X69: ='63'!$V$46 -> 0 | Y69: ='63'!$V$47 -> 0 | Z69: ='63'!$V$48 -> 0 | AA69: ='63'!$V$49 -> 0 | AB69: ='63'!$V$50 -> 0 | AC69: ='63'!$V$51 -> 0 | AD69: ='63'!V$52+'63'!V$53 -> 0 | AE69: =(R69+S69)-SUM(T69:AC69) -> 0
A70: 64 | H70: =SUM(E70:G70) -> 0 | J70: ='64'!$C$64 -> 0 | K70: ='64'!$G$64 -> 0 | L70: ='64'!$L$64 -> 0 | M70: ='64'!$S$64 -> 0 | N70: ='64'!$M$64 -> 0 | R70: ='64'!$V$39 -> 0 | S70: ='64'!$V$40 -> 0 | T70: ='64'!$V$41 -> 0 | U70: ='64'!$V$44 -> 0 | V70: ='64'!$V$42 -> 0 | W70: ='64'!$V$43 -> 0 | X70: ='64'!$V$46 -> 0 | Y70: ='64'!$V$47 -> 0 | Z70: ='64'!$V$48 -> 0 | AA70: ='64'!$V$49 -> 0 | AB70: ='64'!$V$50 -> 0 | AC70: ='64'!$V$51 -> 0 | AD70: ='64'!V$52+'64'!V$53 -> 0 | AE70: =(R70+S70)-SUM(T70:AC70) -> 0
A71: 65 | H71: =SUM(E71:G71) -> 0 | J71: ='65'!$C$64 -> 0 | K71: ='65'!$G$64 -> 0 | L71: ='65'!$L$64 -> 0 | M71: ='65'!$S$64 -> 0 | N71: ='65'!$M$64 -> 0 | R71: ='65'!$V$39 -> 0 | S71: ='65'!$V$40 -> 0 | T71: ='65'!$V$41 -> 0 | U71: ='65'!$V$44 -> 0 | V71: ='65'!$V$42 -> 0 | W71: ='65'!$V$43 -> 0 | X71: ='65'!$V$46 -> 0 | Y71: ='65'!$V$47 -> 0 | Z71: ='65'!$V$48 -> 0 | AA71: ='65'!$V$49 -> 0 | AB71: ='65'!$V$50 -> 0 | AC71: ='65'!$V$51 -> 0 | AD71: ='65'!V$52+'65'!V$53 -> 0 | AE71: =(R71+S71)-SUM(T71:AC71) -> 0
A72: 66 | H72: =SUM(E72:G72) -> 0 | J72: ='66'!$C$64 -> 0 | K72: ='66'!$G$64 -> 0 | L72: ='66'!$L$64 -> 0 | M72: ='66'!$S$64 -> 0 | N72: ='66'!$M$64 -> 0 | R72: ='66'!$V$39 -> 0 | S72: ='66'!$V$40 -> 0 | T72: ='66'!$V$41 -> 0 | U72: ='66'!$V$44 -> 0 | V72: ='66'!$V$42 -> 0 | W72: ='66'!$V$43 -> 0 | X72: ='66'!$V$46 -> 0 | Y72: ='66'!$V$47 -> 0 | Z72: ='66'!$V$48 -> 0 | AA72: ='66'!$V$49 -> 0 | AB72: ='66'!$V$50 -> 0 | AC72: ='66'!$V$51 -> 0 | AD72: ='66'!V$52+'66'!V$53 -> 0 | AE72: =(R72+S72)-SUM(T72:AC72) -> 0
A73: 67 | H73: =SUM(E73:G73) -> 0 | J73: ='67'!$C$64 -> 0 | K73: ='67'!$G$64 -> 0 | L73: ='67'!$L$64 -> 0 | M73: ='67'!$S$64 -> 0 | N73: ='67'!$M$64 -> 0 | R73: ='67'!$V$39 -> 0 | S73: ='67'!$V$40 -> 0 | T73: ='67'!$V$41 -> 0 | U73: ='67'!$V$44 -> 0 | V73: ='67'!$V$42 -> 0 | W73: ='67'!$V$43 -> 0 | X73: ='67'!$V$46 -> 0 | Y73: ='67'!$V$47 -> 0 | Z73: ='67'!$V$48 -> 0 | AA73: ='67'!$V$49 -> 0 | AB73: ='67'!$V$50 -> 0 | AC73: ='67'!$V$51 -> 0 | AD73: ='67'!V$52+'67'!V$53 -> 0 | AE73: =(R73+S73)-SUM(T73:AC73) -> 0
A74: 68 | H74: =SUM(E74:G74) -> 0 | J74: ='68'!$C$64 -> 0 | K74: ='68'!$G$64 -> 0 | L74: ='68'!$L$64 -> 0 | M74: ='68'!$S$64 -> 0 | N74: ='68'!$M$64 -> 0 | R74: ='68'!$V$39 -> 0 | S74: ='68'!$V$40 -> 0 | T74: ='68'!$V$41 -> 0 | U74: ='68'!$V$44 -> 0 | V74: ='68'!$V$42 -> 0 | W74: ='68'!$V$43 -> 0 | X74: ='68'!$V$46 -> 0 | Y74: ='68'!$V$47 -> 0 | Z74: ='68'!$V$48 -> 0 | AA74: ='68'!$V$49 -> 0 | AB74: ='68'!$V$50 -> 0 | AC74: ='68'!$V$51 -> 0 | AD74: ='68'!V$52+'68'!V$53 -> 0 | AE74: =(R74+S74)-SUM(T74:AC74) -> 0
A75: 69 | H75: =SUM(E75:G75) -> 0 | J75: ='69'!$C$64 -> 0 | K75: ='69'!$G$64 -> 0 | L75: ='69'!$L$64 -> 0 | M75: ='69'!$S$64 -> 0 | N75: ='69'!$M$64 -> 0 | R75: ='69'!$V$39 -> 0 | S75: ='69'!$V$40 -> 0 | T75: ='69'!$V$41 -> 0 | U75: ='69'!$V$44 -> 0 | V75: ='69'!$V$42 -> 0 | W75: ='69'!$V$43 -> 0 | X75: ='69'!$V$46 -> 0 | Y75: ='69'!$V$47 -> 0 | Z75: ='69'!$V$48 -> 0 | AA75: ='69'!$V$49 -> 0 | AB75: ='69'!$V$50 -> 0 | AC75: ='69'!$V$51 -> 0 | AD75: ='69'!V$52+'69'!V$53 -> 0 | AE75: =(R75+S75)-SUM(T75:AC75) -> 0
A76: 70 | H76: =SUM(E76:G76) -> 0 | J76: ='70'!$C$64 -> 0 | K76: ='70'!$G$64 -> 0 | L76: ='70'!$L$64 -> 0 | M76: ='70'!$S$64 -> 0 | N76: ='70'!$M$64 -> 0 | R76: ='70'!$V$39 -> 0 | S76: ='70'!$V$40 -> 0 | T76: ='70'!$V$41 -> 0 | U76: ='70'!$V$44 -> 0 | V76: ='70'!$V$42 -> 0 | W76: ='70'!$V$43 -> 0 | X76: ='70'!$V$46 -> 0 | Y76: ='70'!$V$47 -> 0 | Z76: ='70'!$V$48 -> 0 | AA76: ='70'!$V$49 -> 0 | AB76: ='70'!$V$50 -> 0 | AC76: ='70'!$V$51 -> 0 | AD76: ='70'!V$52+'70'!V$53 -> 0 | AE76: =(R76+S76)-SUM(T76:AC76) -> 0
A77: 71 | H77: =SUM(E77:G77) -> 0 | J77: ='71'!$C$64 -> 0 | K77: ='71'!$G$64 -> 0 | L77: ='71'!$L$64 -> 0 | M77: ='71'!$S$64 -> 0 | N77: ='71'!$M$64 -> 0 | R77: ='71'!$V$39 -> 0 | S77: ='71'!$V$40 -> 0 | T77: ='71'!$V$41 -> 0 | U77: ='71'!$V$44 -> 0 | V77: ='71'!$V$42 -> 0 | W77: ='71'!$V$43 -> 0 | X77: ='71'!$V$46 -> 0 | Y77: ='71'!$V$47 -> 0 | Z77: ='71'!$V$48 -> 0 | AA77: ='71'!$V$49 -> 0 | AB77: ='71'!$V$50 -> 0 | AC77: ='71'!$V$51 -> 0 | AD77: ='71'!V$52+'71'!V$53 -> 0 | AE77: =(R77+S77)-SUM(T77:AC77) -> 0
A78: 72 | H78: =SUM(E78:G78) -> 0 | J78: ='72'!$C$64 -> 0 | K78: ='72'!$G$64 -> 0 | L78: ='72'!$L$64 -> 0 | M78: ='72'!$S$64 -> 0 | N78: ='72'!$M$64 -> 0 | R78: ='72'!$V$39 -> 0 | S78: ='72'!$V$40 -> 0 | T78: ='72'!$V$41 -> 0 | U78: ='72'!$V$44 -> 0 | V78: ='72'!$V$42 -> 0 | W78: ='72'!$V$43 -> 0 | X78: ='72'!$V$46 -> 0 | Y78: ='72'!$V$47 -> 0 | Z78: ='72'!$V$48 -> 0 | AA78: ='72'!$V$49 -> 0 | AB78: ='72'!$V$50 -> 0 | AC78: ='72'!$V$51 -> 0 | AD78: ='72'!V$52+'72'!V$53 -> 0 | AE78: =(R78+S78)-SUM(T78:AC78) -> 0
A79: 73 | H79: =SUM(E79:G79) -> 0 | J79: ='73'!$C$64 -> 0 | K79: ='73'!$G$64 -> 0 | L79: ='73'!$L$64 -> 0 | M79: ='73'!$S$64 -> 0 | N79: ='73'!$M$64 -> 0 | R79: ='73'!$V$39 -> 0 | S79: ='73'!$V$40 -> 0 | T79: ='73'!$V$41 -> 0 | U79: ='73'!$V$44 -> 0 | V79: ='73'!$V$42 -> 0 | W79: ='73'!$V$43 -> 0 | X79: ='73'!$V$46 -> 0 | Y79: ='73'!$V$47 -> 0 | Z79: ='73'!$V$48 -> 0 | AA79: ='73'!$V$49 -> 0 | AB79: ='73'!$V$50 -> 0 | AC79: ='73'!$V$51 -> 0 | AD79: ='73'!V$52+'73'!V$53 -> 0 | AE79: =(R79+S79)-SUM(T79:AC79) -> 0
A80: 74 | H80: =SUM(E80:G80) -> 0 | J80: ='74'!$C$64 -> 0 | K80: ='74'!$G$64 -> 0 | L80: ='74'!$L$64 -> 0 | M80: ='74'!$S$64 -> 0 | N80: ='74'!$M$64 -> 0 | R80: ='74'!$V$39 -> 0 | S80: ='74'!$V$40 -> 0 | T80: ='74'!$V$41 -> 0 | U80: ='74'!$V$44 -> 0 | V80: ='74'!$V$42 -> 0 | W80: ='74'!$V$43 -> 0 | X80: ='74'!$V$46 -> 0 | Y80: ='74'!$V$47 -> 0 | Z80: ='74'!$V$48 -> 0 | AA80: ='74'!$V$49 -> 0 | AB80: ='74'!$V$50 -> 0 | AC80: ='74'!$V$51 -> 0 | AD80: ='74'!V$52+'74'!V$53 -> 0 | AE80: =(R80+S80)-SUM(T80:AC80) -> 0
A81: 75 | H81: =SUM(E81:G81) -> 0 | J81: ='75'!$C$64 -> 0 | K81: ='75'!$G$64 -> 0 | L81: ='75'!$L$64 -> 0 | M81: ='75'!$S$64 -> 0 | N81: ='75'!$M$64 -> 0 | R81: ='75'!$V$39 -> 0 | S81: ='75'!$V$40 -> 0 | T81: ='75'!$V$41 -> 0 | U81: ='75'!$V$44 -> 0 | V81: ='75'!$V$42 -> 0 | W81: ='75'!$V$43 -> 0 | X81: ='75'!$V$46 -> 0 | Y81: ='75'!$V$47 -> 0 | Z81: ='75'!$V$48 -> 0 | AA81: ='75'!$V$49 -> 0 | AB81: ='75'!$V$50 -> 0 | AC81: ='75'!$V$51 -> 0 | AD81: ='75'!V$52+'75'!V$53 -> 0 | AE81: =(R81+S81)-SUM(T81:AC81) -> 0
A82: 76 | H82: =SUM(E82:G82) -> 0 | J82: ='76'!$C$64 -> 0 | K82: ='76'!$G$64 -> 0 | L82: ='76'!$L$64 -> 0 | M82: ='76'!$S$64 -> 0 | N82: ='76'!$M$64 -> 0 | R82: ='76'!$V$39 -> 0 | S82: ='76'!$V$40 -> 0 | T82: ='76'!$V$41 -> 0 | U82: ='76'!$V$44 -> 0 | V82: ='76'!$V$42 -> 0 | W82: ='76'!$V$43 -> 0 | X82: ='76'!$V$46 -> 0 | Y82: ='76'!$V$47 -> 0 | Z82: ='76'!$V$48 -> 0 | AA82: ='76'!$V$49 -> 0 | AB82: ='76'!$V$50 -> 0 | AC82: ='76'!$V$51 -> 0 | AD82: ='76'!V$52+'76'!V$53 -> 0 | AE82: =(R82+S82)-SUM(T82:AC82) -> 0
A83: 77 | H83: =SUM(E83:G83) -> 0 | J83: ='77'!$C$64 -> 0 | K83: ='77'!$G$64 -> 0 | L83: ='77'!$L$64 -> 0 | M83: ='77'!$S$64 -> 0 | N83: ='77'!$M$64 -> 0 | R83: ='77'!$V$39 -> 0 | S83: ='77'!$V$40 -> 0 | T83: ='77'!$V$41 -> 0 | U83: ='77'!$V$44 -> 0 | V83: ='77'!$V$42 -> 0 | W83: ='77'!$V$43 -> 0 | X83: ='77'!$V$46 -> 0 | Y83: ='77'!$V$47 -> 0 | Z83: ='77'!$V$48 -> 0 | AA83: ='77'!$V$49 -> 0 | AB83: ='77'!$V$50 -> 0 | AC83: ='77'!$V$51 -> 0 | AD83: ='77'!V$52+'77'!V$53 -> 0 | AE83: =(R83+S83)-SUM(T83:AC83) -> 0
A84: 78 | H84: =SUM(E84:G84) -> 0 | J84: ='78'!$C$64 -> 0 | K84: ='78'!$G$64 -> 0 | L84: ='78'!$L$64 -> 0 | M84: ='78'!$S$64 -> 0 | N84: ='78'!$M$64 -> 0 | R84: ='78'!$V$39 -> 0 | S84: ='78'!$V$40 -> 0 | T84: ='78'!$V$41 -> 0 | U84: ='78'!$V$44 -> 0 | V84: ='78'!$V$42 -> 0 | W84: ='78'!$V$43 -> 0 | X84: ='78'!$V$46 -> 0 | Y84: ='78'!$V$47 -> 0 | Z84: ='78'!$V$48 -> 0 | AA84: ='78'!$V$49 -> 0 | AB84: ='78'!$V$50 -> 0 | AC84: ='78'!$V$51 -> 0 | AD84: ='78'!V$52+'78'!V$53 -> 0 | AE84: =(R84+S84)-SUM(T84:AC84) -> 0
A85: 79 | H85: =SUM(E85:G85) -> 0 | J85: ='79'!$C$64 -> 0 | K85: ='79'!$G$64 -> 0 | L85: ='79'!$L$64 -> 0 | M85: ='79'!$S$64 -> 0 | N85: ='79'!$M$64 -> 0 | R85: ='79'!$V$39 -> 0 | S85: ='79'!$V$40 -> 0 | T85: ='79'!$V$41 -> 0 | U85: ='79'!$V$44 -> 0 | V85: ='79'!$V$42 -> 0 | W85: ='79'!$V$43 -> 0 | X85: ='79'!$V$46 -> 0 | Y85: ='79'!$V$47 -> 0 | Z85: ='79'!$V$48 -> 0 | AA85: ='79'!$V$49 -> 0 | AB85: ='79'!$V$50 -> 0 | AC85: ='79'!$V$51 -> 0 | AD85: ='79'!V$52+'79'!V$53 -> 0 | AE85: =(R85+S85)-SUM(T85:AC85) -> 0
A86: 80 | H86: =SUM(E86:G86) -> 0 | J86: ='80'!$C$64 -> 0 | K86: ='80'!$G$64 -> 0 | L86: ='80'!$L$64 -> 0 | M86: ='80'!$S$64 -> 0 | N86: ='80'!$M$64 -> 0 | R86: ='80'!$V$39 -> 0 | S86: ='80'!$V$40 -> 0 | T86: ='80'!$V$41 -> 0 | U86: ='80'!$V$44 -> 0 | V86: ='80'!$V$42 -> 0 | W86: ='80'!$V$43 -> 0 | X86: ='80'!$V$46 -> 0 | Y86: ='80'!$V$47 -> 0 | Z86: ='80'!$V$48 -> 0 | AA86: ='80'!$V$49 -> 0 | AB86: ='80'!$V$50 -> 0 | AC86: ='80'!$V$51 -> 0 | AD86: ='80'!V$52+'80'!V$53 -> 0 | AE86: =(R86+S86)-SUM(T86:AC86) -> 0
A87: 81 | H87: =SUM(E87:G87) -> 0 | J87: ='81'!$C$64 -> 0 | K87: ='81'!$G$64 -> 0 | L87: ='81'!$L$64 -> 0 | M87: ='81'!$S$64 -> 0 | N87: ='81'!$M$64 -> 0 | R87: ='81'!$V$39 -> 0 | S87: ='81'!$V$40 -> 0 | T87: ='81'!$V$41 -> 0 | U87: ='81'!$V$44 -> 0 | V87: ='81'!$V$42 -> 0 | W87: ='81'!$V$43 -> 0 | X87: ='81'!$V$46 -> 0 | Y87: ='81'!$V$47 -> 0 | Z87: ='81'!$V$48 -> 0 | AA87: ='81'!$V$49 -> 0 | AB87: ='81'!$V$50 -> 0 | AC87: ='81'!$V$51 -> 0 | AD87: ='81'!V$52+'81'!V$53 -> 0 | AE87: =(R87+S87)-SUM(T87:AC87) -> 0
A88: 82 | H88: =SUM(E88:G88) -> 0 | J88: ='82'!$C$64 -> 0 | K88: ='82'!$G$64 -> 0 | L88: ='82'!$L$64 -> 0 | M88: ='82'!$S$64 -> 0 | N88: ='82'!$M$64 -> 0 | R88: ='82'!$V$39 -> 0 | S88: ='82'!$V$40 -> 0 | T88: ='82'!$V$41 -> 0 | U88: ='82'!$V$44 -> 0 | V88: ='82'!$V$42 -> 0 | W88: ='82'!$V$43 -> 0 | X88: ='82'!$V$46 -> 0 | Y88: ='82'!$V$47 -> 0 | Z88: ='82'!$V$48 -> 0 | AA88: ='82'!$V$49 -> 0 | AB88: ='82'!$V$50 -> 0 | AC88: ='82'!$V$51 -> 0 | AD88: ='82'!V$52+'82'!V$53 -> 0 | AE88: =(R88+S88)-SUM(T88:AC88) -> 0
A89: 83 | H89: =SUM(E89:G89) -> 0 | J89: ='83'!$C$64 -> 0 | K89: ='83'!$G$64 -> 0 | L89: ='83'!$L$64 -> 0 | M89: ='83'!$S$64 -> 0 | N89: ='83'!$M$64 -> 0 | R89: ='83'!$V$39 -> 0 | S89: ='83'!$V$40 -> 0 | T89: ='83'!$V$41 -> 0 | U89: ='83'!$V$44 -> 0 | V89: ='83'!$V$42 -> 0 | W89: ='83'!$V$43 -> 0 | X89: ='83'!$V$46 -> 0 | Y89: ='83'!$V$47 -> 0 | Z89: ='83'!$V$48 -> 0 | AA89: ='83'!$V$49 -> 0 | AB89: ='83'!$V$50 -> 0 | AC89: ='83'!$V$51 -> 0 | AD89: ='83'!V$52+'83'!V$53 -> 0 | AE89: =(R89+S89)-SUM(T89:AC89) -> 0
A90: 84 | H90: =SUM(E90:G90) -> 0 | J90: ='84'!$C$64 -> 0 | K90: ='84'!$G$64 -> 0 | L90: ='84'!$L$64 -> 0 | M90: ='84'!$S$64 -> 0 | N90: ='84'!$M$64 -> 0 | R90: ='84'!$V$39 -> 0 | S90: ='84'!$V$40 -> 0 | T90: ='84'!$V$41 -> 0 | U90: ='84'!$V$44 -> 0 | V90: ='84'!$V$42 -> 0 | W90: ='84'!$V$43 -> 0 | X90: ='84'!$V$46 -> 0 | Y90: ='84'!$V$47 -> 0 | Z90: ='84'!$V$48 -> 0 | AA90: ='84'!$V$49 -> 0 | AB90: ='84'!$V$50 -> 0 | AC90: ='84'!$V$51 -> 0 | AD90: ='84'!V$52+'84'!V$53 -> 0 | AE90: =(R90+S90)-SUM(T90:AC90) -> 0
A91: 85 | H91: =SUM(E91:G91) -> 0 | J91: ='85'!$C$64 -> 0 | K91: ='85'!$G$64 -> 0 | L91: ='85'!$L$64 -> 0 | M91: ='85'!$S$64 -> 0 | N91: ='85'!$M$64 -> 0 | R91: ='85'!$V$39 -> 0 | S91: ='85'!$V$40 -> 0 | T91: ='85'!$V$41 -> 0 | U91: ='85'!$V$44 -> 0 | V91: ='85'!$V$42 -> 0 | W91: ='85'!$V$43 -> 0 | X91: ='85'!$V$46 -> 0 | Y91: ='85'!$V$47 -> 0 | Z91: ='85'!$V$48 -> 0 | AA91: ='85'!$V$49 -> 0 | AB91: ='85'!$V$50 -> 0 | AC91: ='85'!$V$51 -> 0 | AD91: ='85'!V$52+'85'!V$53 -> 0 | AE91: =(R91+S91)-SUM(T91:AC91) -> 0
A92: 86 | H92: =SUM(E92:G92) -> 0 | J92: ='86'!$C$64 -> 0 | K92: ='86'!$G$64 -> 0 | L92: ='86'!$L$64 -> 0 | M92: ='86'!$S$64 -> 0 | N92: ='86'!$M$64 -> 0 | R92: ='86'!$V$39 -> 0 | S92: ='86'!$V$40 -> 0 | T92: ='86'!$V$41 -> 0 | U92: ='86'!$V$44 -> 0 | V92: ='86'!$V$42 -> 0 | W92: ='86'!$V$43 -> 0 | X92: ='86'!$V$46 -> 0 | Y92: ='86'!$V$47 -> 0 | Z92: ='86'!$V$48 -> 0 | AA92: ='86'!$V$49 -> 0 | AB92: ='86'!$V$50 -> 0 | AC92: ='86'!$V$51 -> 0 | AD92: ='86'!V$52+'86'!V$53 -> 0 | AE92: =(R92+S92)-SUM(T92:AC92) -> 0
A93: 87 | H93: =SUM(E93:G93) -> 0 | J93: ='87'!$C$64 -> 0 | K93: ='87'!$G$64 -> 0 | L93: ='87'!$L$64 -> 0 | M93: ='87'!$S$64 -> 0 | N93: ='87'!$M$64 -> 0 | R93: ='87'!$V$39 -> 0 | S93: ='87'!$V$40 -> 0 | T93: ='87'!$V$41 -> 0 | U93: ='87'!$V$44 -> 0 | V93: ='87'!$V$42 -> 0 | W93: ='87'!$V$43 -> 0 | X93: ='87'!$V$46 -> 0 | Y93: ='87'!$V$47 -> 0 | Z93: ='87'!$V$48 -> 0 | AA93: ='87'!$V$49 -> 0 | AB93: ='87'!$V$50 -> 0 | AC93: ='87'!$V$51 -> 0 | AD93: ='87'!V$52+'87'!V$53 -> 0 | AE93: =(R93+S93)-SUM(T93:AC93) -> 0
A94: 88 | H94: =SUM(E94:G94) -> 0 | J94: ='88'!$C$64 -> 0 | K94: ='88'!$G$64 -> 0 | L94: ='88'!$L$64 -> 0 | M94: ='88'!$S$64 -> 0 | N94: ='88'!$M$64 -> 0 | R94: ='88'!$V$39 -> 0 | S94: ='88'!$V$40 -> 0 | T94: ='88'!$V$41 -> 0 | U94: ='88'!$V$44 -> 0 | V94: ='88'!$V$42 -> 0 | W94: ='88'!$V$43 -> 0 | X94: ='88'!$V$46 -> 0 | Y94: ='88'!$V$47 -> 0 | Z94: ='88'!$V$48 -> 0 | AA94: ='88'!$V$49 -> 0 | AB94: ='88'!$V$50 -> 0 | AC94: ='88'!$V$51 -> 0 | AD94: ='88'!V$52+'88'!V$53 -> 0 | AE94: =(R94+S94)-SUM(T94:AC94) -> 0
A95: 89 | H95: =SUM(E95:G95) -> 0 | J95: ='89'!$C$64 -> 0 | K95: ='89'!$G$64 -> 0 | L95: ='89'!$L$64 -> 0 | M95: ='89'!$S$64 -> 0 | N95: ='89'!$M$64 -> 0 | R95: ='89'!$V$39 -> 0 | S95: ='89'!$V$40 -> 0 | T95: ='89'!$V$41 -> 0 | U95: ='89'!$V$44 -> 0 | V95: ='89'!$V$42 -> 0 | W95: ='89'!$V$43 -> 0 | X95: ='89'!$V$46 -> 0 | Y95: ='89'!$V$47 -> 0 | Z95: ='89'!$V$48 -> 0 | AA95: ='89'!$V$49 -> 0 | AB95: ='89'!$V$50 -> 0 | AC95: ='89'!$V$51 -> 0 | AD95: ='89'!V$52+'89'!V$53 -> 0 | AE95: =(R95+S95)-SUM(T95:AC95) -> 0
A96: 90 | H96: =SUM(E96:G96) -> 0 | J96: ='90'!$C$64 -> 0 | K96: ='90'!$G$64 -> 0 | L96: ='90'!$L$64 -> 0 | M96: ='90'!$S$64 -> 0 | N96: ='90'!$M$64 -> 0 | R96: ='90'!$V$39 -> 0 | S96: ='90'!$V$40 -> 0 | T96: ='90'!$V$41 -> 0 | U96: ='90'!$V$44 -> 0 | V96: ='90'!$V$42 -> 0 | W96: ='90'!$V$43 -> 0 | X96: ='90'!$V$46 -> 0 | Y96: ='90'!$V$47 -> 0 | Z96: ='90'!$V$48 -> 0 | AA96: ='90'!$V$49 -> 0 | AB96: ='90'!$V$50 -> 0 | AC96: ='90'!$V$51 -> 0 | AD96: ='90'!V$52+'90'!V$53 -> 0 | AE96: =(R96+S96)-SUM(T96:AC96) -> 0
A97: 91 | H97: =SUM(E97:G97) -> 0 | J97: ='91'!$C$64 -> 0 | K97: ='91'!$G$64 -> 0 | L97: ='91'!$L$64 -> 0 | M97: ='91'!$S$64 -> 0 | N97: ='91'!$M$64 -> 0 | R97: ='91'!$V$39 -> 0 | S97: ='91'!$V$40 -> 0 | T97: ='91'!$V$41 -> 0 | U97: ='91'!$V$44 -> 0 | V97: ='91'!$V$42 -> 0 | W97: ='91'!$V$43 -> 0 | X97: ='91'!$V$46 -> 0 | Y97: ='91'!$V$47 -> 0 | Z97: ='91'!$V$48 -> 0 | AA97: ='91'!$V$49 -> 0 | AB97: ='91'!$V$50 -> 0 | AC97: ='91'!$V$51 -> 0 | AD97: ='91'!V$52+'91'!V$53 -> 0 | AE97: =(R97+S97)-SUM(T97:AC97) -> 0
A98: 92 | H98: =SUM(E98:G98) -> 0 | J98: ='92'!$C$64 -> 0 | K98: ='92'!$G$64 -> 0 | L98: ='92'!$L$64 -> 0 | M98: ='92'!$S$64 -> 0 | N98: ='92'!$M$64 -> 0 | R98: ='92'!$V$39 -> 0 | S98: ='92'!$V$40 -> 0 | T98: ='92'!$V$41 -> 0 | U98: ='92'!$V$44 -> 0 | V98: ='92'!$V$42 -> 0 | W98: ='92'!$V$43 -> 0 | X98: ='92'!$V$46 -> 0 | Y98: ='92'!$V$47 -> 0 | Z98: ='92'!$V$48 -> 0 | AA98: ='92'!$V$49 -> 0 | AB98: ='92'!$V$50 -> 0 | AC98: ='92'!$V$51 -> 0 | AD98: ='92'!V$52+'92'!V$53 -> 0 | AE98: =(R98+S98)-SUM(T98:AC98) -> 0
A99: 93 | H99: =SUM(E99:G99) -> 0 | J99: ='93'!$C$64 -> 0 | K99: ='93'!$G$64 -> 0 | L99: ='93'!$L$64 -> 0 | M99: ='93'!$S$64 -> 0 | N99: ='93'!$M$64 -> 0 | R99: ='93'!$V$39 -> 0 | S99: ='93'!$V$40 -> 0 | T99: ='93'!$V$41 -> 0 | U99: ='93'!$V$44 -> 0 | V99: ='93'!$V$42 -> 0 | W99: ='93'!$V$43 -> 0 | X99: ='93'!$V$46 -> 0 | Y99: ='93'!$V$47 -> 0 | Z99: ='93'!$V$48 -> 0 | AA99: ='93'!$V$49 -> 0 | AB99: ='93'!$V$50 -> 0 | AC99: ='93'!$V$51 -> 0 | AD99: ='93'!V$52+'93'!V$53 -> 0 | AE99: =(R99+S99)-SUM(T99:AC99) -> 0
A100: 94 | H100: =SUM(E100:G100) -> 0 | J100: ='94'!$C$64 -> 0 | K100: ='94'!$G$64 -> 0 | L100: ='94'!$L$64 -> 0 | M100: ='94'!$S$64 -> 0 | N100: ='94'!$M$64 -> 0 | R100: ='94'!$V$39 -> 0 | S100: ='94'!$V$40 -> 0 | T100: ='94'!$V$41 -> 0 | U100: ='94'!$V$44 -> 0 | V100: ='94'!$V$42 -> 0 | W100: ='94'!$V$43 -> 0 | X100: ='94'!$V$46 -> 0 | Y100: ='94'!$V$47 -> 0 | Z100: ='94'!$V$48 -> 0 | AA100: ='94'!$V$49 -> 0 | AB100: ='94'!$V$50 -> 0 | AC100: ='94'!$V$51 -> 0 | AD100: ='94'!V$52+'94'!V$53 -> 0 | AE100: =(R100+S100)-SUM(T100:AC100) -> 0
A101: 95 | H101: =SUM(E101:G101) -> 0 | J101: ='95'!$C$64 -> 0 | K101: ='95'!$G$64 -> 0 | L101: ='95'!$L$64 -> 0 | M101: ='95'!$S$64 -> 0 | N101: ='95'!$M$64 -> 0 | R101: ='95'!$V$39 -> 0 | S101: ='95'!$V$40 -> 0 | T101: ='95'!$V$41 -> 0 | U101: ='95'!$V$44 -> 0 | V101: ='95'!$V$42 -> 0 | W101: ='95'!$V$43 -> 0 | X101: ='95'!$V$46 -> 0 | Y101: ='95'!$V$47 -> 0 | Z101: ='95'!$V$48 -> 0 | AA101: ='95'!$V$49 -> 0 | AB101: ='95'!$V$50 -> 0 | AC101: ='95'!$V$51 -> 0 | AD101: ='95'!V$52+'95'!V$53 -> 0 | AE101: =(R101+S101)-SUM(T101:AC101) -> 0
...

Sheet NORTH AMERICA
A1: GLOBAL MERCHANDISING SERVICES, INC
A2: TOUR BUDGET - NORTH AMERICA
A4: ARTIST | I4: BRAND MANAGER
A5: TERRITORY | B5: NORTH AMERICA | I5: CURRENCY | L5: USD
A6: TOUR START/LOAD IN DATE | I6: FIRST SHOW CITY
A7: TOUR FINISH/LOUD OUT DATE | I7: LAST SHOW CITY
A8: TOUR DAYS | B8: =B7-B6 -> 0 | I8: TRANSPORT - RECOUP | L8: YES
A9: ROAD MANAGER | B9: Yes | I9: SECURITY - RECOUP | L9: YES
A11: TOUR ASSUMPTIONS | B11: USA | E11: CANADA | H11: FESTIVALS | K11: TOUR TOTAL
A13: TOTAL CAPACITY | K13: =E13+B13+H13 -> 0
A14: PROJ.ATTENDANCE | B14: 1 | E14: 1 | H14: 0 | K14: =IFERROR(K15/K13,0) -> 0
A15: PROJ.ATTENDANCE | B15: =B13*B14 -> 0 | E15: =E13*E14 -> 0 | H15: 0 | K15: =E15+B15+H15 -> 0
A16: TOUR STAFF | K16: =B16 -> 0
A17: NO.OF SHOWS | K17: =E17+B17+H17 -> 0
A18: P/HEAD | K18: =IFERROR(K20/K15,0) -> 0
A20: GROSS SALES | B20: =B18*B15 -> 0 | E20: =E18*E15 -> 0 | H20: =H18*H15 -> 0 | K20: =E20+B20+H20 -> 0
A21: CREDIT CARD % | B21: 1 | E21: 1 | H21: 1 | K21: =IFERROR(K22/K20,0) -> 0
A22: CREDT CARD AMOUNT | B22: =B20*B21 -> 0 | E22: =E20*E21 -> 0 | H22: =H20*H21 -> 0 | K22: =E22+B22+H22 -> 0
A23: PROGRAM PERCENTAGE | B23: 0 | E23: 0 | H23: 0 | K23: =IFERROR(K24/K20,0) -> 0
A24: PROGRAM GROSS | B24: =B23*B20 -> 0 | E24: =E23*E20 -> 0 | H24: =H23*H20 -> 0 | K24: =E24+B24+H24 -> 0
A25: TAX: | B25: =(B20-B24)*C25/(1+C25) -> 0 | C25: 0.08 | E25: =E20*F25/(1+F25) -> 0 | F25: 0.13 | H25: =H20*I25/(1+I25) -> 0 | I25: 0.08 | K25: =E25+B25+H25 -> 0 | L25: =IF(K25=0,0,K25/$K$26) -> 0
A26: NET SALES | B26: =B20-B25 -> 0 | E26: =E20-E25 -> 0 | H26: =H20-H25 -> 0 | K26: =E26+B26+H26 -> 0
A29: TOUR COSTS - ON NET | B29: =B11 -> USA | E29: =E11 -> CANADA | H29: =H11 -> FESTIVALS | K29: =K11 -> TOUR TOTAL
A31: COST OF GOODS | B31: =ROUND((B$26*C31),2) -> 0 | C31: 0 | E31: =ROUND((E$26*F31),2) -> 0 | F31: 0 | H31: =ROUND((H$26*I31),2) -> 0 | I31: 0 | K31: =B31+E31+H31 -> 0 | L31: =IF(K31=0,0,K31/$K$26) -> 0
A32: COST OF GOODS - UPLIFT | B32: =ROUND(B31*C32,2) -> 0 | C32: 0 | E32: =ROUND(E31*F32,2) -> 0 | F32: 0 | H32: =ROUND(H31*I32,2) -> 0 | I32: 0 | K32: =B32+E32+H32 -> 0 | L32: =IF(K32=0,0,K32/$K$26) -> 0
A33: ARTWORK | B33: =ROUND((B$26*C33),2) -> 0 | C33: 0 | E33: =ROUND((E$26*F33),2) -> 0 | F33: 0 | H33: =ROUND((H$26*I33),2) -> 0 | I33: 0 | K33: =B33+E33+H33 -> 0 | L33: =IF(K33=0,0,K33/$K$26) -> 0
A34: HALL FEES | B34: =ROUND((B$26*C34),2) -> 0 | C34: 0 | E34: =ROUND((E$26*F34),2) -> 0 | F34: 0 | H34: =ROUND((H$26*I34),2) -> 0 | I34: 0 | K34: =B34+E34+H34 -> 0 | L34: =IF(K34=0,0,K34/$K$26) -> 0
A35: CREDIT CARD FEE | B35: =ROUND(((B$26*B21)*C35),2) -> 0 | C35: 0 | E35: =ROUND(((E$26*E21)*F35),2) -> 0 | F35: 0 | H35: =ROUND(((H$26*H21)*I35),2) -> 0 | I35: 0 | K35: =B35+E35+H35 -> 0 | L35: =IF(K35=0,0,K35/$K$26) -> 0
A36: BOOTLEG SECURITY & LEGAL | B36: =IF($L$9="YES",0,ROUND((B$26*C36),2)) -> 0 | C36: 0 | E36: =IF($L$9="YES",0,ROUND((E$26*F36),2)) -> 0 | F36: 0 | H36: =IF($L$9="YES",0,ROUND((H$26*I36),2)) -> 0 | I36: 0 | K36: =B36+E36+H36 -> 0 | L36: =IF(K36=0,0,K36/$K$26) -> 0
A37: VENDORS | B37: =ROUND((B$26*C37),2) -> 0 | C37: 0 | E37: =ROUND((E$26*F37),2) -> 0 | F37: 0 | H37: =ROUND((H$26*I37),2) -> 0 | I37: 0 | K37: =B37+E37+H37 -> 0 | L37: =IF(K37=0,0,K37/$K$26) -> 0
A38: FREIGHT COST | B38: =ROUND((B$26*C38),2) -> 0 | C38: 0 | E38: =ROUND((E$26*F38),2) -> 0 | F38: 0 | H38: =ROUND((H$26*I38),2) -> 0 | I38: 0 | K38: =B38+E38+H38 -> 0 | L38: =IF(K38=0,0,K38/$K$26) -> 0
A39: DUTIES/TAXES | B39: =ROUND((B$31*C39),2) -> 0 | C39: 0 | E39: =ROUND((E$31*F39),2) -> 0 | F39: 0 | H39: =ROUND((H$31*I39),2) -> 0 | I39: 0 | K39: =B39+E39+H39 -> 0 | L39: =IF(K39=0,0,K39/$K$26) -> 0
A40: ROAD EXPENSES | B40: =IF($L$8="YES",B71-SUM(B66:B69),B71) -> 0 | C40: =IF(B40=0,0,B40/B26) -> 0 | E40: =IF($L$8="YES",E71-SUM(E66:E69),E71) -> 0 | F40: =IF(E40=0,0,E40/E26) -> 0 | H40: =IF($L$8="YES",H71-SUM(H66:H69),H71) -> 0 | I40: =IF(H40=0,0,H40/H26) -> 0 | K40: =B40+E40+H40 -> 0 | L40: =IF(K40=0,0,K40/$K$26) -> 0
A41: ADMIN FEE | B41: =ROUND((B$26*C41),2) -> 0 | C41: 0.03 | E41: =ROUND((E$26*F41),2) -> 0 | F41: 0.03 | H41: =ROUND((H$26*I41),2) -> 0 | I41: 0.03 | K41: =B41+E41+H41 -> 0 | L41: =IF(K41=0,0,K41/$K$26) -> 0
A42: TRANSPORT - RECOUPABLE | B42: =IF($L$8="YES",SUM(B66:B69),0) -> 0 | C42: =IF(B42=0,0,B42/B26) -> 0 | E42: =IF($L$8="YES",SUM(E66:E69),0) -> 0 | F42: =IF(E42=0,0,E42/E26) -> 0 | H42: =IF($L$8="YES",SUM(H66:H69),0) -> 0 | I42: =IF(H42=0,0,H42/H26) -> 0 | K42: =B42+E42+H42 -> 0 | L42: =IF(K42=0,0,K42/$K$26) -> 0
A43: BOOTLEG SECURITY & LEGAL - RECOUPABLE | B43: =IF($L$9="YES",ROUND((B$26*C43),2),0) -> 0 | C43: =C36 -> 0 | E43: =IF($L$9="YES",ROUND((E$26*F43),2),0) -> 0 | F43: =F36 -> 0 | H43: =IF($L$9="YES",ROUND((H$26*I43),2),0) -> 0 | I43: =I36 -> 0 | K43: =B43+E43+H43 -> 0 | L43: =IF(K43=0,0,K43/$K$26) -> 0
A45: TOTAL TOUR COSTS | B45: =SUM(B31:B41) -> 0 | C45: =IF(B45=0,0,B45/B26) -> 0 | E45: =SUM(E31:E41) -> 0 | F45: =IF(E45=0,0,E45/E26) -> 0 | H45: =SUM(H31:H41) -> 0 | I45: =IF(H45=0,0,H45/H26) -> 0 | K45: =SUM(K31:K41) -> 0 | L45: =IF(K45=0,0,K45/K26) -> 0
A46: PROFIT | B46: =B26-B45 -> 0 | C46: =IF(B46=0,0,B46/B26) -> 0 | E46: =E26-E45 -> 0 | F46: =IF(E46=0,0,E46/E26) -> 0 | H46: =H26-H45 -> 0 | I46: =IF(H46=0,0,H46/H26) -> 0 | K46: =B46+E46+H46 -> 0 | L46: =IF(K46=0,0,K46/K26) -> 0
A47: ARTIST | B47: =B46*C47 -> 0 | C47: 0.8 | E47: =E46*F47 -> 0 | F47: 0.8 | H47: =H46*I47 -> 0 | I47: 0.8 | K47: =B47+E47+H47 -> 0 | L47: =IF(K47=0,0,K47/K46) -> 0
A48: GLOBAL | B48: =B46*C48 -> 0 | C48: =1-C47 -> 0.2 | E48: =E46*F48 -> 0 | F48: =1-F47 -> 0.2 | H48: =H46*I48 -> 0 | I48: =1-I47 -> 0.2 | K48: =B48+E48+H48 -> 0 | L48: =IF(K48=0,0,K48/K46) -> 0
A51: ROAD EXPENSES BREAKDOWN | B51: =B11 -> USA | E51: =E11 -> CANADA | H51: =H11 -> FESTIVALS | K51: =K11 -> TOUR TOTAL
A53: DAYS | K53: =B53+E53+H53 -> 0
A54: HOTELS | K54: =B54+E54+H54 -> 0
A55: NO. OF STAFF | B55: =B16 -> 0 | C55: RATE | E55: =E16 -> 0 | F55: RATE | H55: =H16 -> 0 | I55: RATE
A57: TOUR MANAGER | B57: =C57*B53 -> 0 | E57: =F57*E53 -> 0 | H57: =I57*H53 -> 0 | K57: =B57+E57+H57 -> 0
A58: ASSISTANT MANAGER | B58: =C58*B53 -> 0 | C58: 0 | E58: =F58*E53 -> 0 | F58: 0 | H58: =I58*H53 -> 0 | K58: =B58+E58+H58 -> 0
A59: PAYROLL COSTS | B59: =(B58+B57)*C59 -> 0 | C59: =IF(B9="YES",8.5%,1%) -> 0.085 | E59: =(E58+E57)*F59 -> 0 | F59: =IF(B9="YES",8.5%,2%) -> 0.085 | H59: =(H58+H57)*I59 -> 0 | I59: =IF(B9="YES",8.5%,2%) -> 0.085 | K59: =B59+E59+H59 -> 0
A60: P/DIEMS | B60: =C60*B53 -> 0 | E60: =F60*E53 -> 0 | H60: =I60*H55*H53 -> 0 | K60: =B60+E60+H60 -> 0
A61: ADDITIONAL STAFF | B61: 0 | E61: 0 | H61: 0 | K61: =B61+E61+H61 -> 0
A62: =("HOTEL - "&K54&" NIGHTS") -> HOTEL - 0 NIGHTS | B62: =C62*B54 -> 0 | E62: =F62*E54 -> 0 | H62: =I62*H54 -> 0 | K62: =B62+E62+H62 -> 0
A63: TAXI/TRAVEL | B63: 0 | E63: 0 | H63: 0 | K63: =B63+E63+H63 -> 0
A64: PHONE / COMPUTER | B64: 0 | E64: 0 | H64: 0 | K64: =B64+E64+H64 -> 0
A65: MISCELLANEOUS | B65: 0 | E65: 0 | H65: 0 | K65: =B65+E65+H65 -> 0
A66: TRUCK RENTAL | B66: =C66*B53 -> 0 | E66: =F66*E53 -> 0 | H66: =I66*H53 -> 0 | K66: =B66+E66+H66 -> 0
A67: INS & GREEN CARD | B67: 0 | E67: 0 | H67: 0 | K67: =B67+E67+H67 -> 0
A68: FUEL | B68: 0 | E68: 0 | H68: 0 | K68: =B68+E68+H68 -> 0
A69: TOLLS | B69: 0 | E69: 0 | H69: 0 | K69: =B69+E69+H69 -> 0
A71: TOTAL ROAD EXPENSES | B71: =SUM(B57:B70) -> 0 | E71: =SUM(E57:E70) -> 0 | H71: =SUM(H57:H70) -> 0 | K71: =SUM(K57:K70) -> 0

Sheet COGS NEW TEMPLATE
A1: GLOBAL MERCHANDISING SERVICES, INC.
A2: =Inventory!C3 -> GHOST
A3: TOUR COST OF GOODS SCHEDULE - NORTH AMERICA in USD
A4: 45874
A6: Brand Manager: | C6: KAYLA
A7: Enter sales tax rate: | C7: 0
A8: Enter specials rate: | C8: 0.2 | E8: CLOSE WHEN PDFing and SENDING TO CLIENT
A9: APPAREL | R9: APPAREL - ADJUSTED PRICE FOR SPECIAL
A10: ITEM # | B10: SKU # | C10: DESCRIPTION | D10: SIZE | E10: BLANK | F10: PRINT | G10: FULL PACKAGE | H10: COG | I10: COG 2 | J10: TOTAL COG | K10: SUGGESTED PRICE | L10: =("TAX @ " &C7) -> TAX @ 0 | M10: AFTER TAX ADJ. GROSS | N10: PRODUCT COST % (A.T.G.) | O10: SPECIAL YES/NO | P10: AGREED DATE BY BM | R10: SPECIAL ITEM PRICE | S10: =L10 -> TAX @ 0 | T10: AFTER TAX ADJ. GROSS | U10: SPECIAL COST % (A.T.G.) | V10: SPECIAL YES/NO
A11: 1 | B11: =VLOOKUP($A:$A,Inventory!$A:$C,2,FALSE) -> GHOSRX203729BK | C11: =VLOOKUP($A:$A,Inventory!$A:$C,3,FALSE) -> BLACK T SKELETOUR 2025 ITIN | D11: SM-XL | E11: 0 | F11: 0 | G11: 5.7 | H11: =SUM(E11:G11) -> 5.7 | I11: 0 | J11: =SUM(H11:I11) -> 5.7 | K11: 50 | L11: =$C$7 -> 0 | M11: =K11-IF(K11<>0,K11-(K11/(1+L11)),0) -> 50 | N11: =J11/M11 -> 0.114 | O11: =IF(N11>$C$8,"YES","NO") -> NO | R11: 55 | S11: =$C$7 -> 0 | T11: =R11-IF(R11<>0,R11-(R11/(1+S11)),0) -> 55 | U11: =J11/T11 -> 0.10363636 | V11: =IF(U11>$C$8,"YES","NO") -> NO
D12: 2XL | E12: 0 | F12: 0 | G12: 7.89 | H12: =SUM(E12:G12) -> 7.89 | I12: 0 | J12: =SUM(H12:I12) -> 7.89 | K12: 50 | L12: =$C$7 -> 0 | M12: =K12-IF(K12<>0,K12-(K12/(1+L12)),0) -> 50 | N12: =J12/M12 -> 0.1578 | O12: =IF(N12>$C$8,"YES","NO") -> NO | R12: 55 | S12: =$C$7 -> 0 | T12: =R12-IF(R12<>0,R12-(R12/(1+S12)),0) -> 55 | U12: =J12/T12 -> 0.14345455 | V12: =IF(U12>$C$8,"YES","NO") -> NO
D13: 3XL | E13: 0 | F13: 0 | G13: 9.22 | H13: =SUM(E13:G13) -> 9.22 | I13: 0 | J13: =SUM(H13:I13) -> 9.22 | K13: 50 | L13: =$C$7 -> 0 | M13: =K13-IF(K13<>0,K13-(K13/(1+L13)),0) -> 50 | N13: =J13/M13 -> 0.1844 | O13: =IF(N13>$C$8,"YES","NO") -> NO | R13: 55 | S13: =$C$7 -> 0 | T13: =R13-IF(R13<>0,R13-(R13/(1+S13)),0) -> 55 | U13: =J13/T13 -> 0.16763636 | V13: =IF(U13>$C$8,"YES","NO") -> NO
D14: 4XL | E14: 0 | F14: 0 | G14: 0 | H14: =SUM(E14:G14) -> 0 | I14: 0 | J14: =SUM(H14:I14) -> 0 | K14: 50 | L14: =$C$7 -> 0 | M14: =K14-IF(K14<>0,K14-(K14/(1+L14)),0) -> 50 | N14: =J14/M14 -> 0 | O14: =IF(N14>$C$8,"YES","NO") -> NO | R14: 55 | S14: =$C$7 -> 0 | T14: =R14-IF(R14<>0,R14-(R14/(1+S14)),0) -> 55 | U14: =J14/T14 -> 0 | V14: =IF(U14>$C$8,"YES","NO") -> NO
A15: 2 | B15: =VLOOKUP($A:$A,Inventory!$A:$C,2,FALSE) -> GHOSRX203728BK | C15: =VLOOKUP($A:$A,Inventory!$A:$C,3,FALSE) -> BLACK T SKELETA ALBUM COVER 2025 ITIN | D15: SM-XL | E15: 0 | F15: 0 | G15: 5.7 | H15: =SUM(E15:G15) -> 5.7 | I15: 0 | J15: =SUM(H15:I15) -> 5.7 | K15: 50 | L15: =$C$7 -> 0 | M15: =K15-IF(K15<>0,K15-(K15/(1+L15)),0) -> 50 | N15: =J15/M15 -> 0.114 | O15: =IF(N15>$C$8,"YES","NO") -> NO | R15: 55 | S15: =$C$7 -> 0 | T15: =R15-IF(R15<>0,R15-(R15/(1+S15)),0) -> 55 | U15: =J15/T15 -> 0.10363636 | V15: =IF(U15>$C$8,"YES","NO") -> NO
D16: 2XL | E16: 0 | F16: 0 | G16: 7.89 | H16: =SUM(E16:G16) -> 7.89 | I16: 0 | J16: =SUM(H16:I16) -> 7.89 | K16: 50 | L16: =$C$7 -> 0 | M16: =K16-IF(K16<>0,K16-(K16/(1+L16)),0) -> 50 | N16: =J16/M16 -> 0.1578 | O16: =IF(N16>$C$8,"YES","NO") -> NO | R16: 55 | S16: =$C$7 -> 0 | T16: =R16-IF(R16<>0,R16-(R16/(1+S16)),0) -> 55 | U16: =J16/T16 -> 0.14345455 | V16: =IF(U16>$C$8,"YES","NO") -> NO
D17: 3XL | E17: 0 | F17: 0 | G17: 9.22 | H17: =SUM(E17:G17) -> 9.22 | I17: 0 | J17: =SUM(H17:I17) -> 9.22 | K17: 50 | L17: =$C$7 -> 0 | M17: =K17-IF(K17<>0,K17-(K17/(1+L17)),0) -> 50 | N17: =J17/M17 -> 0.1844 | O17: =IF(N17>$C$8,"YES","NO") -> NO | R17: 55 | S17: =$C$7 -> 0 | T17: =R17-IF(R17<>0,R17-(R17/(1+S17)),0) -> 55 | U17: =J17/T17 -> 0.16763636 | V17: =IF(U17>$C$8,"YES","NO") -> NO
D18: 4XL | E18: 0 | F18: 0 | G18: 0 | H18: =SUM(E18:G18) -> 0 | I18: 0 | J18: =SUM(H18:I18) -> 0 | K18: 50 | L18: =$C$7 -> 0 | M18: =K18-IF(K18<>0,K18-(K18/(1+L18)),0) -> 50 | N18: =J18/M18 -> 0 | O18: =IF(N18>$C$8,"YES","NO") -> NO | R18: 55 | S18: =$C$7 -> 0 | T18: =R18-IF(R18<>0,R18-(R18/(1+S18)),0) -> 55 | U18: =J18/T18 -> 0 | V18: =IF(U18>$C$8,"YES","NO") -> NO
A19: 3 | B19: =VLOOKUP($A:$A,Inventory!$A:$C,2,FALSE) -> GHOSRX203730BK | C19: =VLOOKUP($A:$A,Inventory!$A:$C,3,FALSE) -> BLACK T WESTERN EMERITUS 2025 ITIN | D19: SM-XL | E19: 0 | F19: 0 | G19: 5.7 | H19: =SUM(E19:G19) -> 5.7 | I19: 0 | J19: =SUM(H19:I19) -> 5.7 | K19: 50 | L19: =$C$7 -> 0 | M19: =K19-IF(K19<>0,K19-(K19/(1+L19)),0) -> 50 | N19: =J19/M19 -> 0.114 | O19: =IF(N19>$C$8,"YES","NO") -> NO | R19: 55 | S19: =$C$7 -> 0 | T19: =R19-IF(R19<>0,R19-(R19/(1+S19)),0) -> 55 | U19: =J19/T19 -> 0.10363636 | V19: =IF(U19>$C$8,"YES","NO") -> NO
D20: 2XL | E20: 0 | F20: 0 | G20: 7.89 | H20: =SUM(E20:G20) -> 7.89 | I20: 0 | J20: =SUM(H20:I20) -> 7.89 | K20: 50 | L20: =$C$7 -> 0 | M20: =K20-IF(K20<>0,K20-(K20/(1+L20)),0) -> 50 | N20: =J20/M20 -> 0.1578 | O20: =IF(N20>$C$8,"YES","NO") -> NO | R20: 55 | S20: =$C$7 -> 0 | T20: =R20-IF(R20<>0,R20-(R20/(1+S20)),0) -> 55 | U20: =J20/T20 -> 0.14345455 | V20: =IF(U20>$C$8,"YES","NO") -> NO
D21: 3XL | E21: 0 | F21: 0 | G21: 9.22 | H21: =SUM(E21:G21) -> 9.22 | I21: 0 | J21: =SUM(H21:I21) -> 9.22 | K21: 50 | L21: =$C$7 -> 0 | M21: =K21-IF(K21<>0,K21-(K21/(1+L21)),0) -> 50 | N21: =J21/M21 -> 0.1844 | O21: =IF(N21>$C$8,"YES","NO") -> NO | R21: 55 | S21: =$C$7 -> 0 | T21: =R21-IF(R21<>0,R21-(R21/(1+S21)),0) -> 55 | U21: =J21/T21 -> 0.16763636 | V21: =IF(U21>$C$8,"YES","NO") -> NO
D22: 4XL | E22: 0 | F22: 0 | G22: 0 | H22: =SUM(E22:G22) -> 0 | I22: 0 | J22: =SUM(H22:I22) -> 0 | K22: 50 | L22: =$C$7 -> 0 | M22: =K22-IF(K22<>0,K22-(K22/(1+L22)),0) -> 50 | N22: =J22/M22 -> 0 | O22: =IF(N22>$C$8,"YES","NO") -> NO | R22: 55 | S22: =$C$7 -> 0 | T22: =R22-IF(R22<>0,R22-(R22/(1+S22)),0) -> 55 | U22: =J22/T22 -> 0 | V22: =IF(U22>$C$8,"YES","NO") -> NO
A23: 4 | B23: =VLOOKUP($A:$A,Inventory!$A:$C,2,FALSE) -> GHOSRX103726BK | C23: =VLOOKUP($A:$A,Inventory!$A:$C,3,FALSE) -> BLACK TANK OPUS EPONYMOUS | D23: SM-XL | E23: 0 | F23: 0 | G23: 7.38 | H23: =SUM(E23:G23) -> 7.38 | I23: 0 | J23: =SUM(H23:I23) -> 7.38 | K23: 50 | L23: =$C$7 -> 0 | M23: =K23-IF(K23<>0,K23-(K23/(1+L23)),0) -> 50 | N23: =J23/M23 -> 0.1476 | O23: =IF(N23>$C$8,"YES","NO") -> NO | R23: 55 | S23: =$C$7 -> 0 | T23: =R23-IF(R23<>0,R23-(R23/(1+S23)),0) -> 55 | U23: =J23/T23 -> 0.13418182 | V23: =IF(U23>$C$8,"YES","NO") -> NO
D24: 2XL | E24: 0 | F24: 0 | G24: 7.38 | H24: =SUM(E24:G24) -> 7.38 | I24: 0 | J24: =SUM(H24:I24) -> 7.38 | K24: 50 | L24: =$C$7 -> 0 | M24: =K24-IF(K24<>0,K24-(K24/(1+L24)),0) -> 50 | N24: =J24/M24 -> 0.1476 | O24: =IF(N24>$C$8,"YES","NO") -> NO | R24: 55 | S24: =$C$7 -> 0 | T24: =R24-IF(R24<>0,R24-(R24/(1+S24)),0) -> 55 | U24: =J24/T24 -> 0.13418182 | V24: =IF(U24>$C$8,"YES","NO") -> NO
D25: 3XL | E25: 0 | F25: 0 | G25: 7.38 | H25: =SUM(E25:G25) -> 7.38 | I25: 0 | J25: =SUM(H25:I25) -> 7.38 | K25: 50 | L25: =$C$7 -> 0 | M25: =K25-IF(K25<>0,K25-(K25/(1+L25)),0) -> 50 | N25: =J25/M25 -> 0.1476 | O25: =IF(N25>$C$8,"YES","NO") -> NO | R25: 55 | S25: =$C$7 -> 0 | T25: =R25-IF(R25<>0,R25-(R25/(1+S25)),0) -> 55 | U25: =J25/T25 -> 0.13418182 | V25: =IF(U25>$C$8,"YES","NO") -> NO
D26: 4XL | E26: 0 | F26: 0 | G26: 0 | H26: =SUM(E26:G26) -> 0 | I26: 0 | J26: =SUM(H26:I26) -> 0 | K26: 50 | L26: =$C$7 -> 0 | M26: =K26-IF(K26<>0,K26-(K26/(1+L26)),0) -> 50 | N26: =J26/M26 -> 0 | O26: =IF(N26>$C$8,"YES","NO") -> NO | R26: 55 | S26: =$C$7 -> 0 | T26: =R26-IF(R26<>0,R26-(R26/(1+S26)),0) -> 55 | U26: =J26/T26 -> 0 | V26: =IF(U26>$C$8,"YES","NO") -> NO
A27: 5 | B27: =VLOOKUP($A:$A,Inventory!$A:$C,2,FALSE) -> GHOSRX203400BK | C27: =VLOOKUP($A:$A,Inventory!$A:$C,3,FALSE) -> LADIES CROP TOP SHOWGHOULS | D27: SM-XL | E27: 0 | F27: 0 | G27: 9.77 | H27: =SUM(E27:G27) -> 9.77 | I27: 0 | J27: =SUM(H27:I27) -> 9.77 | K27: 50 | L27: =$C$7 -> 0 | M27: =K27-IF(K27<>0,K27-(K27/(1+L27)),0) -> 50 | N27: =J27/M27 -> 0.1954 | O27: =IF(N27>$C$8,"YES","NO") -> NO | R27: 55 | S27: =$C$7 -> 0 | T27: =R27-IF(R27<>0,R27-(R27/(1+S27)),0) -> 55 | U27: =J27/T27 -> 0.17763636 | V27: =IF(U27>$C$8,"YES","NO") -> NO
D28: 2XL | E28: 0 | F28: 0 | G28: 0 | H28: =SUM(E28:G28) -> 0 | I28: 0 | J28: =SUM(H28:I28) -> 0 | K28: 50 | L28: =$C$7 -> 0 | M28: =K28-IF(K28<>0,K28-(K28/(1+L28)),0) -> 50 | N28: =J28/M28 -> 0 | O28: =IF(N28>$C$8,"YES","NO") -> NO | R28: 55 | S28: =$C$7 -> 0 | T28: =R28-IF(R28<>0,R28-(R28/(1+S28)),0) -> 55 | U28: =J28/T28 -> 0 | V28: =IF(U28>$C$8,"YES","NO") -> NO
D29: 3XL | E29: 0 | F29: 0 | G29: 0 | H29: =SUM(E29:G29) -> 0 | I29: 0 | J29: =SUM(H29:I29) -> 0 | K29: 50 | L29: =$C$7 -> 0 | M29: =K29-IF(K29<>0,K29-(K29/(1+L29)),0) -> 50 | N29: =J29/M29 -> 0 | O29: =IF(N29>$C$8,"YES","NO") -> NO | R29: 55 | S29: =$C$7 -> 0 | T29: =R29-IF(R29<>0,R29-(R29/(1+S29)),0) -> 55 | U29: =J29/T29 -> 0 | V29: =IF(U29>$C$8,"YES","NO") -> NO
D30: 4XL | E30: 0 | F30: 0 | G30: 0 | H30: =SUM(E30:G30) -> 0 | I30: 0 | J30: =SUM(H30:I30) -> 0 | K30: 50 | L30: =$C$7 -> 0 | M30: =K30-IF(K30<>0,K30-(K30/(1+L30)),0) -> 50 | N30: =J30/M30 -> 0 | O30: =IF(N30>$C$8,"YES","NO") -> NO | R30: 55 | S30: =$C$7 -> 0 | T30: =R30-IF(R30<>0,R30-(R30/(1+S30)),0) -> 55 | U30: =J30/T30 -> 0 | V30: =IF(U30>$C$8,"YES","NO") -> NO
A31: 6 | B31: =VLOOKUP($A:$A,Inventory!$A:$C,2,FALSE) -> GHOSRX203727PK | C31: =VLOOKUP($A:$A,Inventory!$A:$C,3,FALSE) -> LADIES PINK RAGLAN GARGOYLE | D31: SM-XL | E31: 0 | F31: 0 | G31: 12.29 | H31: =SUM(E31:G31) -> 12.29 | I31: 0 | J31: =SUM(H31:I31) -> 12.29 | K31: 50 | L31: =$C$7 -> 0 | M31: =K31-IF(K31<>0,K31-(K31/(1+L31)),0) -> 50 | N31: =J31/M31 -> 0.2458 | O31: =IF(N31>$C$8,"YES","NO") -> YES | R31: 55 | S31: =$C$7 -> 0 | T31: =R31-IF(R31<>0,R31-(R31/(1+S31)),0) -> 55 | U31: =J31/T31 -> 0.22345455 | V31: =IF(U31>$C$8,"YES","NO") -> YES
D32: 2XL | E32: 0 | F32: 0 | G32: 0 | H32: =SUM(E32:G32) -> 0 | I32: 0 | J32: =SUM(H32:I32) -> 0 | K32: 50 | L32: =$C$7 -> 0 | M32: =K32-IF(K32<>0,K32-(K32/(1+L32)),0) -> 50 | N32: =J32/M32 -> 0 | O32: =IF(N32>$C$8,"YES","NO") -> NO | R32: 55 | S32: =$C$7 -> 0 | T32: =R32-IF(R32<>0,R32-(R32/(1+S32)),0) -> 55 | U32: =J32/T32 -> 0 | V32: =IF(U32>$C$8,"YES","NO") -> NO
D33: 3XL | E33: 0 | F33: 0 | G33: 0 | H33: =SUM(E33:G33) -> 0 | I33: 0 | J33: =SUM(H33:I33) -> 0 | K33: 50 | L33: =$C$7 -> 0 | M33: =K33-IF(K33<>0,K33-(K33/(1+L33)),0) -> 50 | N33: =J33/M33 -> 0 | O33: =IF(N33>$C$8,"YES","NO") -> NO | R33: 55 | S33: =$C$7 -> 0 | T33: =R33-IF(R33<>0,R33-(R33/(1+S33)),0) -> 55 | U33: =J33/T33 -> 0 | V33: =IF(U33>$C$8,"YES","NO") -> NO
D34: 4XL | E34: 0 | F34: 0 | G34: 0 | H34: =SUM(E34:G34) -> 0 | I34: 0 | J34: =SUM(H34:I34) -> 0 | K34: 50 | L34: =$C$7 -> 0 | M34: =K34-IF(K34<>0,K34-(K34/(1+L34)),0) -> 50 | N34: =J34/M34 -> 0 | O34: =IF(N34>$C$8,"YES","NO") -> NO | R34: 55 | S34: =$C$7 -> 0 | T34: =R34-IF(R34<>0,R34-(R34/(1+S34)),0) -> 55 | U34: =J34/T34 -> 0 | V34: =IF(U34>$C$8,"YES","NO") -> NO
A35: 7 | B35: =VLOOKUP($A:$A,Inventory!$A:$C,2,FALSE) -> 0 | C35: =VLOOKUP($A:$A,Inventory!$A:$C,3,FALSE) -> 0 | D35: SM-XL | E35: 0 | F35: 0 | G35: 0 | H35: =SUM(E35:G35) -> 0 | I35: 0 | J35: =SUM(H35:I35) -> 0 | K35: 50 | L35: =$C$7 -> 0 | M35: =K35-IF(K35<>0,K35-(K35/(1+L35)),0) -> 50 | N35: =J35/M35 -> 0 | O35: =IF(N35>$C$8,"YES","NO") -> NO | R35: 55 | S35: =$C$7 -> 0 | T35: =R35-IF(R35<>0,R35-(R35/(1+S35)),0) -> 55 | U35: =J35/T35 -> 0 | V35: =IF(U35>$C$8,"YES","NO") -> NO
D36: 2XL | E36: 0 | F36: 0 | G36: 0 | H36: =SUM(E36:G36) -> 0 | I36: 0 | J36: =SUM(H36:I36) -> 0 | K36: 50 | L36: =$C$7 -> 0 | M36: =K36-IF(K36<>0,K36-(K36/(1+L36)),0) -> 50 | N36: =J36/M36 -> 0 | O36: =IF(N36>$C$8,"YES","NO") -> NO | R36: 55 | S36: =$C$7 -> 0 | T36: =R36-IF(R36<>0,R36-(R36/(1+S36)),0) -> 55 | U36: =J36/T36 -> 0 | V36: =IF(U36>$C$8,"YES","NO") -> NO
D37: 3XL | E37: 0 | F37: 0 | G37: 0 | H37: =SUM(E37:G37) -> 0 | I37: 0 | J37: =SUM(H37:I37) -> 0 | K37: 50 | L37: =$C$7 -> 0 | M37: =K37-IF(K37<>0,K37-(K37/(1+L37)),0) -> 50 | N37: =J37/M37 -> 0 | O37: =IF(N37>$C$8,"YES","NO") -> NO | R37: 55 | S37: =$C$7 -> 0 | T37: =R37-IF(R37<>0,R37-(R37/(1+S37)),0) -> 55 | U37: =J37/T37 -> 0 | V37: =IF(U37>$C$8,"YES","NO") -> NO
D38: 4XL | E38: 0 | F38: 0 | G38: 0 | H38: =SUM(E38:G38) -> 0 | I38: 0 | J38: =SUM(H38:I38) -> 0 | K38: 50 | L38: =$C$7 -> 0 | M38: =K38-IF(K38<>0,K38-(K38/(1+L38)),0) -> 50 | N38: =J38/M38 -> 0 | O38: =IF(N38>$C$8,"YES","NO") -> NO | R38: 55 | S38: =$C$7 -> 0 | T38: =R38-IF(R38<>0,R38-(R38/(1+S38)),0) -> 55 | U38: =J38/T38 -> 0 | V38: =IF(U38>$C$8,"YES","NO") -> NO
A39: 8 | B39: =VLOOKUP($A:$A,Inventory!$A:$C,2,FALSE) -> GHOSNS903311BK | C39: =VLOOKUP($A:$A,Inventory!$A:$C,3,FALSE) -> BATWING HOODY | D39: SM-XL | E39: 0 | F39: 0 | G39: 28.5 | H39: =SUM(E39:G39) -> 28.5 | I39: 0 | J39: =SUM(H39:I39) -> 28.5 | K39: 125 | L39: =$C$7 -> 0 | M39: =K39-IF(K39<>0,K39-(K39/(1+L39)),0) -> 125 | N39: =J39/M39 -> 0.228 | O39: =IF(N39>$C$8,"YES","NO") -> YES | R39: 55 | S39: =$C$7 -> 0 | T39: =R39-IF(R39<>0,R39-(R39/(1+S39)),0) -> 55 | U39: =J39/T39 -> 0.51818182 | V39: =IF(U39>$C$8,"YES","NO") -> YES
D40: 2XL | E40: 0 | F40: 0 | G40: 28.5 | H40: =SUM(E40:G40) -> 28.5 | I40: 0 | J40: =SUM(H40:I40) -> 28.5 | K40: 125 | L40: =$C$7 -> 0 | M40: =K40-IF(K40<>0,K40-(K40/(1+L40)),0) -> 125 | N40: =J40/M40 -> 0.228 | O40: =IF(N40>$C$8,"YES","NO") -> YES | R40: 55 | S40: =$C$7 -> 0 | T40: =R40-IF(R40<>0,R40-(R40/(1+S40)),0) -> 55 | U40: =J40/T40 -> 0.51818182 | V40: =IF(U40>$C$8,"YES","NO") -> YES
D41: 3XL | E41: 0 | F41: 0 | G41: 28.5 | H41: =SUM(E41:G41) -> 28.5 | I41: 0 | J41: =SUM(H41:I41) -> 28.5 | K41: 125 | L41: =$C$7 -> 0 | M41: =K41-IF(K41<>0,K41-(K41/(1+L41)),0) -> 125 | N41: =J41/M41 -> 0.228 | O41: =IF(N41>$C$8,"YES","NO") -> YES | R41: 55 | S41: =$C$7 -> 0 | T41: =R41-IF(R41<>0,R41-(R41/(1+S41)),0) -> 55 | U41: =J41/T41 -> 0.51818182 | V41: =IF(U41>$C$8,"YES","NO") -> YES
D42: 4XL | E42: 0 | F42: 0 | G42: 0 | H42: =SUM(E42:G42) -> 0 | I42: 0 | J42: =SUM(H42:I42) -> 0 | K42: 50 | L42: =$C$7 -> 0 | M42: =K42-IF(K42<>0,K42-(K42/(1+L42)),0) -> 50 | N42: =J42/M42 -> 0 | O42: =IF(N42>$C$8,"YES","NO") -> NO | R42: 55 | S42: =$C$7 -> 0 | T42: =R42-IF(R42<>0,R42-(R42/(1+S42)),0) -> 55 | U42: =J42/T42 -> 0 | V42: =IF(U42>$C$8,"YES","NO") -> NO
A43: 9 | B43: =VLOOKUP($A:$A,Inventory!$A:$C,2,FALSE) -> GHOSRX203401BK | C43: =VLOOKUP($A:$A,Inventory!$A:$C,3,FALSE) -> PULLOVER HOODY SKELETON | D43: SM-XL | E43: 0 | F43: 0 | G43: 14.19 | H43: =SUM(E43:G43) -> 14.19 | I43: 0 | J43: =SUM(H43:I43) -> 14.19 | K43: 80 | L43: =$C$7 -> 0 | M43: =K43-IF(K43<>0,K43-(K43/(1+L43)),0) -> 80 | N43: =J43/M43 -> 0.177375 | O43: =IF(N43>$C$8,"YES","NO") -> NO | R43: 55 | S43: =$C$7 -> 0 | T43: =R43-IF(R43<>0,R43-(R43/(1+S43)),0) -> 55 | U43: =J43/T43 -> 0.258 | V43: =IF(U43>$C$8,"YES","NO") -> YES
D44: 2XL | E44: 0 | F44: 0 | G44: 14.19 | H44: =SUM(E44:G44) -> 14.19 | I44: 0 | J44: =SUM(H44:I44) -> 14.19 | K44: 80 | L44: =$C$7 -> 0 | M44: =K44-IF(K44<>0,K44-(K44/(1+L44)),0) -> 80 | N44: =J44/M44 -> 0.177375 | O44: =IF(N44>$C$8,"YES","NO") -> NO | R44: 55 | S44: =$C$7 -> 0 | T44: =R44-IF(R44<>0,R44-(R44/(1+S44)),0) -> 55 | U44: =J44/T44 -> 0.258 | V44: =IF(U44>$C$8,"YES","NO") -> YES
D45: 3XL | E45: 0 | F45: 0 | G45: 15.75 | H45: =SUM(E45:G45) -> 15.75 | I45: 0 | J45: =SUM(H45:I45) -> 15.75 | K45: 80 | L45: =$C$7 -> 0 | M45: =K45-IF(K45<>0,K45-(K45/(1+L45)),0) -> 80 | N45: =J45/M45 -> 0.196875 | O45: =IF(N45>$C$8,"YES","NO") -> NO | R45: 55 | S45: =$C$7 -> 0 | T45: =R45-IF(R45<>0,R45-(R45/(1+S45)),0) -> 55 | U45: =J45/T45 -> 0.28636364 | V45: =IF(U45>$C$8,"YES","NO") -> YES
D46: 4XL | E46: 0 | F46: 0 | G46: 0 | H46: =SUM(E46:G46) -> 0 | I46: 0 | J46: =SUM(H46:I46) -> 0 | K46: 50 | L46: =$C$7 -> 0 | M46: =K46-IF(K46<>0,K46-(K46/(1+L46)),0) -> 50 | N46: =J46/M46 -> 0 | O46: =IF(N46>$C$8,"YES","NO") -> NO | R46: 55 | S46: =$C$7 -> 0 | T46: =R46-IF(R46<>0,R46-(R46/(1+S46)),0) -> 55 | U46: =J46/T46 -> 0 | V46: =IF(U46>$C$8,"YES","NO") -> NO
A47: 10 | B47: =VLOOKUP($A:$A,Inventory!$A:$C,2,FALSE) -> GHOSRX203275BK | C47: =VLOOKUP($A:$A,Inventory!$A:$C,3,FALSE) -> SHORTS BLACK/ WHT PAPA V COSTUME CLAWS | D47: SM-XL | E47: 5.5 | F47: 0 | G47: 0 | H47: =SUM(E47:G47) -> 5.5 | I47: 0 | J47: =SUM(H47:I47) -> 5.5 | K47: 45 | L47: =$C$7 -> 0 | M47: =K47-IF(K47<>0,K47-(K47/(1+L47)),0) -> 45 | N47: =J47/M47 -> 0.12222222 | O47: =IF(N47>$C$8,"YES","NO") -> NO | R47: 55 | S47: =$C$7 -> 0 | T47: =R47-IF(R47<>0,R47-(R47/(1+S47)),0) -> 55 | U47: =J47/T47 -> 0.1 | V47: =IF(U47>$C$8,"YES","NO") -> NO
D48: 2XL | E48: 5.5 | F48: 0 | G48: 0 | H48: =SUM(E48:G48) -> 5.5 | I48: 0 | J48: =SUM(H48:I48) -> 5.5 | K48: 45 | L48: =$C$7 -> 0 | M48: =K48-IF(K48<>0,K48-(K48/(1+L48)),0) -> 45 | N48: =J48/M48 -> 0.12222222 | O48: =IF(N48>$C$8,"YES","NO") -> NO | R48: 55 | S48: =$C$7 -> 0 | T48: =R48-IF(R48<>0,R48-(R48/(1+S48)),0) -> 55 | U48: =J48/T48 -> 0.1 | V48: =IF(U48>$C$8,"YES","NO") -> NO
D49: 3XL | E49: 0 | F49: 0 | G49: 0 | H49: =SUM(E49:G49) -> 0 | I49: 0 | J49: =SUM(H49:I49) -> 0 | K49: 50 | L49: =$C$7 -> 0 | M49: =K49-IF(K49<>0,K49-(K49/(1+L49)),0) -> 50 | N49: =J49/M49 -> 0 | O49: =IF(N49>$C$8,"YES","NO") -> NO | R49: 55 | S49: =$C$7 -> 0 | T49: =R49-IF(R49<>0,R49-(R49/(1+S49)),0) -> 55 | U49: =J49/T49 -> 0 | V49: =IF(U49>$C$8,"YES","NO") -> NO
D50: 4XL | E50: 0 | F50: 0 | G50: 0 | H50: =SUM(E50:G50) -> 0 | I50: 0 | J50: =SUM(H50:I50) -> 0 | K50: 50 | L50: =$C$7 -> 0 | M50: =K50-IF(K50<>0,K50-(K50/(1+L50)),0) -> 50 | N50: =J50/M50 -> 0 | O50: =IF(N50>$C$8,"YES","NO") -> NO | R50: 55 | S50: =$C$7 -> 0 | T50: =R50-IF(R50<>0,R50-(R50/(1+S50)),0) -> 55 | U50: =J50/T50 -> 0 | V50: =IF(U50>$C$8,"YES","NO") -> NO
A51: 11 | B51: =VLOOKUP($A:$A,Inventory!$A:$C,2,FALSE) -> GHOSRX103510OT | C51: =VLOOKUP($A:$A,Inventory!$A:$C,3,FALSE) -> TIE DYE T TOP HAT | D51: SM-XL | E51: 0 | F51: 0 | G51: 12.15 | H51: =SUM(E51:G51) -> 12.15 | I51: 0 | J51: =SUM(H51:I51) -> 12.15 | K51: 60 | L51: =$C$7 -> 0 | M51: =K51-IF(K51<>0,K51-(K51/(1+L51)),0) -> 60 | N51: =J51/M51 -> 0.2025 | O51: =IF(N51>$C$8,"YES","NO") -> YES | R51: 55 | S51: =$C$7 -> 0 | T51: =R51-IF(R51<>0,R51-(R51/(1+S51)),0) -> 55 | U51: =J51/T51 -> 0.22090909 | V51: =IF(U51>$C$8,"YES","NO") -> YES
D52: 2XL | E52: 0 | F52: 0 | G52: 12.15 | H52: =SUM(E52:G52) -> 12.15 | I52: 0 | J52: =SUM(H52:I52) -> 12.15 | K52: 60 | L52: =$C$7 -> 0 | M52: =K52-IF(K52<>0,K52-(K52/(1+L52)),0) -> 60 | N52: =J52/M52 -> 0.2025 | O52: =IF(N52>$C$8,"YES","NO") -> YES | R52: 55 | S52: =$C$7 -> 0 | T52: =R52-IF(R52<>0,R52-(R52/(1+S52)),0) -> 55 | U52: =J52/T52 -> 0.22090909 | V52: =IF(U52>$C$8,"YES","NO") -> YES
D53: 3XL | E53: 0 | F53: 0 | G53: 0 | H53: =SUM(E53:G53) -> 0 | I53: 0 | J53: =SUM(H53:I53) -> 0 | K53: 50 | L53: =$C$7 -> 0 | M53: =K53-IF(K53<>0,K53-(K53/(1+L53)),0) -> 50 | N53: =J53/M53 -> 0 | O53: =IF(N53>$C$8,"YES","NO") -> NO | R53: 55 | S53: =$C$7 -> 0 | T53: =R53-IF(R53<>0,R53-(R53/(1+S53)),0) -> 55 | U53: =J53/T53 -> 0 | V53: =IF(U53>$C$8,"YES","NO") -> NO
D54: 4XL | E54: 0 | F54: 0 | G54: 0 | H54: =SUM(E54:G54) -> 0 | I54: 0 | J54: =SUM(H54:I54) -> 0 | K54: 50 | L54: =$C$7 -> 0 | M54: =K54-IF(K54<>0,K54-(K54/(1+L54)),0) -> 50 | N54: =J54/M54 -> 0 | O54: =IF(N54>$C$8,"YES","NO") -> NO | R54: 55 | S54: =$C$7 -> 0 | T54: =R54-IF(R54<>0,R54-(R54/(1+S54)),0) -> 55 | U54: =J54/T54 -> 0 | V54: =IF(U54>$C$8,"YES","NO") -> NO
A55: 12 | B55: =VLOOKUP($A:$A,Inventory!$A:$C,2,FALSE) -> GHOSRX103437OT | C55: =VLOOKUP($A:$A,Inventory!$A:$C,3,FALSE) -> CRYSTAL WASHED T AT THE GATES | D55: SM-XL | E55: 0 | F55: 0 | G55: 8.71 | H55: =SUM(E55:G55) -> 8.71 | I55: 0 | J55: =SUM(H55:I55) -> 8.71 | K55: 60 | L55: =$C$7 -> 0 | M55: =K55-IF(K55<>0,K55-(K55/(1+L55)),0) -> 60 | N55: =J55/M55 -> 0.14516667 | O55: =IF(N55>$C$8,"YES","NO") -> NO | R55: 55 | S55: =$C$7 -> 0 | T55: =R55-IF(R55<>0,R55-(R55/(1+S55)),0) -> 55 | U55: =J55/T55 -> 0.15836364 | V55: =IF(U55>$C$8,"YES","NO") -> NO
D56: 2XL | E56: 0 | F56: 0 | G56: 11.57 | H56: =SUM(E56:G56) -> 11.57 | I56: 0 | J56: =SUM(H56:I56) -> 11.57 | K56: 60 | L56: =$C$7 -> 0 | M56: =K56-IF(K56<>0,K56-(K56/(1+L56)),0) -> 60 | N56: =J56/M56 -> 0.19283333 | O56: =IF(N56>$C$8,"YES","NO") -> NO | R56: 55 | S56: =$C$7 -> 0 | T56: =R56-IF(R56<>0,R56-(R56/(1+S56)),0) -> 55 | U56: =J56/T56 -> 0.21036364 | V56: =IF(U56>$C$8,"YES","NO") -> YES
D57: 3XL | E57: 0 | F57: 0 | G57: 11.68 | H57: =SUM(E57:G57) -> 11.68 | I57: 0 | J57: =SUM(H57:I57) -> 11.68 | K57: 60 | L57: =$C$7 -> 0 | M57: =K57-IF(K57<>0,K57-(K57/(1+L57)),0) -> 60 | N57: =J57/M57 -> 0.19466667 | O57: =IF(N57>$C$8,"YES","NO") -> NO | R57: 55 | S57: =$C$7 -> 0 | T57: =R57-IF(R57<>0,R57-(R57/(1+S57)),0) -> 55 | U57: =J57/T57 -> 0.21236364 | V57: =IF(U57>$C$8,"YES","NO") -> YES
D58: 4XL | E58: 0 | F58: 0 | G58: 0 | H58: =SUM(E58:G58) -> 0 | I58: 0 | J58: =SUM(H58:I58) -> 0 | K58: 50 | L58: =$C$7 -> 0 | M58: =K58-IF(K58<>0,K58-(K58/(1+L58)),0) -> 50 | N58: =J58/M58 -> 0 | O58: =IF(N58>$C$8,"YES","NO") -> NO | R58: 55 | S58: =$C$7 -> 0 | T58: =R58-IF(R58<>0,R58-(R58/(1+S58)),0) -> 55 | U58: =J58/T58 -> 0 | V58: =IF(U58>$C$8,"YES","NO") -> NO
A59: 13 | B59: =VLOOKUP($A:$A,Inventory!$A:$C,2,FALSE) -> GHOSRX203738BL | C59: =VLOOKUP($A:$A,Inventory!$A:$C,3,FALSE) -> OILWASHED NAVY BLUE T COME TOGETHER | D59: SM-XL | E59: 0 | F59: 0 | G59: 11.15 | H59: =SUM(E59:G59) -> 11.15 | I59: 0 | J59: =SUM(H59:I59) -> 11.15 | K59: 60 | L59: =$C$7 -> 0 | M59: =K59-IF(K59<>0,K59-(K59/(1+L59)),0) -> 60 | N59: =J59/M59 -> 0.18583333 | O59: =IF(N59>$C$8,"YES","NO") -> NO | R59: 55 | S59: =$C$7 -> 0 | T59: =R59-IF(R59<>0,R59-(R59/(1+S59)),0) -> 55 | U59: =J59/T59 -> 0.20272727 | V59: =IF(U59>$C$8,"YES","NO") -> YES
D60: 2XL | E60: 0 | F60: 0 | G60: 14.18 | H60: =SUM(E60:G60) -> 14.18 | I60: 0 | J60: =SUM(H60:I60) -> 14.18 | K60: 60 | L60: =$C$7 -> 0 | M60: =K60-IF(K60<>0,K60-(K60/(1+L60)),0) -> 60 | N60: =J60/M60 -> 0.23633333 | O60: =IF(N60>$C$8,"YES","NO") -> YES | R60: 55 | S60: =$C$7 -> 0 | T60: =R60-IF(R60<>0,R60-(R60/(1+S60)),0) -> 55 | U60: =J60/T60 -> 0.25781818 | V60: =IF(U60>$C$8,"YES","NO") -> YES
D61: 3XL | E61: 0 | F61: 0 | G61: 14.57 | H61: =SUM(E61:G61) -> 14.57 | I61: 0 | J61: =SUM(H61:I61) -> 14.57 | K61: 60 | L61: =$C$7 -> 0 | M61: =K61-IF(K61<>0,K61-(K61/(1+L61)),0) -> 60 | N61: =J61/M61 -> 0.24283333 | O61: =IF(N61>$C$8,"YES","NO") -> YES | R61: 55 | S61: =$C$7 -> 0 | T61: =R61-IF(R61<>0,R61-(R61/(1+S61)),0) -> 55 | U61: =J61/T61 -> 0.26490909 | V61: =IF(U61>$C$8,"YES","NO") -> YES
D62: 4XL | E62: 0 | F62: 0 | G62: 0 | H62: =SUM(E62:G62) -> 0 | I62: 0 | J62: =SUM(H62:I62) -> 0 | K62: 50 | L62: =$C$7 -> 0 | M62: =K62-IF(K62<>0,K62-(K62/(1+L62)),0) -> 50 | N62: =J62/M62 -> 0 | O62: =IF(N62>$C$8,"YES","NO") -> NO | R62: 55 | S62: =$C$7 -> 0 | T62: =R62-IF(R62<>0,R62-(R62/(1+S62)),0) -> 55 | U62: =J62/T62 -> 0 | V62: =IF(U62>$C$8,"YES","NO") -> NO
A63: 14 | B63: =VLOOKUP($A:$A,Inventory!$A:$C,2,FALSE) -> GHOSRX203570RD | C63: =VLOOKUP($A:$A,Inventory!$A:$C,3,FALSE) -> SHORTS RED/WHITE LOGO | D63: SM-XL | E63: 0 | F63: 0 | G63: 12.19 | H63: =SUM(E63:G63) -> 12.19 | I63: 0 | J63: =SUM(H63:I63) -> 12.19 | K63: 45 | L63: =$C$7 -> 0 | M63: =K63-IF(K63<>0,K63-(K63/(1+L63)),0) -> 45 | N63: =J63/M63 -> 0.27088889 | O63: =IF(N63>$C$8,"YES","NO") -> YES | R63: 55 | S63: =$C$7 -> 0 | T63: =R63-IF(R63<>0,R63-(R63/(1+S63)),0) -> 55 | U63: =J63/T63 -> 0.22163636 | V63: =IF(U63>$C$8,"YES","NO") -> YES
D64: 2XL | E64: 0 | F64: 0 | G64: 13.39 | H64: =SUM(E64:G64) -> 13.39 | I64: 0 | J64: =SUM(H64:I64) -> 13.39 | K64: 45 | L64: =$C$7 -> 0 | M64: =K64-IF(K64<>0,K64-(K64/(1+L64)),0) -> 45 | N64: =J64/M64 -> 0.29755556 | O64: =IF(N64>$C$8,"YES","NO") -> YES | R64: 55 | S64: =$C$7 -> 0 | T64: =R64-IF(R64<>0,R64-(R64/(1+S64)),0) -> 55 | U64: =J64/T64 -> 0.24345455 | V64: =IF(U64>$C$8,"YES","NO") -> YES
D65: 3XL | E65: 0 | F65: 0 | G65: 0 | H65: =SUM(E65:G65) -> 0 | I65: 0 | J65: =SUM(H65:I65) -> 0 | K65: 50 | L65: =$C$7 -> 0 | M65: =K65-IF(K65<>0,K65-(K65/(1+L65)),0) -> 50 | N65: =J65/M65 -> 0 | O65: =IF(N65>$C$8,"YES","NO") -> NO | R65: 55 | S65: =$C$7 -> 0 | T65: =R65-IF(R65<>0,R65-(R65/(1+S65)),0) -> 55 | U65: =J65/T65 -> 0 | V65: =IF(U65>$C$8,"YES","NO") -> NO
D66: 4XL | E66: 0 | F66: 0 | G66: 0 | H66: =SUM(E66:G66) -> 0 | I66: 0 | J66: =SUM(H66:I66) -> 0 | K66: 50 | L66: =$C$7 -> 0 | M66: =K66-IF(K66<>0,K66-(K66/(1+L66)),0) -> 50 | N66: =J66/M66 -> 0 | O66: =IF(N66>$C$8,"YES","NO") -> NO | R66: 55 | S66: =$C$7 -> 0 | T66: =R66-IF(R66<>0,R66-(R66/(1+S66)),0) -> 55 | U66: =J66/T66 -> 0 | V66: =IF(U66>$C$8,"YES","NO") -> NO
A67: 15 | B67: =VLOOKUP($A:$A,Inventory!$A:$C,2,FALSE) -> GHOSRX203800BK | C67: =VLOOKUP($A:$A,Inventory!$A:$C,3,FALSE) -> EVENT T TAMPA | D67: SM-XL | E67: 0 | F67: 0 | G67: 6.2 | H67: =SUM(E67:G67) -> 6.2 | I67: 0 | J67: =SUM(H67:I67) -> 6.2 | K67: 50 | L67: =$C$7 -> 0 | M67: =K67-IF(K67<>0,K67-(K67/(1+L67)),0) -> 50 | N67: =J67/M67 -> 0.124 | O67: =IF(N67>$C$8,"YES","NO") -> NO | R67: 55 | S67: =$C$7 -> 0 | T67: =R67-IF(R67<>0,R67-(R67/(1+S67)),0) -> 55 | U67: =J67/T67 -> 0.11272727 | V67: =IF(U67>$C$8,"YES","NO") -> NO
D68: 2XL | E68: 0 | F68: 0 | G68: 8.39 | H68: =SUM(E68:G68) -> 8.39 | I68: 0 | J68: =SUM(H68:I68) -> 8.39 | K68: 50 | L68: =$C$7 -> 0 | M68: =K68-IF(K68<>0,K68-(K68/(1+L68)),0) -> 50 | N68: =J68/M68 -> 0.1678 | O68: =IF(N68>$C$8,"YES","NO") -> NO | R68: 55 | S68: =$C$7 -> 0 | T68: =R68-IF(R68<>0,R68-(R68/(1+S68)),0) -> 55 | U68: =J68/T68 -> 0.15254545 | V68: =IF(U68>$C$8,"YES","NO") -> NO
D69: 3XL | E69: 0 | F69: 0 | G69: 9.72 | H69: =SUM(E69:G69) -> 9.72 | I69: 0 | J69: =SUM(H69:I69) -> 9.72 | K69: 50 | L69: =$C$7 -> 0 | M69: =K69-IF(K69<>0,K69-(K69/(1+L69)),0) -> 50 | N69: =J69/M69 -> 0.1944 | O69: =IF(N69>$C$8,"YES","NO") -> NO | R69: 55 | S69: =$C$7 -> 0 | T69: =R69-IF(R69<>0,R69-(R69/(1+S69)),0) -> 55 | U69: =J69/T69 -> 0.17672727 | V69: =IF(U69>$C$8,"YES","NO") -> NO
D70: 4XL | E70: 0 | F70: 0 | G70: 0 | H70: =SUM(E70:G70) -> 0 | I70: 0 | J70: =SUM(H70:I70) -> 0 | K70: 50 | L70: =$C$7 -> 0 | M70: =K70-IF(K70<>0,K70-(K70/(1+L70)),0) -> 50 | N70: =J70/M70 -> 0 | O70: =IF(N70>$C$8,"YES","NO") -> NO | R70: 55 | S70: =$C$7 -> 0 | T70: =R70-IF(R70<>0,R70-(R70/(1+S70)),0) -> 55 | U70: =J70/T70 -> 0 | V70: =IF(U70>$C$8,"YES","NO") -> NO
A71: 16 | B71: =VLOOKUP($A:$A,Inventory!$A:$C,2,FALSE) -> GHOSRX203799BK | C71: =VLOOKUP($A:$A,Inventory!$A:$C,3,FALSE) -> EVENT T PHILLY | D71: SM-XL | E71: 0 | F71: 0 | G71: 5.7 | H71: =SUM(E71:G71) -> 5.7 | I71: 0 | J71: =SUM(H71:I71) -> 5.7 | K71: 50 | L71: =$C$7 -> 0 | M71: =K71-IF(K71<>0,K71-(K71/(1+L71)),0) -> 50 | N71: =J71/M71 -> 0.114 | O71: =IF(N71>$C$8,"YES","NO") -> NO | R71: 55 | S71: =$C$7 -> 0 | T71: =R71-IF(R71<>0,R71-(R71/(1+S71)),0) -> 55 | U71: =J71/T71 -> 0.10363636 | V71: =IF(U71>$C$8,"YES","NO") -> NO
D72: 2XL | E72: 0 | F72: 0 | G72: 7.89 | H72: =SUM(E72:G72) -> 7.89 | I72: 0 | J72: =SUM(H72:I72) -> 7.89 | K72: 50 | L72: =$C$7 -> 0 | M72: =K72-IF(K72<>0,K72-(K72/(1+L72)),0) -> 50 | N72: =J72/M72 -> 0.1578 | O72: =IF(N72>$C$8,"YES","NO") -> NO | R72: 55 | S72: =$C$7 -> 0 | T72: =R72-IF(R72<>0,R72-(R72/(1+S72)),0) -> 55 | U72: =J72/T72 -> 0.14345455 | V72: =IF(U72>$C$8,"YES","NO") -> NO
D73: 3XL | E73: 0 | F73: 0 | G73: 9.22 | H73: =SUM(E73:G73) -> 9.22 | I73: 0 | J73: =SUM(H73:I73) -> 9.22 | K73: 50 | L73: =$C$7 -> 0 | M73: =K73-IF(K73<>0,K73-(K73/(1+L73)),0) -> 50 | N73: =J73/M73 -> 0.1844 | O73: =IF(N73>$C$8,"YES","NO") -> NO | R73: 55 | S73: =$C$7 -> 0 | T73: =R73-IF(R73<>0,R73-(R73/(1+S73)),0) -> 55 | U73: =J73/T73 -> 0.16763636 | V73: =IF(U73>$C$8,"YES","NO") -> NO
D74: 4XL | E74: 0 | F74: 0 | G74: 0 | H74: =SUM(E74:G74) -> 0 | I74: 0 | J74: =SUM(H74:I74) -> 0 | K74: 50 | L74: =$C$7 -> 0 | M74: =K74-IF(K74<>0,K74-(K74/(1+L74)),0) -> 50 | N74: =J74/M74 -> 0 | O74: =IF(N74>$C$8,"YES","NO") -> NO | R74: 55 | S74: =$C$7 -> 0 | T74: =R74-IF(R74<>0,R74-(R74/(1+S74)),0) -> 55 | U74: =J74/T74 -> 0 | V74: =IF(U74>$C$8,"YES","NO") -> NO
A75: 17 | B75: =VLOOKUP($A:$A,Inventory!$A:$C,2,FALSE) -> GHOSRX203798BK | C75: =VLOOKUP($A:$A,Inventory!$A:$C,3,FALSE) -> EVENT T BOSTON | D75: SM-XL | E75: 0 | F75: 0 | G75: 5.7 | H75: =SUM(E75:G75) -> 5.7 | I75: 0 | J75: =SUM(H75:I75) -> 5.7 | K75: 50 | L75: =$C$7 -> 0 | M75: =K75-IF(K75<>0,K75-(K75/(1+L75)),0) -> 50 | N75: =J75/M75 -> 0.114 | O75: =IF(N75>$C$8,"YES","NO") -> NO | R75: 55 | S75: =$C$7 -> 0 | T75: =R75-IF(R75<>0,R75-(R75/(1+S75)),0) -> 55 | U75: =J75/T75 -> 0.10363636 | V75: =IF(U75>$C$8,"YES","NO") -> NO
D76: 2XL | E76: 0 | F76: 0 | G76: 7.89 | H76: =SUM(E76:G76) -> 7.89 | I76: 0 | J76: =SUM(H76:I76) -> 7.89 | K76: 50 | L76: =$C$7 -> 0 | M76: =K76-IF(K76<>0,K76-(K76/(1+L76)),0) -> 50 | N76: =J76/M76 -> 0.1578 | O76: =IF(N76>$C$8,"YES","NO") -> NO | R76: 55 | S76: =$C$7 -> 0 | T76: =R76-IF(R76<>0,R76-(R76/(1+S76)),0) -> 55 | U76: =J76/T76 -> 0.14345455 | V76: =IF(U76>$C$8,"YES","NO") -> NO
D77: 3XL | E77: 0 | F77: 0 | G77: 9.22 | H77: =SUM(E77:G77) -> 9.22 | I77: 0 | J77: =SUM(H77:I77) -> 9.22 | K77: 50 | L77: =$C$7 -> 0 | M77: =K77-IF(K77<>0,K77-(K77/(1+L77)),0) -> 50 | N77: =J77/M77 -> 0.1844 | O77: =IF(N77>$C$8,"YES","NO") -> NO | R77: 55 | S77: =$C$7 -> 0 | T77: =R77-IF(R77<>0,R77-(R77/(1+S77)),0) -> 55 | U77: =J77/T77 -> 0.16763636 | V77: =IF(U77>$C$8,"YES","NO") -> NO
D78: 4XL | E78: 0 | F78: 0 | G78: 0 | H78: =SUM(E78:G78) -> 0 | I78: 0 | J78: =SUM(H78:I78) -> 0 | K78: 50 | L78: =$C$7 -> 0 | M78: =K78-IF(K78<>0,K78-(K78/(1+L78)),0) -> 50 | N78: =J78/M78 -> 0 | O78: =IF(N78>$C$8,"YES","NO") -> NO | R78: 55 | S78: =$C$7 -> 0 | T78: =R78-IF(R78<>0,R78-(R78/(1+S78)),0) -> 55 | U78: =J78/T78 -> 0 | V78: =IF(U78>$C$8,"YES","NO") -> NO
A79: 18 | B79: =VLOOKUP($A:$A,Inventory!$A:$C,2,FALSE) -> GHOSRX203801BK | C79: =VLOOKUP($A:$A,Inventory!$A:$C,3,FALSE) -> EVENT T NEW YORK | D79: SM-XL | E79: 0 | F79: 0 | G79: 5.7 | H79: =SUM(E79:G79) -> 5.7 | I79: 0 | J79: =SUM(H79:I79) -> 5.7 | K79: 50 | L79: =$C$7 -> 0 | M79: =K79-IF(K79<>0,K79-(K79/(1+L79)),0) -> 50 | N79: =J79/M79 -> 0.114 | O79: =IF(N79>$C$8,"YES","NO") -> NO | R79: 55 | S79: =$C$7 -> 0 | T79: =R79-IF(R79<>0,R79-(R79/(1+S79)),0) -> 55 | U79: =J79/T79 -> 0.10363636 | V79: =IF(U79>$C$8,"YES","NO") -> NO
D80: 2XL | E80: 0 | F80: 0 | G80: 7.89 | H80: =SUM(E80:G80) -> 7.89 | I80: 0 | J80: =SUM(H80:I80) -> 7.89 | K80: 50 | L80: =$C$7 -> 0 | M80: =K80-IF(K80<>0,K80-(K80/(1+L80)),0) -> 50 | N80: =J80/M80 -> 0.1578 | O80: =IF(N80>$C$8,"YES","NO") -> NO | R80: 55 | S80: =$C$7 -> 0 | T80: =R80-IF(R80<>0,R80-(R80/(1+S80)),0) -> 55 | U80: =J80/T80 -> 0.14345455 | V80: =IF(U80>$C$8,"YES","NO") -> NO
D81: 3XL | E81: 0 | F81: 0 | G81: 9.22 | H81: =SUM(E81:G81) -> 9.22 | I81: 0 | J81: =SUM(H81:I81) -> 9.22 | K81: 50 | L81: =$C$7 -> 0 | M81: =K81-IF(K81<>0,K81-(K81/(1+L81)),0) -> 50 | N81: =J81/M81 -> 0.1844 | O81: =IF(N81>$C$8,"YES","NO") -> NO | R81: 55 | S81: =$C$7 -> 0 | T81: =R81-IF(R81<>0,R81-(R81/(1+S81)),0) -> 55 | U81: =J81/T81 -> 0.16763636 | V81: =IF(U81>$C$8,"YES","NO") -> NO
D82: 4XL | E82: 0 | F82: 0 | G82: 0 | H82: =SUM(E82:G82) -> 0 | I82: 0 | J82: =SUM(H82:I82) -> 0 | K82: 50 | L82: =$C$7 -> 0 | M82: =K82-IF(K82<>0,K82-(K82/(1+L82)),0) -> 50 | N82: =J82/M82 -> 0 | O82: =IF(N82>$C$8,"YES","NO") -> NO | R82: 55 | S82: =$C$7 -> 0 | T82: =R82-IF(R82<>0,R82-(R82/(1+S82)),0) -> 55 | U82: =J82/T82 -> 0 | V82: =IF(U82>$C$8,"YES","NO") -> NO
A83: 19 | B83: =VLOOKUP($A:$A,Inventory!$A:$C,2,FALSE) -> GHOSRX203822BK | C83: =VLOOKUP($A:$A,Inventory!$A:$C,3,FALSE) -> EVENT T CHICAGO | D83: SM-XL | E83: 0 | F83: 0 | G83: 5.7 | H83: =SUM(E83:G83) -> 5.7 | I83: 0 | J83: =SUM(H83:I83) -> 5.7 | K83: 50 | L83: =$C$7 -> 0 | M83: =K83-IF(K83<>0,K83-(K83/(1+L83)),0) -> 50 | N83: =J83/M83 -> 0.114 | O83: =IF(N83>$C$8,"YES","NO") -> NO | R83: 55 | S83: =$C$7 -> 0 | T83: =R83-IF(R83<>0,R83-(R83/(1+S83)),0) -> 55 | U83: =J83/T83 -> 0.10363636 | V83: =IF(U83>$C$8,"YES","NO") -> NO
D84: 2XL | E84: 0 | F84: 0 | G84: 7.89 | H84: =SUM(E84:G84) -> 7.89 | I84: 0 | J84: =SUM(H84:I84) -> 7.89 | K84: 50 | L84: =$C$7 -> 0 | M84: =K84-IF(K84<>0,K84-(K84/(1+L84)),0) -> 50 | N84: =J84/M84 -> 0.1578 | O84: =IF(N84>$C$8,"YES","NO") -> NO | R84: 55 | S84: =$C$7 -> 0 | T84: =R84-IF(R84<>0,R84-(R84/(1+S84)),0) -> 55 | U84: =J84/T84 -> 0.14345455 | V84: =IF(U84>$C$8,"YES","NO") -> NO
D85: 3XL | E85: 0 | F85: 0 | G85: 9.22 | H85: =SUM(E85:G85) -> 9.22 | I85: 0 | J85: =SUM(H85:I85) -> 9.22 | K85: 50 | L85: =$C$7 -> 0 | M85: =K85-IF(K85<>0,K85-(K85/(1+L85)),0) -> 50 | N85: =J85/M85 -> 0.1844 | O85: =IF(N85>$C$8,"YES","NO") -> NO | R85: 55 | S85: =$C$7 -> 0 | T85: =R85-IF(R85<>0,R85-(R85/(1+S85)),0) -> 55 | U85: =J85/T85 -> 0.16763636 | V85: =IF(U85>$C$8,"YES","NO") -> NO
D86: 4XL | E86: 0 | F86: 0 | G86: 0 | H86: =SUM(E86:G86) -> 0 | I86: 0 | J86: =SUM(H86:I86) -> 0 | K86: 50 | L86: =$C$7 -> 0 | M86: =K86-IF(K86<>0,K86-(K86/(1+L86)),0) -> 50 | N86: =J86/M86 -> 0 | O86: =IF(N86>$C$8,"YES","NO") -> NO | R86: 55 | S86: =$C$7 -> 0 | T86: =R86-IF(R86<>0,R86-(R86/(1+S86)),0) -> 55 | U86: =J86/T86 -> 0 | V86: =IF(U86>$C$8,"YES","NO") -> NO
A87: 20 | B87: =VLOOKUP($A:$A,Inventory!$A:$C,2,FALSE) -> 0 | C87: =VLOOKUP($A:$A,Inventory!$A:$C,3,FALSE) -> 0 | D87: SM-XL | E87: 0 | F87: 0 | G87: 0 | H87: =SUM(E87:G87) -> 0 | I87: 0 | J87: =SUM(H87:I87) -> 0 | K87: 50 | L87: =$C$7 -> 0 | M87: =K87-IF(K87<>0,K87-(K87/(1+L87)),0) -> 50 | N87: =J87/M87 -> 0 | O87: =IF(N87>$C$8,"YES","NO") -> NO | R87: 55 | S87: =$C$7 -> 0 | T87: =R87-IF(R87<>0,R87-(R87/(1+S87)),0) -> 55 | U87: =J87/T87 -> 0 | V87: =IF(U87>$C$8,"YES","NO") -> NO
D88: 2XL | E88: 0 | F88: 0 | G88: 0 | H88: =SUM(E88:G88) -> 0 | I88: 0 | J88: =SUM(H88:I88) -> 0 | K88: 50 | L88: =$C$7 -> 0 | M88: =K88-IF(K88<>0,K88-(K88/(1+L88)),0) -> 50 | N88: =J88/M88 -> 0 | O88: =IF(N88>$C$8,"YES","NO") -> NO | R88: 55 | S88: =$C$7 -> 0 | T88: =R88-IF(R88<>0,R88-(R88/(1+S88)),0) -> 55 | U88: =J88/T88 -> 0 | V88: =IF(U88>$C$8,"YES","NO") -> NO
D89: 3XL | E89: 0 | F89: 0 | G89: 0 | H89: =SUM(E89:G89) -> 0 | I89: 0 | J89: =SUM(H89:I89) -> 0 | K89: 50 | L89: =$C$7 -> 0 | M89: =K89-IF(K89<>0,K89-(K89/(1+L89)),0) -> 50 | N89: =J89/M89 -> 0 | O89: =IF(N89>$C$8,"YES","NO") -> NO | R89: 55 | S89: =$C$7 -> 0 | T89: =R89-IF(R89<>0,R89-(R89/(1+S89)),0) -> 55 | U89: =J89/T89 -> 0 | V89: =IF(U89>$C$8,"YES","NO") -> NO
D90: 4XL | E90: 0 | F90: 0 | G90: 0 | H90: =SUM(E90:G90) -> 0 | I90: 0 | J90: =SUM(H90:I90) -> 0 | K90: 50 | L90: =$C$7 -> 0 | M90: =K90-IF(K90<>0,K90-(K90/(1+L90)),0) -> 50 | N90: =J90/M90 -> 0 | O90: =IF(N90>$C$8,"YES","NO") -> NO | R90: 55 | S90: =$C$7 -> 0 | T90: =R90-IF(R90<>0,R90-(R90/(1+S90)),0) -> 55 | U90: =J90/T90 -> 0 | V90: =IF(U90>$C$8,"YES","NO") -> NO
A92: TRINKETS | R92: TRINKETS - ADJUSTED PRICE FOR SPECIAL
A93: ITEM # | B93: SKU # | C93: DESCRIPTION | D93: SIZE | E93: ITEM COST | F93: OTHER COSTS | H93: COG | I93: COG 2 | J93: TOTAL COG | K93: SUGGESTED PRICE | L93: =L10 -> TAX @ 0 | M93: AFTER TAX ADJ. GROSS | N93: PRODUCT COST % (A.T.G.) | O93: SPECIAL YES/NO | P93: AGREED DATE BY BM | R93: SPECIAL ITEM PRICE | S93: =L93 -> TAX @ 0 | T93: SPECIAL PRICE NET | U93: SPECIAL C.O.G | V93: SPECIAL YES/NO
A94: 22 | B94: =VLOOKUP($A:$A,Inventory!$A:$C,2,FALSE) -> GHOSNS103665BK | C94: =VLOOKUP($A:$A,Inventory!$A:$C,3,FALSE) -> HAT SATANIC PANIC | D94: OS | E94: 3.92 | H94: =SUM(E94:G94) -> 3.92 | I94: 0 | J94: =SUM(H94:I94) -> 3.92 | K94: 35 | L94: =$C$7 -> 0 | M94: =K94-IF(K94<>0,K94-(K94/(1+L94)),0) -> 35 | N94: =J94/M94 -> 0.112 | O94: =IF(N94>$C$8,"YES","NO") -> NO | R94: 30 | S94: =$C$7 -> 0 | T94: =R94-IF(R94<>0,R94-(R94/(1+S94)),0) -> 30 | U94: =J94/T94 -> 0.13066667 | V94: =IF(U94>$C$8,"YES","NO") -> NO
A95: 23 | B95: =VLOOKUP($A:$A,Inventory!$A:$C,2,FALSE) -> GHOSNS903309GR | C95: =VLOOKUP($A:$A,Inventory!$A:$C,3,FALSE) -> MASK BURNT GHOUL | D95: OS | E95: 4.8 | H95: =SUM(E95:G95) -> 4.8 | I95: 0 | J95: =SUM(H95:I95) -> 4.8 | K95: 40 | L95: =$C$7 -> 0 | M95: =K95-IF(K95<>0,K95-(K95/(1+L95)),0) -> 40 | N95: =J95/M95 -> 0.12 | O95: =IF(N95>$C$8,"YES","NO") -> NO | R95: 20 | S95: =$C$7 -> 0 | T95: =R95-IF(R95<>0,R95-(R95/(1+S95)),0) -> 20 | U95: =J95/T95 -> 0.24 | V95: =IF(U95>$C$8,"YES","NO") -> YES
A96: 24 | B96: =VLOOKUP($A:$A,Inventory!$A:$C,2,FALSE) -> GHOSNS903279OT | C96: =VLOOKUP($A:$A,Inventory!$A:$C,3,FALSE) -> PLUSHIE FRATER IMPERATOR | D96: OS | E96: 8.9 | H96: =SUM(E96:G96) -> 8.9 | I96: 0 | J96: =SUM(H96:I96) -> 8.9 | K96: 50 | L96: =$C$7 -> 0 | M96: =K96-IF(K96<>0,K96-(K96/(1+L96)),0) -> 50 | N96: =J96/M96 -> 0.178 | O96: =IF(N96>$C$8,"YES","NO") -> NO | R96: 15 | S96: =$C$7 -> 0 | T96: =R96-IF(R96<>0,R96-(R96/(1+S96)),0) -> 15 | U96: =J96/T96 -> 0.59333333 | V96: =IF(U96>$C$8,"YES","NO") -> YES
A97: 25 | B97: =VLOOKUP($A:$A,Inventory!$A:$C,2,FALSE) -> GHOSRX103259OT | C97: =VLOOKUP($A:$A,Inventory!$A:$C,3,FALSE) -> CLEAR SLING BAG-SILVER LOGO | D97: OS | E97: 3.8 | H97: =SUM(E97:G97) -> 3.8 | I97: 0 | J97: =SUM(H97:I97) -> 3.8 | K97: 40 | L97: =$C$7 -> 0 | M97: =K97-IF(K97<>0,K97-(K97/(1+L97)),0) -> 40 | N97: =J97/M97 -> 0.095 | O97: =IF(N97>$C$8,"YES","NO") -> NO | R97: 10 | S97: =$C$7 -> 0 | T97: =R97-IF(R97<>0,R97-(R97/(1+S97)),0) -> 10 | U97: =J97/T97 -> 0.38 | V97: =IF(U97>$C$8,"YES","NO") -> YES
A98: 26 | B98: =VLOOKUP($A:$A,Inventory!$A:$C,2,FALSE) -> GHOSRX103241BK | C98: =VLOOKUP($A:$A,Inventory!$A:$C,3,FALSE) -> CHOKER PAPA V | D98: OS | E98: 3.6 | H98: =SUM(E98:G98) -> 3.6 | I98: 0 | J98: =SUM(H98:I98) -> 3.6 | K98: 30 | L98: =$C$7 -> 0 | M98: =K98-IF(K98<>0,K98-(K98/(1+L98)),0) -> 30 | N98: =J98/M98 -> 0.12 | O98: =IF(N98>$C$8,"YES","NO") -> NO | R98: 15 | S98: =$C$7 -> 0 | T98: =R98-IF(R98<>0,R98-(R98/(1+S98)),0) -> 15 | U98: =J98/T98 -> 0.24 | V98: =IF(U98>$C$8,"YES","NO") -> YES
A99: 27 | B99: =VLOOKUP($A:$A,Inventory!$A:$C,2,FALSE) -> GHOSRX203254GR | C99: =VLOOKUP($A:$A,Inventory!$A:$C,3,FALSE) -> KEYCHAIN SKELETON GRUCIFIX | D99: OS | E99: 1.5 | H99: =SUM(E99:G99) -> 1.5 | I99: 0 | J99: =SUM(H99:I99) -> 1.5 | K99: 15 | L99: =$C$7 -> 0 | M99: =K99-IF(K99<>0,K99-(K99/(1+L99)),0) -> 15 | N99: =J99/M99 -> 0.1 | O99: =IF(N99>$C$8,"YES","NO") -> NO | R99: 15 | S99: =$C$7 -> 0 | T99: =R99-IF(R99<>0,R99-(R99/(1+S99)),0) -> 15 | U99: =J99/T99 -> 0.1 | V99: =IF(U99>$C$8,"YES","NO") -> NO
A100: 28 | B100: =VLOOKUP($A:$A,Inventory!$A:$C,2,FALSE) -> GHOSRX903403OT | C100: =VLOOKUP($A:$A,Inventory!$A:$C,3,FALSE) -> PATCH SET OF 3 | D100: OS | E100: 2.05 | H100: =SUM(E100:G100) -> 2.05 | I100: 0 | J100: =SUM(H100:I100) -> 2.05 | K100: 20 | L100: =$C$7 -> 0 | M100: =K100-IF(K100<>0,K100-(K100/(1+L100)),0) -> 20 | N100: =J100/M100 -> 0.1025 | O100: =IF(N100>$C$8,"YES","NO") -> NO | R100: 20 | S100: =$C$7 -> 0 | T100: =R100-IF(R100<>0,R100-(R100/(1+S100)),0) -> 20 | U100: =J100/T100 -> 0.1025 | V100: =IF(U100>$C$8,"YES","NO") -> NO
A101: 29 | B101: =VLOOKUP($A:$A,Inventory!$A:$C,2,FALSE) -> GHOSNS103814BK | C101: =VLOOKUP($A:$A,Inventory!$A:$C,3,FALSE) -> TOUR PROGRAM | D101: OS | E101: =4.64+0.95 -> 5.59 | H101: =SUM(E101:G101) -> 5.59 | I101: 0 | J101: =SUM(H101:I101) -> 5.59 | K101: 30 | L101: =$C$7 -> 0 | M101: =K101-IF(K101<>0,K101-(K101/(1+L101)),0) -> 30 | N101: =J101/M101 -> 0.18633333 | O101: =IF(N101>$C$8,"YES","NO") -> NO | R101: 25 | S101: =$C$7 -> 0 | T101: =R101-IF(R101<>0,R101-(R101/(1+S101)),0) -> 25 | U101: =J101/T101 -> 0.2236 | V101: =IF(U101>$C$8,"YES","NO") -> YES
A102: 30 | B102: =VLOOKUP($A:$A,Inventory!$A:$C,2,FALSE) -> GHOSRX903408OT | C102: =VLOOKUP($A:$A,Inventory!$A:$C,3,FALSE) -> LP SKELETA POLTERGEIST | D102: OS | E102: 16.89 | H102: =SUM(E102:G102) -> 16.89 | I102: 0 | J102: =SUM(H102:I102) -> 16.89 | K102: 40 | L102: =$C$7 -> 0 | M102: =K102-IF(K102<>0,K102-(K102/(1+L102)),0) -> 40 | N102: =J102/M102 -> 0.42225 | O102: =IF(N102>$C$8,"YES","NO") -> YES | R102: 25 | S102: =$C$7 -> 0 | T102: =R102-IF(R102<>0,R102-(R102/(1+S102)),0) -> 25 | U102: =J102/T102 -> 0.6756 | V102: =IF(U102>$C$8,"YES","NO") -> YES
...

Sheet Selling Prices
A1: Tour Inventory
B3: Tour | C3: =Inventory!C3 -> GHOST
B4: Tour Date | C4: =Inventory!C4 -> SUMMER 2025
D6: USD | E6: CAD
B7: NAV Item Code | C7: Product Description | D7: Selling Price | E7: Selling Price | F7: Selling Price | G7: Selling Price
A8: 1 | B8: =Inventory!B7 -> GHOSRX203729BK | C8: =Inventory!C7 -> BLACK T SKELETOUR 2025 ITIN | D8: ='Projection Sheet'!D15 -> 50
A9: 2 | B9: =Inventory!B8 -> GHOSRX203728BK | C9: =Inventory!C8 -> BLACK T SKELETA ALBUM COVER 2025 ITIN | D9: ='Projection Sheet'!D16 -> 50
A10: 3 | B10: =Inventory!B9 -> GHOSRX203730BK | C10: =Inventory!C9 -> BLACK T WESTERN EMERITUS 2025 ITIN | D10: ='Projection Sheet'!D17 -> 50
A11: 4 | B11: =Inventory!B10 -> GHOSRX103726BK | C11: =Inventory!C10 -> BLACK TANK OPUS EPONYMOUS | D11: ='Projection Sheet'!D18 -> 50
A12: 5 | B12: =Inventory!B11 -> GHOSRX203400BK | C12: =Inventory!C11 -> LADIES CROP TOP SHOWGHOULS | D12: ='Projection Sheet'!D19 -> 50
A13: 6 | B13: =Inventory!B12 -> GHOSRX203727PK | C13: =Inventory!C12 -> LADIES PINK RAGLAN GARGOYLE | D13: ='Projection Sheet'!D20 -> 50
A14: 7 | B14: =Inventory!B13 -> 0 | C14: =Inventory!C13 -> 0 | D14: ='Projection Sheet'!D21 -> 1
A15: 8 | B15: =Inventory!B14 -> GHOSNS903311BK | C15: =Inventory!C14 -> BATWING HOODY | D15: ='Projection Sheet'!D22 -> 125
A16: 9 | B16: =Inventory!B15 -> GHOSRX203401BK | C16: =Inventory!C15 -> PULLOVER HOODY SKELETON | D16: ='Projection Sheet'!D23 -> 80
A17: 10 | B17: =Inventory!B16 -> GHOSRX203275BK | C17: =Inventory!C16 -> SHORTS BLACK/ WHT PAPA V COSTUME CLAWS | D17: ='Projection Sheet'!D24 -> 45
A18: 11 | B18: =Inventory!B17 -> GHOSRX103510OT | C18: =Inventory!C17 -> TIE DYE T TOP HAT | D18: ='Projection Sheet'!D25 -> 60
A19: 12 | B19: =Inventory!B18 -> GHOSRX103437OT | C19: =Inventory!C18 -> CRYSTAL WASHED T AT THE GATES | D19: ='Projection Sheet'!D26 -> 60
... A67: 60 | B67: =Inventory!B66 -> 0 | C67: =Inventory!C66 -> 0 | D67: ='Projection Sheet'!D74 -> 0
A68: 61 | B68: =Inventory!B67 -> 0 | C68: =Inventory!C67 -> 0 | D68: ='Projection Sheet'!D75 -> 0
A69: 62 | B69: =Inventory!B68 -> 0 | C69: =Inventory!C68 -> 0 | D69: ='Projection Sheet'!D76 -> 0
A70: 63 | B70: =Inventory!B69 -> 0 | C70: =Inventory!C69 -> 0 | D70: ='Projection Sheet'!D77 -> 0
A71: 64 | B71: =Inventory!B70 -> 0 | C71: =Inventory!C70 -> 0 | D71: ='Projection Sheet'!D78 -> 0
A72: 65 | B72: =Inventory!B71 -> 0 | C72: =Inventory!C71 -> 0 | D72: ='Projection Sheet'!D79 -> 0
A73: 66 | B73: =Inventory!B72 -> 0 | C73: =Inventory!C72 -> 0 | D73: ='Projection Sheet'!D80 -> 0
A74: 67 | B74: =Inventory!B73 -> 0 | C74: =Inventory!C73 -> 0 | D74: ='Projection Sheet'!D81 -> 0
A75: 68 | B75: =Inventory!B74 -> 0 | C75: =Inventory!C74 -> 0 | D75: ='Projection Sheet'!D82 -> 0
A76: 69 | B76: =Inventory!B75 -> 0 | C76: =Inventory!C75 -> 0 | D76: ='Projection Sheet'!D83 -> 0
A77: 70 | B77: =Inventory!B76 -> 0 | C77: =Inventory!C76 -> 0 | D77: ='Projection Sheet'!D84 -> 0
A78: 71 | B78: =Inventory!B77 -> 0 | C78: =Inventory!C77 -> 0 | D78: ='Projection Sheet'!D85 -> 0
A79: 72 | B79: =Inventory!B78 -> 0 | C79: =Inventory!C78 -> 0 | D79: ='Projection Sheet'!D86 -> 0
... A107: 100 | B107: =Inventory!B106 -> 0 | C107: =Inventory!C106 -> 0 | D107: ='Projection Sheet'!D114 -> 0

Sheet Projection Sheet
F2: SM | G2: MED | H2: LG | I2: XL | J2: 2X | K2: 3X | L2: TOTAL | N2: TOUR STOCK | O2: ORDER QTY | P2: TOTAL | Q2: SIZE | R2: SIZE % | S2: AMOUNT | T2: LESS TOUR INV | U2: ORDER QTY | X2: TS | Y2: LADIES | Z2: LS | AA2: ZIP | AB2: SHORTS
L3: =SUM(F3:K3) -> 0 | N3: 1811 | O3: 720 | P3: =N3+O3 -> 2531 | Q3: SM | R3: 0.08 | S3: =P3*R3 -> 202.48 | T3: 107 | U3: =S3-T3 -> 95.48 | X3: 0.09 | Y3: 0.25 | Z3: 0.04 | AA3: 0.08 | AB3: 0.2
L4: =SUM(F4:K4) -> 0 | P4: =P3 -> 2531 | Q4: MED | R4: 0.18 | S4: =P4*R4 -> 455.58 | T4: 356 | U4: =S4-T4 -> 99.58 | X4: 0.21 | Y4: 0.32 | Z4: 0.17 | AA4: 0.18 | AB4: 0.27
L5: =SUM(F5:K5) -> 0 | P5: =P3 -> 2531 | Q5: LG | R5: 0.27 | S5: =P5*R5 -> 683.37 | T5: 415 | U5: =S5-T5 -> 268.37 | X5: 0.29 | Y5: 0.24 | Z5: 0.24 | AA5: 0.27 | AB5: 0.21 | AG5: DATE | AH5: CITY | AI5: ST | AJ5: VENUE | AK5: CAPACITY | AL5: SOLD | AM5: EXPECT | AO5: PH | AP5: GROSS | AQ5: SELLS | AR5: MERCH | AS5: MEDIA
B6: DATE: | C6: 45796 | L6: =SUM(F6:K6) -> 0 | P6: =P3 -> 2531 | Q6: XL | R6: 0.23 | S6: =P6*R6 -> 582.13 | T6: 540 | U6: =S6-T6 -> 42.13 | X6: 0.23 | Y6: 0.19 | Z6: 0.26 | AA6: 0.23 | AB6: 0.2 | AG6: ='Tour Dates'!A4 -> 45847 | AH6: ='Tour Dates'!B4 -> Baltimore | AI6: ='Tour Dates'!C4 -> MD | AJ6: ='Tour Dates'!D4 -> CFG Bank Arena | AK6: 10153 | AL6: 7892 | AM6: 8500 | AO6: 30 | AP6: =AM6*AO6 -> 255000
B7: BAND: | C7: =Inventory!C3 -> GHOST | L7: =SUM(F7:K7) -> 0 | P7: =P5 -> 2531 | Q7: 2X | R7: 0.15 | S7: =P7*R7 -> 379.65 | T7: 393 | U7: =S7-T7 -> -13.35 | X7: 0.12 | Y7: 0 | Z7: 0.18 | AA7: 0.15 | AB7: 0.12 | AG7: ='Tour Dates'!A5 -> 45849 | AH7: ='Tour Dates'!B5 -> Atlanta | AI7: ='Tour Dates'!C5 -> GA | AJ7: ='Tour Dates'!D5 -> State Farm Arena | AK7: 10699 | AL7: 8803 | AM7: 9500 | AO7: 30 | AP7: =AM7*AO7 -> 285000
B8: TOUR: | C8: North America | L8: =SUM(F8:K8) -> 0 | P8: =P5 -> 2531 | Q8: 3X | R8: 0.09 | S8: =P8*R8 -> 227.79 | T8: 0 | U8: =S8-T8 -> 227.79 | X8: 0.06 | Y8: 0 | Z8: 0.09 | AA8: 0.09 | AB8: 0 | AG8: ='Tour Dates'!A6 -> 45850 | AH8: ='Tour Dates'!B6 -> Tampa | AI8: ='Tour Dates'!C6 -> FL | AJ8: ='Tour Dates'!D6 -> Amalie Arena | AK8: 12354 | AL8: 11053 | AM8: 11500 | AO8: 30 | AP8: =AM8*AO8 -> 345000
B9: # OF SHOWS: | C9: 27 | R9: =SUM(R3:R8) -> 1 | T9: =SUM(T3:T8) -> 1811 | U9: =SUM(U3:U8) -> 720 | X9: 0 | Y9: 0 | Z9: 0.02 | AA9: 0 | AB9: 0 | AG9: ='Tour Dates'!A7 -> 45851 | AH9: ='Tour Dates'!B7 -> Miami | AI9: ='Tour Dates'!C7 -> FL | AJ9: ='Tour Dates'!D7 -> Kaseya Center | AK9: 5497 | AL9: 4290 | AM9: 4500 | AO9: 30 | AP9: =AM9*AO9 -> 135000
B10: ATTENDANCE: | C10: =AM33 -> 234985 | X10: =SUM(X3:X9) -> 1 | Y10: =SUM(Y3:Y9) -> 1 | Z10: =SUM(Z3:Z9) -> 1 | AA10: =SUM(AA3:AA9) -> 1 | AB10: =SUM(AB3:AB9) -> 1 | AG10: ='Tour Dates'!A8 -> 45853 | AH10: ='Tour Dates'!B8 -> Raleigh | AI10: ='Tour Dates'!C8 -> NC | AJ10: ='Tour Dates'!D8 -> Lenovo Center | AK10: 11664 | AL10: 9939 | AM10: 10500 | AO10: 30 | AP10: =AM10*AO10 -> 315000
AG11: ='Tour Dates'!A9 -> 45855 | AH11: ='Tour Dates'!B9 -> Cleveland | AI11: ='Tour Dates'!C9 -> OH | AJ11: ='Tour Dates'!D9 -> Rocket Mortgage FieldHouse | AK11: 10781 | AL11: 8086 | AM11: 8500 | AO11: 30 | AP11: =AM11*AO11 -> 255000
D12: EXP. GROSS | E12: =C10*E13 -> 5874625 | F12: =C10*F13 -> 6344595 | G12: =C10*G13 -> 6814565 | H12: =C10*H13 -> 7284535 | I12: STOCK | J12: STOCK | K12: STOCK | L12: STOCK | M12: STOCK | N12: STOCK | O12: PO's | P12: PRODUCT OVER (+) or UNDER (-) | T12: BLANKS | U12: PRINTER | V12: SM | W12: MED | X12: LG | Y12: XL | Z12: 2X | AA12: 3X | AB12: TOTAL | AC12: DUE | AD12: BLANK PO | AE12: PRINT PO | AG12: ='Tour Dates'!A10 -> 45856 | AH12: ='Tour Dates'!B10 -> Pittsburgh | AI12: ='Tour Dates'!C10 -> PA | AJ12: ='Tour Dates'!D10 -> PPG Paints Arena | AK12: 11009 | AL12: 8560 | AM12: 9000 | AO12: 30 | AP12: =AM12*AO12 -> 270000
C13: =SUM(C15:C59) -> 1 | D13: PRICE/P.H. | E13: 25 | F13: 27 | G13: 29 | H13: 31 | I13: TOUR | J13: CITY-A | K13: CITY-B | L13: SWEDES | M13: UK | N13: LAX | O13: ON ORDER | P13: =E13 -> 25 | Q13: =F13 -> 27 | R13: =G13 -> 29 | S13: =H13 -> 31 | AG13: ='Tour Dates'!A11 -> 45857 | AH13: ='Tour Dates'!B11 -> Philadelphia | AI13: ='Tour Dates'!C11 -> PA | AJ13: ='Tour Dates'!D11 -> Wells Fargo Center | AK13: 12750 | AL13: 11210 | AM13: 12000 | AO13: 30 | AP13: =AM13*AO13 -> 360000
A14: SKU # | B14: DESIGN | C14: % GROSS | AG14: ='Tour Dates'!A12 -> 45859 | AH14: ='Tour Dates'!B12 -> Boston | AI14: ='Tour Dates'!C12 -> MA | AJ14: ='Tour Dates'!D12 -> TD Garden | AK14: 11985 | AL14: 11793 | AM14: 11985 | AO14: 30 | AP14: =AM14*AO14 -> 359550
A15: =Inventory!B7 -> GHOSRX203729BK | B15: =Inventory!C7 -> BLACK T SKELETOUR 2025 ITIN | C15: 0.18 | D15: 50 | E15: =E12/D15*C15 -> 21148.65 | F15: =F12/D15*C15 -> 22840.542 | G15: =G12/D15*C15 -> 24532.434 | H15: =H12/D15*C15 -> 26224.326 | I15: 0 | J15: 0 | K15: 0 | L15: 0 | M15: 0 | N15: 0 | O15: 7200 | P15: =I15+J15+K15+L15+M15+N15+O15-E15 -> -13948.65 | Q15: =I15+J15+K15+L15+M15+N15+O15-F15 -> -15640.542 | R15: =I15+J15+K15+L15+M15+N15+O15-G15 -> -17332.434 | S15: =I15+J15+K15+L15+M15+N15+O15-H15 -> -19024.326 | T15: GILDAN 64000 | U15: =Inventory!D7 -> CULTURE | V15: 648 | W15: 1512 | X15: 2088 | Y15: 1656 | Z15: 864 | AA15: 432 | AB15: =SUM(V15:AA15) -> 7200 | AC15: 45841 | AG15: ='Tour Dates'!A13 -> 45860 | AH15: ='Tour Dates'!B13 -> New York | AI15: ='Tour Dates'!C13 -> NY | AJ15: ='Tour Dates'!D13 -> Madison Square Garden | AK15: 11450 | AL15: 10655 | AM15: 11000 | AO15: 25 | AP15: =AM15*AO15 -> 275000
A16: =Inventory!B8 -> GHOSRX203728BK | B16: =Inventory!C8 -> BLACK T SKELETA ALBUM COVER 2025 ITIN | C16: 0.135 | D16: 50 | E16: =E12/D16*C16 -> 15861.488 | F16: =F12/D16*C16 -> 17130.407 | G16: =G12/D16*C16 -> 18399.325 | H16: =H12/D16*C16 -> 19668.245 | I16: 0 | J16: 0 | K16: 0 | L16: 0 | M16: 0 | N16: 0 | O16: 5246 | P16: =I16+J16+K16+L16+M16+N16+O16-E16 -> -10615.488 | Q16: =I16+J16+K16+L16+M16+N16+O16-F16 -> -11884.407 | R16: =I16+J16+K16+L16+M16+N16+O16-G16 -> -13153.325 | S16: =I16+J16+K16+L16+M16+N16+O16-H16 -> -14422.245 | T16: GILDAN 64000 | U16: =Inventory!D8 -> CULTURE | V16: 504 | W16: 1152 | X16: 1440 | Y16: 1224 | Z16: 648 | AA16: 288 | AB16: =SUM(V16:AA16) -> 5256 | AC16: 45841 | AG16: ='Tour Dates'!A14 -> 45862 | AH16: ='Tour Dates'!B14 -> Detroit | AI16: ='Tour Dates'!C14 -> MI | AJ16: ='Tour Dates'!D14 -> Little Caesars Arena | AK16: 10117 | AL16: 7564 | AM16: 8000 | AO16: 30 | AP16: =AM16*AO16 -> 240000
A17: =Inventory!B9 -> GHOSRX203730BK | B17: =Inventory!C9 -> BLACK T WESTERN EMERITUS 2025 ITIN | C17: 0.18 | D17: 50 | E17: =E12/D17*C17 -> 21148.65 | F17: =F12/D17*C17 -> 22840.542 | G17: =G12/D17*C17 -> 24532.434 | H17: =H12/D17*C17 -> 26224.326 | I17: 0 | J17: 0 | K17: 0 | L17: 0 | M17: 0 | N17: 0 | O17: 7200 | P17: =I17+J17+K17+L17+M17+N17+O17-E17 -> -13948.65 | Q17: =I17+J17+K17+L17+M17+N17+O17-F17 -> -15640.542 | R17: =I17+J17+K17+L17+M17+N17+O17-G17 -> -17332.434 | S17: =I17+J17+K17+L17+M17+N17+O17-H17 -> -19024.326 | T17: GILDAN 64000 | U17: =Inventory!D9 -> CULTURE | V17: 648 | W17: 1512 | X17: 2088 | Y17: 1656 | Z17: 864 | AA17: 432 | AB17: =SUM(V17:AA17) -> 7200 | AC17: 45841 | AG17: ='Tour Dates'!A15 -> 45863 | AH17: ='Tour Dates'!B15 -> Louisville | AI17: ='Tour Dates'!C15 -> KY | AJ17: ='Tour Dates'!D15 -> KFC Yum! Center | AK17: 9832 | AL17: 8848 | AM17: 9500 | AO17: 30 | AP17: =AM17*AO17 -> 285000
A18: =Inventory!B10 -> GHOSRX103726BK | B18: =Inventory!C10 -> BLACK TANK OPUS EPONYMOUS | C18: 0.03 | D18: 50 | E18: =E12/D18*C18 -> 3524.775 | F18: =F12/D18*C18 -> 3806.757 | G18: =G12/D18*C18 -> 4088.739 | H18: =H12/D18*C18 -> 4370.721 | I18: 0 | J18: 0 | K18: 0 | L18: 0 | M18: 0 | N18: 0 | O18: 1440 | P18: =I18+J18+K18+L18+M18+N18+O18-E18 -> -2084.775 | Q18: =I18+J18+K18+L18+M18+N18+O18-F18 -> -2366.757 | R18: =I18+J18+K18+L18+M18+N18+O18-G18 -> -2648.739 | S18: =I18+J18+K18+L18+M18+N18+O18-H18 -> -2930.721 | T18: ASC 5025 | U18: =Inventory!D10 -> CULTURE | V18: 216 | W18: 288 | X18: 360 | Y18: 288 | Z18: 216 | AA18: 72 | AB18: =SUM(V18:AA18) -> 1440 | AC18: 45841 | AG18: ='Tour Dates'!A16 -> 45864 | AH18: ='Tour Dates'!B16 -> Nashville | AI18: ='Tour Dates'!C16 -> TN | AJ18: ='Tour Dates'!D16 -> Bridgestone Arena | AK18: 10596 | AL18: 8189 | AM18: 8500 | AO18: 30 | AP18: =AM18*AO18 -> 255000
A19: =Inventory!B11 -> GHOSRX203400BK | B19: =Inventory!C11 -> LADIES CROP TOP SHOWGHOULS | C19: 0.02 | D19: 50 | E19: =E12/D19*C19 -> 2349.85 | F19: =F12/D19*C19 -> 2537.838 | G19: =G12/D19*C19 -> 2725.826 | H19: =H12/D19*C19 -> 2913.814 | I19: 0 | J19: 0 | K19: 0 | L19: 0 | M19: 1028 | N19: 0 | O19: 0 | P19: =I19+J19+K19+L19+M19+N19+O19-E19 -> -1321.85 | Q19: =I19+J19+K19+L19+M19+N19+O19-F19 -> -1509.838 | R19: =I19+J19+K19+L19+M19+N19+O19-G19 -> -1697.826 | S19: =I19+J19+K19+L19+M19+N19+O19-H19 -> -1885.814 | T19: GMSUK | U19: =Inventory!D11 -> GMSUK | AB19: =SUM(V19:AA19) -> 0 | AG19: ='Tour Dates'!A17 -> 45866 | AH19: ='Tour Dates'!B17 -> Grand Rapids | AI19: ='Tour Dates'!C17 -> MI | AJ19: ='Tour Dates'!D17 -> Van Andel Arena | AK19: 6932 | AL19: 5548 | AM19: 6000 | AO19: 30 | AP19: =AM19*AO19 -> 180000
A20: =Inventory!B12 -> GHOSRX203727PK | B20: =Inventory!C12 -> LADIES PINK RAGLAN GARGOYLE | C20: 0.02 | D20: 50 | E20: =E12/D20*C20 -> 2349.85 | F20: =F12/D20*C20 -> 2537.838 | G20: =G12/D20*C20 -> 2725.826 | H20: =H12/D20*C20 -> 2913.814 | I20: 0 | J20: 0 | K20: 0 | L20: 0 | M20: 0 | N20: 0 | O20: 1152 | P20: =I20+J20+K20+L20+M20+N20+O20-E20 -> -1197.85 | Q20: =I20+J20+K20+L20+M20+N20+O20-F20 -> -1385.838 | R20: =I20+J20+K20+L20+M20+N20+O20-G20 -> -1573.826 | S20: =I20+J20+K20+L20+M20+N20+O20-H20 -> -1761.814 | T20: TBC | U20: =Inventory!D12 -> CULTURE | V20: 288 | W20: 360 | X20: 288 | Y20: 216 | Z20: 0 | AA20: 0 | AB20: =SUM(V20:AA20) -> 1152 | AC20: 45841 | AG20: ='Tour Dates'!A18 -> 45867 | AH20: ='Tour Dates'!B18 -> Milwaukee | AI20: ='Tour Dates'!C18 -> WI | AJ20: ='Tour Dates'!D18 -> Fiserv Forum | AK20: 8693 | AL20: 5844 | AM20: 6500 | AO20: 30 | AP20: =AM20*AO20 -> 195000
A21: =Inventory!B13 -> 0 | B21: =Inventory!C13 -> 0 | C21: 0 | D21: 1 | E21: =E12/D21*C21 -> 0 | F21: =F12/D21*C21 -> 0 | G21: =G12/D21*C21 -> 0 | H21: =H12/D21*C21 -> 0 | I21: 0 | J21: 0 | K21: 0 | L21: 0 | M21: 0 | N21: 0 | O21: 0 | P21: =I21+J21+K21+L21+M21+N21+O21-E21 -> 0 | Q21: =I21+J21+K21+L21+M21+N21+O21-F21 -> 0 | R21: =I21+J21+K21+L21+M21+N21+O21-G21 -> 0 | S21: =I21+J21+K21+L21+M21+N21+O21-H21 -> 0 | U21: =Inventory!D13 -> 0 | AB21: =SUM(V21:AA21) -> 0 | AG21: ='Tour Dates'!A19 -> 45868 | AH21: ='Tour Dates'!B19 -> St. Louis | AI21: ='Tour Dates'!C19 -> MO | AJ21: ='Tour Dates'!D19 -> Enterprise Center | AK21: 8569 | AL21: 5844 | AM21: 6500 | AO21: 30 | AP21: =AM21*AO21 -> 195000
A22: =Inventory!B14 -> GHOSNS903311BK | B22: =Inventory!C14 -> BATWING HOODY | C22: 0.095 | D22: 125 | E22: =E12/D22*C22 -> 4464.715 | F22: =F12/D22*C22 -> 4821.8922 | G22: =G12/D22*C22 -> 5179.0694 | H22: =H12/D22*C22 -> 5536.2466 | I22: 0 | J22: 0 | K22: 0 | L22: 0 | M22: 1247 | N22: 4636 | O22: 0 | P22: =I22+J22+K22+L22+M22+N22+O22-E22 -> 1418.285 | Q22: =I22+J22+K22+L22+M22+N22+O22-F22 -> 1061.1078 | R22: =I22+J22+K22+L22+M22+N22+O22-G22 -> 703.9306 | S22: =I22+J22+K22+L22+M22+N22+O22-H22 -> 346.7534 | T22: CUSTOM | U22: =Inventory!D14 -> FARSTAR | V22: 350 | W22: 900 | X22: 1200 | Y22: 1000 | Z22: 700 | AA22: 350 | AB22: =SUM(V22:AA22) -> 4500 | AC22: 45792 | AG22: ='Tour Dates'!A20 -> 45870 | AH22: ='Tour Dates'!B20 -> Rosemont | AI22: ='Tour Dates'!C20 -> IL | AJ22: ='Tour Dates'!D20 -> Allstate Arena | AK22: 11214 | AL22: 10005 | AM22: 11000 | AO22: 30 | AP22: =AM22*AO22 -> 330000
A23: =Inventory!B15 -> GHOSRX203401BK | B23: =Inventory!C15 -> PULLOVER HOODY SKELETON | C23: 0.06 | D23: 80 | E23: =E12/D23*C23 -> 4405.9688 | F23: =F12/D23*C23 -> 4758.4462 | G23: =G12/D23*C23 -> 5110.9237 | H23: =H12/D23*C23 -> 5463.4012 | I23: 0 | J23: 0 | K23: 0 | L23: 0 | M23: =107+356+415+540+393 -> 1811 | N23: 0 | O23: 720 | P23: =I23+J23+K23+L23+M23+N23+O23-E23 -> -1874.9688 | Q23: =I23+J23+K23+L23+M23+N23+O23-F23 -> -2227.4462 | R23: =I23+J23+K23+L23+M23+N23+O23-G23 -> -2579.9237 | S23: =I23+J23+K23+L23+M23+N23+O23-H23 -> -2932.4012 | T23: IND SS4500 | U23: =Inventory!D15 -> CULTURE | V23: 96 | W23: 108 | X23: 264 | Y23: 36 | Z23: 0 | AA23: 216 | AB23: =SUM(V23:AA23) -> 720 | AC23: 45841 | AG23: ='Tour Dates'!A21 -> 45871 | AH23: ='Tour Dates'!B21 -> Saint Paul | AI23: ='Tour Dates'!C21 -> MN | AJ23: ='Tour Dates'!D21 -> Xcel Energy Center | AK23: 11460 | AL23: 8926 | AM23: 9500 | AO23: 30 | AP23: =AM23*AO23 -> 285000
A24: =Inventory!B16 -> GHOSRX203275BK | B24: =Inventory!C16 -> SHORTS BLACK/ WHT PAPA V COSTUME CLAWS | C24: 0.02 | D24: 45 | E24: =E12/D24*C24 -> 2610.9444 | F24: =F12/D24*C24 -> 2819.82 | G24: =G12/D24*C24 -> 3028.6956 | H24: =H12/D24*C24 -> 3237.5711 | I24: 0 | J24: 0 | K24: 0 | L24: 0 | M24: 323 | N24: 0 | O24: 3000 | P24: =I24+J24+K24+L24+M24+N24+O24-E24 -> 712.05556 | Q24: =I24+J24+K24+L24+M24+N24+O24-F24 -> 503.18 | R24: =I24+J24+K24+L24+M24+N24+O24-G24 -> 294.30444 | S24: =I24+J24+K24+L24+M24+N24+O24-H24 -> 85.428889 | T24: LAA73001 / FARSTAR | U24: =Inventory!D16 -> CULTURE | V24: 600 | W24: 800 | X24: 700 | Y24: 600 | Z24: 300 | AA24: 0 | AB24: =SUM(V24:AA24) -> 3000 | AC24: 45842 | AG24: ='Tour Dates'!A22 -> 45872 | AH24: ='Tour Dates'!B22 -> Omaha | AI24: ='Tour Dates'!C22 -> NE | AJ24: ='Tour Dates'!D22 -> CHI Health Center | AK24: 7393 | AL24: 4761 | AM24: 6000 | AO24: 30 | AP24: =AM24*AO24 -> 180000
A25: =Inventory!B17 -> GHOSRX103510OT | B25: =Inventory!C17 -> TIE DYE T TOP HAT | C25: 0.02 | D25: 60 | E25: =E12/D25*C25 -> 1958.2083 | F25: =F12/D25*C25 -> 2114.865 | G25: =G12/D25*C25 -> 2271.5217 | H25: =H12/D25*C25 -> 2428.1783 | I25: 0 | J25: 0 | K25: 0 | L25: 0 | M25: 2407 | N25: 0 | O25: 0 | P25: =I25+J25+K25+L25+M25+N25+O25-E25 -> 448.79167 | Q25: =I25+J25+K25+L25+M25+N25+O25-F25 -> 292.135 | R25: =I25+J25+K25+L25+M25+N25+O25-G25 -> 135.47833 | S25: =I25+J25+K25+L25+M25+N25+O25-H25 -> -21.178333 | U25: =Inventory!D17 -> GMSUK | AB25: =SUM(V25:AA25) -> 0 | AG25: ='Tour Dates'!A23 -> 45874 | AH25: ='Tour Dates'!B23 -> Kansas City | AI25: ='Tour Dates'!C23 -> MO | AJ25: ='Tour Dates'!D23 -> T-Mobile Center | AK25: 8131 | AL25: 5909 | AM25: 6500 | AO25: 30 | AP25: =AM25*AO25 -> 195000
A26: =Inventory!B18 -> GHOSRX103437OT | B26: =Inventory!C18 -> CRYSTAL WASHED T AT THE GATES | C26: 0.02 | D26: 60 | E26: =E12/D26*C26 -> 1958.2083 | F26: =F12/D26*C26 -> 2114.865 | G26: =G12/D26*C26 -> 2271.5217 | H26: =H12/D26*C26 -> 2428.1783 | I26: 0 | J26: 0 | K26: 0 | L26: 0 | M26: 0 | N26: 0 | O26: 1296 | P26: =I26+J26+K26+L26+M26+N26+O26-E26 -> -662.20833 | Q26: =I26+J26+K26+L26+M26+N26+O26-F26 -> -818.865 | R26: =I26+J26+K26+L26+M26+N26+O26-G26 -> -975.52167 | S26: =I26+J26+K26+L26+M26+N26+O26-H26 -> -1132.1783 | T26: COLORTONE 390 | U26: =Inventory!D18 -> CULTURE DAYTONA | V26: 144 | W26: 288 | X26: 360 | Y26: 288 | Z26: 144 | AA26: 72 | AB26: =SUM(V26:AA26) -> 1296 | AC26: 45841 | AG26: ='Tour Dates'!A24 -> 45876 | AH26: ='Tour Dates'!B24 -> Denver | AI26: ='Tour Dates'!C24 -> CO | AJ26: ='Tour Dates'!D24 -> Ball Arena | AK26: 10511 | AL26: 7861 | AM26: 8500 | AO26: 30 | AP26: =AM26*AO26 -> 255000
A27: =Inventory!B19 -> GHOSRX203738BL | B27: =Inventory!C19 -> OILWASHED NAVY BLUE T COME TOGETHER | C27: 0.01 | D27: 60 | E27: =E12/D27*C27 -> 979.10417 | F27: =F12/D27*C27 -> 1057.4325 | G27: =G12/D27*C27 -> 1135.7608 | H27: =H12/D27*C27 -> 1214.0892 | I27: 0 | J27: 0 | K27: 0 | L27: 0 | M27: 0 | N27: 0 | O27: 684 | P27: =I27+J27+K27+L27+M27+N27+O27-E27 -> -295.10417 | Q27: =I27+J27+K27+L27+M27+N27+O27-F27 -> -373.4325 | R27: =I27+J27+K27+L27+M27+N27+O27-G27 -> -451.76083 | S27: =I27+J27+K27+L27+M27+N27+O27-H27 -> -530.08917 | T27: COLORTONE 1310 | U27: =Inventory!D19 -> CULTURE DAYTONA | V27: 72 | W27: 144 | X27: 216 | Y27: 144 | Z27: 72 | AA27: 36 | AB27: =SUM(V27:AA27) -> 684 | AC27: 45841 | AG27: ='Tour Dates'!A25 -> 45878 | AH27: ='Tour Dates'!B25 -> Las Vegas | AI27: ='Tour Dates'!C25 -> NV | AJ27: ='Tour Dates'!D25 -> MGM Grand Garden Arena | AK27: 9678 | AL27: 8863 | AM27: 9500 | AO27: 30 | AP27: =AM27*AO27 -> 285000
A28: =Inventory!B20 -> GHOSRX203570RD | B28: =Inventory!C20 -> SHORTS RED/WHITE LOGO | C28: 0 | D28: 45 | E28: =E12/D28*C28 -> 0 | F28: =F12/D28*C28 -> 0 | G28: =G12/D28*C28 -> 0 | H28: =H12/D28*C28 -> 0 | I28: 0 | J28: 0 | K28: 0 | L28: 0 | M28: 0 | N28: 0 | O28: 576 | P28: =I28+J28+K28+L28+M28+N28+O28-E28 -> 576 | Q28: =I28+J28+K28+L28+M28+N28+O28-F28 -> 576 | R28: =I28+J28+K28+L28+M28+N28+O28-G28 -> 576 | S28: =I28+J28+K28+L28+M28+N28+O28-H28 -> 576 | T28: LAA73001 | U28: =Inventory!D20 -> CULTURE | V28: 96 | W28: 168 | X28: 168 | Y28: 96 | Z28: 48 | AA28: 0 | AB28: =SUM(V28:AA28) -> 576 | AC28: 45845 | AG28: ='Tour Dates'!A26 -> 8/10/2025 | AH28: ='Tour Dates'!B26 -> San Diego | AI28: ='Tour Dates'!C26 -> CA | AJ28: ='Tour Dates'!D26 -> Viejas Arena | AK28: 7758 | AL28: 7755 | AM28: 8500 | AO28: 30 | AP28: =AM28*AO28 -> 255000
A29: =Inventory!B21 -> GHOSRX203800BK | B29: =Inventory!C21 -> EVENT T TAMPA | C29: 0 | D29: 50 | E29: =E12/D29*C29 -> 0 | F29: =F12/D29*C29 -> 0 | G29: =G12/D29*C29 -> 0 | H29: =H12/D29*C29 -> 0 | I29: 0 | J29: 0 | K29: 0 | L29: 0 | M29: 0 | N29: 0 | O29: 0 | P29: =I29+J29+K29+L29+M29+N29+O29-E29 -> 0 | Q29: =I29+J29+K29+L29+M29+N29+O29-F29 -> 0 | R29: =I29+J29+K29+L29+M29+N29+O29-G29 -> 0 | S29: =I29+J29+K29+L29+M29+N29+O29-H29 -> 0 | U29: =Inventory!D21 -> CULTURE DAYTONA | AB29: =SUM(V29:AA29) -> 0 | AG29: ='Tour Dates'!A27 -> 8/11/2025 | AH29: ='Tour Dates'!B27 -> Phoenix | AI29: ='Tour Dates'!C27 -> AZ | AJ29: ='Tour Dates'!D27 -> Footprint Center | AK29: 10625 | AL29: 8363 | AM29: 9000 | AO29: 30 | AP29: =AM29*AO29 -> 270000
A30: =Inventory!B22 -> GHOSRX203799BK | B30: =Inventory!C22 -> EVENT T PHILLY | C30: 0 | D30: 50 | E30: =E12/D30*C30 -> 0 | F30: =F12/D30*C30 -> 0 | G30: =G12/D30*C30 -> 0 | H30: =H12/D30*C30 -> 0 | I30: 0 | J30: 0 | K30: 0 | L30: 0 | M30: 0 | N30: 0 | O30: 0 | P30: =I30+J30+K30+L30+M30+N30+O30-E30 -> 0 | Q30: =I30+J30+K30+L30+M30+N30+O30-F30 -> 0 | R30: =I30+J30+K30+L30+M30+N30+O30-G30 -> 0 | S30: =I30+J30+K30+L30+M30+N30+O30-H30 -> 0 | U30: =Inventory!D22 -> CULTURE | AB30: =SUM(V30:AA30) -> 0 | AG30: ='Tour Dates'!A28 -> 8/14/2025 | AH30: ='Tour Dates'!B28 -> Austin | AI30: ='Tour Dates'!C28 -> TX | AJ30: ='Tour Dates'!D28 -> Moody Center | AK30: 9196 | AL30: 6675 | AM30: 7500 | AO30: 35 | AP30: =AM30*AO30 -> 262500
A31: =Inventory!B23 -> GHOSRX203798BK | B31: =Inventory!C23 -> EVENT T BOSTON | C31: 0 | D31: 50 | E31: =E12/D31*C31 -> 0 | F31: =F12/D31*C31 -> 0 | G31: =G12/D31*C31 -> 0 | H31: =H12/D31*C31 -> 0 | I31: 0 | J31: 0 | K31: 0 | L31: 0 | M31: 0 | N31: 0 | O31: 0 | P31: =I31+J31+K31+L31+M31+N31+O31-E31 -> 0 | Q31: =I31+J31+K31+L31+M31+N31+O31-F31 -> 0 | R31: =I31+J31+K31+L31+M31+N31+O31-G31 -> 0 | S31: =I31+J31+K31+L31+M31+N31+O31-H31 -> 0 | U31: =Inventory!D23 -> CULTURE | AB31: =SUM(V31:AA31) -> 0 | AG31: ='Tour Dates'!A29 -> 8/15/2025 | AH31: ='Tour Dates'!B29 -> Fort Worth | AI31: ='Tour Dates'!C29 -> TX | AJ31: ='Tour Dates'!D29 -> Dickies Arena | AK31: 10268 | AL31: 8620 | AM31: 9500 | AO31: 35 | AP31: =AM31*AO31 -> 332500
A32: =Inventory!B24 -> GHOSRX203801BK | B32: =Inventory!C24 -> EVENT T NEW YORK | C32: 0 | D32: 50 | E32: =E12/D32*C32 -> 0 | F32: =F12/D32*C32 -> 0 | G32: =G12/D32*C32 -> 0 | H32: =H12/D32*C32 -> 0 | I32: 0 | J32: 0 | K32: 0 | L32: 0 | M32: 0 | N32: 0 | O32: 0 | P32: =I32+J32+K32+L32+M32+N32+O32-E32 -> 0 | Q32: =I32+J32+K32+L32+M32+N32+O32-F32 -> 0 | R32: =I32+J32+K32+L32+M32+N32+O32-G32 -> 0 | S32: =I32+J32+K32+L32+M32+N32+O32-H32 -> 0 | U32: =Inventory!D24 -> CULTURE | AB32: =SUM(V32:AA32) -> 0 | AG32: ='Tour Dates'!A30 -> 8/16/2025 | AH32: ='Tour Dates'!B30 -> Houston | AI32: ='Tour Dates'!C30 -> TX | AJ32: ='Tour Dates'!D30 -> Toyota Center | AK32: 9922 | AL32: 5922 | AM32: 7500 | AO32: 35 | AP32: =AM32*AO32 -> 262500
A33: =Inventory!B25 -> GHOSRX203822BK | B33: =Inventory!C25 -> EVENT T CHICAGO | C33: 0 | D33: 50 | E33: =E12/D33*C33 -> 0 | F33: =F12/D33*C33 -> 0 | G33: =G12/D33*C33 -> 0 | H33: =H12/D33*C33 -> 0 | I33: 0 | J33: 0 | K33: 0 | L33: 0 | M33: 0 | N33: 0 | O33: 0 | P33: =I33+J33+K33+L33+M33+N33+O33-E33 -> 0 | Q33: =I33+J33+K33+L33+M33+N33+O33-F33 -> 0 | R33: =I33+J33+K33+L33+M33+N33+O33-G33 -> 0 | S33: =I33+J33+K33+L33+M33+N33+O33-H33 -> 0 | U33: =Inventory!D25 -> CULTURE | AB33: =SUM(V33:AA33) -> 0 | AK33: =SUM(AK6:AK32) -> 269237 | AL33: =SUM(AL6:AL32) -> 217778 | AM33: =SUM(AM6:AM32) -> 234985 | AO33: =AP33/AM33 -> 30.287252 | AP33: =SUM(AP6:AP32) -> 7117050
A34: =Inventory!B26 -> 0 | B34: =Inventory!C26 -> 0 | C34: 0 | D34: 1 | E34: =E12/D34*C34 -> 0 | F34: =F12/D34*C34 -> 0 | G34: =G12/D34*C34 -> 0 | H34: =H12/D34*C34 -> 0 | I34: 0 | J34: 0 | K34: 0 | L34: 0 | M34: 0 | N34: 0 | O34: 0 | P34: =I34+J34+K34+L34+M34+N34+O34-E34 -> 0 | Q34: =I34+J34+K34+L34+M34+N34+O34-F34 -> 0 | R34: =I34+J34+K34+L34+M34+N34+O34-G34 -> 0 | S34: =I34+J34+K34+L34+M34+N34+O34-H34 -> 0 | U34: =Inventory!D26 -> 0 | AB34: =SUM(V34:AA34) -> 0 | AL34: =AL33/AK33 -> 0.80887099 | AM34: =AM33/AK33 -> 0.87278123
A35: =Inventory!B27 -> 0 | B35: =Inventory!C27 -> 0 | C35: 0 | D35: 1 | E35: =E12/D35*C35 -> 0 | F35: =F12/D35*C35 -> 0 | G35: =G12/D35*C35 -> 0 | H35: =H12/D35*C35 -> 0 | I35: 0 | J35: 0 | K35: 0 | L35: 0 | M35: 0 | N35: 0 | O35: 0 | P35: =I35+J35+K35+L35+M35+N35+O35-E35 -> 0 | Q35: =I35+J35+K35+L35+M35+N35+O35-F35 -> 0 | R35: =I35+J35+K35+L35+M35+N35+O35-G35 -> 0 | S35: =I35+J35+K35+L35+M35+N35+O35-H35 -> 0 | U35: =Inventory!D27 -> 0 | AB35: =SUM(V35:AA35) -> 0
A36: =Inventory!B28 -> GHOSNS103665BK | B36: =Inventory!C28 -> HAT SATANIC PANIC | C36: 0.01 | D36: 35 | E36: =E12/D36*C36 -> 1678.4643 | F36: =F12/D36*C36 -> 1812.7414 | G36: =G12/D36*C36 -> 1947.0186 | H36: =H12/D36*C36 -> 2081.2957 | I36: 0 | J36: 0 | K36: 0 | L36: 1215 | M36: 0 | N36: 0 | O36: 0 | P36: =I36+J36+K36+L36+M36+N36+O36-E36 -> -463.46429 | Q36: =I36+J36+K36+L36+M36+N36+O36-F36 -> -597.74143 | R36: =I36+J36+K36+L36+M36+N36+O36-G36 -> -732.01857 | S36: =I36+J36+K36+L36+M36+N36+O36-H36 -> -866.29571 | U36: =Inventory!D28 -> WELLSUCCEED | AB36: =SUM(V36:AA36) -> 0
A37: =Inventory!B29 -> GHOSNS903309GR | B37: =Inventory!C29 -> MASK BURNT GHOUL | C37: 0.015 | D37: 40 | E37: =E12/D37*C37 -> 2202.9844 | F37: =F12/D37*C37 -> 2379.2231 | G37: =G12/D37*C37 -> 2555.4619 | H37: =H12/D37*C37 -> 2731.7006 | I37: 0 | J37: 0 | K37: 0 | L37: 0 | M37: 1060 | N37: 3000 | O37: 0 | P37: =I37+J37+K37+L37+M37+N37+O37-E37 -> 1857.0156 | Q37: =I37+J37+K37+L37+M37+N37+O37-F37 -> 1680.7769 | R37: =I37+J37+K37+L37+M37+N37+O37-G37 -> 1504.5381 | S37: =I37+J37+K37+L37+M37+N37+O37-H37 -> 1328.2994 | T37: CUSTOM | U37: =Inventory!D29 -> FARSTAR | AB37: 3000 | AC37: 45792
A38: =Inventory!B30 -> GHOSNS903279OT | B38: =Inventory!C30 -> PLUSHIE FRATER IMPERATOR | C38: 0.08 | D38: 50 | E38: =E12/D38*C38 -> 9399.4 | F38: =F12/D38*C38 -> 10151.352 | G38: =G12/D38*C38 -> 10903.304 | H38: =H12/D38*C38 -> 11655.256 | I38: 0 | J38: 0 | K38: 0 | L38: 0 | M38: 4118 | N38: 12096 | O38: 0 | P38: =I38+J38+K38+L38+M38+N38+O38-E38 -> 6814.6 | Q38: =I38+J38+K38+L38+M38+N38+O38-F38 -> 6062.648 | R38: =I38+J38+K38+L38+M38+N38+O38-G38 -> 5310.696 | S38: =I38+J38+K38+L38+M38+N38+O38-H38 -> 4558.744 | T38: CUSTOM | U38: =Inventory!D30 -> FARSTAR | AB38: 12000
A39: =Inventory!B31 -> GHOSRX103259OT | B39: =Inventory!C31 -> CLEAR SLING BAG-SILVER LOGO | C39: 0.005 | D39: 40 | E39: =E12/D39*C39 -> 734.32812 | F39: =F12/D39*C39 -> 793.07438 | G39: =G12/D39*C39 -> 851.82063 | H39: =H12/D39*C39 -> 910.56687 | I39: 0 | J39: 0 | K39: 0 | L39: 0 | M39: 0 | N39: 1000 | O39: 0 | P39: =I39+J39+K39+L39+M39+N39+O39-E39 -> 265.67188 | Q39: =I39+J39+K39+L39+M39+N39+O39-F39 -> 206.92562 | R39: =I39+J39+K39+L39+M39+N39+O39-G39 -> 148.17937 | S39: =I39+J39+K39+L39+M39+N39+O39-H39 -> 89.433125 | T39: CUSTOM | U39: =Inventory!D31 -> FARSTAR | AB39: 1000 | AC39: 45792
A40: =Inventory!B32 -> GHOSRX103241BK | B40: =Inventory!C32 -> CHOKER PAPA V | C40: 0.0125 | D40: 30 | E40: =E12/D40*C40 -> 2447.7604 | F40: =F12/D40*C40 -> 2643.5813 | G40: =G12/D40*C40 -> 2839.4021 | H40: =H12/D40*C40 -> 3035.2229 | I40: 0 | J40: 0 | K40: 0 | L40: 0 | M40: 1359 | N40: 2500 | O40: 0 | P40: =I40+J40+K40+L40+M40+N40+O40-E40 -> 1411.2396 | Q40: =I40+J40+K40+L40+M40+N40+O40-F40 -> 1215.4187 | R40: =I40+J40+K40+L40+M40+N40+O40-G40 -> 1019.5979 | S40: =I40+J40+K40+L40+M40+N40+O40-H40 -> 823.77708 | T40: CUSTOM | U40: =Inventory!D32 -> FARSTAR | AB40: 2500 | AC40: 45792
A41: =Inventory!B33 -> GHOSRX203254GR | B41: =Inventory!C33 -> KEYCHAIN SKELETON GRUCIFIX | C41: 0.0175 | D41: 15 | E41: =E12/D41*C41 -> 6853.7292 | F41: =F12/D41*C41 -> 7402.0275 | G41: =G12/D41*C41 -> 7950.3258 | H41: =H12/D41*C41 -> 8498.6242 | I41: 0 | J41: 0 | K41: 0 | L41: 0 | M41: 4483 | N41: 6000 | O41: 0 | P41: =I41+J41+K41+L41+M41+N41+O41-E41 -> 3629.2708 | Q41: =I41+J41+K41+L41+M41+N41+O41-F41 -> 3080.9725 | R41: =I41+J41+K41+L41+M41+N41+O41-G41 -> 2532.6742 | S41: =I41+J41+K41+L41+M41+N41+O41-H41 -> 1984.3758 | T41: CUSTOM | U41: =Inventory!D33 -> FARSTAR | AB41: 6000 | AC41: 45792
A42: =Inventory!B34 -> GHOSRX903403OT | B42: =Inventory!C34 -> PATCH SET OF 3 | C42: 0.0175 | D42: 20 | E42: =E12/D42*C42 -> 5140.2969 | F42: =F12/D42*C42 -> 5551.5206 | G42: =G12/D42*C42 -> 5962.7444 | H42: =H12/D42*C42 -> 6373.9681 | I42: 0 | J42: 0 | K42: 0 | L42: 0 | M42: 1910 | N42: 5000 | O42: 0 | P42: =I42+J42+K42+L42+M42+N42+O42-E42 -> 1769.7031 | Q42: =I42+J42+K42+L42+M42+N42+O42-F42 -> 1358.4794 | R42: =I42+J42+K42+L42+M42+N42+O42-G42 -> 947.25562 | S42: =I42+J42+K42+L42+M42+N42+O42-H42 -> 536.03187 | T42: CUSTOM | U42: =Inventory!D34 -> WELLSUCCEED | AB42: 5000 | AC42: 45792
A43: =Inventory!B35 -> GHOSNS103814BK | B43: =Inventory!C35 -> TOUR PROGRAM | C43: 0.02 | D43: 30 | E43: =E12/D43*C43 -> 3916.4167 | F43: =F12/D43*C43 -> 4229.73 | G43: =G12/D43*C43 -> 4543.0433 | H43: =H12/D43*C43 -> 4856.3567 | I43: 0 | J43: 0 | K43: 0 | L43: 0 | M43: 0 | N43: 0 | O43: 5000 | P43: =I43+J43+K43+L43+M43+N43+O43-E43 -> 1083.5833 | Q43: =I43+J43+K43+L43+M43+N43+O43-F43 -> 770.27 | R43: =I43+J43+K43+L43+M43+N43+O43-G43 -> 456.95667 | S43: =I43+J43+K43+L43+M43+N43+O43-H43 -> 143.64333 | U43: =Inventory!D35 -> VANDALAY | AB43: =SUM(V43:AA43) -> 0
A44: =Inventory!B36 -> GHOSRX903408OT | B44: =Inventory!C36 -> LP SKELETA POLTERGEIST | C44: 0.005 | D44: 40 | E44: =E12/D44*C44 -> 734.32812 | F44: =F12/D44*C44 -> 793.07438 | G44: =G12/D44*C44 -> 851.82063 | H44: =H12/D44*C44 -> 910.56687 | I44: 0 | J44: 0 | K44: 0 | L44: 2000 | M44: 0 | N44: 0 | O44: 0 | P44: =I44+J44+K44+L44+M44+N44+O44-E44 -> 1265.6719 | Q44: =I44+J44+K44+L44+M44+N44+O44-F44 -> 1206.9256 | R44: =I44+J44+K44+L44+M44+N44+O44-G44 -> 1148.1794 | S44: =I44+J44+K44+L44+M44+N44+O44-H44 -> 1089.4331 | U44: =Inventory!D36 -> CONCORD | AB44: =SUM(V44:AA44) -> 0
A45: =Inventory!B37 -> GHOSNS203369OT | B45: =Inventory!C37 -> FOILED COMIC BOOK SISTER IMPERATOR # 1 | C45: 0.005 | D45: 30 | E45: =E12/D45*C45 -> 979.10417 | F45: =F12/D45*C45 -> 1057.4325 | G45: =G12/D45*C45 -> 1135.7608 | H45: =H12/D45*C45 -> 1214.0892 | I45: 0 | J45: 0 | K45: 0 | L45: 0 | M45: 545 | N45: 0 | O45: 2500 | P45: =I45+J45+K45+L45+M45+N45+O45-E45 -> 2065.8958 | Q45: =I45+J45+K45+L45+M45+N45+O45-F45 -> 1987.5675 | R45: =I45+J45+K45+L45+M45+N45+O45-G45 -> 1909.2392 | S45: =I45+J45+K45+L45+M45+N45+O45-H45 -> 1830.9108 | T45: UPC 761568014181 | U45: =Inventory!D37 -> DARK HORSE COMICS | AB45: =SUM(V45:AA45) -> 0
A46: =Inventory!B38 -> GHOSNS203533OT | B46: =Inventory!C38 -> COMIC BOOK SISTER IMPERATOR #2 | C46: 0.0025 | D46: 15 | E46: =E12/D46*C46 -> 979.10417 | F46: =F12/D46*C46 -> 1057.4325 | G46: =G12/D46*C46 -> 1135.7608 | H46: =H12/D46*C46 -> 1214.0892 | I46: 0 | J46: 0 | K46: 0 | L46: 300 | M46: 0 | N46: 0 | O46: 0 | P46: =I46+J46+K46+L46+M46+N46+O46-E46 -> -679.10417 | Q46: =I46+J46+K46+L46+M46+N46+O46-F46 -> -757.4325 | R46: =I46+J46+K46+L46+M46+N46+O46-G46 -> -835.76083 | S46: =I46+J46+K46+L46+M46+N46+O46-H46 -> -914.08917 | U46: =Inventory!D38 -> DARK HORSE COMICS | AB46: =SUM(V46:AA46) -> 0
A47: =Inventory!B39 -> GHOSNS203534OT | B47: =Inventory!C39 -> COMIC BOOK SISTER IMPERATOR #3 | C47: 0.0025 | D47: 15 | E47: =E12/D47*C47 -> 979.10417 | F47: =F12/D47*C47 -> 1057.4325 | G47: =G12/D47*C47 -> 1135.7608 | H47: =H12/D47*C47 -> 1214.0892 | I47: 0 | J47: 0 | K47: 0 | L47: 300 | M47: 0 | N47: 0 | O47: 0 | P47: =I47+J47+K47+L47+M47+N47+O47-E47 -> -679.10417 | Q47: =I47+J47+K47+L47+M47+N47+O47-F47 -> -757.4325 | R47: =I47+J47+K47+L47+M47+N47+O47-G47 -> -835.76083 | S47: =I47+J47+K47+L47+M47+N47+O47-H47 -> -914.08917 | U47: =Inventory!D39 -> DARK HORSE COMICS | AB47: =SUM(V47:AA47) -> 0
A48: =Inventory!B40 -> GHOSNS203535OT | B48: =Inventory!C40 -> COMIC BOOK SISTER IMPERATOR #4 | C48: 0.0025 | D48: 15 | E48: =E12/D48*C48 -> 979.10417 | F48: =F12/D48*C48 -> 1057.4325 | G48: =G12/D48*C48 -> 1135.7608 | H48: =H12/D48*C48 -> 1214.0892 | I48: 0 | J48: 0 | K48: 0 | L48: 300 | M48: 0 | N48: 0 | O48: 0 | P48: =I48+J48+K48+L48+M48+N48+O48-E48 -> -679.10417 | Q48: =I48+J48+K48+L48+M48+N48+O48-F48 -> -757.4325 | R48: =I48+J48+K48+L48+M48+N48+O48-G48 -> -835.76083 | S48: =I48+J48+K48+L48+M48+N48+O48-H48 -> -914.08917 | U48: =Inventory!D40 -> DARK HORSE COMICS | AB48: =SUM(V48:AA48) -> 0
A49: =Inventory!B41 -> 0 | B49: =Inventory!C41 -> 0 | C49: 0 | D49: 1 | E49: =E12/D49*C49 -> 0 | F49: =F12/D49*C49 -> 0 | G49: =G12/D49*C49 -> 0 | H49: =H12/D49*C49 -> 0 | I49: 0 | J49: 0 | K49: 0 | L49: 0 | M49: 0 | N49: 0 | O49: 0 | P49: =I49+J49+K49+L49+M49+N49+O49-E49 -> 0 | Q49: =I49+J49+K49+L49+M49+N49+O49-F49 -> 0 | R49: =I49+J49+K49+L49+M49+N49+O49-G49 -> 0 | S49: =I49+J49+K49+L49+M49+N49+O49-H49 -> 0 | U49: =Inventory!D41 -> 0 | AB49: =SUM(V49:AA49) -> 0
A50: =Inventory!B42 -> GHOSNS103619OT | B50: =Inventory!C42 -> FOILED COMIC BOOK SISTER IMPERATOR #2 | C50: 0.005 | D50: 30 | E50: =E12/D50*C50 -> 979.10417 | F50: =F12/D50*C50 -> 1057.4325 | G50: =G12/D50*C50 -> 1135.7608 | H50: =H12/D50*C50 -> 1214.0892 | I50: 0 | J50: 0 | K50: 0 | L50: 0 | M50: 0 | N50: 0 | O50: 1000 | P50: =I50+J50+K50+L50+M50+N50+O50-E50 -> 20.895833 | Q50: =I50+J50+K50+L50+M50+N50+O50-F50 -> -57.4325 | R50: =I50+J50+K50+L50+M50+N50+O50-G50 -> -135.76083 | S50: =I50+J50+K50+L50+M50+N50+O50-H50 -> -214.08917 | U50: =Inventory!D42 -> DARK HORSE COMICS | AB50: =SUM(V50:AA50) -> 0
A51: =Inventory!B43 -> GHOSNS103622OT | B51: =Inventory!C43 -> FOILED COMIC BOOK SISTER IMPERATOR #3 | C51: 0.005 | D51: 30 | E51: =E12/D51*C51 -> 979.10417 | F51: =F12/D51*C51 -> 1057.4325 | G51: =G12/D51*C51 -> 1135.7608 | H51: =H12/D51*C51 -> 1214.0892 | I51: 0 | J51: 0 | K51: 0 | L51: 0 | M51: 0 | N51: 0 | O51: 1000 | P51: =I51+J51+K51+L51+M51+N51+O51-E51 -> 20.895833 | Q51: =I51+J51+K51+L51+M51+N51+O51-F51 -> -57.4325 | R51: =I51+J51+K51+L51+M51+N51+O51-G51 -> -135.76083 | S51: =I51+J51+K51+L51+M51+N51+O51-H51 -> -214.08917 | U51: =Inventory!D43 -> DARK HORSE COMICS | AB51: =SUM(V51:AA51) -> 0
A52: =Inventory!B44 -> GHOSNS103624OT | B52: =Inventory!C44 -> FOILED COMIC BOOK SISTER IMPERATOR #4 | C52: 0.005 | D52: 30 | E52: =E12/D52*C52 -> 979.10417 | F52: =F12/D52*C52 -> 1057.4325 | G52: =G12/D52*C52 -> 1135.7608 | H52: =H12/D52*C52 -> 1214.0892 | I52: 0 | J52: 0 | K52: 0 | L52: 0 | M52: 0 | N52: 0 | O52: 1000 | P52: =I52+J52+K52+L52+M52+N52+O52-E52 -> 20.895833 | Q52: =I52+J52+K52+L52+M52+N52+O52-F52 -> -57.4325 | R52: =I52+J52+K52+L52+M52+N52+O52-G52 -> -135.76083 | S52: =I52+J52+K52+L52+M52+N52+O52-H52 -> -214.08917 | U52: =Inventory!D44 -> DARK HORSE COMICS | AB52: =SUM(V52:AA52) -> 0
A53: =Inventory!B45 -> GHOSRX003463OT | B53: =Inventory!C45 -> CD SKELETA | D53: 20 | E53: =E12/D53*C53 -> 0 | F53: =F12/D53*C53 -> 0 | G53: =G12/D53*C53 -> 0 | H53: =H12/D53*C53 -> 0 | I53: 0 | J53: 0 | K53: 0 | L53: 0 | M53: 0 | N53: 0 | O53: 0 | P53: =I53+J53+K53+L53+M53+N53+O53-E53 -> 0 | Q53: =I53+J53+K53+L53+M53+N53+O53-F53 -> 0 | R53: =I53+J53+K53+L53+M53+N53+O53-G53 -> 0 | S53: =I53+J53+K53+L53+M53+N53+O53-H53 -> 0 | U53: =Inventory!D45 -> GMSUK | AB53: =SUM(V53:AA53) -> 0
A54: =Inventory!B46 -> GHOSRX003470OT | B54: =Inventory!C46 -> ROLLING STONE MAG & ALBUM | D54: 30 | E54: =E12/D54*C54 -> 0 | F54: =F12/D54*C54 -> 0 | G54: =G12/D54*C54 -> 0 | H54: =H12/D54*C54 -> 0 | I54: 0 | J54: 0 | K54: 0 | L54: 0 | M54: 0 | N54: 0 | O54: 0 | P54: =I54+J54+K54+L54+M54+N54+O54-E54 -> 0 | Q54: =I54+J54+K54+L54+M54+N54+O54-F54 -> 0 | R54: =I54+J54+K54+L54+M54+N54+O54-G54 -> 0 | S54: =I54+J54+K54+L54+M54+N54+O54-H54 -> 0 | U54: =Inventory!D46 -> GMSUK | AB54: =SUM(V54:AA54) -> 0
A55: =Inventory!B47 -> GHOSRX003611BK | B55: =Inventory!C47 -> LP SKELETA BLACK VINYL | D55: 40 | E55: =E12/D55*C55 -> 0 | F55: =F12/D55*C55 -> 0 | G55: =G12/D55*C55 -> 0 | H55: =H12/D55*C55 -> 0 | I55: 0 | J55: 0 | K55: 0 | L55: 0 | M55: 0 | N55: 0 | O55: 0 | P55: =I55+J55+K55+L55+M55+N55+O55-E55 -> 0 | Q55: =I55+J55+K55+L55+M55+N55+O55-F55 -> 0 | R55: =I55+J55+K55+L55+M55+N55+O55-G55 -> 0 | S55: =I55+J55+K55+L55+M55+N55+O55-H55 -> 0 | U55: =Inventory!D47 -> GMSUK | AB55: =SUM(V55:AA55) -> 0
A56: =Inventory!B48 -> GHOSCG103805PU | B56: =Inventory!C48 -> LP PURPLE LENTICULAR | D56: 1 | E56: =E12/D56*C56 -> 0 | F56: =F12/D56*C56 -> 0 | G56: =G12/D56*C56 -> 0 | H56: =H12/D56*C56 -> 0 | I56: 0 | J56: 0 | K56: 0 | L56: 0 | M56: 0 | N56: 0 | O56: 0 | P56: =I56+J56+K56+L56+M56+N56+O56-E56 -> 0 | Q56: =I56+J56+K56+L56+M56+N56+O56-F56 -> 0 | R56: =I56+J56+K56+L56+M56+N56+O56-G56 -> 0 | S56: =I56+J56+K56+L56+M56+N56+O56-H56 -> 0 | U56: =Inventory!D48 -> CONCORD | AB56: =SUM(V56:AA56) -> 0
A57: =Inventory!B49 -> GHOSCG103844BK | B57: =Inventory!C49 -> CASSETTE | D57: 1 | E57: =E12/D57*C57 -> 0 | F57: =F12/D57*C57 -> 0 | G57: =G12/D57*C57 -> 0 | H57: =H12/D57*C57 -> 0 | I57: 0 | J57: 0 | K57: 0 | L57: 0 | M57: 0 | N57: 0 | O57: 0 | P57: =I57+J57+K57+L57+M57+N57+O57-E57 -> 0 | Q57: =I57+J57+K57+L57+M57+N57+O57-F57 -> 0 | R57: =I57+J57+K57+L57+M57+N57+O57-G57 -> 0 | S57: =I57+J57+K57+L57+M57+N57+O57-H57 -> 0 | U57: =Inventory!D49 -> CONCORD | AB57: =SUM(V57:AA57) -> 0
A58: =Inventory!B50 -> 0 | B58: =Inventory!C50 -> 0 | D58: 1 | E58: =E12/D58*C58 -> 0 | F58: =F12/D58*C58 -> 0 | G58: =G12/D58*C58 -> 0 | H58: =H12/D58*C58 -> 0 | I58: 0 | J58: 0 | K58: 0 | L58: 0 | M58: 0 | N58: 0 | O58: 0 | P58: =I58+J58+K58+L58+M58+N58+O58-E58 -> 0 | Q58: =I58+J58+K58+L58+M58+N58+O58-F58 -> 0 | R58: =I58+J58+K58+L58+M58+N58+O58-G58 -> 0 | S58: =I58+J58+K58+L58+M58+N58+O58-H58 -> 0 | U58: =Inventory!D50 -> 0 | AB58: =SUM(V58:AA58) -> 0
A59: =Inventory!B51 -> 0 | B59: =Inventory!C51 -> 0 | D59: 1 | E59: =E23/D59*C59 -> 0 | F59: =F12/D59*C59 -> 0 | G59: =G12/D59*C59 -> 0 | H59: =H12/D59*C59 -> 0 | I59: 0 | J59: 0 | K59: 0 | L59: 0 | M59: 0 | N59: 0 | O59: 0 | P59: =I59+J59+K59+L59+M59+N59+O59-E59 -> 0 | Q59: =I59+J59+K59+L59+M59+N59+O59-F59 -> 0 | R59: =I59+J59+K59+L59+M59+N59+O59-G59 -> 0 | S59: =I59+J59+K59+L59+M59+N59+O59-H59 -> 0 | U59: =Inventory!D51 -> 0 | AB59: =SUM(V59:AA59) -> 0
C60: =SUM(C15:C52) -> 1

Sheet MIAMI HOUSTON
F2: SM | G2: MED | H2: LG | I2: XL | J2: 2X | K2: 3X | L2: TOTAL | N2: TOUR STOCK | O2: ORDER QTY | P2: TOTAL | Q2: SIZE | R2: SIZE % | S2: AMOUNT | T2: LESS TOUR INV | U2: ORDER QTY | X2: TS | Y2: LADIES | Z2: LS | AA2: ZIP | AB2: SHORTS
L3: =SUM(F3:K3) -> 0 | O3: 4000 | P3: =N3+O3 -> 4000 | Q3: SM | R3: 0.18 | S3: =P3*R3 -> 720 | T3: 0 | U3: =S3-T3 -> 720 | X3: 0.09 | Y3: 0.25 | Z3: 0.04 | AA3: 0.08 | AB3: 0.2
L4: =SUM(F4:K4) -> 0 | P4: =P3 -> 4000 | Q4: MED | R4: 0.24 | S4: =P4*R4 -> 960 | T4: 0 | U4: =S4-T4 -> 960 | X4: 0.21 | Y4: 0.32 | Z4: 0.17 | AA4: 0.18 | AB4: 0.27
L5: =SUM(F5:K5) -> 0 | P5: =P3 -> 4000 | Q5: LG | R5: 0.21 | S5: =P5*R5 -> 840 | T5: 0 | U5: =S5-T5 -> 840 | X5: 0.29 | Y5: 0.24 | Z5: 0.24 | AA5: 0.27 | AB5: 0.21 | AG5: DATE | AH5: CITY | AI5: ST | AJ5: VENUE | AK5: CAPACITY | AL5: SOLD | AM5: EXPECT | AO5: PH | AP5: GROSS | AQ5: SELLS | AR5: MERCH | AS5: MEDIA
B6: DATE: | C6: 45848 | L6: =SUM(F6:K6) -> 0 | P6: =P3 -> 4000 | Q6: XL | R6: 0.21 | S6: =P6*R6 -> 840 | T6: 0 | U6: =S6-T6 -> 840 | X6: 0.23 | Y6: 0.19 | Z6: 0.26 | AA6: 0.23 | AB6: 0.2 | AG6: ='Tour Dates'!A4 -> 45847 | AH6: ='Tour Dates'!B4 -> Baltimore | AI6: ='Tour Dates'!C4 -> MD | AJ6: ='Tour Dates'!D4 -> CFG Bank Arena | AO6: 30 | AP6: =AM6*AO6 -> 0
B7: BAND: | C7: =Inventory!C3 -> GHOST | L7: =SUM(F7:K7) -> 0 | P7: =P5 -> 4000 | Q7: 2X | R7: 0.16 | S7: =P7*R7 -> 640 | T7: 0 | U7: =S7-T7 -> 640 | X7: 0.12 | Y7: 0 | Z7: 0.18 | AA7: 0.15 | AB7: 0.12 | AG7: ='Tour Dates'!A5 -> 45849 | AH7: ='Tour Dates'!B5 -> Atlanta | AI7: ='Tour Dates'!C5 -> GA | AJ7: ='Tour Dates'!D5 -> State Farm Arena | AO7: 35 | AP7: =AM7*AO7 -> 0
B8: TOUR: | C8: North America | L8: =SUM(F8:K8) -> 0 | P8: =P5 -> 4000 | Q8: 3X | R8: 0 | S8: =P8*R8 -> 0 | T8: 0 | U8: =S8-T8 -> 0 | X8: 0.06 | Y8: 0 | Z8: 0.09 | AA8: 0.09 | AB8: 0 | AG8: ='Tour Dates'!A6 -> 45850 | AH8: ='Tour Dates'!B6 -> Tampa | AI8: ='Tour Dates'!C6 -> FL | AJ8: ='Tour Dates'!D6 -> Amalie Arena | AO8: 35 | AP8: =AM8*AO8 -> 0
B9: # OF SHOWS: | C9: 27 | R9: =SUM(R3:R8) -> 1 | T9: =SUM(T3:T8) -> 0 | U9: =SUM(U3:U8) -> 4000 | X9: 0 | Y9: 0 | Z9: 0.02 | AA9: 0 | AB9: 0 | AG9: ='Tour Dates'!A7 -> 45851 | AH9: ='Tour Dates'!B7 -> Miami | AI9: ='Tour Dates'!C7 -> FL | AJ9: ='Tour Dates'!D7 -> Kaseya Center | AK9: 5497 | AL9: 4290 | AM9: 4500 | AO9: 30 | AP9: =AM9*AO9 -> 135000
B10: ATTENDANCE: | C10: =AM33 -> 205485 | X10: =SUM(X3:X9) -> 1 | Y10: =SUM(Y3:Y9) -> 1 | Z10: =SUM(Z3:Z9) -> 1 | AA10: =SUM(AA3:AA9) -> 1 | AB10: =SUM(AB3:AB9) -> 1 | AG10: ='Tour Dates'!A8 -> 45853 | AH10: ='Tour Dates'!B8 -> Raleigh | AI10: ='Tour Dates'!C8 -> NC | AJ10: ='Tour Dates'!D8 -> Lenovo Center | AK10: 11664 | AL10: 9939 | AM10: 10500 | AO10: 35 | AP10: =AM10*AO10 -> 367500
AG11: ='Tour Dates'!A9 -> 45855 | AH11: ='Tour Dates'!B9 -> Cleveland | AI11: ='Tour Dates'!C9 -> OH | AJ11: ='Tour Dates'!D9 -> Rocket Mortgage FieldHouse | AK11: 10781 | AL11: 8086 | AM11: 8500 | AO11: 35 | AP11: =AM11*AO11 -> 297500
D12: EXP. GROSS | E12: =C10*E13 -> 6164550 | F12: =C10*F13 -> 6575520 | G12: =C10*G13 -> 6986490 | H12: =C10*H13 -> 7397460 | I12: STOCK | J12: STOCK | K12: STOCK | L12: STOCK | M12: STOCK | N12: STOCK | O12: PO's | P12: PRODUCT OVER (+) or UNDER (-) | T12: BLANKS | U12: PRINTER | V12: SM | W12: MED | X12: LG | Y12: XL | Z12: 2X | AA12: 3X | AB12: TOTAL | AC12: DUE | AD12: BLANK PO | AE12: PRINT PO | AG12: ='Tour Dates'!A10 -> 45856 | AH12: ='Tour Dates'!B10 -> Pittsburgh | AI12: ='Tour Dates'!C10 -> PA | AJ12: ='Tour Dates'!D10 -> PPG Paints Arena | AK12: 11009 | AL12: 8560 | AM12: 9000 | AO12: 35 | AP12: =AM12*AO12 -> 315000
C13: =SUM(C15:C59) -> 1.015 | D13: PRICE/P.H. | E13: 30 | F13: 32 | G13: 34 | H13: 36 | I13: TOUR | J13: ATLANT | K13: CITY-B | L13: SWEDES | M13: UK | N13: LAX | O13: ON ORDER | P13: =E13 -> 30 | Q13: =F13 -> 32 | R13: =G13 -> 34 | S13: =H13 -> 36 | AG13: ='Tour Dates'!A11 -> 45857 | AH13: ='Tour Dates'!B11 -> Philadelphia | AI13: ='Tour Dates'!C11 -> PA | AJ13: ='Tour Dates'!D11 -> Wells Fargo Center | AK13: 12750 | AL13: 11210 | AM13: 12000 | AO13: 32 | AP13: =AM13*AO13 -> 384000
A14: SKU # | B14: DESIGN | C14: % GROSS | AG14: ='Tour Dates'!A12 -> 45859 | AH14: ='Tour Dates'!B12 -> Boston | AI14: ='Tour Dates'!C12 -> MA | AJ14: ='Tour Dates'!D12 -> TD Garden | AK14: 11985 | AL14: 11793 | AM14: 11985 | AO14: 32 | AP14: =AM14*AO14 -> 383520
A15: =Inventory!B7 -> GHOSRX203729BK | B15: =Inventory!C7 -> BLACK T SKELETOUR 2025 ITIN | C15: 0.18 | D15: 50 | E15: =E12/D15*C15 -> 22192.38 | F15: =F12/D15*C15 -> 23671.872 | G15: =G12/D15*C15 -> 25151.364 | H15: =H12/D15*C15 -> 26630.856 | I15: 6219 | J15: 0 | K15: 0 | L15: 0 | M15: 0 | N15: 0 | O15: 10800 | P15: =I15+J15+K15+L15+M15+N15+O15-E15 -> -5173.38 | Q15: =I15+J15+K15+L15+M15+N15+O15-F15 -> -6652.872 | R15: =I15+J15+K15+L15+M15+N15+O15-G15 -> -8132.364 | S15: =I15+J15+K15+L15+M15+N15+O15-H15 -> -9611.856 | T15: GILDAN 64000 | U15: =Inventory!D7 -> CULTURE | V15: 864 | W15: 2160 | X15: 2880 | Y15: 2880 | Z15: 1152 | AA15: 864 | AB15: =SUM(V15:AA15) -> 10800 | AC15: 45854 | AG15: ='Tour Dates'!A13 -> 45860 | AH15: ='Tour Dates'!B13 -> New York | AI15: ='Tour Dates'!C13 -> NY | AJ15: ='Tour Dates'!D13 -> Madison Square Garden | AK15: 11450 | AL15: 10655 | AM15: 11000 | AO15: 30 | AP15: =AM15*AO15 -> 330000
A16: =Inventory!B8 -> GHOSRX203728BK | B16: =Inventory!C8 -> BLACK T SKELETA ALBUM COVER 2025 ITIN | C16: 0.135 | D16: 50 | E16: =E12/D16*C16 -> 16644.285 | F16: =F12/D16*C16 -> 17753.904 | G16: =G12/D16*C16 -> 18863.523 | H16: =H12/D16*C16 -> 19973.142 | I16: 4423 | J16: 0 | K16: 0 | L16: 0 | M16: 0 | N16: 0 | O16: 7200 | P16: =I16+J16+K16+L16+M16+N16+O16-E16 -> -5021.285 | Q16: =I16+J16+K16+L16+M16+N16+O16-F16 -> -6130.904 | R16: =I16+J16+K16+L16+M16+N16+O16-G16 -> -7240.523 | S16: =I16+J16+K16+L16+M16+N16+O16-H16 -> -8350.142 | T16: GILDAN 64000 | U16: =Inventory!D8 -> CULTURE | V16: 576 | W16: 1440 | X16: 1944 | Y16: 1872 | Z16: 792 | AA16: 576 | AB16: =SUM(V16:AA16) -> 7200 | AC16: 45854 | AG16: ='Tour Dates'!A14 -> 45862 | AH16: ='Tour Dates'!B14 -> Detroit | AI16: ='Tour Dates'!C14 -> MI | AJ16: ='Tour Dates'!D14 -> Little Caesars Arena | AK16: 10117 | AL16: 7564 | AM16: 8000 | AO16: 32 | AP16: =AM16*AO16 -> 256000
A17: =Inventory!B9 -> GHOSRX203730BK | B17: =Inventory!C9 -> BLACK T WESTERN EMERITUS 2025 ITIN | C17: 0.18 | D17: 50 | E17: =E12/D17*C17 -> 22192.38 | F17: =F12/D17*C17 -> 23671.872 | G17: =G12/D17*C17 -> 25151.364 | H17: =H12/D17*C17 -> 26630.856 | I17: 6194 | J17: 0 | K17: 0 | L17: 0 | M17: 0 | N17: 0 | O17: 10800 | P17: =I17+J17+K17+L17+M17+N17+O17-E17 -> -5198.38 | Q17: =I17+J17+K17+L17+M17+N17+O17-F17 -> -6677.872 | R17: =I17+J17+K17+L17+M17+N17+O17-G17 -> -8157.364 | S17: =I17+J17+K17+L17+M17+N17+O17-H17 -> -9636.856 | T17: GILDAN 64000 | U17: =Inventory!D9 -> CULTURE | V17: 864 | W17: 2160 | X17: 2880 | Y17: 2880 | Z17: 1152 | AA17: 864 | AB17: =SUM(V17:AA17) -> 10800 | AC17: 45854 | AG17: ='Tour Dates'!A15 -> 45863 | AH17: ='Tour Dates'!B15 -> Louisville | AI17: ='Tour Dates'!C15 -> KY | AJ17: ='Tour Dates'!D15 -> KFC Yum! Center | AK17: 9832 | AL17: 8848 | AM17: 9500 | AO17: 32 | AP17: =AM17*AO17 -> 304000
A18: =Inventory!B10 -> GHOSRX103726BK | B18: =Inventory!C10 -> BLACK TANK OPUS EPONYMOUS | C18: 0.02 | D18: 50 | E18: =E12/D18*C18 -> 2465.82 | F18: =F12/D18*C18 -> 2630.208 | G18: =G12/D18*C18 -> 2794.596 | H18: =H12/D18*C18 -> 2958.984 | I18: 1302 | J18: 0 | K18: 0 | L18: 0 | M18: 0 | N18: 0 | O18: 720 | P18: =I18+J18+K18+L18+M18+N18+O18-E18 -> -443.82 | Q18: =I18+J18+K18+L18+M18+N18+O18-F18 -> -608.208 | R18: =I18+J18+K18+L18+M18+N18+O18-G18 -> -772.596 | S18: =I18+J18+K18+L18+M18+N18+O18-H18 -> -936.984 | T18: ASC 5025 | U18: =Inventory!D10 -> CULTURE | V18: 108 | W18: 180 | X18: 216 | Y18: 144 | Z18: 72 | AA18: 0 | AB18: =SUM(V18:AA18) -> 720 | AC18: 45854 | AG18: ='Tour Dates'!A16 -> 45864 | AH18: ='Tour Dates'!B16 -> Nashville | AI18: ='Tour Dates'!C16 -> TN | AJ18: ='Tour Dates'!D16 -> Bridgestone Arena | AK18: 10596 | AL18: 8189 | AM18: 8500 | AO18: 32 | AP18: =AM18*AO18 -> 272000
A19: =Inventory!B11 -> GHOSRX203400BK | B19: =Inventory!C11 -> LADIES CROP TOP SHOWGHOULS | C19: 0.02 | D19: 50 | E19: =E12/D19*C19 -> 2465.82 | F19: =F12/D19*C19 -> 2630.208 | G19: =G12/D19*C19 -> 2794.596 | H19: =H12/D19*C19 -> 2958.984 | I19: 893 | J19: 0 | K19: 0 | L19: 0 | M19: 0 | N19: 0 | O19: 720 | P19: =I19+J19+K19+L19+M19+N19+O19-E19 -> -852.82 | Q19: =I19+J19+K19+L19+M19+N19+O19-F19 -> -1017.208 | R19: =I19+J19+K19+L19+M19+N19+O19-G19 -> -1181.596 | S19: =I19+J19+K19+L19+M19+N19+O19-H19 -> -1345.984 | T19: NLA 5080 | U19: CULTURE | V19: 144 | W19: 216 | X19: 180 | Y19: 180 | Z19: 0 | AA19: 0 | AB19: =SUM(V19:AA19) -> 720 | AC19: 45854 | AG19: ='Tour Dates'!A17 -> 45866 | AH19: ='Tour Dates'!B17 -> Grand Rapids | AI19: ='Tour Dates'!C17 -> MI | AJ19: ='Tour Dates'!D17 -> Van Andel Arena | AK19: 6932 | AL19: 5548 | AM19: 6000 | AO19: 32 | AP19: =AM19*AO19 -> 192000
A20: =Inventory!B12 -> GHOSRX203727PK | B20: =Inventory!C12 -> LADIES PINK RAGLAN GARGOYLE | C20: 0.02 | D20: 50 | E20: =E12/D20*C20 -> 2465.82 | F20: =F12/D20*C20 -> 2630.208 | G20: =G12/D20*C20 -> 2794.596 | H20: =H12/D20*C20 -> 2958.984 | I20: 1017 | J20: 0 | K20: 0 | L20: 0 | M20: 0 | N20: 0 | O20: 720 | P20: =I20+J20+K20+L20+M20+N20+O20-E20 -> -728.82 | Q20: =I20+J20+K20+L20+M20+N20+O20-F20 -> -893.208 | R20: =I20+J20+K20+L20+M20+N20+O20-G20 -> -1057.596 | S20: =I20+J20+K20+L20+M20+N20+O20-H20 -> -1221.984 | T20: BELLA 1201 | U20: =Inventory!D12 -> CULTURE | V20: 180 | W20: 252 | X20: 144 | Y20: 144 | Z20: 0 | AA20: 0 | AB20: =SUM(V20:AA20) -> 720 | AC20: 45854 | AG20: ='Tour Dates'!A18 -> 45867 | AH20: ='Tour Dates'!B18 -> Milwaukee | AI20: ='Tour Dates'!C18 -> WI | AJ20: ='Tour Dates'!D18 -> Fiserv Forum | AK20: 8693 | AL20: 5844 | AM20: 6500 | AO20: 32 | AP20: =AM20*AO20 -> 208000
A21: =Inventory!B13 -> 0 | B21: =Inventory!C13 -> 0 | C21: 0 | D21: 1 | E21: =E12/D21*C21 -> 0 | F21: =F12/D21*C21 -> 0 | G21: =G12/D21*C21 -> 0 | H21: =H12/D21*C21 -> 0 | I21: 0 | J21: 0 | K21: 0 | L21: 0 | M21: 0 | N21: 0 | O21: 0 | P21: =I21+J21+K21+L21+M21+N21+O21-E21 -> 0 | Q21: =I21+J21+K21+L21+M21+N21+O21-F21 -> 0 | R21: =I21+J21+K21+L21+M21+N21+O21-G21 -> 0 | S21: =I21+J21+K21+L21+M21+N21+O21-H21 -> 0 | U21: =Inventory!D13 -> 0 | AB21: =SUM(V21:AA21) -> 0 | AG21: ='Tour Dates'!A19 -> 45868 | AH21: ='Tour Dates'!B19 -> St. Louis | AI21: ='Tour Dates'!C19 -> MO | AJ21: ='Tour Dates'!D19 -> Enterprise Center | AK21: 8569 | AL21: 5844 | AM21: 6500 | AO21: 32 | AP21: =AM21*AO21 -> 208000
A22: =Inventory!B14 -> GHOSNS903311BK | B22: =Inventory!C14 -> BATWING HOODY | C22: 0.07 | D22: 125 | E22: =E12/D22*C22 -> 3452.148 | F22: =F12/D22*C22 -> 3682.2912 | G22: =G12/D22*C22 -> 3912.4344 | H22: =H12/D22*C22 -> 4142.5776 | I22: 1159 | J22: 0 | K22: 0 | L22: 0 | M22: 0 | N22: 3960 | O22: 0 | P22: =I22+J22+K22+L22+M22+N22+O22-E22 -> 1666.852 | Q22: =I22+J22+K22+L22+M22+N22+O22-F22 -> 1436.7088 | R22: =I22+J22+K22+L22+M22+N22+O22-G22 -> 1206.5656 | S22: =I22+J22+K22+L22+M22+N22+O22-H22 -> 976.4224 | T22: CUSTOM | U22: =Inventory!D14 -> FARSTAR | AB22: =SUM(V22:AA22) -> 0 | AG22: ='Tour Dates'!A20 -> 45870 | AH22: ='Tour Dates'!B20 -> Rosemont | AI22: ='Tour Dates'!C20 -> IL | AJ22: ='Tour Dates'!D20 -> Allstate Arena | AK22: 11214 | AL22: 10005 | AM22: 11000 | AO22: 32 | AP22: =AM22*AO22 -> 352000
A23: =Inventory!B15 -> GHOSRX203401BK | B23: =Inventory!C15 -> PULLOVER HOODY SKELETON | C23: 0.08 | D23: 80 | E23: =E12/D23*C23 -> 6164.55 | F23: =F12/D23*C23 -> 6575.52 | G23: =G12/D23*C23 -> 6986.49 | H23: =H12/D23*C23 -> 7397.46 | I23: 2248 | J23: 0 | K23: 0 | L23: 0 | M23: 0 | N23: 0 | O23: 2520 | P23: =I23+J23+K23+L23+M23+N23+O23-E23 -> -1396.55 | Q23: =I23+J23+K23+L23+M23+N23+O23-F23 -> -1807.52 | R23: =I23+J23+K23+L23+M23+N23+O23-G23 -> -2218.49 | S23: =I23+J23+K23+L23+M23+N23+O23-H23 -> -2629.46 | T23: IND SS4500 | U23: =Inventory!D15 -> CULTURE | V23: 240 | W23: 432 | X23: 648 | Y23: 720 | Z23: 360 | AA23: 120 | AB23: =SUM(V23:AA23) -> 2520 | AC23: 45854 | AG23: ='Tour Dates'!A21 -> 45871 | AH23: ='Tour Dates'!B21 -> Saint Paul | AI23: ='Tour Dates'!C21 -> MN | AJ23: ='Tour Dates'!D21 -> Xcel Energy Center | AK23: 11460 | AL23: 8926 | AM23: 9500 | AO23: 32 | AP23: =AM23*AO23 -> 304000
A24: =Inventory!B16 -> GHOSRX203275BK | B24: =Inventory!C16 -> SHORTS BLACK/ WHT PAPA V COSTUME CLAWS | C24: 0.03 | D24: 45 | E24: =E12/D24*C24 -> 4109.7 | F24: =F12/D24*C24 -> 4383.68 | G24: =G12/D24*C24 -> 4657.66 | H24: =H12/D24*C24 -> 4931.64 | I24: 119 | J24: 900 | K24: 0 | L24: 0 | M24: 0 | N24: 0 | O24: 4000 | P24: =I24+J24+K24+L24+M24+N24+O24-E24 -> 909.3 | Q24: =I24+J24+K24+L24+M24+N24+O24-F24 -> 635.32 | R24: =I24+J24+K24+L24+M24+N24+O24-G24 -> 361.34 | S24: =I24+J24+K24+L24+M24+N24+O24-H24 -> 87.36 | T24: FARSTAR | U24: FARSTAR | V24: 700 | W24: 1100 | X24: 900 | Y24: 800 | Z24: 500 | AA24: 0 | AB24: =SUM(V24:AA24) -> 4000 | AC24: 45866 | AG24: ='Tour Dates'!A22 -> 45872 | AH24: ='Tour Dates'!B22 -> Omaha | AI24: ='Tour Dates'!C22 -> NE | AJ24: ='Tour Dates'!D22 -> CHI Health Center | AK24: 7393 | AL24: 4761 | AM24: 6000 | AO24: 32 | AP24: =AM24*AO24 -> 192000
A25: =Inventory!B17 -> GHOSRX103510OT | B25: =Inventory!C17 -> TIE DYE T TOP HAT | C25: 0.03 | D25: 60 | E25: =E12/D25*C25 -> 3082.275 | F25: =F12/D25*C25 -> 3287.76 | G25: =G12/D25*C25 -> 3493.245 | H25: =H12/D25*C25 -> 3698.73 | I25: 2221 | J25: 0 | K25: 0 | L25: 0 | M25: 0 | N25: 0 | O25: 0 | P25: =I25+J25+K25+L25+M25+N25+O25-E25 -> -861.275 | Q25: =I25+J25+K25+L25+M25+N25+O25-F25 -> -1066.76 | R25: =I25+J25+K25+L25+M25+N25+O25-G25 -> -1272.245 | S25: =I25+J25+K25+L25+M25+N25+O25-H25 -> -1477.73 | U25: =Inventory!D17 -> GMSUK | AB25: =SUM(V25:AA25) -> 0 | AG25: ='Tour Dates'!A23 -> 45874 | AH25: ='Tour Dates'!B23 -> Kansas City | AI25: ='Tour Dates'!C23 -> MO | AJ25: ='Tour Dates'!D23 -> T-Mobile Center | AK25: 8131 | AL25: 5909 | AM25: 6500 | AO25: 32 | AP25: =AM25*AO25 -> 208000
A26: =Inventory!B18 -> GHOSRX103437OT | B26: =Inventory!C18 -> CRYSTAL WASHED T AT THE GATES | C26: 0.04 | D26: 60 | E26: =E12/D26*C26 -> 4109.7 | F26: =F12/D26*C26 -> 4383.68 | G26: =G12/D26*C26 -> 4657.66 | H26: =H12/D26*C26 -> 4931.64 | I26: 1076 | J26: 0 | K26: 0 | L26: 0 | M26: 0 | N26: 0 | O26: 1800 | P26: =I26+J26+K26+L26+M26+N26+O26-E26 -> -1233.7 | Q26: =I26+J26+K26+L26+M26+N26+O26-F26 -> -1507.68 | R26: =I26+J26+K26+L26+M26+N26+O26-G26 -> -1781.66 | S26: =I26+J26+K26+L26+M26+N26+O26-H26 -> -2055.64 | T26: COLORTONE 390 | U26: =Inventory!D18 -> CULTURE DAYTONA | V26: 180 | W26: 324 | X26: 504 | Y26: 432 | Z26: 216 | AA26: 144 | AB26: =SUM(V26:AA26) -> 1800 | AC26: 45852 | AG26: ='Tour Dates'!A24 -> 45876 | AH26: ='Tour Dates'!B24 -> Denver | AI26: ='Tour Dates'!C24 -> CO | AJ26: ='Tour Dates'!D24 -> Ball Arena | AK26: 10511 | AL26: 7861 | AM26: 8500 | AO26: 32 | AP26: =AM26*AO26 -> 272000
A27: =Inventory!B19 -> GHOSRX203738BL | B27: =Inventory!C19 -> OILWASHED NAVY BLUE T COME TOGETHER | C27: 0.02 | D27: 60 | E27: =E12/D27*C27 -> 2054.85 | F27: =F12/D27*C27 -> 2191.84 | G27: =G12/D27*C27 -> 2328.83 | H27: =H12/D27*C27 -> 2465.82 | I27: 603 | J27: 0 | K27: 0 | L27: 0 | M27: 0 | N27: 0 | O27: 720 | P27: =I27+J27+K27+L27+M27+N27+O27-E27 -> -731.85 | Q27: =I27+J27+K27+L27+M27+N27+O27-F27 -> -868.84 | R27: =I27+J27+K27+L27+M27+N27+O27-G27 -> -1005.83 | S27: =I27+J27+K27+L27+M27+N27+O27-H27 -> -1142.82 | T27: COLORTONE 1310 | U27: =Inventory!D19 -> CULTURE DAYTONA | V27: 72 | W27: 144 | X27: 216 | Y27: 180 | Z27: 72 | AA27: 36 | AB27: =SUM(V27:AA27) -> 720 | AC27: 45852 | AG27: ='Tour Dates'!A25 -> 45878 | AH27: ='Tour Dates'!B25 -> Las Vegas | AI27: ='Tour Dates'!C25 -> NV | AJ27: ='Tour Dates'!D25 -> MGM Grand Garden Arena | AK27: 9678 | AL27: 8863 | AM27: 9500 | AO27: 32 | AP27: =AM27*AO27 -> 304000
A28: =Inventory!B20 -> GHOSRX203570RD | B28: =Inventory!C20 -> SHORTS RED/WHITE LOGO | C28: 0 | D28: 45 | E28: =E12/D28*C28 -> 0 | F28: =F12/D28*C28 -> 0 | G28: =G12/D28*C28 -> 0 | H28: =H12/D28*C28 -> 0 | I28: 0 | J28: 0 | K28: 0 | L28: 0 | M28: 0 | N28: 0 | O28: 0 | P28: =I28+J28+K28+L28+M28+N28+O28-E28 -> 0 | Q28: =I28+J28+K28+L28+M28+N28+O28-F28 -> 0 | R28: =I28+J28+K28+L28+M28+N28+O28-G28 -> 0 | S28: =I28+J28+K28+L28+M28+N28+O28-H28 -> 0 | T28: LAA73001 | U28: =Inventory!D20 -> CULTURE | AB28: =SUM(V28:AA28) -> 0 | AG28: ='Tour Dates'!A26 -> 8/10/2025 | AH28: ='Tour Dates'!B26 -> San Diego | AI28: ='Tour Dates'!C26 -> CA | AJ28: ='Tour Dates'!D26 -> Viejas Arena | AK28: 7758 | AL28: 7755 | AM28: 8500 | AO28: 32 | AP28: =AM28*AO28 -> 272000
A29: =Inventory!B21 -> GHOSRX203800BK | B29: =Inventory!C21 -> EVENT T TAMPA | C29: 0 | D29: 50 | E29: =E12/D29*C29 -> 0 | F29: =F12/D29*C29 -> 0 | G29: =G12/D29*C29 -> 0 | H29: =H12/D29*C29 -> 0 | I29: 0 | J29: 0 | K29: 0 | L29: 0 | M29: 0 | N29: 0 | O29: 720 | P29: =I29+J29+K29+L29+M29+N29+O29-E29 -> 720 | Q29: =I29+J29+K29+L29+M29+N29+O29-F29 -> 720 | R29: =I29+J29+K29+L29+M29+N29+O29-G29 -> 720 | S29: =I29+J29+K29+L29+M29+N29+O29-H29 -> 720 | T29: FULL PACKAGE GILDAN 6400 | U29: =Inventory!D21 -> CULTURE DAYTONA | V29: 72 | W29: 144 | X29: 216 | Y29: 180 | Z29: 108 | AA29: 72 | AB29: =SUM(V29:AA29) -> 792 | AC29: 45850 | AG29: ='Tour Dates'!A27 -> 8/11/2025 | AH29: ='Tour Dates'!B27 -> Phoenix | AI29: ='Tour Dates'!C27 -> AZ | AJ29: ='Tour Dates'!D27 -> Footprint Center | AK29: 10625 | AL29: 8363 | AM29: 9000 | AO29: 32 | AP29: =AM29*AO29 -> 288000
A30: =Inventory!B22 -> GHOSRX203799BK | B30: =Inventory!C22 -> EVENT T PHILLY | C30: 0 | D30: 50 | E30: =E12/D30*C30 -> 0 | F30: =F12/D30*C30 -> 0 | G30: =G12/D30*C30 -> 0 | H30: =H12/D30*C30 -> 0 | I30: 0 | J30: 0 | K30: 0 | L30: 0 | M30: 0 | N30: 0 | O30: 0 | P30: =I30+J30+K30+L30+M30+N30+O30-E30 -> 0 | Q30: =I30+J30+K30+L30+M30+N30+O30-F30 -> 0 | R30: =I30+J30+K30+L30+M30+N30+O30-G30 -> 0 | S30: =I30+J30+K30+L30+M30+N30+O30-H30 -> 0 | U30: =Inventory!D22 -> CULTURE | AB30: =SUM(V30:AA30) -> 0 | AG30: ='Tour Dates'!A28 -> 8/14/2025 | AH30: ='Tour Dates'!B28 -> Austin | AI30: ='Tour Dates'!C28 -> TX | AJ30: ='Tour Dates'!D28 -> Moody Center | AK30: 9196 | AL30: 6675 | AM30: 7500 | AO30: 38 | AP30: =AM30*AO30 -> 285000
A31: =Inventory!B23 -> GHOSRX203798BK | B31: =Inventory!C23 -> EVENT T BOSTON | C31: 0 | D31: 50 | E31: =E12/D31*C31 -> 0 | F31: =F12/D31*C31 -> 0 | G31: =G12/D31*C31 -> 0 | H31: =H12/D31*C31 -> 0 | I31: 0 | J31: 0 | K31: 0 | L31: 0 | M31: 0 | N31: 0 | O31: 0 | P31: =I31+J31+K31+L31+M31+N31+O31-E31 -> 0 | Q31: =I31+J31+K31+L31+M31+N31+O31-F31 -> 0 | R31: =I31+J31+K31+L31+M31+N31+O31-G31 -> 0 | S31: =I31+J31+K31+L31+M31+N31+O31-H31 -> 0 | U31: =Inventory!D23 -> CULTURE | AB31: =SUM(V31:AA31) -> 0 | AG31: ='Tour Dates'!A29 -> 8/15/2025 | AH31: ='Tour Dates'!B29 -> Fort Worth | AI31: ='Tour Dates'!C29 -> TX | AJ31: ='Tour Dates'!D29 -> Dickies Arena | AK31: 10268 | AL31: 8620 | AM31: 9500 | AO31: 38 | AP31: =AM31*AO31 -> 361000
A32: =Inventory!B24 -> GHOSRX203801BK | B32: =Inventory!C24 -> EVENT T NEW YORK | C32: 0 | D32: 50 | E32: =E12/D32*C32 -> 0 | F32: =F12/D32*C32 -> 0 | G32: =G12/D32*C32 -> 0 | H32: =H12/D32*C32 -> 0 | I32: 0 | J32: 0 | K32: 0 | L32: 0 | M32: 0 | N32: 0 | O32: 0 | P32: =I32+J32+K32+L32+M32+N32+O32-E32 -> 0 | Q32: =I32+J32+K32+L32+M32+N32+O32-F32 -> 0 | R32: =I32+J32+K32+L32+M32+N32+O32-G32 -> 0 | S32: =I32+J32+K32+L32+M32+N32+O32-H32 -> 0 | U32: =Inventory!D24 -> CULTURE | AB32: =SUM(V32:AA32) -> 0 | AG32: ='Tour Dates'!A30 -> 8/16/2025 | AH32: ='Tour Dates'!B30 -> Houston | AI32: ='Tour Dates'!C30 -> TX | AJ32: ='Tour Dates'!D30 -> Toyota Center | AK32: 9922 | AL32: 5922 | AM32: 7500 | AO32: 38 | AP32: =AM32*AO32 -> 285000
A33: =Inventory!B25 -> GHOSRX203822BK | B33: =Inventory!C25 -> EVENT T CHICAGO | C33: 0 | D33: 50 | E33: =E12/D33*C33 -> 0 | F33: =F12/D33*C33 -> 0 | G33: =G12/D33*C33 -> 0 | H33: =H12/D33*C33 -> 0 | I33: 0 | J33: 0 | K33: 0 | L33: 0 | M33: 0 | N33: 0 | O33: 0 | P33: =I33+J33+K33+L33+M33+N33+O33-E33 -> 0 | Q33: =I33+J33+K33+L33+M33+N33+O33-F33 -> 0 | R33: =I33+J33+K33+L33+M33+N33+O33-G33 -> 0 | S33: =I33+J33+K33+L33+M33+N33+O33-H33 -> 0 | U33: =Inventory!D25 -> CULTURE | AB33: =SUM(V33:AA33) -> 0 | AK33: =SUM(AK6:AK32) -> 236031 | AL33: =SUM(AL6:AL32) -> 190030 | AM33: =SUM(AM6:AM32) -> 205485 | AO33: =AP33/AM33 -> 32.973307 | AP33: =SUM(AP6:AP32) -> 6775520
A34: =Inventory!B26 -> 0 | B34: =Inventory!C26 -> 0 | C34: 0 | D34: 1 | E34: =E12/D34*C34 -> 0 | F34: =F12/D34*C34 -> 0 | G34: =G12/D34*C34 -> 0 | H34: =H12/D34*C34 -> 0 | I34: 0 | J34: 0 | K34: 0 | L34: 0 | M34: 0 | N34: 0 | O34: 0 | P34: =I34+J34+K34+L34+M34+N34+O34-E34 -> 0 | Q34: =I34+J34+K34+L34+M34+N34+O34-F34 -> 0 | R34: =I34+J34+K34+L34+M34+N34+O34-G34 -> 0 | S34: =I34+J34+K34+L34+M34+N34+O34-H34 -> 0 | U34: =Inventory!D26 -> 0 | AB34: =SUM(V34:AA34) -> 0 | AL34: =AL33/AK33 -> 0.80510611 | AM34: =AM33/AK33 -> 0.8705848
A35: =Inventory!B27 -> 0 | B35: =Inventory!C27 -> 0 | C35: 0 | D35: 1 | E35: =E12/D35*C35 -> 0 | F35: =F12/D35*C35 -> 0 | G35: =G12/D35*C35 -> 0 | H35: =H12/D35*C35 -> 0 | I35: 0 | J35: 0 | K35: 0 | L35: 0 | M35: 0 | N35: 0 | O35: 0 | P35: =I35+J35+K35+L35+M35+N35+O35-E35 -> 0 | Q35: =I35+J35+K35+L35+M35+N35+O35-F35 -> 0 | R35: =I35+J35+K35+L35+M35+N35+O35-G35 -> 0 | S35: =I35+J35+K35+L35+M35+N35+O35-H35 -> 0 | U35: =Inventory!D27 -> 0 | AB35: =SUM(V35:AA35) -> 0
A36: =Inventory!B28 -> GHOSNS103665BK | B36: =Inventory!C28 -> HAT SATANIC PANIC | C36: 0.01 | D36: 35 | E36: =E12/D36*C36 -> 1761.3 | F36: =F12/D36*C36 -> 1878.72 | G36: =G12/D36*C36 -> 1996.14 | H36: =H12/D36*C36 -> 2113.56 | I36: 1082 | J36: 0 | K36: 0 | L36: 0 | M36: 0 | N36: 0 | O36: 0 | P36: =I36+J36+K36+L36+M36+N36+O36-E36 -> -679.3 | Q36: =I36+J36+K36+L36+M36+N36+O36-F36 -> -796.72 | R36: =I36+J36+K36+L36+M36+N36+O36-G36 -> -914.14 | S36: =I36+J36+K36+L36+M36+N36+O36-H36 -> -1031.56 | U36: =Inventory!D28 -> WELLSUCCEED | AB36: =SUM(V36:AA36) -> 0
A37: =Inventory!B29 -> GHOSNS903309GR | B37: =Inventory!C29 -> MASK BURNT GHOUL | C37: 0.02 | D37: 40 | E37: =E12/D37*C37 -> 3082.275 | F37: =F12/D37*C37 -> 3287.76 | G37: =G12/D37*C37 -> 3493.245 | H37: =H12/D37*C37 -> 3698.73 | I37: 3930 | J37: 0 | K37: 0 | L37: 0 | M37: 0 | N37: 0 | O37: 0 | P37: =I37+J37+K37+L37+M37+N37+O37-E37 -> 847.725 | Q37: =I37+J37+K37+L37+M37+N37+O37-F37 -> 642.24 | R37: =I37+J37+K37+L37+M37+N37+O37-G37 -> 436.755 | S37: =I37+J37+K37+L37+M37+N37+O37-H37 -> 231.27 | T37: CUSTOM | U37: =Inventory!D29 -> FARSTAR | AB37: 0
A38: =Inventory!B30 -> GHOSNS903279OT | B38: =Inventory!C30 -> PLUSHIE FRATER IMPERATOR | C38: 0.07 | D38: 50 | E38: =E12/D38*C38 -> 8630.37 | F38: =F12/D38*C38 -> 9205.728 | G38: =G12/D38*C38 -> 9781.086 | H38: =H12/D38*C38 -> 10356.444 | I38: 3733 | J38: 0 | K38: 0 | L38: 0 | M38: 0 | N38: 11880 | O38: 0 | P38: =I38+J38+K38+L38+M38+N38+O38-E38 -> 6982.63 | Q38: =I38+J38+K38+L38+M38+N38+O38-F38 -> 6407.272 | R38: =I38+J38+K38+L38+M38+N38+O38-G38 -> 5831.914 | S38: =I38+J38+K38+L38+M38+N38+O38-H38 -> 5256.556 | T38: CUSTOM | U38: =Inventory!D30 -> FARSTAR | AB38: 0
A39: =Inventory!B31 -> GHOSRX103259OT | B39: =Inventory!C31 -> CLEAR SLING BAG-SILVER LOGO | C39: 0.01 | D39: 40 | E39: =E12/D39*C39 -> 1541.1375 | F39: =F12/D39*C39 -> 1643.88 | G39: =G12/D39*C39 -> 1746.6225 | H39: =H12/D39*C39 -> 1849.365 | I39: 940 | J39: 0 | K39: 0 | L39: 0 | M39: 0 | N39: 0 | O39: 0 | P39: =I39+J39+K39+L39+M39+N39+O39-E39 -> -601.1375 | Q39: =I39+J39+K39+L39+M39+N39+O39-F39 -> -703.88 | R39: =I39+J39+K39+L39+M39+N39+O39-G39 -> -806.6225 | S39: =I39+J39+K39+L39+M39+N39+O39-H39 -> -909.365 | T39: CUSTOM | U39: =Inventory!D31 -> FARSTAR | AB39: 0
A40: =Inventory!B32 -> GHOSRX103241BK | B40: =Inventory!C32 -> CHOKER PAPA V | C40: 0.0125 | D40: 30 | E40: =E12/D40*C40 -> 2568.5625 | F40: =F12/D40*C40 -> 2739.8 | G40: =G12/D40*C40 -> 2911.0375 | H40: =H12/D40*C40 -> 3082.275 | I40: 3783 | J40: 0 | K40: 0 | L40: 0 | M40: 0 | N40: 0 | O40: 0 | P40: =I40+J40+K40+L40+M40+N40+O40-E40 -> 1214.4375 | Q40: =I40+J40+K40+L40+M40+N40+O40-F40 -> 1043.2 | R40: =I40+J40+K40+L40+M40+N40+O40-G40 -> 871.9625 | S40: =I40+J40+K40+L40+M40+N40+O40-H40 -> 700.725 | T40: CUSTOM | U40: =Inventory!D32 -> FARSTAR | AB40: 0
A41: =Inventory!B33 -> GHOSRX203254GR | B41: =Inventory!C33 -> KEYCHAIN SKELETON GRUCIFIX | C41: 0.02 | D41: 15 | E41: =E12/D41*C41 -> 8219.4 | F41: =F12/D41*C41 -> 8767.36 | G41: =G12/D41*C41 -> 9315.32 | H41: =H12/D41*C41 -> 9863.28 | I41: 10188 | J41: 0 | K41: 0 | L41: 0 | M41: 0 | N41: 0 | O41: 0 | P41: =I41+J41+K41+L41+M41+N41+O41-E41 -> 1968.6 | Q41: =I41+J41+K41+L41+M41+N41+O41-F41 -> 1420.64 | R41: =I41+J41+K41+L41+M41+N41+O41-G41 -> 872.68 | S41: =I41+J41+K41+L41+M41+N41+O41-H41 -> 324.72 | T41: CUSTOM | U41: =Inventory!D33 -> FARSTAR | AB41: 0
A42: =Inventory!B34 -> GHOSRX903403OT | B42: =Inventory!C34 -> PATCH SET OF 3 | C42: 0.015 | D42: 20 | E42: =E12/D42*C42 -> 4623.4125 | F42: =F12/D42*C42 -> 4931.64 | G42: =G12/D42*C42 -> 5239.8675 | H42: =H12/D42*C42 -> 5548.095 | I42: 6716 | J42: 0 | K42: 0 | L42: 0 | M42: 0 | N42: 0 | O42: 0 | P42: =I42+J42+K42+L42+M42+N42+O42-E42 -> 2092.5875 | Q42: =I42+J42+K42+L42+M42+N42+O42-F42 -> 1784.36 | R42: =I42+J42+K42+L42+M42+N42+O42-G42 -> 1476.1325 | S42: =I42+J42+K42+L42+M42+N42+O42-H42 -> 1167.905 | T42: CUSTOM | U42: =Inventory!D34 -> WELLSUCCEED | AB42: 0
A43: =Inventory!B35 -> GHOSNS103814BK | B43: =Inventory!C35 -> TOUR PROGRAM | C43: 0 | D43: 1 | E43: =E12/D43*C43 -> 0 | F43: =F12/D43*C43 -> 0 | G43: =G12/D43*C43 -> 0 | H43: =H12/D43*C43 -> 0 | I43: 0 | J43: 0 | K43: 0 | L43: 0 | M43: 0 | N43: 0 | O43: 0 | P43: =I43+J43+K43+L43+M43+N43+O43-E43 -> 0 | Q43: =I43+J43+K43+L43+M43+N43+O43-F43 -> 0 | R43: =I43+J43+K43+L43+M43+N43+O43-G43 -> 0 | S43: =I43+J43+K43+L43+M43+N43+O43-H43 -> 0 | U43: =Inventory!D35 -> VANDALAY | AB43: =SUM(V43:AA43) -> 0
A44: =Inventory!B36 -> GHOSRX903408OT | B44: =Inventory!C36 -> LP SKELETA POLTERGEIST | C44: 0.005 | D44: 40 | E44: =E12/D44*C44 -> 770.56875 | F44: =F12/D44*C44 -> 821.94 | G44: =G12/D44*C44 -> 873.31125 | H44: =H12/D44*C44 -> 924.6825 | I44: 0 | J44: 0 | K44: 0 | L44: 0 | M44: 0 | N44: 0 | O44: 0 | P44: =I44+J44+K44+L44+M44+N44+O44-E44 -> -770.56875 | Q44: =I44+J44+K44+L44+M44+N44+O44-F44 -> -821.94 | R44: =I44+J44+K44+L44+M44+N44+O44-G44 -> -873.31125 | S44: =I44+J44+K44+L44+M44+N44+O44-H44 -> -924.6825 | U44: =Inventory!D36 -> CONCORD | AB44: =SUM(V44:AA44) -> 0
A45: =Inventory!B37 -> GHOSNS203369OT | B45: =Inventory!C37 -> FOILED COMIC BOOK SISTER IMPERATOR # 1 | C45: 0.005 | D45: 30 | E45: =E12/D45*C45 -> 1027.425 | F45: =F12/D45*C45 -> 1095.92 | G45: =G12/D45*C45 -> 1164.415 | H45: =H12/D45*C45 -> 1232.91 | I45: 0 | J45: 0 | K45: 0 | L45: 0 | M45: 0 | N45: 0 | O45: 0 | P45: =I45+J45+K45+L45+M45+N45+O45-E45 -> -1027.425 | Q45: =I45+J45+K45+L45+M45+N45+O45-F45 -> -1095.92 | R45: =I45+J45+K45+L45+M45+N45+O45-G45 -> -1164.415 | S45: =I45+J45+K45+L45+M45+N45+O45-H45 -> -1232.91 | T45: UPC 761568014181 | U45: =Inventory!D37 -> DARK HORSE COMICS | AB45: =SUM(V45:AA45) -> 0
A46: =Inventory!B38 -> GHOSNS203533OT | B46: =Inventory!C38 -> COMIC BOOK SISTER IMPERATOR #2 | C46: 0.0025 | D46: 15 | E46: =E12/D46*C46 -> 1027.425 | F46: =F12/D46*C46 -> 1095.92 | G46: =G12/D46*C46 -> 1164.415 | H46: =H12/D46*C46 -> 1232.91 | I46: 0 | J46: 0 | K46: 0 | L46: 0 | M46: 0 | N46: 0 | O46: 0 | P46: =I46+J46+K46+L46+M46+N46+O46-E46 -> -1027.425 | Q46: =I46+J46+K46+L46+M46+N46+O46-F46 -> -1095.92 | R46: =I46+J46+K46+L46+M46+N46+O46-G46 -> -1164.415 | S46: =I46+J46+K46+L46+M46+N46+O46-H46 -> -1232.91 | U46: =Inventory!D38 -> DARK HORSE COMICS | AB46: =SUM(V46:AA46) -> 0
A47: =Inventory!B39 -> GHOSNS203534OT | B47: =Inventory!C39 -> COMIC BOOK SISTER IMPERATOR #3 | C47: 0.0025 | D47: 15 | E47: =E12/D47*C47 -> 1027.425 | F47: =F12/D47*C47 -> 1095.92 | G47: =G12/D47*C47 -> 1164.415 | H47: =H12/D47*C47 -> 1232.91 | I47: 0 | J47: 0 | K47: 0 | L47: 0 | M47: 0 | N47: 0 | O47: 0 | P47: =I47+J47+K47+L47+M47+N47+O47-E47 -> -1027.425 | Q47: =I47+J47+K47+L47+M47+N47+O47-F47 -> -1095.92 | R47: =I47+J47+K47+L47+M47+N47+O47-G47 -> -1164.415 | S47: =I47+J47+K47+L47+M47+N47+O47-H47 -> -1232.91 | U47: =Inventory!D39 -> DARK HORSE COMICS | AB47: =SUM(V47:AA47) -> 0
A48: =Inventory!B40 -> GHOSNS203535OT | B48: =Inventory!C40 -> COMIC BOOK SISTER IMPERATOR #4 | C48: 0.0025 | D48: 15 | E48: =E12/D48*C48 -> 1027.425 | F48: =F12/D48*C48 -> 1095.92 | G48: =G12/D48*C48 -> 1164.415 | H48: =H12/D48*C48 -> 1232.91 | I48: 0 | J48: 0 | K48: 0 | L48: 0 | M48: 0 | N48: 0 | O48: 0 | P48: =I48+J48+K48+L48+M48+N48+O48-E48 -> -1027.425 | Q48: =I48+J48+K48+L48+M48+N48+O48-F48 -> -1095.92 | R48: =I48+J48+K48+L48+M48+N48+O48-G48 -> -1164.415 | S48: =I48+J48+K48+L48+M48+N48+O48-H48 -> -1232.91 | U48: =Inventory!D40 -> DARK HORSE COMICS | AB48: =SUM(V48:AA48) -> 0
A49: =Inventory!B41 -> 0 | B49: =Inventory!C41 -> 0 | C49: 0 | D49: 1 | E49: =E12/D49*C49 -> 0 | F49: =F12/D49*C49 -> 0 | G49: =G12/D49*C49 -> 0 | H49: =H12/D49*C49 -> 0 | I49: 0 | J49: 0 | K49: 0 | L49: 0 | M49: 0 | N49: 0 | O49: 0 | P49: =I49+J49+K49+L49+M49+N49+O49-E49 -> 0 | Q49: =I49+J49+K49+L49+M49+N49+O49-F49 -> 0 | R49: =I49+J49+K49+L49+M49+N49+O49-G49 -> 0 | S49: =I49+J49+K49+L49+M49+N49+O49-H49 -> 0 | U49: =Inventory!D41 -> 0 | AB49: =SUM(V49:AA49) -> 0
A50: =Inventory!B42 -> GHOSNS103619OT | B50: =Inventory!C42 -> FOILED COMIC BOOK SISTER IMPERATOR #2 | C50: 0.005 | D50: 30 | E50: =E12/D50*C50 -> 1027.425 | F50: =F12/D50*C50 -> 1095.92 | G50: =G12/D50*C50 -> 1164.415 | H50: =H12/D50*C50 -> 1232.91 | I50: 0 | J50: 0 | K50: 0 | L50: 0 | M50: 0 | N50: 0 | O50: 0 | P50: =I50+J50+K50+L50+M50+N50+O50-E50 -> -1027.425 | Q50: =I50+J50+K50+L50+M50+N50+O50-F50 -> -1095.92 | R50: =I50+J50+K50+L50+M50+N50+O50-G50 -> -1164.415 | S50: =I50+J50+K50+L50+M50+N50+O50-H50 -> -1232.91 | U50: =Inventory!D42 -> DARK HORSE COMICS | AB50: =SUM(V50:AA50) -> 0
A51: =Inventory!B43 -> GHOSNS103622OT | B51: =Inventory!C43 -> FOILED COMIC BOOK SISTER IMPERATOR #3 | C51: 0.005 | D51: 30 | E51: =E12/D51*C51 -> 1027.425 | F51: =F12/D51*C51 -> 1095.92 | G51: =G12/D51*C51 -> 1164.415 | H51: =H12/D51*C51 -> 1232.91 | I51: 0 | J51: 0 | K51: 0 | L51: 0 | M51: 0 | N51: 0 | O51: 0 | P51: =I51+J51+K51+L51+M51+N51+O51-E51 -> -1027.425 | Q51: =I51+J51+K51+L51+M51+N51+O51-F51 -> -1095.92 | R51: =I51+J51+K51+L51+M51+N51+O51-G51 -> -1164.415 | S51: =I51+J51+K51+L51+M51+N51+O51-H51 -> -1232.91 | U51: =Inventory!D43 -> DARK HORSE COMICS | AB51: =SUM(V51:AA51) -> 0
A52: =Inventory!B44 -> GHOSNS103624OT | B52: =Inventory!C44 -> FOILED COMIC BOOK SISTER IMPERATOR #4 | C52: 0.005 | D52: 30 | E52: =E12/D52*C52 -> 1027.425 | F52: =F12/D52*C52 -> 1095.92 | G52: =G12/D52*C52 -> 1164.415 | H52: =H12/D52*C52 -> 1232.91 | I52: 0 | J52: 0 | K52: 0 | L52: 0 | M52: 0 | N52: 0 | O52: 0 | P52: =I52+J52+K52+L52+M52+N52+O52-E52 -> -1027.425 | Q52: =I52+J52+K52+L52+M52+N52+O52-F52 -> -1095.92 | R52: =I52+J52+K52+L52+M52+N52+O52-G52 -> -1164.415 | S52: =I52+J52+K52+L52+M52+N52+O52-H52 -> -1232.91 | U52: =Inventory!D44 -> DARK HORSE COMICS | AB52: =SUM(V52:AA52) -> 0
A53: =Inventory!B45 -> GHOSRX003463OT | B53: =Inventory!C45 -> CD SKELETA | D53: 20 | E53: =E12/D53*C53 -> 0 | F53: =F12/D53*C53 -> 0 | G53: =G12/D53*C53 -> 0 | H53: =H12/D53*C53 -> 0 | I53: 0 | J53: 0 | K53: 0 | L53: 0 | M53: 0 | N53: 0 | O53: 0 | P53: =I53+J53+K53+L53+M53+N53+O53-E53 -> 0 | Q53: =I53+J53+K53+L53+M53+N53+O53-F53 -> 0 | R53: =I53+J53+K53+L53+M53+N53+O53-G53 -> 0 | S53: =I53+J53+K53+L53+M53+N53+O53-H53 -> 0 | U53: =Inventory!D45 -> GMSUK | AB53: =SUM(V53:AA53) -> 0
A54: =Inventory!B46 -> GHOSRX003470OT | B54: =Inventory!C46 -> ROLLING STONE MAG & ALBUM | D54: 30 | E54: =E12/D54*C54 -> 0 | F54: =F12/D54*C54 -> 0 | G54: =G12/D54*C54 -> 0 | H54: =H12/D54*C54 -> 0 | I54: 0 | J54: 0 | K54: 0 | L54: 0 | M54: 0 | N54: 0 | O54: 0 | P54: =I54+J54+K54+L54+M54+N54+O54-E54 -> 0 | Q54: =I54+J54+K54+L54+M54+N54+O54-F54 -> 0 | R54: =I54+J54+K54+L54+M54+N54+O54-G54 -> 0 | S54: =I54+J54+K54+L54+M54+N54+O54-H54 -> 0 | U54: =Inventory!D46 -> GMSUK | AB54: =SUM(V54:AA54) -> 0
A55: =Inventory!B47 -> GHOSRX003611BK | B55: =Inventory!C47 -> LP SKELETA BLACK VINYL | D55: 40 | E55: =E12/D55*C55 -> 0 | F55: =F12/D55*C55 -> 0 | G55: =G12/D55*C55 -> 0 | H55: =H12/D55*C55 -> 0 | I55: 0 | J55: 0 | K55: 0 | L55: 0 | M55: 0 | N55: 0 | O55: 0 | P55: =I55+J55+K55+L55+M55+N55+O55-E55 -> 0 | Q55: =I55+J55+K55+L55+M55+N55+O55-F55 -> 0 | R55: =I55+J55+K55+L55+M55+N55+O55-G55 -> 0 | S55: =I55+J55+K55+L55+M55+N55+O55-H55 -> 0 | U55: =Inventory!D47 -> GMSUK | AB55: =SUM(V55:AA55) -> 0
A56: =Inventory!B48 -> GHOSCG103805PU | B56: =Inventory!C48 -> LP PURPLE LENTICULAR | D56: 1 | E56: =E12/D56*C56 -> 0 | F56: =F12/D56*C56 -> 0 | G56: =G12/D56*C56 -> 0 | H56: =H12/D56*C56 -> 0 | I56: 0 | J56: 0 | K56: 0 | L56: 0 | M56: 0 | N56: 0 | O56: 0 | P56: =I56+J56+K56+L56+M56+N56+O56-E56 -> 0 | Q56: =I56+J56+K56+L56+M56+N56+O56-F56 -> 0 | R56: =I56+J56+K56+L56+M56+N56+O56-G56 -> 0 | S56: =I56+J56+K56+L56+M56+N56+O56-H56 -> 0 | U56: =Inventory!D48 -> CONCORD | AB56: =SUM(V56:AA56) -> 0
A57: =Inventory!B49 -> GHOSCG103844BK | B57: =Inventory!C49 -> CASSETTE | D57: 1 | E57: =E12/D57*C57 -> 0 | F57: =F12/D57*C57 -> 0 | G57: =G12/D57*C57 -> 0 | H57: =H12/D57*C57 -> 0 | I57: 0 | J57: 0 | K57: 0 | L57: 0 | M57: 0 | N57: 0 | O57: 0 | P57: =I57+J57+K57+L57+M57+N57+O57-E57 -> 0 | Q57: =I57+J57+K57+L57+M57+N57+O57-F57 -> 0 | R57: =I57+J57+K57+L57+M57+N57+O57-G57 -> 0 | S57: =I57+J57+K57+L57+M57+N57+O57-H57 -> 0 | U57: =Inventory!D49 -> CONCORD | AB57: =SUM(V57:AA57) -> 0
A58: =Inventory!B50 -> 0 | B58: =Inventory!C50 -> 0 | D58: 1 | E58: =E12/D58*C58 -> 0 | F58: =F12/D58*C58 -> 0 | G58: =G12/D58*C58 -> 0 | H58: =H12/D58*C58 -> 0 | I58: 0 | J58: 0 | K58: 0 | L58: 0 | M58: 0 | N58: 0 | O58: 0 | P58: =I58+J58+K58+L58+M58+N58+O58-E58 -> 0 | Q58: =I58+J58+K58+L58+M58+N58+O58-F58 -> 0 | R58: =I58+J58+K58+L58+M58+N58+O58-G58 -> 0 | S58: =I58+J58+K58+L58+M58+N58+O58-H58 -> 0 | U58: =Inventory!D50 -> 0 | AB58: =SUM(V58:AA58) -> 0
A59: =Inventory!B51 -> 0 | B59: =Inventory!C51 -> 0 | D59: 1 | E59: =E23/D59*C59 -> 0 | F59: =F12/D59*C59 -> 0 | G59: =G12/D59*C59 -> 0 | H59: =H12/D59*C59 -> 0 | I59: 0 | J59: 0 | K59: 0 | L59: 0 | M59: 0 | N59: 0 | O59: 0 | P59: =I59+J59+K59+L59+M59+N59+O59-E59 -> 0 | Q59: =I59+J59+K59+L59+M59+N59+O59-F59 -> 0 | R59: =I59+J59+K59+L59+M59+N59+O59-G59 -> 0 | S59: =I59+J59+K59+L59+M59+N59+O59-H59 -> 0 | U59: =Inventory!D51 -> 0 | AB59: =SUM(V59:AA59) -> 0
C60: =SUM(C15:C52) -> 1.015

Sheet CLEVE HOUSTON
F2: SM | G2: MED | H2: LG | I2: XL | J2: 2X | K2: 3X | L2: TOTAL | N2: TOUR STOCK | O2: ORDER QTY | P2: TOTAL | Q2: SIZE | R2: SIZE % | S2: AMOUNT | T2: LESS TOUR INV | U2: ORDER QTY | X2: TS | Y2: LADIES | Z2: LS | AA2: ZIP | AB2: SHORTS | AC2: BATWING
L3: =SUM(F3:K3) -> 0 | O3: 5400 | P3: =N3+O3 -> 5400 | Q3: SM | R3: 0.07 | S3: =P3*R3 -> 378 | T3: 0 | U3: =S3-T3 -> 378 | X3: 0.09 | Y3: 0.25 | Z3: 0.04 | AA3: 0.08 | AB3: 0.2 | AC3: 0.1
L4: =SUM(F4:K4) -> 0 | P4: =P3 -> 5400 | Q4: MED | R4: 0.2 | S4: =P4*R4 -> 1080 | T4: 0 | U4: =S4-T4 -> 1080 | X4: 0.21 | Y4: 0.32 | Z4: 0.17 | AA4: 0.18 | AB4: 0.27 | AC4: 0.2
L5: =SUM(F5:K5) -> 0 | P5: =P3 -> 5400 | Q5: LG | R5: 0.27 | S5: =P5*R5 -> 1458 | T5: 0 | U5: =S5-T5 -> 1458 | X5: 0.29 | Y5: 0.24 | Z5: 0.24 | AA5: 0.27 | AB5: 0.21 | AC5: 0.3 | AG5: DATE | AH5: CITY | AI5: ST | AJ5: VENUE | AK5: CAPACITY | AL5: SOLD | AM5: EXPECT | AO5: PH | AP5: GROSS | AQ5: SELLS | AR5: MERCH | AS5: MEDIA
B6: DATE: | C6: 45854 | L6: =SUM(F6:K6) -> 0 | P6: =P3 -> 5400 | Q6: XL | R6: 0.25 | S6: =P6*R6 -> 1350 | T6: 0 | U6: =S6-T6 -> 1350 | X6: 0.23 | Y6: 0.19 | Z6: 0.26 | AA6: 0.23 | AB6: 0.2 | AC6: 0.2 | AG6: ='Tour Dates'!A4 -> 45847 | AH6: ='Tour Dates'!B4 -> Baltimore | AI6: ='Tour Dates'!C4 -> MD | AJ6: ='Tour Dates'!D4 -> CFG Bank Arena | AO6: 30 | AP6: =AM6*AO6 -> 0
B7: BAND: | C7: =Inventory!C3 -> GHOST | L7: =SUM(F7:K7) -> 0 | P7: =P5 -> 5400 | Q7: 2X | R7: 0.15 | S7: =P7*R7 -> 810 | T7: 0 | U7: =S7-T7 -> 810 | X7: 0.12 | Y7: 0 | Z7: 0.18 | AA7: 0.15 | AB7: 0.12 | AC7: 0.15 | AG7: ='Tour Dates'!A5 -> 45849 | AH7: ='Tour Dates'!B5 -> Atlanta | AI7: ='Tour Dates'!C5 -> GA | AJ7: ='Tour Dates'!D5 -> State Farm Arena | AO7: 35 | AP7: =AM7*AO7 -> 0
B8: TOUR: | C8: North America | L8: =SUM(F8:K8) -> 0 | P8: =P5 -> 5400 | Q8: 3X | R8: 0.07 | S8: =P8*R8 -> 378 | T8: 0 | U8: =S8-T8 -> 378 | X8: 0.06 | Y8: 0 | Z8: 0.09 | AA8: 0.09 | AB8: 0 | AC8: 0.05 | AG8: ='Tour Dates'!A6 -> 45850 | AH8: ='Tour Dates'!B6 -> Tampa | AI8: ='Tour Dates'!C6 -> FL | AJ8: ='Tour Dates'!D6 -> Amalie Arena | AO8: 35 | AP8: =AM8*AO8 -> 0
B9: # OF SHOWS: | C9: 22 | R9: =SUM(R3:R8) -> 1.01 | T9: =SUM(T3:T8) -> 0 | U9: =SUM(U3:U8) -> 5454 | X9: 0 | Y9: 0 | Z9: 0.02 | AA9: 0 | AB9: 0 | AC9: 0 | AG9: ='Tour Dates'!A7 -> 45851 | AH9: ='Tour Dates'!B7 -> Miami | AI9: ='Tour Dates'!C7 -> FL | AJ9: ='Tour Dates'!D7 -> Kaseya Center | AO9: 30 | AP9: =AM9*AO9 -> 0
B10: ATTENDANCE: | C10: =AM33 -> 194935 | X10: =SUM(X3:X9) -> 1 | Y10: =SUM(Y3:Y9) -> 1 | Z10: =SUM(Z3:Z9) -> 1 | AA10: =SUM(AA3:AA9) -> 1 | AB10: =SUM(AB3:AB9) -> 1 | AC10: =SUM(AC3:AC9) -> 1 | AG10: ='Tour Dates'!A8 -> 45853 | AH10: ='Tour Dates'!B8 -> Raleigh | AI10: ='Tour Dates'!C8 -> NC | AJ10: ='Tour Dates'!D8 -> Lenovo Center | AO10: 35 | AP10: =AM10*AO10 -> 0
AG11: ='Tour Dates'!A9 -> 45855 | AH11: ='Tour Dates'!B9 -> Cleveland | AI11: ='Tour Dates'!C9 -> OH | AJ11: ='Tour Dates'!D9 -> Rocket Mortgage FieldHouse | AK11: 10781 | AL11: 8275 | AM11: 8500 | AO11: 38 | AP11: =AM11*AO11 -> 323000
D12: EXP. GROSS | E12: =C10*E13 -> 6822725 | F12: =C10*F13 -> 7017660 | G12: =C10*G13 -> 7212595 | H12: =C10*H13 -> 7407530 | I12: STOCK | J12: STOCK | K12: STOCK | L12: STOCK | M12: STOCK | N12: STOCK | O12: PO's | P12: PRODUCT OVER (+) or UNDER (-) | T12: BLANKS | U12: PRINTER | V12: SM | W12: MED | X12: LG | Y12: XL | Z12: 2X | AA12: 3X | AB12: TOTAL | AC12: DUE | AD12: BLANK PO | AE12: PRINT PO | AG12: ='Tour Dates'!A10 -> 45856 | AH12: ='Tour Dates'!B10 -> Pittsburgh | AI12: ='Tour Dates'!C10 -> PA | AJ12: ='Tour Dates'!D10 -> PPG Paints Arena | AK12: 11009 | AL12: 8905 | AM12: 9500 | AO12: 38 | AP12: =AM12*AO12 -> 361000
C13: =SUM(C15:C59) -> 1 | D13: PRICE/P.H. | E13: 35 | F13: 36 | G13: 37 | H13: 38 | I13: TOUR | J13: CLEVELAND | K13: BOSTON | L13: PITTS | M13: DET | N13: LAX | O13: ON ORDER | P13: =E13 -> 35 | Q13: =F13 -> 36 | R13: =G13 -> 37 | S13: =H13 -> 38 | AG13: ='Tour Dates'!A11 -> 45857 | AH13: ='Tour Dates'!B11 -> Philadelphia | AI13: ='Tour Dates'!C11 -> PA | AJ13: ='Tour Dates'!D11 -> Wells Fargo Center | AK13: 12750 | AL13: 11624 | AM13: 12000 | AO13: 38 | AP13: =AM13*AO13 -> 456000
A14: SKU # | B14: DESIGN | C14: % GROSS | AG14: ='Tour Dates'!A12 -> 45859 | AH14: ='Tour Dates'!B12 -> Boston | AI14: ='Tour Dates'!C12 -> MA | AJ14: ='Tour Dates'!D12 -> TD Garden | AK14: 11985 | AL14: 11914 | AM14: 11985 | AO14: 35 | AP14: =AM14*AO14 -> 419475
A15: =Inventory!B7 -> GHOSRX203729BK | B15: =Inventory!C7 -> BLACK T SKELETOUR 2025 ITIN | C15: 0.17 | D15: 50 | E15: =E12/D15*C15 -> 23197.265 | F15: =F12/D15*C15 -> 23860.044 | G15: =G12/D15*C15 -> 24522.823 | H15: =H12/D15*C15 -> 25185.602 | I15: 3158 | J15: 0 | K15: 0 | L15: 5400 | M15: 5400 | N15: 0 | O15: 7200 | P15: =I15+J15+K15+L15+M15+N15+O15-E15 -> -2039.265 | Q15: =I15+J15+K15+L15+M15+N15+O15-F15 -> -2702.044 | R15: =I15+J15+K15+L15+M15+N15+O15-G15 -> -3364.823 | S15: =I15+J15+K15+L15+M15+N15+O15-H15 -> -4027.602 | T15: GILDAN 64000 | U15: =Inventory!D7 -> CULTURE | V15: 504 | W15: 1440 | X15: 1944 | Y15: 1872 | Z15: 936 | AA15: 504 | AB15: =SUM(V15:AA15) -> 7200 | AC15: 45861 | AG15: ='Tour Dates'!A13 -> 45860 | AH15: ='Tour Dates'!B13 -> New York | AI15: ='Tour Dates'!C13 -> NY | AJ15: ='Tour Dates'!D13 -> Madison Square Garden | AK15: 11450 | AL15: 11207 | AM15: 11450 | AO15: 35 | AP15: =AM15*AO15 -> 400750
A16: =Inventory!B8 -> GHOSRX203728BK | B16: =Inventory!C8 -> BLACK T SKELETA ALBUM COVER 2025 ITIN | C16: 0.12 | D16: 50 | E16: =E12/D16*C16 -> 16374.54 | F16: =F12/D16*C16 -> 16842.384 | G16: =G12/D16*C16 -> 17310.228 | H16: =H12/D16*C16 -> 17778.072 | I16: 1985 | J16: 0 | K16: 0 | L16: 3600 | M16: 3600 | N16: 0 | O16: 5112 | P16: =I16+J16+K16+L16+M16+N16+O16-E16 -> -2077.54 | Q16: =I16+J16+K16+L16+M16+N16+O16-F16 -> -2545.384 | R16: =I16+J16+K16+L16+M16+N16+O16-G16 -> -3013.228 | S16: =I16+J16+K16+L16+M16+N16+O16-H16 -> -3481.072 | T16: GILDAN 64000 | U16: =Inventory!D8 -> CULTURE | V16: 360 | W16: 1080 | X16: 1440 | Y16: 1224 | Z16: 648 | AA16: 360 | AB16: =SUM(V16:AA16) -> 5112 | AC16: 45861 | AG16: ='Tour Dates'!A14 -> 45862 | AH16: ='Tour Dates'!B14 -> Detroit | AI16: ='Tour Dates'!C14 -> MI | AJ16: ='Tour Dates'!D14 -> Little Caesars Arena | AK16: 10117 | AL16: 7745 | AM16: 8500 | AO16: 35 | AP16: =AM16*AO16 -> 297500
A17: =Inventory!B9 -> GHOSRX203730BK | B17: =Inventory!C9 -> BLACK T WESTERN EMERITUS 2025 ITIN | C17: 0.175 | D17: 50 | E17: =E12/D17*C17 -> 23879.537 | F17: =F12/D17*C17 -> 24561.81 | G17: =G12/D17*C17 -> 25244.082 | H17: =H12/D17*C17 -> 25926.355 | I17: 2471 | J17: 0 | K17: 0 | L17: 5400 | M17: 5400 | N17: 0 | O17: 7200 | P17: =I17+J17+K17+L17+M17+N17+O17-E17 -> -3408.5375 | Q17: =I17+J17+K17+L17+M17+N17+O17-F17 -> -4090.81 | R17: =I17+J17+K17+L17+M17+N17+O17-G17 -> -4773.0825 | S17: =I17+J17+K17+L17+M17+N17+O17-H17 -> -5455.355 | T17: GILDAN 64000 | U17: =Inventory!D9 -> CULTURE | V17: 504 | W17: 1440 | X17: 1944 | Y17: 1872 | Z17: 936 | AA17: 504 | AB17: =SUM(V17:AA17) -> 7200 | AC17: 45861 | AG17: ='Tour Dates'!A15 -> 45863 | AH17: ='Tour Dates'!B15 -> Louisville | AI17: ='Tour Dates'!C15 -> KY | AJ17: ='Tour Dates'!D15 -> KFC Yum! Center | AK17: 9832 | AL17: 9053 | AM17: 9500 | AO17: 35 | AP17: =AM17*AO17 -> 332500
A18: =Inventory!B10 -> GHOSRX103726BK | B18: =Inventory!C10 -> BLACK TANK OPUS EPONYMOUS | C18: 0.02 | D18: 50 | E18: =E12/D18*C18 -> 2729.09 | F18: =F12/D18*C18 -> 2807.064 | G18: =G12/D18*C18 -> 2885.038 | H18: =H12/D18*C18 -> 2963.012 | I18: 610 | J18: 0 | K18: 0 | L18: 720 | M18: 0 | N18: 0 | O18: 1440 | P18: =I18+J18+K18+L18+M18+N18+O18-E18 -> 40.91 | Q18: =I18+J18+K18+L18+M18+N18+O18-F18 -> -37.064 | R18: =I18+J18+K18+L18+M18+N18+O18-G18 -> -115.038 | S18: =I18+J18+K18+L18+M18+N18+O18-H18 -> -193.012 | T18: ASC 5025 | U18: =Inventory!D10 -> CULTURE | V18: 216 | W18: 360 | X18: 432 | Y18: 288 | Z18: 144 | AA18: 0 | AB18: =SUM(V18:AA18) -> 1440 | AC18: 45861 | AG18: ='Tour Dates'!A16 -> 45864 | AH18: ='Tour Dates'!B16 -> Nashville | AI18: ='Tour Dates'!C16 -> TN | AJ18: ='Tour Dates'!D16 -> Bridgestone Arena | AK18: 10596 | AL18: 8522 | AM18: 9000 | AO18: 35 | AP18: =AM18*AO18 -> 315000
A19: =Inventory!B11 -> GHOSRX203400BK | B19: =Inventory!C11 -> LADIES CROP TOP SHOWGHOULS | C19: 0.02 | D19: 50 | E19: =E12/D19*C19 -> 2729.09 | F19: =F12/D19*C19 -> 2807.064 | G19: =G12/D19*C19 -> 2885.038 | H19: =H12/D19*C19 -> 2963.012 | I19: 328 | J19: 0 | K19: 0 | L19: 720 | M19: 0 | N19: 0 | O19: 1440 | P19: =I19+J19+K19+L19+M19+N19+O19-E19 -> -241.09 | Q19: =I19+J19+K19+L19+M19+N19+O19-F19 -> -319.064 | R19: =I19+J19+K19+L19+M19+N19+O19-G19 -> -397.038 | S19: =I19+J19+K19+L19+M19+N19+O19-H19 -> -475.012 | T19: NLA 5080 | U19: CULTURE | V19: 288 | W19: 432 | X19: 360 | Y19: 360 | Z19: 0 | AA19: 0 | AB19: =SUM(V19:AA19) -> 1440 | AC19: 45861 | AG19: ='Tour Dates'!A17 -> 45866 | AH19: ='Tour Dates'!B17 -> Grand Rapids | AI19: ='Tour Dates'!C17 -> MI | AJ19: ='Tour Dates'!D17 -> Van Andel Arena | AK19: 6932 | AL19: 5736 | AM19: 6500 | AO19: 35 | AP19: =AM19*AO19 -> 227500
A20: =Inventory!B12 -> GHOSRX203727PK | B20: =Inventory!C12 -> LADIES PINK RAGLAN GARGOYLE | C20: 0.02 | D20: 50 | E20: =E12/D20*C20 -> 2729.09 | F20: =F12/D20*C20 -> 2807.064 | G20: =G12/D20*C20 -> 2885.038 | H20: =H12/D20*C20 -> 2963.012 | I20: 534 | J20: 0 | K20: 0 | L20: 720 | M20: 0 | N20: 0 | O20: 1440 | P20: =I20+J20+K20+L20+M20+N20+O20-E20 -> -35.09 | Q20: =I20+J20+K20+L20+M20+N20+O20-F20 -> -113.064 | R20: =I20+J20+K20+L20+M20+N20+O20-G20 -> -191.038 | S20: =I20+J20+K20+L20+M20+N20+O20-H20 -> -269.012 | T20: BELLA 1201 | U20: =Inventory!D12 -> CULTURE | V20: 360 | W20: 504 | X20: 288 | Y20: 288 | Z20: 0 | AA20: 0 | AB20: =SUM(V20:AA20) -> 1440 | AC20: 45861 | AG20: ='Tour Dates'!A18 -> 45867 | AH20: ='Tour Dates'!B18 -> Milwaukee | AI20: ='Tour Dates'!C18 -> WI | AJ20: ='Tour Dates'!D18 -> Fiserv Forum | AK20: 8693 | AL20: 6022 | AM20: 6500 | AO20: 35 | AP20: =AM20*AO20 -> 227500
A21: =Inventory!B13 -> 0 | B21: =Inventory!C13 -> 0 | C21: 0 | D21: 1 | E21: =E12/D21*C21 -> 0 | F21: =F12/D21*C21 -> 0 | G21: =G12/D21*C21 -> 0 | H21: =H12/D21*C21 -> 0 | I21: 0 | J21: 0 | K21: 0 | L21: 0 | M21: 0 | N21: 0 | O21: 0 | P21: =I21+J21+K21+L21+M21+N21+O21-E21 -> 0 | Q21: =I21+J21+K21+L21+M21+N21+O21-F21 -> 0 | R21: =I21+J21+K21+L21+M21+N21+O21-G21 -> 0 | S21: =I21+J21+K21+L21+M21+N21+O21-H21 -> 0 | U21: =Inventory!D13 -> 0 | AB21: =SUM(V21:AA21) -> 0 | AG21: ='Tour Dates'!A19 -> 45868 | AH21: ='Tour Dates'!B19 -> St. Louis | AI21: ='Tour Dates'!C19 -> MO | AJ21: ='Tour Dates'!D19 -> Enterprise Center | AK21: 8569 | AL21: 6067 | AM21: 6500 | AO21: 35 | AP21: =AM21*AO21 -> 227500
